Workbook

Sheet README
A1: Porsche Company Lens - 2026 Margin Recovery: business-analysis workbook
A2: Phase 5 (Excel). Built from the validated PostgreSQL database porsche_lens (Phases 3-4). Prepared 2026-09-28.
A4: Question | B4: Porsche's reported margin rose from 5.5% to 7.8% in H1 2026. After removing the exceptional items Porsche itself discloses, and isolating non-cash effects from R&D capitalisation and depreciation, is underlying profitability actually improving, and what does FY2026 guidance imply for H2 2026?
A5: Purpose | B5: A transparent, formula-driven model that a business team can audit: every number traces back to a Porsche document and page.
A6: Model status | B6: =IF(COUNTIF(Audit_Checks!$H$7:$H$56,"FAIL")=0,"ALL "&COUNTA(Audit_Checks!$H$7:$H$56)&" CHECKS PASS",COUNTIF(Audit_Checks!$H$7:$H$56,"FAIL")&" OF "&COUNTA(Audit_Checks!$H$7:$H$56)&" CHECK(S) FAIL - see Audit_Checks") -> ALL 50 CHECKS PASS
A8: SHEET MAP | B8: What each sheet answers
A9: KPI_Overview | B9: What happened? Headline KPIs by half-year, H1 2025 vs H1 2026, formula-driven readings, two charts.
A10: EBIT_Analysis | B10: Is underlying profitability improving? Reported (L0) vs adjusted (L1, L2) EBIT and margin; own YoY bridge in EUR m and pp; reconciliation to Porsche's bridge. L3 in a grey supplementary box.
A11: RD_DA | B11: Are non-cash effects flattering EBIT? Total R&D costs, capitalisation rate, P&L charge, counterfactual; D&A cleaned of impairments.
A12: Commercial | B12: Is value compensating for volume? ASP (Porsche definition), vehicle sales, volume vs ASP effect, model and regional mix.
A13: Cash_Crosscheck | B13: Does cash confirm the profit picture? EBIT/EBITDA vs net cash flow, published-margin reconciliation, simple cash proxy.
A14: Guidance_Scenarios | B14: What must H2 2026 look like to meet guidance? Scenario selector + all 27 combinations + automotive view. Scenarios, NOT forecasts.
A15: Audit_Checks | B15: Can the numbers be trusted? 50 formula checks: imports, lookup integrity (unique keys + panel round-trip), Excel vs SQL reconciliation, identities, Porsche reconciliation, labelling, and 8 anchor values displayed on KPI_Overview vs the SQL export.
A16: Audit_Register | B16: Where does it come from? Source register, assumptions A-01..A-09, known data gaps, audit findings, SQL view catalogue, SQL check results.
A17: Data_Panel | B17: Half-year panel (formula pivot of Data_Long) with a FACT/DERIVED label grid; derived cells shaded.
A18: Data_Long / Data_Mix | B18: Controlled imports from SQL (core.fact_financial, deliveries). The only place where Porsche values are typed in.
A19: SQL_Outputs | B19: Mart view results, used ONLY by Audit_Checks to prove that Excel and SQL agree.
A21: CONVENTIONS
A22: Colours | B22: Blue = imported or hard-coded input. Black = formula. Green = link to another sheet. Yellow fill = headline KPI. Grey fill = supplementary sensitivity. Orange band = scenario area.
A23: Units | B23: Money in EUR m. Margins stored as fractions and shown as %. 'pp' = percentage points. ASP in EUR k. Volumes in units.
A24: Signs | B24: Exceptional items and tariffs are positive numbers = expense; adding them back raises EBIT. Bridge effects: + = raises EBIT.
A25: Periods | B25: Half-years 2023-H1 .. 2026-H1. Porsche publishes H1 and FY; H2 = FY - H1 (DERIVED in SQL). Year-on-year always compares the same half of the prior year.
A26: FACT / DERIVED | B26: FACT = published by Porsche. DERIVED = calculated from published values (H2, identities, FY2025 one-off total). See Data_Panel label grid and Data_Long source_ref.
A28: PROFIT LEVELS
A29: L0 (headline) | B29: Reported group EBIT.
A30: L1 (headline) | B30: L0 + strategic realignment & battery items as disclosed by Porsche (net of related provision releases).
A31: L2 (headline) | B31: L1 + US import tariffs.
A32: L3 (supplementary) | B32: Supplementary HYBRID SENSITIVITY only: L1 + clean automotive D&A - automotive capitalised development costs. Not underlying group profitability; never used as headline KPI.
A33: Residual | B33: 'Residual / other EBIT drivers' in the bridge is NOT operating performance: it mixes price, mix, volume, total R&D cost changes, material/supplier costs, SG&A, other operating result, FX, consolidation and one-off rounding.
A35: KEY ASSUMPTIONS | B35: Full register: Audit_Register section 2.
A36: A-01 / A-02 | B36: No realignment items disclosed for 2023-2024 and no US tariffs before April 2025 -> treated as 0.
A37: A-03 / A-04 | B37: Undisclosed impairments (H2 2023, H2 2024) -> 0; H1 2026 impairments (EUR 61m) assumed inside D&A (alternative shown).
A38: A-05..A-08 | B38: Guidance: automotive revenue share, extraordinary-expense basis, H2 tariffs = H1, range ends combined independently.
A39: A-09 | B39: Derived H2 values inherit the EUR 0.1bn rounding of one-off disclosures (rounding band shown).
A41: LINEAGE | B41: Porsche documents (S001-S027) -> PCL_02_Manual_Inputs.xlsx + fact sheet S025 -> PostgreSQL core.fact_financial -> mart views -> Data_Long (this workbook) -> analysis sheets. Refresh: re-export fact_long / mix / SQL outputs and replace the blue import rows; Audit_Checks must show ALL PASS.
A42: Not in scope | B42: No forecasts, no internal Porsche data, no estimates for missing values. Interpretation and recommendations follow in Phases 6-9.

Sheet Data_Panel
A1: Data_Panel - half-year panel built by formula from Data_Long
A2: Each cell = two-criteria lookup on Data_Long: SUMIFS(value, period_code = column header, var_id = row id), guarded by COUNTIFS (0 matches -> blank; Data_Long!K proves each pair is unique). Blank = not published. Shaded cells are DERIVED (H2 = FY - H1 or identity); label grid below states FACT / DERIVED per cell.
A3: Money in EUR m; % variables as published (e.g. 18.3 = 18.3%). Analysis sheets convert.
A5: var_id | B5: variable | C5: unit | D5: 2023-H1 | E5: 2023-H2 | F5: 2024-H1 | G5: 2024-H2 | H5: 2025-H1 | I5: 2025-H2 | J5: 2026-H1 | K5: sources used (from Data_Long)
A6: G01 | B6: Group sales revenue | C6: EUR m | D6: =IF(COUNTIFS(Data_Long!$A$6:$A$243,D$5,Data_Long!$B$6:$B$243,$A6)=0,"",SUMIFS(Data_Long!$D$6:$D$243,Data_Long!$A$6:$A$243,D$5,Data_Long!$B$6:$B$243,$A6)) -> 20430.923 | E6: =IF(COUNTIFS(Data_Long!$A$6:$A$243,E$5,Data_Long!$B$6:$B$243,$A6)=0,"",SUMIFS(Data_Long!$D$6:$D$243,Data_Long!$A$6:$A$243,E$5,Data_Long!$B$6:$B$243,$A6)) -> 20098.71 | F6: =IF(COUNTIFS(Data_Long!$A$6:$A$243,F$5,Data_Long!$B$6:$B$243,$A6)=0,"",SUMIFS(Data_Long!$D$6:$D$243,Data_Long!$A$6:$A$243,F$5,Data_Long!$B$6:$B$243,$A6)) -> 19457.009 | G6: =IF(COUNTIFS(Data_Long!$A$6:$A$243,G$5,Data_Long!$B$6:$B$243,$A6)=0,"",SUMIFS(Data_Long!$D$6:$D$243,Data_Long!$A$6:$A$243,G$5,Data_Long!$B$6:$B$243,$A6)) -> 20626.284 | H6: =IF(COUNTIFS(Data_Long!$A$6:$A$243,H$5,Data_Long!$B$6:$B$243,$A6)=0,"",SUMIFS(Data_Long!$D$6:$D$243,Data_Long!$A$6:$A$243,H$5,Data_Long!$B$6:$B$243,$A6)) -> 18157.275 | I6: =IF(COUNTIFS(Data_Long!$A$6:$A$243,I$5,Data_Long!$B$6:$B$243,$A6)=0,"",SUMIFS(Data_Long!$D$6:$D$243,Data_Long!$A$6:$A$243,I$5,Data_Long!$B$6:$B$243,$A6)) -> 18114.353 | J6: =IF(COUNTIFS(Data_Long!$A$6:$A$243,J$5,Data_Long!$B$6:$B$243,$A6)=0,"",SUMIFS(Data_Long!$D$6:$D$243,Data_Long!$A$6:$A$243,J$5,Data_Long!$B$6:$B$243,$A6)) -> 17229.456 | K6: S025, SQL derived
A7: G02 | B7: Cost of sales | C7: EUR m | D7: =IF(COUNTIFS(Data_Long!$A$6:$A$243,D$5,Data_Long!$B$6:$B$243,$A7)=0,"",SUMIFS(Data_Long!$D$6:$D$243,Data_Long!$A$6:$A$243,D$5,Data_Long!$B$6:$B$243,$A7)) -> -14521.515 | E7: =IF(COUNTIFS(Data_Long!$A$6:$A$243,E$5,Data_Long!$B$6:$B$243,$A7)=0,"",SUMIFS(Data_Long!$D$6:$D$243,Data_Long!$A$6:$A$243,E$5,Data_Long!$B$6:$B$243,$A7)) -> -14402.255 | F7: =IF(COUNTIFS(Data_Long!$A$6:$A$243,F$5,Data_Long!$B$6:$B$243,$A7)=0,"",SUMIFS(Data_Long!$D$6:$D$243,Data_Long!$A$6:$A$243,F$5,Data_Long!$B$6:$B$243,$A7)) -> -14251.029 | G7: =IF(COUNTIFS(Data_Long!$A$6:$A$243,G$5,Data_Long!$B$6:$B$243,$A7)=0,"",SUMIFS(Data_Long!$D$6:$D$243,Data_Long!$A$6:$A$243,G$5,Data_Long!$B$6:$B$243,$A7)) -> -15504.837 | H7: =IF(COUNTIFS(Data_Long!$A$6:$A$243,H$5,Data_Long!$B$6:$B$243,$A7)=0,"",SUMIFS(Data_Long!$D$6:$D$243,Data_Long!$A$6:$A$243,H$5,Data_Long!$B$6:$B$243,$A7)) -> -14793.386 | I7: =IF(COUNTIFS(Data_Long!$A$6:$A$243,I$5,Data_Long!$B$6:$B$243,$A7)=0,"",SUMIFS(Data_Long!$D$6:$D$243,Data_Long!$A$6:$A$243,I$5,Data_Long!$B$6:$B$243,$A7)) -> -16427.364 | J7: =IF(COUNTIFS(Data_Long!$A$6:$A$243,J$5,Data_Long!$B$6:$B$243,$A7)=0,"",SUMIFS(Data_Long!$D$6:$D$243,Data_Long!$A$6:$A$243,J$5,Data_Long!$B$6:$B$243,$A7)) -> -13763.625 | K7: S025, SQL derived
A8: G03 | B8: Gross profit | C8: EUR m | D8: =IF(COUNTIFS(Data_Long!$A$6:$A$243,D$5,Data_Long!$B$6:$B$243,$A8)=0,"",SUMIFS(Data_Long!$D$6:$D$243,Data_Long!$A$6:$A$243,D$5,Data_Long!$B$6:$B$243,$A8)) -> 5909.4077 | E8: =IF(COUNTIFS(Data_Long!$A$6:$A$243,E$5,Data_Long!$B$6:$B$243,$A8)=0,"",SUMIFS(Data_Long!$D$6:$D$243,Data_Long!$A$6:$A$243,E$5,Data_Long!$B$6:$B$243,$A8)) -> 5696.4553 | F8: =IF(COUNTIFS(Data_Long!$A$6:$A$243,F$5,Data_Long!$B$6:$B$243,$A8)=0,"",SUMIFS(Data_Long!$D$6:$D$243,Data_Long!$A$6:$A$243,F$5,Data_Long!$B$6:$B$243,$A8)) -> 5205.9796 | G8: =IF(COUNTIFS(Data_Long!$A$6:$A$243,G$5,Data_Long!$B$6:$B$243,$A8)=0,"",SUMIFS(Data_Long!$D$6:$D$243,Data_Long!$A$6:$A$243,G$5,Data_Long!$B$6:$B$243,$A8)) -> 5121.4476 | H8: =IF(COUNTIFS(Data_Long!$A$6:$A$243,H$5,Data_Long!$B$6:$B$243,$A8)=0,"",SUMIFS(Data_Long!$D$6:$D$243,Data_Long!$A$6:$A$243,H$5,Data_Long!$B$6:$B$243,$A8)) -> 3363.8889 | I8: =IF(COUNTIFS(Data_Long!$A$6:$A$243,I$5,Data_Long!$B$6:$B$243,$A8)=0,"",SUMIFS(Data_Long!$D$6:$D$243,Data_Long!$A$6:$A$243,I$5,Data_Long!$B$6:$B$243,$A8)) -> 1686.989 | J8: =IF(COUNTIFS(Data_Long!$A$6:$A$243,J$5,Data_Long!$B$6:$B$243,$A8)=0,"",SUMIFS(Data_Long!$D$6:$D$243,Data_Long!$A$6:$A$243,J$5,Data_Long!$B$6:$B$243,$A8)) -> 3465.8305 | K8: S025, SQL derived
A9: G04 | B9: Distribution expenses | C9: EUR m | D9: =IF(COUNTIFS(Data_Long!$A$6:$A$243,D$5,Data_Long!$B$6:$B$243,$A9)=0,"",SUMIFS(Data_Long!$D$6:$D$243,Data_Long!$A$6:$A$243,D$5,Data_Long!$B$6:$B$243,$A9)) -> -1292.9307 | E9: =IF(COUNTIFS(Data_Long!$A$6:$A$243,E$5,Data_Long!$B$6:$B$243,$A9)=0,"",SUMIFS(Data_Long!$D$6:$D$243,Data_Long!$A$6:$A$243,E$5,Data_Long!$B$6:$B$243,$A9)) -> -1576.4607 | F9: =IF(COUNTIFS(Data_Long!$A$6:$A$243,F$5,Data_Long!$B$6:$B$243,$A9)=0,"",SUMIFS(Data_Long!$D$6:$D$243,Data_Long!$A$6:$A$243,F$5,Data_Long!$B$6:$B$243,$A9)) -> -1379.2659 | G9: =IF(COUNTIFS(Data_Long!$A$6:$A$243,G$5,Data_Long!$B$6:$B$243,$A9)=0,"",SUMIFS(Data_Long!$D$6:$D$243,Data_Long!$A$6:$A$243,G$5,Data_Long!$B$6:$B$243,$A9)) -> -1720.1293 | H9: =IF(COUNTIFS(Data_Long!$A$6:$A$243,H$5,Data_Long!$B$6:$B$243,$A9)=0,"",SUMIFS(Data_Long!$D$6:$D$243,Data_Long!$A$6:$A$243,H$5,Data_Long!$B$6:$B$243,$A9)) -> -1310.3138 | I9: =IF(COUNTIFS(Data_Long!$A$6:$A$243,I$5,Data_Long!$B$6:$B$243,$A9)=0,"",SUMIFS(Data_Long!$D$6:$D$243,Data_Long!$A$6:$A$243,I$5,Data_Long!$B$6:$B$243,$A9)) -> -1485.2685 | J9: =IF(COUNTIFS(Data_Long!$A$6:$A$243,J$5,Data_Long!$B$6:$B$243,$A9)=0,"",SUMIFS(Data_Long!$D$6:$D$243,Data_Long!$A$6:$A$243,J$5,Data_Long!$B$6:$B$243,$A9)) -> -1278.4594 | K9: S025, SQL derived
A10: G05 | B10: Administrative expenses | C10: EUR m | D10: =IF(COUNTIFS(Data_Long!$A$6:$A$243,D$5,Data_Long!$B$6:$B$243,$A10)=0,"",SUMIFS(Data_Long!$D$6:$D$243,Data_Long!$A$6:$A$243,D$5,Data_Long!$B$6:$B$243,$A10)) -> -875.09562 | E10: =IF(COUNTIFS(Data_Long!$A$6:$A$243,E$5,Data_Long!$B$6:$B$243,$A10)=0,"",SUMIFS(Data_Long!$D$6:$D$243,Data_Long!$A$6:$A$243,E$5,Data_Long!$B$6:$B$243,$A10)) -> -911.68941 | F10: =IF(COUNTIFS(Data_Long!$A$6:$A$243,F$5,Data_Long!$B$6:$B$243,$A10)=0,"",SUMIFS(Data_Long!$D$6:$D$243,Data_Long!$A$6:$A$243,F$5,Data_Long!$B$6:$B$243,$A10)) -> -951.8289 | G10: =IF(COUNTIFS(Data_Long!$A$6:$A$243,G$5,Data_Long!$B$6:$B$243,$A10)=0,"",SUMIFS(Data_Long!$D$6:$D$243,Data_Long!$A$6:$A$243,G$5,Data_Long!$B$6:$B$243,$A10)) -> -907.45239 | H10: =IF(COUNTIFS(Data_Long!$A$6:$A$243,H$5,Data_Long!$B$6:$B$243,$A10)=0,"",SUMIFS(Data_Long!$D$6:$D$243,Data_Long!$A$6:$A$243,H$5,Data_Long!$B$6:$B$243,$A10)) -> -977.85327 | I10: =IF(COUNTIFS(Data_Long!$A$6:$A$243,I$5,Data_Long!$B$6:$B$243,$A10)=0,"",SUMIFS(Data_Long!$D$6:$D$243,Data_Long!$A$6:$A$243,I$5,Data_Long!$B$6:$B$243,$A10)) -> -920.81009 | J10: =IF(COUNTIFS(Data_Long!$A$6:$A$243,J$5,Data_Long!$B$6:$B$243,$A10)=0,"",SUMIFS(Data_Long!$D$6:$D$243,Data_Long!$A$6:$A$243,J$5,Data_Long!$B$6:$B$243,$A10)) -> -997.07232 | K10: S025, SQL derived
A11: G06 | B11: Net other operating result | C11: EUR m | D11: =IF(COUNTIFS(Data_Long!$A$6:$A$243,D$5,Data_Long!$B$6:$B$243,$A11)=0,"",SUMIFS(Data_Long!$D$6:$D$243,Data_Long!$A$6:$A$243,D$5,Data_Long!$B$6:$B$243,$A11)) -> 110.85388 | E11: =IF(COUNTIFS(Data_Long!$A$6:$A$243,E$5,Data_Long!$B$6:$B$243,$A11)=0,"",SUMIFS(Data_Long!$D$6:$D$243,Data_Long!$A$6:$A$243,E$5,Data_Long!$B$6:$B$243,$A11)) -> 223.76728 | F11: =IF(COUNTIFS(Data_Long!$A$6:$A$243,F$5,Data_Long!$B$6:$B$243,$A11)=0,"",SUMIFS(Data_Long!$D$6:$D$243,Data_Long!$A$6:$A$243,F$5,Data_Long!$B$6:$B$243,$A11)) -> 186.57065 | G11: =IF(COUNTIFS(Data_Long!$A$6:$A$243,G$5,Data_Long!$B$6:$B$243,$A11)=0,"",SUMIFS(Data_Long!$D$6:$D$243,Data_Long!$A$6:$A$243,G$5,Data_Long!$B$6:$B$243,$A11)) -> 81.571308 | H11: =IF(COUNTIFS(Data_Long!$A$6:$A$243,H$5,Data_Long!$B$6:$B$243,$A11)=0,"",SUMIFS(Data_Long!$D$6:$D$243,Data_Long!$A$6:$A$243,H$5,Data_Long!$B$6:$B$243,$A11)) -> -68.930531 | I11: =IF(COUNTIFS(Data_Long!$A$6:$A$243,I$5,Data_Long!$B$6:$B$243,$A11)=0,"",SUMIFS(Data_Long!$D$6:$D$243,Data_Long!$A$6:$A$243,I$5,Data_Long!$B$6:$B$243,$A11)) -> 125.58225 | J11: =IF(COUNTIFS(Data_Long!$A$6:$A$243,J$5,Data_Long!$B$6:$B$243,$A11)=0,"",SUMIFS(Data_Long!$D$6:$D$243,Data_Long!$A$6:$A$243,J$5,Data_Long!$B$6:$B$243,$A11)) -> 157.88631 | K11: S025, SQL derived
A12: G07 | B12: Operating profit (EBIT), group | C12: EUR m | D12: =IF(COUNTIFS(Data_Long!$A$6:$A$243,D$5,Data_Long!$B$6:$B$243,$A12)=0,"",SUMIFS(Data_Long!$D$6:$D$243,Data_Long!$A$6:$A$243,D$5,Data_Long!$B$6:$B$243,$A12)) -> 3852.2352 | E12: =IF(COUNTIFS(Data_Long!$A$6:$A$243,E$5,Data_Long!$B$6:$B$243,$A12)=0,"",SUMIFS(Data_Long!$D$6:$D$243,Data_Long!$A$6:$A$243,E$5,Data_Long!$B$6:$B$243,$A12)) -> 3432.0724 | F12: =IF(COUNTIFS(Data_Long!$A$6:$A$243,F$5,Data_Long!$B$6:$B$243,$A12)=0,"",SUMIFS(Data_Long!$D$6:$D$243,Data_Long!$A$6:$A$243,F$5,Data_Long!$B$6:$B$243,$A12)) -> 3061.4555 | G12: =IF(COUNTIFS(Data_Long!$A$6:$A$243,G$5,Data_Long!$B$6:$B$243,$A12)=0,"",SUMIFS(Data_Long!$D$6:$D$243,Data_Long!$A$6:$A$243,G$5,Data_Long!$B$6:$B$243,$A12)) -> 2575.4372 | H12: =IF(COUNTIFS(Data_Long!$A$6:$A$243,H$5,Data_Long!$B$6:$B$243,$A12)=0,"",SUMIFS(Data_Long!$D$6:$D$243,Data_Long!$A$6:$A$243,H$5,Data_Long!$B$6:$B$243,$A12)) -> 1006.7913 | I12: =IF(COUNTIFS(Data_Long!$A$6:$A$243,I$5,Data_Long!$B$6:$B$243,$A12)=0,"",SUMIFS(Data_Long!$D$6:$D$243,Data_Long!$A$6:$A$243,I$5,Data_Long!$B$6:$B$243,$A12)) -> -593.50733 | J12: =IF(COUNTIFS(Data_Long!$A$6:$A$243,J$5,Data_Long!$B$6:$B$243,$A12)=0,"",SUMIFS(Data_Long!$D$6:$D$243,Data_Long!$A$6:$A$243,J$5,Data_Long!$B$6:$B$243,$A12)) -> 1348.185 | K12: S025, SQL derived
A13: A01 | B13: Automotive sales revenue | C13: EUR m | D13: =IF(COUNTIFS(Data_Long!$A$6:$A$243,D$5,Data_Long!$B$6:$B$243,$A13)=0,"",SUMIFS(Data_Long!$D$6:$D$243,Data_Long!$A$6:$A$243,D$5,Data_Long!$B$6:$B$243,$A13)) -> 18892 | E13: =IF(COUNTIFS(Data_Long!$A$6:$A$243,E$5,Data_Long!$B$6:$B$243,$A13)=0,"",SUMIFS(Data_Long!$D$6:$D$243,Data_Long!$A$6:$A$243,E$5,Data_Long!$B$6:$B$243,$A13)) -> 18457 | F13: =IF(COUNTIFS(Data_Long!$A$6:$A$243,F$5,Data_Long!$B$6:$B$243,$A13)=0,"",SUMIFS(Data_Long!$D$6:$D$243,Data_Long!$A$6:$A$243,F$5,Data_Long!$B$6:$B$243,$A13)) -> 17695 | G13: =IF(COUNTIFS(Data_Long!$A$6:$A$243,G$5,Data_Long!$B$6:$B$243,$A13)=0,"",SUMIFS(Data_Long!$D$6:$D$243,Data_Long!$A$6:$A$243,G$5,Data_Long!$B$6:$B$243,$A13)) -> 18743 | H13: =IF(COUNTIFS(Data_Long!$A$6:$A$243,H$5,Data_Long!$B$6:$B$243,$A13)=0,"",SUMIFS(Data_Long!$D$6:$D$243,Data_Long!$A$6:$A$243,H$5,Data_Long!$B$6:$B$243,$A13)) -> 16138 | I13: =IF(COUNTIFS(Data_Long!$A$6:$A$243,I$5,Data_Long!$B$6:$B$243,$A13)=0,"",SUMIFS(Data_Long!$D$6:$D$243,Data_Long!$A$6:$A$243,I$5,Data_Long!$B$6:$B$243,$A13)) -> 16047 | J13: =IF(COUNTIFS(Data_Long!$A$6:$A$243,J$5,Data_Long!$B$6:$B$243,$A13)=0,"",SUMIFS(Data_Long!$D$6:$D$243,Data_Long!$A$6:$A$243,J$5,Data_Long!$B$6:$B$243,$A13)) -> 15158 | K13: S002, S006, S010, S017, SQL derived
A14: A02 | B14: Automotive operating profit | C14: EUR m | D14: =IF(COUNTIFS(Data_Long!$A$6:$A$243,D$5,Data_Long!$B$6:$B$243,$A14)=0,"",SUMIFS(Data_Long!$D$6:$D$243,Data_Long!$A$6:$A$243,D$5,Data_Long!$B$6:$B$243,$A14)) -> 3653 | E14: =IF(COUNTIFS(Data_Long!$A$6:$A$243,E$5,Data_Long!$B$6:$B$243,$A14)=0,"",SUMIFS(Data_Long!$D$6:$D$243,Data_Long!$A$6:$A$243,E$5,Data_Long!$B$6:$B$243,$A14)) -> 3285 | F14: =IF(COUNTIFS(Data_Long!$A$6:$A$243,F$5,Data_Long!$B$6:$B$243,$A14)=0,"",SUMIFS(Data_Long!$D$6:$D$243,Data_Long!$A$6:$A$243,F$5,Data_Long!$B$6:$B$243,$A14)) -> 2904 | G14: =IF(COUNTIFS(Data_Long!$A$6:$A$243,G$5,Data_Long!$B$6:$B$243,$A14)=0,"",SUMIFS(Data_Long!$D$6:$D$243,Data_Long!$A$6:$A$243,G$5,Data_Long!$B$6:$B$243,$A14)) -> 2382 | H14: =IF(COUNTIFS(Data_Long!$A$6:$A$243,H$5,Data_Long!$B$6:$B$243,$A14)=0,"",SUMIFS(Data_Long!$D$6:$D$243,Data_Long!$A$6:$A$243,H$5,Data_Long!$B$6:$B$243,$A14)) -> 832 | I14: =IF(COUNTIFS(Data_Long!$A$6:$A$243,I$5,Data_Long!$B$6:$B$243,$A14)=0,"",SUMIFS(Data_Long!$D$6:$D$243,Data_Long!$A$6:$A$243,I$5,Data_Long!$B$6:$B$243,$A14)) -> -742 | J14: =IF(COUNTIFS(Data_Long!$A$6:$A$243,J$5,Data_Long!$B$6:$B$243,$A14)=0,"",SUMIFS(Data_Long!$D$6:$D$243,Data_Long!$A$6:$A$243,J$5,Data_Long!$B$6:$B$243,$A14)) -> 1208 | K14: S002, S006, S010, S017, SQL derived
A15: A03 | B15: Automotive EBITDA | C15: EUR m | D15: =IF(COUNTIFS(Data_Long!$A$6:$A$243,D$5,Data_Long!$B$6:$B$243,$A15)=0,"",SUMIFS(Data_Long!$D$6:$D$243,Data_Long!$A$6:$A$243,D$5,Data_Long!$B$6:$B$243,$A15)) -> 4829 | E15: =IF(COUNTIFS(Data_Long!$A$6:$A$243,E$5,Data_Long!$B$6:$B$243,$A15)=0,"",SUMIFS(Data_Long!$D$6:$D$243,Data_Long!$A$6:$A$243,E$5,Data_Long!$B$6:$B$243,$A15)) -> 4765 | F15: =IF(COUNTIFS(Data_Long!$A$6:$A$243,F$5,Data_Long!$B$6:$B$243,$A15)=0,"",SUMIFS(Data_Long!$D$6:$D$243,Data_Long!$A$6:$A$243,F$5,Data_Long!$B$6:$B$243,$A15)) -> 4268 | G15: =IF(COUNTIFS(Data_Long!$A$6:$A$243,G$5,Data_Long!$B$6:$B$243,$A15)=0,"",SUMIFS(Data_Long!$D$6:$D$243,Data_Long!$A$6:$A$243,G$5,Data_Long!$B$6:$B$243,$A15)) -> 4003 | H15: =IF(COUNTIFS(Data_Long!$A$6:$A$243,H$5,Data_Long!$B$6:$B$243,$A15)=0,"",SUMIFS(Data_Long!$D$6:$D$243,Data_Long!$A$6:$A$243,H$5,Data_Long!$B$6:$B$243,$A15)) -> 2588 | I15: =IF(COUNTIFS(Data_Long!$A$6:$A$243,I$5,Data_Long!$B$6:$B$243,$A15)=0,"",SUMIFS(Data_Long!$D$6:$D$243,Data_Long!$A$6:$A$243,I$5,Data_Long!$B$6:$B$243,$A15)) -> 1694 | J15: =IF(COUNTIFS(Data_Long!$A$6:$A$243,J$5,Data_Long!$B$6:$B$243,$A15)=0,"",SUMIFS(Data_Long!$D$6:$D$243,Data_Long!$A$6:$A$243,J$5,Data_Long!$B$6:$B$243,$A15)) -> 2767 | K15: S002, S006, S010, S017, SQL derived
A16: A04 | B16: Automotive EBITDA margin (published) | C16: % | D16: =IF(COUNTIFS(Data_Long!$A$6:$A$243,D$5,Data_Long!$B$6:$B$243,$A16)=0,"",SUMIFS(Data_Long!$D$6:$D$243,Data_Long!$A$6:$A$243,D$5,Data_Long!$B$6:$B$243,$A16)) -> 25.6 | E16: =IF(COUNTIFS(Data_Long!$A$6:$A$243,E$5,Data_Long!$B$6:$B$243,$A16)=0,"",SUMIFS(Data_Long!$D$6:$D$243,Data_Long!$A$6:$A$243,E$5,Data_Long!$B$6:$B$243,$A16)) | F16: =IF(COUNTIFS(Data_Long!$A$6:$A$243,F$5,Data_Long!$B$6:$B$243,$A16)=0,"",SUMIFS(Data_Long!$D$6:$D$243,Data_Long!$A$6:$A$243,F$5,Data_Long!$B$6:$B$243,$A16)) -> 24.1 | G16: =IF(COUNTIFS(Data_Long!$A$6:$A$243,G$5,Data_Long!$B$6:$B$243,$A16)=0,"",SUMIFS(Data_Long!$D$6:$D$243,Data_Long!$A$6:$A$243,G$5,Data_Long!$B$6:$B$243,$A16)) | H16: =IF(COUNTIFS(Data_Long!$A$6:$A$243,H$5,Data_Long!$B$6:$B$243,$A16)=0,"",SUMIFS(Data_Long!$D$6:$D$243,Data_Long!$A$6:$A$243,H$5,Data_Long!$B$6:$B$243,$A16)) -> 16 | I16: =IF(COUNTIFS(Data_Long!$A$6:$A$243,I$5,Data_Long!$B$6:$B$243,$A16)=0,"",SUMIFS(Data_Long!$D$6:$D$243,Data_Long!$A$6:$A$243,I$5,Data_Long!$B$6:$B$243,$A16)) | J16: =IF(COUNTIFS(Data_Long!$A$6:$A$243,J$5,Data_Long!$B$6:$B$243,$A16)=0,"",SUMIFS(Data_Long!$D$6:$D$243,Data_Long!$A$6:$A$243,J$5,Data_Long!$B$6:$B$243,$A16)) -> 18.3 | K16: S002, S006, S010, S017
A17: A05 | B17: Automotive R&D costs (total) | C17: EUR m | D17: =IF(COUNTIFS(Data_Long!$A$6:$A$243,D$5,Data_Long!$B$6:$B$243,$A17)=0,"",SUMIFS(Data_Long!$D$6:$D$243,Data_Long!$A$6:$A$243,D$5,Data_Long!$B$6:$B$243,$A17)) -> 1545 | E17: =IF(COUNTIFS(Data_Long!$A$6:$A$243,E$5,Data_Long!$B$6:$B$243,$A17)=0,"",SUMIFS(Data_Long!$D$6:$D$243,Data_Long!$A$6:$A$243,E$5,Data_Long!$B$6:$B$243,$A17)) -> 1289 | F17: =IF(COUNTIFS(Data_Long!$A$6:$A$243,F$5,Data_Long!$B$6:$B$243,$A17)=0,"",SUMIFS(Data_Long!$D$6:$D$243,Data_Long!$A$6:$A$243,F$5,Data_Long!$B$6:$B$243,$A17)) -> 1665 | G17: =IF(COUNTIFS(Data_Long!$A$6:$A$243,G$5,Data_Long!$B$6:$B$243,$A17)=0,"",SUMIFS(Data_Long!$D$6:$D$243,Data_Long!$A$6:$A$243,G$5,Data_Long!$B$6:$B$243,$A17)) -> 863 | H17: =IF(COUNTIFS(Data_Long!$A$6:$A$243,H$5,Data_Long!$B$6:$B$243,$A17)=0,"",SUMIFS(Data_Long!$D$6:$D$243,Data_Long!$A$6:$A$243,H$5,Data_Long!$B$6:$B$243,$A17)) -> 1264 | I17: =IF(COUNTIFS(Data_Long!$A$6:$A$243,I$5,Data_Long!$B$6:$B$243,$A17)=0,"",SUMIFS(Data_Long!$D$6:$D$243,Data_Long!$A$6:$A$243,I$5,Data_Long!$B$6:$B$243,$A17)) -> 1028 | J17: =IF(COUNTIFS(Data_Long!$A$6:$A$243,J$5,Data_Long!$B$6:$B$243,$A17)=0,"",SUMIFS(Data_Long!$D$6:$D$243,Data_Long!$A$6:$A$243,J$5,Data_Long!$B$6:$B$243,$A17)) -> 1116 | K17: S002, S016, SQL derived
... A44: O07 | B44: BEV share (published) | C44: % | D44: =IF(COUNTIFS(Data_Long!$A$6:$A$243,D$5,Data_Long!$B$6:$B$243,$A44)=0,"",SUMIFS(Data_Long!$D$6:$D$243,Data_Long!$A$6:$A$243,D$5,Data_Long!$B$6:$B$243,$A44)) -> 10.8 | E44: =IF(COUNTIFS(Data_Long!$A$6:$A$243,E$5,Data_Long!$B$6:$B$243,$A44)=0,"",SUMIFS(Data_Long!$D$6:$D$243,Data_Long!$A$6:$A$243,E$5,Data_Long!$B$6:$B$243,$A44)) | F44: =IF(COUNTIFS(Data_Long!$A$6:$A$243,F$5,Data_Long!$B$6:$B$243,$A44)=0,"",SUMIFS(Data_Long!$D$6:$D$243,Data_Long!$A$6:$A$243,F$5,Data_Long!$B$6:$B$243,$A44)) -> 5.9 | G44: =IF(COUNTIFS(Data_Long!$A$6:$A$243,G$5,Data_Long!$B$6:$B$243,$A44)=0,"",SUMIFS(Data_Long!$D$6:$D$243,Data_Long!$A$6:$A$243,G$5,Data_Long!$B$6:$B$243,$A44)) | H44: =IF(COUNTIFS(Data_Long!$A$6:$A$243,H$5,Data_Long!$B$6:$B$243,$A44)=0,"",SUMIFS(Data_Long!$D$6:$D$243,Data_Long!$A$6:$A$243,H$5,Data_Long!$B$6:$B$243,$A44)) -> 23.5 | I44: =IF(COUNTIFS(Data_Long!$A$6:$A$243,I$5,Data_Long!$B$6:$B$243,$A44)=0,"",SUMIFS(Data_Long!$D$6:$D$243,Data_Long!$A$6:$A$243,I$5,Data_Long!$B$6:$B$243,$A44)) | J44: =IF(COUNTIFS(Data_Long!$A$6:$A$243,J$5,Data_Long!$B$6:$B$243,$A44)=0,"",SUMIFS(Data_Long!$D$6:$D$243,Data_Long!$A$6:$A$243,J$5,Data_Long!$B$6:$B$243,$A44)) -> 19.4 | K44: S006, S010, S017
A46: Label grid: FACT = published by Porsche; DERIVED = calculated in SQL from published values (see Data_Long source_ref).
A47: var_id | B47: variable | D47: 2023-H1 | E47: 2023-H2 | F47: 2024-H1 | G47: 2024-H2 | H47: 2025-H1 | I47: 2025-H2 | J47: 2026-H1
A48: G01 | B48: Group sales revenue | D48: =IF(COUNTIFS(Data_Long!$A$6:$A$243,D$5,Data_Long!$B$6:$B$243,$A48)=0,"not published",IF(COUNTIFS(Data_Long!$A$6:$A$243,D$5,Data_Long!$B$6:$B$243,$A48,Data_Long!$F$6:$F$243,"DERIVED")>0,"DERIVED","FACT")) -> FACT | E48: =IF(COUNTIFS(Data_Long!$A$6:$A$243,E$5,Data_Long!$B$6:$B$243,$A48)=0,"not published",IF(COUNTIFS(Data_Long!$A$6:$A$243,E$5,Data_Long!$B$6:$B$243,$A48,Data_Long!$F$6:$F$243,"DERIVED")>0,"DERIVED","FACT")) -> DERIVED | F48: =IF(COUNTIFS(Data_Long!$A$6:$A$243,F$5,Data_Long!$B$6:$B$243,$A48)=0,"not published",IF(COUNTIFS(Data_Long!$A$6:$A$243,F$5,Data_Long!$B$6:$B$243,$A48,Data_Long!$F$6:$F$243,"DERIVED")>0,"DERIVED","FACT")) -> FACT | G48: =IF(COUNTIFS(Data_Long!$A$6:$A$243,G$5,Data_Long!$B$6:$B$243,$A48)=0,"not published",IF(COUNTIFS(Data_Long!$A$6:$A$243,G$5,Data_Long!$B$6:$B$243,$A48,Data_Long!$F$6:$F$243,"DERIVED")>0,"DERIVED","FACT")) -> DERIVED | H48: =IF(COUNTIFS(Data_Long!$A$6:$A$243,H$5,Data_Long!$B$6:$B$243,$A48)=0,"not published",IF(COUNTIFS(Data_Long!$A$6:$A$243,H$5,Data_Long!$B$6:$B$243,$A48,Data_Long!$F$6:$F$243,"DERIVED")>0,"DERIVED","FACT")) -> FACT | I48: =IF(COUNTIFS(Data_Long!$A$6:$A$243,I$5,Data_Long!$B$6:$B$243,$A48)=0,"not published",IF(COUNTIFS(Data_Long!$A$6:$A$243,I$5,Data_Long!$B$6:$B$243,$A48,Data_Long!$F$6:$F$243,"DERIVED")>0,"DERIVED","FACT")) -> DERIVED | J48: =IF(COUNTIFS(Data_Long!$A$6:$A$243,J$5,Data_Long!$B$6:$B$243,$A48)=0,"not published",IF(COUNTIFS(Data_Long!$A$6:$A$243,J$5,Data_Long!$B$6:$B$243,$A48,Data_Long!$F$6:$F$243,"DERIVED")>0,"DERIVED","FACT")) -> FACT
A49: G02 | B49: Cost of sales | D49: =IF(COUNTIFS(Data_Long!$A$6:$A$243,D$5,Data_Long!$B$6:$B$243,$A49)=0,"not published",IF(COUNTIFS(Data_Long!$A$6:$A$243,D$5,Data_Long!$B$6:$B$243,$A49,Data_Long!$F$6:$F$243,"DERIVED")>0,"DERIVED","FACT")) -> FACT | E49: =IF(COUNTIFS(Data_Long!$A$6:$A$243,E$5,Data_Long!$B$6:$B$243,$A49)=0,"not published",IF(COUNTIFS(Data_Long!$A$6:$A$243,E$5,Data_Long!$B$6:$B$243,$A49,Data_Long!$F$6:$F$243,"DERIVED")>0,"DERIVED","FACT")) -> DERIVED | F49: =IF(COUNTIFS(Data_Long!$A$6:$A$243,F$5,Data_Long!$B$6:$B$243,$A49)=0,"not published",IF(COUNTIFS(Data_Long!$A$6:$A$243,F$5,Data_Long!$B$6:$B$243,$A49,Data_Long!$F$6:$F$243,"DERIVED")>0,"DERIVED","FACT")) -> FACT | G49: =IF(COUNTIFS(Data_Long!$A$6:$A$243,G$5,Data_Long!$B$6:$B$243,$A49)=0,"not published",IF(COUNTIFS(Data_Long!$A$6:$A$243,G$5,Data_Long!$B$6:$B$243,$A49,Data_Long!$F$6:$F$243,"DERIVED")>0,"DERIVED","FACT")) -> DERIVED | H49: =IF(COUNTIFS(Data_Long!$A$6:$A$243,H$5,Data_Long!$B$6:$B$243,$A49)=0,"not published",IF(COUNTIFS(Data_Long!$A$6:$A$243,H$5,Data_Long!$B$6:$B$243,$A49,Data_Long!$F$6:$F$243,"DERIVED")>0,"DERIVED","FACT")) -> FACT | I49: =IF(COUNTIFS(Data_Long!$A$6:$A$243,I$5,Data_Long!$B$6:$B$243,$A49)=0,"not published",IF(COUNTIFS(Data_Long!$A$6:$A$243,I$5,Data_Long!$B$6:$B$243,$A49,Data_Long!$F$6:$F$243,"DERIVED")>0,"DERIVED","FACT")) -> DERIVED | J49: =IF(COUNTIFS(Data_Long!$A$6:$A$243,J$5,Data_Long!$B$6:$B$243,$A49)=0,"not published",IF(COUNTIFS(Data_Long!$A$6:$A$243,J$5,Data_Long!$B$6:$B$243,$A49,Data_Long!$F$6:$F$243,"DERIVED")>0,"DERIVED","FACT")) -> FACT
A50: G03 | B50: Gross profit | D50: =IF(COUNTIFS(Data_Long!$A$6:$A$243,D$5,Data_Long!$B$6:$B$243,$A50)=0,"not published",IF(COUNTIFS(Data_Long!$A$6:$A$243,D$5,Data_Long!$B$6:$B$243,$A50,Data_Long!$F$6:$F$243,"DERIVED")>0,"DERIVED","FACT")) -> FACT | E50: =IF(COUNTIFS(Data_Long!$A$6:$A$243,E$5,Data_Long!$B$6:$B$243,$A50)=0,"not published",IF(COUNTIFS(Data_Long!$A$6:$A$243,E$5,Data_Long!$B$6:$B$243,$A50,Data_Long!$F$6:$F$243,"DERIVED")>0,"DERIVED","FACT")) -> DERIVED | F50: =IF(COUNTIFS(Data_Long!$A$6:$A$243,F$5,Data_Long!$B$6:$B$243,$A50)=0,"not published",IF(COUNTIFS(Data_Long!$A$6:$A$243,F$5,Data_Long!$B$6:$B$243,$A50,Data_Long!$F$6:$F$243,"DERIVED")>0,"DERIVED","FACT")) -> FACT | G50: =IF(COUNTIFS(Data_Long!$A$6:$A$243,G$5,Data_Long!$B$6:$B$243,$A50)=0,"not published",IF(COUNTIFS(Data_Long!$A$6:$A$243,G$5,Data_Long!$B$6:$B$243,$A50,Data_Long!$F$6:$F$243,"DERIVED")>0,"DERIVED","FACT")) -> DERIVED | H50: =IF(COUNTIFS(Data_Long!$A$6:$A$243,H$5,Data_Long!$B$6:$B$243,$A50)=0,"not published",IF(COUNTIFS(Data_Long!$A$6:$A$243,H$5,Data_Long!$B$6:$B$243,$A50,Data_Long!$F$6:$F$243,"DERIVED")>0,"DERIVED","FACT")) -> FACT | I50: =IF(COUNTIFS(Data_Long!$A$6:$A$243,I$5,Data_Long!$B$6:$B$243,$A50)=0,"not published",IF(COUNTIFS(Data_Long!$A$6:$A$243,I$5,Data_Long!$B$6:$B$243,$A50,Data_Long!$F$6:$F$243,"DERIVED")>0,"DERIVED","FACT")) -> DERIVED | J50: =IF(COUNTIFS(Data_Long!$A$6:$A$243,J$5,Data_Long!$B$6:$B$243,$A50)=0,"not published",IF(COUNTIFS(Data_Long!$A$6:$A$243,J$5,Data_Long!$B$6:$B$243,$A50,Data_Long!$F$6:$F$243,"DERIVED")>0,"DERIVED","FACT")) -> FACT
A51: G04 | B51: Distribution expenses | D51: =IF(COUNTIFS(Data_Long!$A$6:$A$243,D$5,Data_Long!$B$6:$B$243,$A51)=0,"not published",IF(COUNTIFS(Data_Long!$A$6:$A$243,D$5,Data_Long!$B$6:$B$243,$A51,Data_Long!$F$6:$F$243,"DERIVED")>0,"DERIVED","FACT")) -> FACT | E51: =IF(COUNTIFS(Data_Long!$A$6:$A$243,E$5,Data_Long!$B$6:$B$243,$A51)=0,"not published",IF(COUNTIFS(Data_Long!$A$6:$A$243,E$5,Data_Long!$B$6:$B$243,$A51,Data_Long!$F$6:$F$243,"DERIVED")>0,"DERIVED","FACT")) -> DERIVED | F51: =IF(COUNTIFS(Data_Long!$A$6:$A$243,F$5,Data_Long!$B$6:$B$243,$A51)=0,"not published",IF(COUNTIFS(Data_Long!$A$6:$A$243,F$5,Data_Long!$B$6:$B$243,$A51,Data_Long!$F$6:$F$243,"DERIVED")>0,"DERIVED","FACT")) -> FACT | G51: =IF(COUNTIFS(Data_Long!$A$6:$A$243,G$5,Data_Long!$B$6:$B$243,$A51)=0,"not published",IF(COUNTIFS(Data_Long!$A$6:$A$243,G$5,Data_Long!$B$6:$B$243,$A51,Data_Long!$F$6:$F$243,"DERIVED")>0,"DERIVED","FACT")) -> DERIVED | H51: =IF(COUNTIFS(Data_Long!$A$6:$A$243,H$5,Data_Long!$B$6:$B$243,$A51)=0,"not published",IF(COUNTIFS(Data_Long!$A$6:$A$243,H$5,Data_Long!$B$6:$B$243,$A51,Data_Long!$F$6:$F$243,"DERIVED")>0,"DERIVED","FACT")) -> FACT | I51: =IF(COUNTIFS(Data_Long!$A$6:$A$243,I$5,Data_Long!$B$6:$B$243,$A51)=0,"not published",IF(COUNTIFS(Data_Long!$A$6:$A$243,I$5,Data_Long!$B$6:$B$243,$A51,Data_Long!$F$6:$F$243,"DERIVED")>0,"DERIVED","FACT")) -> DERIVED | J51: =IF(COUNTIFS(Data_Long!$A$6:$A$243,J$5,Data_Long!$B$6:$B$243,$A51)=0,"not published",IF(COUNTIFS(Data_Long!$A$6:$A$243,J$5,Data_Long!$B$6:$B$243,$A51,Data_Long!$F$6:$F$243,"DERIVED")>0,"DERIVED","FACT")) -> FACT
A52: G05 | B52: Administrative expenses | D52: =IF(COUNTIFS(Data_Long!$A$6:$A$243,D$5,Data_Long!$B$6:$B$243,$A52)=0,"not published",IF(COUNTIFS(Data_Long!$A$6:$A$243,D$5,Data_Long!$B$6:$B$243,$A52,Data_Long!$F$6:$F$243,"DERIVED")>0,"DERIVED","FACT")) -> FACT | E52: =IF(COUNTIFS(Data_Long!$A$6:$A$243,E$5,Data_Long!$B$6:$B$243,$A52)=0,"not published",IF(COUNTIFS(Data_Long!$A$6:$A$243,E$5,Data_Long!$B$6:$B$243,$A52,Data_Long!$F$6:$F$243,"DERIVED")>0,"DERIVED","FACT")) -> DERIVED | F52: =IF(COUNTIFS(Data_Long!$A$6:$A$243,F$5,Data_Long!$B$6:$B$243,$A52)=0,"not published",IF(COUNTIFS(Data_Long!$A$6:$A$243,F$5,Data_Long!$B$6:$B$243,$A52,Data_Long!$F$6:$F$243,"DERIVED")>0,"DERIVED","FACT")) -> FACT | G52: =IF(COUNTIFS(Data_Long!$A$6:$A$243,G$5,Data_Long!$B$6:$B$243,$A52)=0,"not published",IF(COUNTIFS(Data_Long!$A$6:$A$243,G$5,Data_Long!$B$6:$B$243,$A52,Data_Long!$F$6:$F$243,"DERIVED")>0,"DERIVED","FACT")) -> DERIVED | H52: =IF(COUNTIFS(Data_Long!$A$6:$A$243,H$5,Data_Long!$B$6:$B$243,$A52)=0,"not published",IF(COUNTIFS(Data_Long!$A$6:$A$243,H$5,Data_Long!$B$6:$B$243,$A52,Data_Long!$F$6:$F$243,"DERIVED")>0,"DERIVED","FACT")) -> FACT | I52: =IF(COUNTIFS(Data_Long!$A$6:$A$243,I$5,Data_Long!$B$6:$B$243,$A52)=0,"not published",IF(COUNTIFS(Data_Long!$A$6:$A$243,I$5,Data_Long!$B$6:$B$243,$A52,Data_Long!$F$6:$F$243,"DERIVED")>0,"DERIVED","FACT")) -> DERIVED | J52: =IF(COUNTIFS(Data_Long!$A$6:$A$243,J$5,Data_Long!$B$6:$B$243,$A52)=0,"not published",IF(COUNTIFS(Data_Long!$A$6:$A$243,J$5,Data_Long!$B$6:$B$243,$A52,Data_Long!$F$6:$F$243,"DERIVED")>0,"DERIVED","FACT")) -> FACT
A53: G06 | B53: Net other operating result | D53: =IF(COUNTIFS(Data_Long!$A$6:$A$243,D$5,Data_Long!$B$6:$B$243,$A53)=0,"not published",IF(COUNTIFS(Data_Long!$A$6:$A$243,D$5,Data_Long!$B$6:$B$243,$A53,Data_Long!$F$6:$F$243,"DERIVED")>0,"DERIVED","FACT")) -> FACT | E53: =IF(COUNTIFS(Data_Long!$A$6:$A$243,E$5,Data_Long!$B$6:$B$243,$A53)=0,"not published",IF(COUNTIFS(Data_Long!$A$6:$A$243,E$5,Data_Long!$B$6:$B$243,$A53,Data_Long!$F$6:$F$243,"DERIVED")>0,"DERIVED","FACT")) -> DERIVED | F53: =IF(COUNTIFS(Data_Long!$A$6:$A$243,F$5,Data_Long!$B$6:$B$243,$A53)=0,"not published",IF(COUNTIFS(Data_Long!$A$6:$A$243,F$5,Data_Long!$B$6:$B$243,$A53,Data_Long!$F$6:$F$243,"DERIVED")>0,"DERIVED","FACT")) -> FACT | G53: =IF(COUNTIFS(Data_Long!$A$6:$A$243,G$5,Data_Long!$B$6:$B$243,$A53)=0,"not published",IF(COUNTIFS(Data_Long!$A$6:$A$243,G$5,Data_Long!$B$6:$B$243,$A53,Data_Long!$F$6:$F$243,"DERIVED")>0,"DERIVED","FACT")) -> DERIVED | H53: =IF(COUNTIFS(Data_Long!$A$6:$A$243,H$5,Data_Long!$B$6:$B$243,$A53)=0,"not published",IF(COUNTIFS(Data_Long!$A$6:$A$243,H$5,Data_Long!$B$6:$B$243,$A53,Data_Long!$F$6:$F$243,"DERIVED")>0,"DERIVED","FACT")) -> FACT | I53: =IF(COUNTIFS(Data_Long!$A$6:$A$243,I$5,Data_Long!$B$6:$B$243,$A53)=0,"not published",IF(COUNTIFS(Data_Long!$A$6:$A$243,I$5,Data_Long!$B$6:$B$243,$A53,Data_Long!$F$6:$F$243,"DERIVED")>0,"DERIVED","FACT")) -> DERIVED | J53: =IF(COUNTIFS(Data_Long!$A$6:$A$243,J$5,Data_Long!$B$6:$B$243,$A53)=0,"not published",IF(COUNTIFS(Data_Long!$A$6:$A$243,J$5,Data_Long!$B$6:$B$243,$A53,Data_Long!$F$6:$F$243,"DERIVED")>0,"DERIVED","FACT")) -> FACT
A54: G07 | B54: Operating profit (EBIT), group | D54: =IF(COUNTIFS(Data_Long!$A$6:$A$243,D$5,Data_Long!$B$6:$B$243,$A54)=0,"not published",IF(COUNTIFS(Data_Long!$A$6:$A$243,D$5,Data_Long!$B$6:$B$243,$A54,Data_Long!$F$6:$F$243,"DERIVED")>0,"DERIVED","FACT")) -> FACT | E54: =IF(COUNTIFS(Data_Long!$A$6:$A$243,E$5,Data_Long!$B$6:$B$243,$A54)=0,"not published",IF(COUNTIFS(Data_Long!$A$6:$A$243,E$5,Data_Long!$B$6:$B$243,$A54,Data_Long!$F$6:$F$243,"DERIVED")>0,"DERIVED","FACT")) -> DERIVED | F54: =IF(COUNTIFS(Data_Long!$A$6:$A$243,F$5,Data_Long!$B$6:$B$243,$A54)=0,"not published",IF(COUNTIFS(Data_Long!$A$6:$A$243,F$5,Data_Long!$B$6:$B$243,$A54,Data_Long!$F$6:$F$243,"DERIVED")>0,"DERIVED","FACT")) -> FACT | G54: =IF(COUNTIFS(Data_Long!$A$6:$A$243,G$5,Data_Long!$B$6:$B$243,$A54)=0,"not published",IF(COUNTIFS(Data_Long!$A$6:$A$243,G$5,Data_Long!$B$6:$B$243,$A54,Data_Long!$F$6:$F$243,"DERIVED")>0,"DERIVED","FACT")) -> DERIVED | H54: =IF(COUNTIFS(Data_Long!$A$6:$A$243,H$5,Data_Long!$B$6:$B$243,$A54)=0,"not published",IF(COUNTIFS(Data_Long!$A$6:$A$243,H$5,Data_Long!$B$6:$B$243,$A54,Data_Long!$F$6:$F$243,"DERIVED")>0,"DERIVED","FACT")) -> FACT | I54: =IF(COUNTIFS(Data_Long!$A$6:$A$243,I$5,Data_Long!$B$6:$B$243,$A54)=0,"not published",IF(COUNTIFS(Data_Long!$A$6:$A$243,I$5,Data_Long!$B$6:$B$243,$A54,Data_Long!$F$6:$F$243,"DERIVED")>0,"DERIVED","FACT")) -> DERIVED | J54: =IF(COUNTIFS(Data_Long!$A$6:$A$243,J$5,Data_Long!$B$6:$B$243,$A54)=0,"not published",IF(COUNTIFS(Data_Long!$A$6:$A$243,J$5,Data_Long!$B$6:$B$243,$A54,Data_Long!$F$6:$F$243,"DERIVED")>0,"DERIVED","FACT")) -> FACT
A55: A01 | B55: Automotive sales revenue | D55: =IF(COUNTIFS(Data_Long!$A$6:$A$243,D$5,Data_Long!$B$6:$B$243,$A55)=0,"not published",IF(COUNTIFS(Data_Long!$A$6:$A$243,D$5,Data_Long!$B$6:$B$243,$A55,Data_Long!$F$6:$F$243,"DERIVED")>0,"DERIVED","FACT")) -> FACT | E55: =IF(COUNTIFS(Data_Long!$A$6:$A$243,E$5,Data_Long!$B$6:$B$243,$A55)=0,"not published",IF(COUNTIFS(Data_Long!$A$6:$A$243,E$5,Data_Long!$B$6:$B$243,$A55,Data_Long!$F$6:$F$243,"DERIVED")>0,"DERIVED","FACT")) -> DERIVED | F55: =IF(COUNTIFS(Data_Long!$A$6:$A$243,F$5,Data_Long!$B$6:$B$243,$A55)=0,"not published",IF(COUNTIFS(Data_Long!$A$6:$A$243,F$5,Data_Long!$B$6:$B$243,$A55,Data_Long!$F$6:$F$243,"DERIVED")>0,"DERIVED","FACT")) -> FACT | G55: =IF(COUNTIFS(Data_Long!$A$6:$A$243,G$5,Data_Long!$B$6:$B$243,$A55)=0,"not published",IF(COUNTIFS(Data_Long!$A$6:$A$243,G$5,Data_Long!$B$6:$B$243,$A55,Data_Long!$F$6:$F$243,"DERIVED")>0,"DERIVED","FACT")) -> DERIVED | H55: =IF(COUNTIFS(Data_Long!$A$6:$A$243,H$5,Data_Long!$B$6:$B$243,$A55)=0,"not published",IF(COUNTIFS(Data_Long!$A$6:$A$243,H$5,Data_Long!$B$6:$B$243,$A55,Data_Long!$F$6:$F$243,"DERIVED")>0,"DERIVED","FACT")) -> FACT | I55: =IF(COUNTIFS(Data_Long!$A$6:$A$243,I$5,Data_Long!$B$6:$B$243,$A55)=0,"not published",IF(COUNTIFS(Data_Long!$A$6:$A$243,I$5,Data_Long!$B$6:$B$243,$A55,Data_Long!$F$6:$F$243,"DERIVED")>0,"DERIVED","FACT")) -> DERIVED | J55: =IF(COUNTIFS(Data_Long!$A$6:$A$243,J$5,Data_Long!$B$6:$B$243,$A55)=0,"not published",IF(COUNTIFS(Data_Long!$A$6:$A$243,J$5,Data_Long!$B$6:$B$243,$A55,Data_Long!$F$6:$F$243,"DERIVED")>0,"DERIVED","FACT")) -> FACT
A56: A02 | B56: Automotive operating profit | D56: =IF(COUNTIFS(Data_Long!$A$6:$A$243,D$5,Data_Long!$B$6:$B$243,$A56)=0,"not published",IF(COUNTIFS(Data_Long!$A$6:$A$243,D$5,Data_Long!$B$6:$B$243,$A56,Data_Long!$F$6:$F$243,"DERIVED")>0,"DERIVED","FACT")) -> FACT | E56: =IF(COUNTIFS(Data_Long!$A$6:$A$243,E$5,Data_Long!$B$6:$B$243,$A56)=0,"not published",IF(COUNTIFS(Data_Long!$A$6:$A$243,E$5,Data_Long!$B$6:$B$243,$A56,Data_Long!$F$6:$F$243,"DERIVED")>0,"DERIVED","FACT")) -> DERIVED | F56: =IF(COUNTIFS(Data_Long!$A$6:$A$243,F$5,Data_Long!$B$6:$B$243,$A56)=0,"not published",IF(COUNTIFS(Data_Long!$A$6:$A$243,F$5,Data_Long!$B$6:$B$243,$A56,Data_Long!$F$6:$F$243,"DERIVED")>0,"DERIVED","FACT")) -> FACT | G56: =IF(COUNTIFS(Data_Long!$A$6:$A$243,G$5,Data_Long!$B$6:$B$243,$A56)=0,"not published",IF(COUNTIFS(Data_Long!$A$6:$A$243,G$5,Data_Long!$B$6:$B$243,$A56,Data_Long!$F$6:$F$243,"DERIVED")>0,"DERIVED","FACT")) -> DERIVED | H56: =IF(COUNTIFS(Data_Long!$A$6:$A$243,H$5,Data_Long!$B$6:$B$243,$A56)=0,"not published",IF(COUNTIFS(Data_Long!$A$6:$A$243,H$5,Data_Long!$B$6:$B$243,$A56,Data_Long!$F$6:$F$243,"DERIVED")>0,"DERIVED","FACT")) -> FACT | I56: =IF(COUNTIFS(Data_Long!$A$6:$A$243,I$5,Data_Long!$B$6:$B$243,$A56)=0,"not published",IF(COUNTIFS(Data_Long!$A$6:$A$243,I$5,Data_Long!$B$6:$B$243,$A56,Data_Long!$F$6:$F$243,"DERIVED")>0,"DERIVED","FACT")) -> DERIVED | J56: =IF(COUNTIFS(Data_Long!$A$6:$A$243,J$5,Data_Long!$B$6:$B$243,$A56)=0,"not published",IF(COUNTIFS(Data_Long!$A$6:$A$243,J$5,Data_Long!$B$6:$B$243,$A56,Data_Long!$F$6:$F$243,"DERIVED")>0,"DERIVED","FACT")) -> FACT
A57: A03 | B57: Automotive EBITDA | D57: =IF(COUNTIFS(Data_Long!$A$6:$A$243,D$5,Data_Long!$B$6:$B$243,$A57)=0,"not published",IF(COUNTIFS(Data_Long!$A$6:$A$243,D$5,Data_Long!$B$6:$B$243,$A57,Data_Long!$F$6:$F$243,"DERIVED")>0,"DERIVED","FACT")) -> FACT | E57: =IF(COUNTIFS(Data_Long!$A$6:$A$243,E$5,Data_Long!$B$6:$B$243,$A57)=0,"not published",IF(COUNTIFS(Data_Long!$A$6:$A$243,E$5,Data_Long!$B$6:$B$243,$A57,Data_Long!$F$6:$F$243,"DERIVED")>0,"DERIVED","FACT")) -> DERIVED | F57: =IF(COUNTIFS(Data_Long!$A$6:$A$243,F$5,Data_Long!$B$6:$B$243,$A57)=0,"not published",IF(COUNTIFS(Data_Long!$A$6:$A$243,F$5,Data_Long!$B$6:$B$243,$A57,Data_Long!$F$6:$F$243,"DERIVED")>0,"DERIVED","FACT")) -> FACT | G57: =IF(COUNTIFS(Data_Long!$A$6:$A$243,G$5,Data_Long!$B$6:$B$243,$A57)=0,"not published",IF(COUNTIFS(Data_Long!$A$6:$A$243,G$5,Data_Long!$B$6:$B$243,$A57,Data_Long!$F$6:$F$243,"DERIVED")>0,"DERIVED","FACT")) -> DERIVED | H57: =IF(COUNTIFS(Data_Long!$A$6:$A$243,H$5,Data_Long!$B$6:$B$243,$A57)=0,"not published",IF(COUNTIFS(Data_Long!$A$6:$A$243,H$5,Data_Long!$B$6:$B$243,$A57,Data_Long!$F$6:$F$243,"DERIVED")>0,"DERIVED","FACT")) -> FACT | I57: =IF(COUNTIFS(Data_Long!$A$6:$A$243,I$5,Data_Long!$B$6:$B$243,$A57)=0,"not published",IF(COUNTIFS(Data_Long!$A$6:$A$243,I$5,Data_Long!$B$6:$B$243,$A57,Data_Long!$F$6:$F$243,"DERIVED")>0,"DERIVED","FACT")) -> DERIVED | J57: =IF(COUNTIFS(Data_Long!$A$6:$A$243,J$5,Data_Long!$B$6:$B$243,$A57)=0,"not published",IF(COUNTIFS(Data_Long!$A$6:$A$243,J$5,Data_Long!$B$6:$B$243,$A57,Data_Long!$F$6:$F$243,"DERIVED")>0,"DERIVED","FACT")) -> FACT
A58: A04 | B58: Automotive EBITDA margin (published) | D58: =IF(COUNTIFS(Data_Long!$A$6:$A$243,D$5,Data_Long!$B$6:$B$243,$A58)=0,"not published",IF(COUNTIFS(Data_Long!$A$6:$A$243,D$5,Data_Long!$B$6:$B$243,$A58,Data_Long!$F$6:$F$243,"DERIVED")>0,"DERIVED","FACT")) -> FACT | E58: =IF(COUNTIFS(Data_Long!$A$6:$A$243,E$5,Data_Long!$B$6:$B$243,$A58)=0,"not published",IF(COUNTIFS(Data_Long!$A$6:$A$243,E$5,Data_Long!$B$6:$B$243,$A58,Data_Long!$F$6:$F$243,"DERIVED")>0,"DERIVED","FACT")) -> not published | F58: =IF(COUNTIFS(Data_Long!$A$6:$A$243,F$5,Data_Long!$B$6:$B$243,$A58)=0,"not published",IF(COUNTIFS(Data_Long!$A$6:$A$243,F$5,Data_Long!$B$6:$B$243,$A58,Data_Long!$F$6:$F$243,"DERIVED")>0,"DERIVED","FACT")) -> FACT | G58: =IF(COUNTIFS(Data_Long!$A$6:$A$243,G$5,Data_Long!$B$6:$B$243,$A58)=0,"not published",IF(COUNTIFS(Data_Long!$A$6:$A$243,G$5,Data_Long!$B$6:$B$243,$A58,Data_Long!$F$6:$F$243,"DERIVED")>0,"DERIVED","FACT")) -> not published | H58: =IF(COUNTIFS(Data_Long!$A$6:$A$243,H$5,Data_Long!$B$6:$B$243,$A58)=0,"not published",IF(COUNTIFS(Data_Long!$A$6:$A$243,H$5,Data_Long!$B$6:$B$243,$A58,Data_Long!$F$6:$F$243,"DERIVED")>0,"DERIVED","FACT")) -> FACT | I58: =IF(COUNTIFS(Data_Long!$A$6:$A$243,I$5,Data_Long!$B$6:$B$243,$A58)=0,"not published",IF(COUNTIFS(Data_Long!$A$6:$A$243,I$5,Data_Long!$B$6:$B$243,$A58,Data_Long!$F$6:$F$243,"DERIVED")>0,"DERIVED","FACT")) -> not published | J58: =IF(COUNTIFS(Data_Long!$A$6:$A$243,J$5,Data_Long!$B$6:$B$243,$A58)=0,"not published",IF(COUNTIFS(Data_Long!$A$6:$A$243,J$5,Data_Long!$B$6:$B$243,$A58,Data_Long!$F$6:$F$243,"DERIVED")>0,"DERIVED","FACT")) -> FACT
A59: A05 | B59: Automotive R&D costs (total) | D59: =IF(COUNTIFS(Data_Long!$A$6:$A$243,D$5,Data_Long!$B$6:$B$243,$A59)=0,"not published",IF(COUNTIFS(Data_Long!$A$6:$A$243,D$5,Data_Long!$B$6:$B$243,$A59,Data_Long!$F$6:$F$243,"DERIVED")>0,"DERIVED","FACT")) -> FACT | E59: =IF(COUNTIFS(Data_Long!$A$6:$A$243,E$5,Data_Long!$B$6:$B$243,$A59)=0,"not published",IF(COUNTIFS(Data_Long!$A$6:$A$243,E$5,Data_Long!$B$6:$B$243,$A59,Data_Long!$F$6:$F$243,"DERIVED")>0,"DERIVED","FACT")) -> DERIVED | F59: =IF(COUNTIFS(Data_Long!$A$6:$A$243,F$5,Data_Long!$B$6:$B$243,$A59)=0,"not published",IF(COUNTIFS(Data_Long!$A$6:$A$243,F$5,Data_Long!$B$6:$B$243,$A59,Data_Long!$F$6:$F$243,"DERIVED")>0,"DERIVED","FACT")) -> FACT | G59: =IF(COUNTIFS(Data_Long!$A$6:$A$243,G$5,Data_Long!$B$6:$B$243,$A59)=0,"not published",IF(COUNTIFS(Data_Long!$A$6:$A$243,G$5,Data_Long!$B$6:$B$243,$A59,Data_Long!$F$6:$F$243,"DERIVED")>0,"DERIVED","FACT")) -> DERIVED | H59: =IF(COUNTIFS(Data_Long!$A$6:$A$243,H$5,Data_Long!$B$6:$B$243,$A59)=0,"not published",IF(COUNTIFS(Data_Long!$A$6:$A$243,H$5,Data_Long!$B$6:$B$243,$A59,Data_Long!$F$6:$F$243,"DERIVED")>0,"DERIVED","FACT")) -> FACT | I59: =IF(COUNTIFS(Data_Long!$A$6:$A$243,I$5,Data_Long!$B$6:$B$243,$A59)=0,"not published",IF(COUNTIFS(Data_Long!$A$6:$A$243,I$5,Data_Long!$B$6:$B$243,$A59,Data_Long!$F$6:$F$243,"DERIVED")>0,"DERIVED","FACT")) -> DERIVED | J59: =IF(COUNTIFS(Data_Long!$A$6:$A$243,J$5,Data_Long!$B$6:$B$243,$A59)=0,"not published",IF(COUNTIFS(Data_Long!$A$6:$A$243,J$5,Data_Long!$B$6:$B$243,$A59,Data_Long!$F$6:$F$243,"DERIVED")>0,"DERIVED","FACT")) -> FACT
... A86: O07 | B86: BEV share (published) | D86: =IF(COUNTIFS(Data_Long!$A$6:$A$243,D$5,Data_Long!$B$6:$B$243,$A86)=0,"not published",IF(COUNTIFS(Data_Long!$A$6:$A$243,D$5,Data_Long!$B$6:$B$243,$A86,Data_Long!$F$6:$F$243,"DERIVED")>0,"DERIVED","FACT")) -> FACT | E86: =IF(COUNTIFS(Data_Long!$A$6:$A$243,E$5,Data_Long!$B$6:$B$243,$A86)=0,"not published",IF(COUNTIFS(Data_Long!$A$6:$A$243,E$5,Data_Long!$B$6:$B$243,$A86,Data_Long!$F$6:$F$243,"DERIVED")>0,"DERIVED","FACT")) -> not published | F86: =IF(COUNTIFS(Data_Long!$A$6:$A$243,F$5,Data_Long!$B$6:$B$243,$A86)=0,"not published",IF(COUNTIFS(Data_Long!$A$6:$A$243,F$5,Data_Long!$B$6:$B$243,$A86,Data_Long!$F$6:$F$243,"DERIVED")>0,"DERIVED","FACT")) -> FACT | G86: =IF(COUNTIFS(Data_Long!$A$6:$A$243,G$5,Data_Long!$B$6:$B$243,$A86)=0,"not published",IF(COUNTIFS(Data_Long!$A$6:$A$243,G$5,Data_Long!$B$6:$B$243,$A86,Data_Long!$F$6:$F$243,"DERIVED")>0,"DERIVED","FACT")) -> not published | H86: =IF(COUNTIFS(Data_Long!$A$6:$A$243,H$5,Data_Long!$B$6:$B$243,$A86)=0,"not published",IF(COUNTIFS(Data_Long!$A$6:$A$243,H$5,Data_Long!$B$6:$B$243,$A86,Data_Long!$F$6:$F$243,"DERIVED")>0,"DERIVED","FACT")) -> FACT | I86: =IF(COUNTIFS(Data_Long!$A$6:$A$243,I$5,Data_Long!$B$6:$B$243,$A86)=0,"not published",IF(COUNTIFS(Data_Long!$A$6:$A$243,I$5,Data_Long!$B$6:$B$243,$A86,Data_Long!$F$6:$F$243,"DERIVED")>0,"DERIVED","FACT")) -> not published | J86: =IF(COUNTIFS(Data_Long!$A$6:$A$243,J$5,Data_Long!$B$6:$B$243,$A86)=0,"not published",IF(COUNTIFS(Data_Long!$A$6:$A$243,J$5,Data_Long!$B$6:$B$243,$A86,Data_Long!$F$6:$F$243,"DERIVED")>0,"DERIVED","FACT")) -> FACT

Sheet Data_Long
A1: Data_Long - controlled import of core.fact_financial (analysis window)
A2: Source: PostgreSQL porsche_lens, core.fact_financial filtered on dim_period.in_analysis_window (2023-H1..2026-H1). Blue = imported value (do not edit). K = rows with the same period_code + var_id (must be 1); L = value read back from Data_Panel; M = |L - D| (must be 0).
A3: Rows imported: 238 | Export query: see 03_SQL/12_export_mart.sql conventions; re-import by replacing rows 6-243.
A5: period_code | B5: var_id | C5: var_name | D5: value | E5: unit_std | F5: value_label | G5: origin | H5: source_id | I5: source_ref | J5: rounding | K5: dup_count | L5: panel_readback | M5: readback_diff
A6: 2023-H1 | B6: A01 | C6: Automotive sales revenue | D6: 18892 | E6: EUR m | F6: FACT | G6: MANUAL | H6: S002 | I6: 9 (Automotive EBITDA margin table) | J6: EUR 1m | K6: =COUNTIFS($A$6:$A$243,A6,$B$6:$B$243,B6) -> 1 | L6: =IF(COUNTIF(Data_Panel!$A$6:$A$44,B6)=0,"not in panel",IF(A6=Data_Panel!$D$5,SUMIFS(Data_Panel!$D$6:$D$44,Data_Panel!$A$6:$A$44,B6),IF(A6=Data_Panel!$E$5,SUMIFS(Data_Panel!$E$6:$E$44,Data_Panel!$A$6:$A$44,B6),IF(A6=Data_Panel!$F$5,SUMIFS(Data_Panel!$F$6:$F$44,Data_Panel!$A$6:$A$44,B6),IF(A6=Data_Panel!$G$5,SUMIFS(Data_Panel!$G$6:$G$44,Data_Panel!$A$6:$A$44,B6),IF(A6=Data_Panel!$H$5,SUMIFS(Data_Panel!$H$6:$H$44,Data_Panel!$A$6:$A$44,B6),IF(A6=Data_Panel!$I$5,SUMIFS(Data_Panel!$I$6:$I$44,Data_Panel!$A$6:$A$44,B6),IF(A6=Data_Panel!$J$5,SUMIFS(Data_Panel!$J$6:$J$44,Data_Panel!$A$6:$A$44,B6),"period not in panel")))))))) -> 18892 | M6: =IF(L6="not in panel",0,ABS(N(L6)-D6)) -> 0
A7: 2023-H1 | B7: A02 | C7: Automotive operating profit | D7: 3653 | E7: EUR m | F7: FACT | G7: MANUAL | H7: S002 | I7: 9 (Automotive EBITDA margin table) | J7: EUR 1m | K7: =COUNTIFS($A$6:$A$243,A7,$B$6:$B$243,B7) -> 1 | L7: =IF(COUNTIF(Data_Panel!$A$6:$A$44,B7)=0,"not in panel",IF(A7=Data_Panel!$D$5,SUMIFS(Data_Panel!$D$6:$D$44,Data_Panel!$A$6:$A$44,B7),IF(A7=Data_Panel!$E$5,SUMIFS(Data_Panel!$E$6:$E$44,Data_Panel!$A$6:$A$44,B7),IF(A7=Data_Panel!$F$5,SUMIFS(Data_Panel!$F$6:$F$44,Data_Panel!$A$6:$A$44,B7),IF(A7=Data_Panel!$G$5,SUMIFS(Data_Panel!$G$6:$G$44,Data_Panel!$A$6:$A$44,B7),IF(A7=Data_Panel!$H$5,SUMIFS(Data_Panel!$H$6:$H$44,Data_Panel!$A$6:$A$44,B7),IF(A7=Data_Panel!$I$5,SUMIFS(Data_Panel!$I$6:$I$44,Data_Panel!$A$6:$A$44,B7),IF(A7=Data_Panel!$J$5,SUMIFS(Data_Panel!$J$6:$J$44,Data_Panel!$A$6:$A$44,B7),"period not in panel")))))))) -> 3653 | M7: =IF(L7="not in panel",0,ABS(N(L7)-D7)) -> 0
A8: 2023-H1 | B8: A03 | C8: Automotive EBITDA | D8: 4829 | E8: EUR m | F8: FACT | G8: MANUAL | H8: S002 | I8: 9 (Automotive EBITDA margin table) | J8: EUR 1m | K8: =COUNTIFS($A$6:$A$243,A8,$B$6:$B$243,B8) -> 1 | L8: =IF(COUNTIF(Data_Panel!$A$6:$A$44,B8)=0,"not in panel",IF(A8=Data_Panel!$D$5,SUMIFS(Data_Panel!$D$6:$D$44,Data_Panel!$A$6:$A$44,B8),IF(A8=Data_Panel!$E$5,SUMIFS(Data_Panel!$E$6:$E$44,Data_Panel!$A$6:$A$44,B8),IF(A8=Data_Panel!$F$5,SUMIFS(Data_Panel!$F$6:$F$44,Data_Panel!$A$6:$A$44,B8),IF(A8=Data_Panel!$G$5,SUMIFS(Data_Panel!$G$6:$G$44,Data_Panel!$A$6:$A$44,B8),IF(A8=Data_Panel!$H$5,SUMIFS(Data_Panel!$H$6:$H$44,Data_Panel!$A$6:$A$44,B8),IF(A8=Data_Panel!$I$5,SUMIFS(Data_Panel!$I$6:$I$44,Data_Panel!$A$6:$A$44,B8),IF(A8=Data_Panel!$J$5,SUMIFS(Data_Panel!$J$6:$J$44,Data_Panel!$A$6:$A$44,B8),"period not in panel")))))))) -> 4829 | M8: =IF(L8="not in panel",0,ABS(N(L8)-D8)) -> 0
A9: 2023-H1 | B9: A04 | C9: Automotive EBITDA margin | D9: 25.6 | E9: % | F9: FACT | G9: MANUAL | H9: S002 | I9: 9 (Automotive EBITDA margin table) | J9: 0.1pp | K9: =COUNTIFS($A$6:$A$243,A9,$B$6:$B$243,B9) -> 1 | L9: =IF(COUNTIF(Data_Panel!$A$6:$A$44,B9)=0,"not in panel",IF(A9=Data_Panel!$D$5,SUMIFS(Data_Panel!$D$6:$D$44,Data_Panel!$A$6:$A$44,B9),IF(A9=Data_Panel!$E$5,SUMIFS(Data_Panel!$E$6:$E$44,Data_Panel!$A$6:$A$44,B9),IF(A9=Data_Panel!$F$5,SUMIFS(Data_Panel!$F$6:$F$44,Data_Panel!$A$6:$A$44,B9),IF(A9=Data_Panel!$G$5,SUMIFS(Data_Panel!$G$6:$G$44,Data_Panel!$A$6:$A$44,B9),IF(A9=Data_Panel!$H$5,SUMIFS(Data_Panel!$H$6:$H$44,Data_Panel!$A$6:$A$44,B9),IF(A9=Data_Panel!$I$5,SUMIFS(Data_Panel!$I$6:$I$44,Data_Panel!$A$6:$A$44,B9),IF(A9=Data_Panel!$J$5,SUMIFS(Data_Panel!$J$6:$J$44,Data_Panel!$A$6:$A$44,B9),"period not in panel")))))))) -> 25.6 | M9: =IF(L9="not in panel",0,ABS(N(L9)-D9)) -> 0
A10: 2023-H1 | B10: A05 | C10: Automotive R&D costs (total) | D10: 1545 | E10: EUR m | F10: FACT | G10: MANUAL | H10: S002 | I10: 29 (Note 3) | J10: EUR 1m | K10: =COUNTIFS($A$6:$A$243,A10,$B$6:$B$243,B10) -> 1 | L10: =IF(COUNTIF(Data_Panel!$A$6:$A$44,B10)=0,"not in panel",IF(A10=Data_Panel!$D$5,SUMIFS(Data_Panel!$D$6:$D$44,Data_Panel!$A$6:$A$44,B10),IF(A10=Data_Panel!$E$5,SUMIFS(Data_Panel!$E$6:$E$44,Data_Panel!$A$6:$A$44,B10),IF(A10=Data_Panel!$F$5,SUMIFS(Data_Panel!$F$6:$F$44,Data_Panel!$A$6:$A$44,B10),IF(A10=Data_Panel!$G$5,SUMIFS(Data_Panel!$G$6:$G$44,Data_Panel!$A$6:$A$44,B10),IF(A10=Data_Panel!$H$5,SUMIFS(Data_Panel!$H$6:$H$44,Data_Panel!$A$6:$A$44,B10),IF(A10=Data_Panel!$I$5,SUMIFS(Data_Panel!$I$6:$I$44,Data_Panel!$A$6:$A$44,B10),IF(A10=Data_Panel!$J$5,SUMIFS(Data_Panel!$J$6:$J$44,Data_Panel!$A$6:$A$44,B10),"period not in panel")))))))) -> 1545 | M10: =IF(L10="not in panel",0,ABS(N(L10)-D10)) -> 0
A11: 2023-H1 | B11: A06 | C11: Automotive capitalised development costs | D11: 1201 | E11: EUR m | F11: FACT | G11: MANUAL | H11: S002 | I11: 29 (Note 3) | J11: EUR 1m | K11: =COUNTIFS($A$6:$A$243,A11,$B$6:$B$243,B11) -> 1 | L11: =IF(COUNTIF(Data_Panel!$A$6:$A$44,B11)=0,"not in panel",IF(A11=Data_Panel!$D$5,SUMIFS(Data_Panel!$D$6:$D$44,Data_Panel!$A$6:$A$44,B11),IF(A11=Data_Panel!$E$5,SUMIFS(Data_Panel!$E$6:$E$44,Data_Panel!$A$6:$A$44,B11),IF(A11=Data_Panel!$F$5,SUMIFS(Data_Panel!$F$6:$F$44,Data_Panel!$A$6:$A$44,B11),IF(A11=Data_Panel!$G$5,SUMIFS(Data_Panel!$G$6:$G$44,Data_Panel!$A$6:$A$44,B11),IF(A11=Data_Panel!$H$5,SUMIFS(Data_Panel!$H$6:$H$44,Data_Panel!$A$6:$A$44,B11),IF(A11=Data_Panel!$I$5,SUMIFS(Data_Panel!$I$6:$I$44,Data_Panel!$A$6:$A$44,B11),IF(A11=Data_Panel!$J$5,SUMIFS(Data_Panel!$J$6:$J$44,Data_Panel!$A$6:$A$44,B11),"period not in panel")))))))) -> 1201 | M11: =IF(L11="not in panel",0,ABS(N(L11)-D11)) -> 0
A12: 2023-H1 | B12: A07 | C12: Capitalisation rate | D12: 77.7 | E12: % | F12: FACT | G12: MANUAL | H12: S002 | I12: 29 (Note 3) | J12: 0.1pp | K12: =COUNTIFS($A$6:$A$243,A12,$B$6:$B$243,B12) -> 1 | L12: =IF(COUNTIF(Data_Panel!$A$6:$A$44,B12)=0,"not in panel",IF(A12=Data_Panel!$D$5,SUMIFS(Data_Panel!$D$6:$D$44,Data_Panel!$A$6:$A$44,B12),IF(A12=Data_Panel!$E$5,SUMIFS(Data_Panel!$E$6:$E$44,Data_Panel!$A$6:$A$44,B12),IF(A12=Data_Panel!$F$5,SUMIFS(Data_Panel!$F$6:$F$44,Data_Panel!$A$6:$A$44,B12),IF(A12=Data_Panel!$G$5,SUMIFS(Data_Panel!$G$6:$G$44,Data_Panel!$A$6:$A$44,B12),IF(A12=Data_Panel!$H$5,SUMIFS(Data_Panel!$H$6:$H$44,Data_Panel!$A$6:$A$44,B12),IF(A12=Data_Panel!$I$5,SUMIFS(Data_Panel!$I$6:$I$44,Data_Panel!$A$6:$A$44,B12),IF(A12=Data_Panel!$J$5,SUMIFS(Data_Panel!$J$6:$J$44,Data_Panel!$A$6:$A$44,B12),"period not in panel")))))))) -> 77.7 | M12: =IF(L12="not in panel",0,ABS(N(L12)-D12)) -> 0
A13: 2023-H1 | B13: A08 | C13: Expensed automotive R&D | D13: 343 | E13: EUR m | F13: FACT | G13: MANUAL | H13: S005 | I13: 28 (prior-year column) | J13: EUR 1m | K13: =COUNTIFS($A$6:$A$243,A13,$B$6:$B$243,B13) -> 1 | L13: =IF(COUNTIF(Data_Panel!$A$6:$A$44,B13)=0,"not in panel",IF(A13=Data_Panel!$D$5,SUMIFS(Data_Panel!$D$6:$D$44,Data_Panel!$A$6:$A$44,B13),IF(A13=Data_Panel!$E$5,SUMIFS(Data_Panel!$E$6:$E$44,Data_Panel!$A$6:$A$44,B13),IF(A13=Data_Panel!$F$5,SUMIFS(Data_Panel!$F$6:$F$44,Data_Panel!$A$6:$A$44,B13),IF(A13=Data_Panel!$G$5,SUMIFS(Data_Panel!$G$6:$G$44,Data_Panel!$A$6:$A$44,B13),IF(A13=Data_Panel!$H$5,SUMIFS(Data_Panel!$H$6:$H$44,Data_Panel!$A$6:$A$44,B13),IF(A13=Data_Panel!$I$5,SUMIFS(Data_Panel!$I$6:$I$44,Data_Panel!$A$6:$A$44,B13),IF(A13=Data_Panel!$J$5,SUMIFS(Data_Panel!$J$6:$J$44,Data_Panel!$A$6:$A$44,B13),"period not in panel")))))))) -> 343 | M13: =IF(L13="not in panel",0,ABS(N(L13)-D13)) -> 0
A14: 2023-H1 | B14: A09 | C14: Amortisation of capitalised R&D | D14: 427 | E14: EUR m | F14: FACT | G14: MANUAL | H14: S002 | I14: 29 (Note 3) | J14: EUR 1m | K14: =COUNTIFS($A$6:$A$243,A14,$B$6:$B$243,B14) -> 1 | L14: =IF(COUNTIF(Data_Panel!$A$6:$A$44,B14)=0,"not in panel",IF(A14=Data_Panel!$D$5,SUMIFS(Data_Panel!$D$6:$D$44,Data_Panel!$A$6:$A$44,B14),IF(A14=Data_Panel!$E$5,SUMIFS(Data_Panel!$E$6:$E$44,Data_Panel!$A$6:$A$44,B14),IF(A14=Data_Panel!$F$5,SUMIFS(Data_Panel!$F$6:$F$44,Data_Panel!$A$6:$A$44,B14),IF(A14=Data_Panel!$G$5,SUMIFS(Data_Panel!$G$6:$G$44,Data_Panel!$A$6:$A$44,B14),IF(A14=Data_Panel!$H$5,SUMIFS(Data_Panel!$H$6:$H$44,Data_Panel!$A$6:$A$44,B14),IF(A14=Data_Panel!$I$5,SUMIFS(Data_Panel!$I$6:$I$44,Data_Panel!$A$6:$A$44,B14),IF(A14=Data_Panel!$J$5,SUMIFS(Data_Panel!$J$6:$J$44,Data_Panel!$A$6:$A$44,B14),"period not in panel")))))))) -> 427 | M14: =IF(L14="not in panel",0,ABS(N(L14)-D14)) -> 0
A15: 2023-H1 | B15: A10 | C15: Automotive capex | D15: 866 | E15: EUR m | F15: FACT | G15: MANUAL | H15: S002 | I15: 3 (key figures) | J15: EUR 1m | K15: =COUNTIFS($A$6:$A$243,A15,$B$6:$B$243,B15) -> 1 | L15: =IF(COUNTIF(Data_Panel!$A$6:$A$44,B15)=0,"not in panel",IF(A15=Data_Panel!$D$5,SUMIFS(Data_Panel!$D$6:$D$44,Data_Panel!$A$6:$A$44,B15),IF(A15=Data_Panel!$E$5,SUMIFS(Data_Panel!$E$6:$E$44,Data_Panel!$A$6:$A$44,B15),IF(A15=Data_Panel!$F$5,SUMIFS(Data_Panel!$F$6:$F$44,Data_Panel!$A$6:$A$44,B15),IF(A15=Data_Panel!$G$5,SUMIFS(Data_Panel!$G$6:$G$44,Data_Panel!$A$6:$A$44,B15),IF(A15=Data_Panel!$H$5,SUMIFS(Data_Panel!$H$6:$H$44,Data_Panel!$A$6:$A$44,B15),IF(A15=Data_Panel!$I$5,SUMIFS(Data_Panel!$I$6:$I$44,Data_Panel!$A$6:$A$44,B15),IF(A15=Data_Panel!$J$5,SUMIFS(Data_Panel!$J$6:$J$44,Data_Panel!$A$6:$A$44,B15),"period not in panel")))))))) -> 866 | M15: =IF(L15="not in panel",0,ABS(N(L15)-D15)) -> 0
A16: 2023-H1 | B16: A11 | C16: Automotive depreciation on capex | D16: 749 | E16: EUR m | F16: DERIVED | G16: SQL_DERIVED | I16: A12 - A09: S002 9 (Automotive EBITDA margin table) minus S002 29 (Note 3) | J16: derived from EUR 1m inputs | K16: =COUNTIFS($A$6:$A$243,A16,$B$6:$B$243,B16) -> 1 | L16: =IF(COUNTIF(Data_Panel!$A$6:$A$44,B16)=0,"not in panel",IF(A16=Data_Panel!$D$5,SUMIFS(Data_Panel!$D$6:$D$44,Data_Panel!$A$6:$A$44,B16),IF(A16=Data_Panel!$E$5,SUMIFS(Data_Panel!$E$6:$E$44,Data_Panel!$A$6:$A$44,B16),IF(A16=Data_Panel!$F$5,SUMIFS(Data_Panel!$F$6:$F$44,Data_Panel!$A$6:$A$44,B16),IF(A16=Data_Panel!$G$5,SUMIFS(Data_Panel!$G$6:$G$44,Data_Panel!$A$6:$A$44,B16),IF(A16=Data_Panel!$H$5,SUMIFS(Data_Panel!$H$6:$H$44,Data_Panel!$A$6:$A$44,B16),IF(A16=Data_Panel!$I$5,SUMIFS(Data_Panel!$I$6:$I$44,Data_Panel!$A$6:$A$44,B16),IF(A16=Data_Panel!$J$5,SUMIFS(Data_Panel!$J$6:$J$44,Data_Panel!$A$6:$A$44,B16),"period not in panel")))))))) -> 749 | M16: =IF(L16="not in panel",0,ABS(N(L16)-D16)) -> 0
A17: 2023-H1 | B17: A12 | C17: Automotive total D&A | D17: 1176 | E17: EUR m | F17: FACT | G17: MANUAL | H17: S002 | I17: 9 (Automotive EBITDA margin table) | J17: EUR 1m | K17: =COUNTIFS($A$6:$A$243,A17,$B$6:$B$243,B17) -> 1 | L17: =IF(COUNTIF(Data_Panel!$A$6:$A$44,B17)=0,"not in panel",IF(A17=Data_Panel!$D$5,SUMIFS(Data_Panel!$D$6:$D$44,Data_Panel!$A$6:$A$44,B17),IF(A17=Data_Panel!$E$5,SUMIFS(Data_Panel!$E$6:$E$44,Data_Panel!$A$6:$A$44,B17),IF(A17=Data_Panel!$F$5,SUMIFS(Data_Panel!$F$6:$F$44,Data_Panel!$A$6:$A$44,B17),IF(A17=Data_Panel!$G$5,SUMIFS(Data_Panel!$G$6:$G$44,Data_Panel!$A$6:$A$44,B17),IF(A17=Data_Panel!$H$5,SUMIFS(Data_Panel!$H$6:$H$44,Data_Panel!$A$6:$A$44,B17),IF(A17=Data_Panel!$I$5,SUMIFS(Data_Panel!$I$6:$I$44,Data_Panel!$A$6:$A$44,B17),IF(A17=Data_Panel!$J$5,SUMIFS(Data_Panel!$J$6:$J$44,Data_Panel!$A$6:$A$44,B17),"period not in panel")))))))) -> 1176 | M17: =IF(L17="not in panel",0,ABS(N(L17)-D17)) -> 0
A18: 2023-H1 | B18: A13 | C18: Automotive net cash flow | D18: 2216.9809 | E18: EUR m | F18: FACT | G18: FACTSHEET | H18: S025 | I18: 02 - Automotive CF AA24 | J18: exact (EUR, converted to EUR m) | K18: =COUNTIFS($A$6:$A$243,A18,$B$6:$B$243,B18) -> 1 | L18: =IF(COUNTIF(Data_Panel!$A$6:$A$44,B18)=0,"not in panel",IF(A18=Data_Panel!$D$5,SUMIFS(Data_Panel!$D$6:$D$44,Data_Panel!$A$6:$A$44,B18),IF(A18=Data_Panel!$E$5,SUMIFS(Data_Panel!$E$6:$E$44,Data_Panel!$A$6:$A$44,B18),IF(A18=Data_Panel!$F$5,SUMIFS(Data_Panel!$F$6:$F$44,Data_Panel!$A$6:$A$44,B18),IF(A18=Data_Panel!$G$5,SUMIFS(Data_Panel!$G$6:$G$44,Data_Panel!$A$6:$A$44,B18),IF(A18=Data_Panel!$H$5,SUMIFS(Data_Panel!$H$6:$H$44,Data_Panel!$A$6:$A$44,B18),IF(A18=Data_Panel!$I$5,SUMIFS(Data_Panel!$I$6:$I$44,Data_Panel!$A$6:$A$44,B18),IF(A18=Data_Panel!$J$5,SUMIFS(Data_Panel!$J$6:$J$44,Data_Panel!$A$6:$A$44,B18),"period not in panel")))))))) -> 2216.9809 | M18: =IF(L18="not in panel",0,ABS(N(L18)-D18)) -> 0
A19: 2023-H1 | B19: A13a | C19: Automotive cash flows from operating activities | D19: 4391.6849 | E19: EUR m | F19: FACT | G19: FACTSHEET | H19: S025 | I19: 02 - Automotive CF AA22 | J19: exact (EUR, converted to EUR m) | K19: =COUNTIFS($A$6:$A$243,A19,$B$6:$B$243,B19) -> 1 | L19: =IF(COUNTIF(Data_Panel!$A$6:$A$44,B19)=0,"not in panel",IF(A19=Data_Panel!$D$5,SUMIFS(Data_Panel!$D$6:$D$44,Data_Panel!$A$6:$A$44,B19),IF(A19=Data_Panel!$E$5,SUMIFS(Data_Panel!$E$6:$E$44,Data_Panel!$A$6:$A$44,B19),IF(A19=Data_Panel!$F$5,SUMIFS(Data_Panel!$F$6:$F$44,Data_Panel!$A$6:$A$44,B19),IF(A19=Data_Panel!$G$5,SUMIFS(Data_Panel!$G$6:$G$44,Data_Panel!$A$6:$A$44,B19),IF(A19=Data_Panel!$H$5,SUMIFS(Data_Panel!$H$6:$H$44,Data_Panel!$A$6:$A$44,B19),IF(A19=Data_Panel!$I$5,SUMIFS(Data_Panel!$I$6:$I$44,Data_Panel!$A$6:$A$44,B19),IF(A19=Data_Panel!$J$5,SUMIFS(Data_Panel!$J$6:$J$44,Data_Panel!$A$6:$A$44,B19),"period not in panel")))))))) -> 4391.6849 | M19: =IF(L19="not in panel",0,ABS(N(L19)-D19)) -> 0
A20: 2023-H1 | B20: A13b | C20: Automotive investing activities of current operations | D20: -2174.704 | E20: EUR m | F20: FACT | G20: FACTSHEET | H20: S025 | I20: 02 - Automotive CF AA23 | J20: exact (EUR, converted to EUR m) | K20: =COUNTIFS($A$6:$A$243,A20,$B$6:$B$243,B20) -> 1 | L20: =IF(COUNTIF(Data_Panel!$A$6:$A$44,B20)=0,"not in panel",IF(A20=Data_Panel!$D$5,SUMIFS(Data_Panel!$D$6:$D$44,Data_Panel!$A$6:$A$44,B20),IF(A20=Data_Panel!$E$5,SUMIFS(Data_Panel!$E$6:$E$44,Data_Panel!$A$6:$A$44,B20),IF(A20=Data_Panel!$F$5,SUMIFS(Data_Panel!$F$6:$F$44,Data_Panel!$A$6:$A$44,B20),IF(A20=Data_Panel!$G$5,SUMIFS(Data_Panel!$G$6:$G$44,Data_Panel!$A$6:$A$44,B20),IF(A20=Data_Panel!$H$5,SUMIFS(Data_Panel!$H$6:$H$44,Data_Panel!$A$6:$A$44,B20),IF(A20=Data_Panel!$I$5,SUMIFS(Data_Panel!$I$6:$I$44,Data_Panel!$A$6:$A$44,B20),IF(A20=Data_Panel!$J$5,SUMIFS(Data_Panel!$J$6:$J$44,Data_Panel!$A$6:$A$44,B20),"period not in panel")))))))) -> -2174.704 | M20: =IF(L20="not in panel",0,ABS(N(L20)-D20)) -> 0
A21: 2023-H1 | B21: A14 | C21: Automotive net liquidity | D21: 6432.0234 | E21: EUR m | F21: FACT | G21: FACTSHEET | H21: S025 | I21: 02 - Automotive CF AA25 | J21: exact (EUR, converted to EUR m) | K21: =COUNTIFS($A$6:$A$243,A21,$B$6:$B$243,B21) -> 1 | L21: =IF(COUNTIF(Data_Panel!$A$6:$A$44,B21)=0,"not in panel",IF(A21=Data_Panel!$D$5,SUMIFS(Data_Panel!$D$6:$D$44,Data_Panel!$A$6:$A$44,B21),IF(A21=Data_Panel!$E$5,SUMIFS(Data_Panel!$E$6:$E$44,Data_Panel!$A$6:$A$44,B21),IF(A21=Data_Panel!$F$5,SUMIFS(Data_Panel!$F$6:$F$44,Data_Panel!$A$6:$A$44,B21),IF(A21=Data_Panel!$G$5,SUMIFS(Data_Panel!$G$6:$G$44,Data_Panel!$A$6:$A$44,B21),IF(A21=Data_Panel!$H$5,SUMIFS(Data_Panel!$H$6:$H$44,Data_Panel!$A$6:$A$44,B21),IF(A21=Data_Panel!$I$5,SUMIFS(Data_Panel!$I$6:$I$44,Data_Panel!$A$6:$A$44,B21),IF(A21=Data_Panel!$J$5,SUMIFS(Data_Panel!$J$6:$J$44,Data_Panel!$A$6:$A$44,B21),"period not in panel")))))))) -> 6432.0234 | M21: =IF(L21="not in panel",0,ABS(N(L21)-D21)) -> 0
A22: 2023-H1 | B22: F01 | C22: Financial Services sales revenue | D22: 1652 | E22: EUR m | F22: FACT | G22: MANUAL | H22: S002 | I22: 38 (segment reporting) | J22: EUR 1m | K22: =COUNTIFS($A$6:$A$243,A22,$B$6:$B$243,B22) -> 1 | L22: =IF(COUNTIF(Data_Panel!$A$6:$A$44,B22)=0,"not in panel",IF(A22=Data_Panel!$D$5,SUMIFS(Data_Panel!$D$6:$D$44,Data_Panel!$A$6:$A$44,B22),IF(A22=Data_Panel!$E$5,SUMIFS(Data_Panel!$E$6:$E$44,Data_Panel!$A$6:$A$44,B22),IF(A22=Data_Panel!$F$5,SUMIFS(Data_Panel!$F$6:$F$44,Data_Panel!$A$6:$A$44,B22),IF(A22=Data_Panel!$G$5,SUMIFS(Data_Panel!$G$6:$G$44,Data_Panel!$A$6:$A$44,B22),IF(A22=Data_Panel!$H$5,SUMIFS(Data_Panel!$H$6:$H$44,Data_Panel!$A$6:$A$44,B22),IF(A22=Data_Panel!$I$5,SUMIFS(Data_Panel!$I$6:$I$44,Data_Panel!$A$6:$A$44,B22),IF(A22=Data_Panel!$J$5,SUMIFS(Data_Panel!$J$6:$J$44,Data_Panel!$A$6:$A$44,B22),"period not in panel")))))))) -> 1652 | M22: =IF(L22="not in panel",0,ABS(N(L22)-D22)) -> 0
A23: 2023-H1 | B23: F02 | C23: Financial Services operating profit | D23: 174 | E23: EUR m | F23: FACT | G23: MANUAL | H23: S002 | I23: 38 (segment reporting) | J23: EUR 1m | K23: =COUNTIFS($A$6:$A$243,A23,$B$6:$B$243,B23) -> 1 | L23: =IF(COUNTIF(Data_Panel!$A$6:$A$44,B23)=0,"not in panel",IF(A23=Data_Panel!$D$5,SUMIFS(Data_Panel!$D$6:$D$44,Data_Panel!$A$6:$A$44,B23),IF(A23=Data_Panel!$E$5,SUMIFS(Data_Panel!$E$6:$E$44,Data_Panel!$A$6:$A$44,B23),IF(A23=Data_Panel!$F$5,SUMIFS(Data_Panel!$F$6:$F$44,Data_Panel!$A$6:$A$44,B23),IF(A23=Data_Panel!$G$5,SUMIFS(Data_Panel!$G$6:$G$44,Data_Panel!$A$6:$A$44,B23),IF(A23=Data_Panel!$H$5,SUMIFS(Data_Panel!$H$6:$H$44,Data_Panel!$A$6:$A$44,B23),IF(A23=Data_Panel!$I$5,SUMIFS(Data_Panel!$I$6:$I$44,Data_Panel!$A$6:$A$44,B23),IF(A23=Data_Panel!$J$5,SUMIFS(Data_Panel!$J$6:$J$44,Data_Panel!$A$6:$A$44,B23),"period not in panel")))))))) -> 174 | M23: =IF(L23="not in panel",0,ABS(N(L23)-D23)) -> 0
A24: 2023-H1 | B24: G01 | C24: Group sales revenue | D24: 20430.923 | E24: EUR m | F24: FACT | G24: FACTSHEET | H24: S025 | I24: 01 - Group EBIT AM29 | J24: exact (EUR, converted to EUR m) | K24: =COUNTIFS($A$6:$A$243,A24,$B$6:$B$243,B24) -> 1 | L24: =IF(COUNTIF(Data_Panel!$A$6:$A$44,B24)=0,"not in panel",IF(A24=Data_Panel!$D$5,SUMIFS(Data_Panel!$D$6:$D$44,Data_Panel!$A$6:$A$44,B24),IF(A24=Data_Panel!$E$5,SUMIFS(Data_Panel!$E$6:$E$44,Data_Panel!$A$6:$A$44,B24),IF(A24=Data_Panel!$F$5,SUMIFS(Data_Panel!$F$6:$F$44,Data_Panel!$A$6:$A$44,B24),IF(A24=Data_Panel!$G$5,SUMIFS(Data_Panel!$G$6:$G$44,Data_Panel!$A$6:$A$44,B24),IF(A24=Data_Panel!$H$5,SUMIFS(Data_Panel!$H$6:$H$44,Data_Panel!$A$6:$A$44,B24),IF(A24=Data_Panel!$I$5,SUMIFS(Data_Panel!$I$6:$I$44,Data_Panel!$A$6:$A$44,B24),IF(A24=Data_Panel!$J$5,SUMIFS(Data_Panel!$J$6:$J$44,Data_Panel!$A$6:$A$44,B24),"period not in panel")))))))) -> 20430.923 | M24: =IF(L24="not in panel",0,ABS(N(L24)-D24)) -> 0
A25: 2023-H1 | B25: G02 | C25: Cost of sales | D25: -14521.515 | E25: EUR m | F25: FACT | G25: FACTSHEET | H25: S025 | I25: 01 - Group EBIT AM30 | J25: exact (EUR, converted to EUR m) | K25: =COUNTIFS($A$6:$A$243,A25,$B$6:$B$243,B25) -> 1 | L25: =IF(COUNTIF(Data_Panel!$A$6:$A$44,B25)=0,"not in panel",IF(A25=Data_Panel!$D$5,SUMIFS(Data_Panel!$D$6:$D$44,Data_Panel!$A$6:$A$44,B25),IF(A25=Data_Panel!$E$5,SUMIFS(Data_Panel!$E$6:$E$44,Data_Panel!$A$6:$A$44,B25),IF(A25=Data_Panel!$F$5,SUMIFS(Data_Panel!$F$6:$F$44,Data_Panel!$A$6:$A$44,B25),IF(A25=Data_Panel!$G$5,SUMIFS(Data_Panel!$G$6:$G$44,Data_Panel!$A$6:$A$44,B25),IF(A25=Data_Panel!$H$5,SUMIFS(Data_Panel!$H$6:$H$44,Data_Panel!$A$6:$A$44,B25),IF(A25=Data_Panel!$I$5,SUMIFS(Data_Panel!$I$6:$I$44,Data_Panel!$A$6:$A$44,B25),IF(A25=Data_Panel!$J$5,SUMIFS(Data_Panel!$J$6:$J$44,Data_Panel!$A$6:$A$44,B25),"period not in panel")))))))) -> -14521.515 | M25: =IF(L25="not in panel",0,ABS(N(L25)-D25)) -> 0
A26: 2023-H1 | B26: G03 | C26: Gross profit | D26: 5909.4077 | E26: EUR m | F26: FACT | G26: FACTSHEET | H26: S025 | I26: 01 - Group EBIT AM31 | J26: exact (EUR, converted to EUR m) | K26: =COUNTIFS($A$6:$A$243,A26,$B$6:$B$243,B26) -> 1 | L26: =IF(COUNTIF(Data_Panel!$A$6:$A$44,B26)=0,"not in panel",IF(A26=Data_Panel!$D$5,SUMIFS(Data_Panel!$D$6:$D$44,Data_Panel!$A$6:$A$44,B26),IF(A26=Data_Panel!$E$5,SUMIFS(Data_Panel!$E$6:$E$44,Data_Panel!$A$6:$A$44,B26),IF(A26=Data_Panel!$F$5,SUMIFS(Data_Panel!$F$6:$F$44,Data_Panel!$A$6:$A$44,B26),IF(A26=Data_Panel!$G$5,SUMIFS(Data_Panel!$G$6:$G$44,Data_Panel!$A$6:$A$44,B26),IF(A26=Data_Panel!$H$5,SUMIFS(Data_Panel!$H$6:$H$44,Data_Panel!$A$6:$A$44,B26),IF(A26=Data_Panel!$I$5,SUMIFS(Data_Panel!$I$6:$I$44,Data_Panel!$A$6:$A$44,B26),IF(A26=Data_Panel!$J$5,SUMIFS(Data_Panel!$J$6:$J$44,Data_Panel!$A$6:$A$44,B26),"period not in panel")))))))) -> 5909.4077 | M26: =IF(L26="not in panel",0,ABS(N(L26)-D26)) -> 0
A27: 2023-H1 | B27: G04 | C27: Distribution expenses | D27: -1292.9307 | E27: EUR m | F27: FACT | G27: FACTSHEET | H27: S025 | I27: 01 - Group EBIT AM32 | J27: exact (EUR, converted to EUR m) | K27: =COUNTIFS($A$6:$A$243,A27,$B$6:$B$243,B27) -> 1 | L27: =IF(COUNTIF(Data_Panel!$A$6:$A$44,B27)=0,"not in panel",IF(A27=Data_Panel!$D$5,SUMIFS(Data_Panel!$D$6:$D$44,Data_Panel!$A$6:$A$44,B27),IF(A27=Data_Panel!$E$5,SUMIFS(Data_Panel!$E$6:$E$44,Data_Panel!$A$6:$A$44,B27),IF(A27=Data_Panel!$F$5,SUMIFS(Data_Panel!$F$6:$F$44,Data_Panel!$A$6:$A$44,B27),IF(A27=Data_Panel!$G$5,SUMIFS(Data_Panel!$G$6:$G$44,Data_Panel!$A$6:$A$44,B27),IF(A27=Data_Panel!$H$5,SUMIFS(Data_Panel!$H$6:$H$44,Data_Panel!$A$6:$A$44,B27),IF(A27=Data_Panel!$I$5,SUMIFS(Data_Panel!$I$6:$I$44,Data_Panel!$A$6:$A$44,B27),IF(A27=Data_Panel!$J$5,SUMIFS(Data_Panel!$J$6:$J$44,Data_Panel!$A$6:$A$44,B27),"period not in panel")))))))) -> -1292.9307 | M27: =IF(L27="not in panel",0,ABS(N(L27)-D27)) -> 0
A28: 2023-H1 | B28: G05 | C28: Administrative expenses | D28: -875.09562 | E28: EUR m | F28: FACT | G28: FACTSHEET | H28: S025 | I28: 01 - Group EBIT AM33 | J28: exact (EUR, converted to EUR m) | K28: =COUNTIFS($A$6:$A$243,A28,$B$6:$B$243,B28) -> 1 | L28: =IF(COUNTIF(Data_Panel!$A$6:$A$44,B28)=0,"not in panel",IF(A28=Data_Panel!$D$5,SUMIFS(Data_Panel!$D$6:$D$44,Data_Panel!$A$6:$A$44,B28),IF(A28=Data_Panel!$E$5,SUMIFS(Data_Panel!$E$6:$E$44,Data_Panel!$A$6:$A$44,B28),IF(A28=Data_Panel!$F$5,SUMIFS(Data_Panel!$F$6:$F$44,Data_Panel!$A$6:$A$44,B28),IF(A28=Data_Panel!$G$5,SUMIFS(Data_Panel!$G$6:$G$44,Data_Panel!$A$6:$A$44,B28),IF(A28=Data_Panel!$H$5,SUMIFS(Data_Panel!$H$6:$H$44,Data_Panel!$A$6:$A$44,B28),IF(A28=Data_Panel!$I$5,SUMIFS(Data_Panel!$I$6:$I$44,Data_Panel!$A$6:$A$44,B28),IF(A28=Data_Panel!$J$5,SUMIFS(Data_Panel!$J$6:$J$44,Data_Panel!$A$6:$A$44,B28),"period not in panel")))))))) -> -875.09562 | M28: =IF(L28="not in panel",0,ABS(N(L28)-D28)) -> 0
... A37: 2023-H1 | B37: X05 | C37: Impairment losses included in automotive D&A | D37: 0 | E37: EUR m | F37: FACT | G37: MANUAL | H37: S002 | I37: 38-39 (segment reporting) | J37: EUR 1m | K37: =COUNTIFS($A$6:$A$243,A37,$B$6:$B$243,B37) -> 1 | L37: =IF(COUNTIF(Data_Panel!$A$6:$A$44,B37)=0,"not in panel",IF(A37=Data_Panel!$D$5,SUMIFS(Data_Panel!$D$6:$D$44,Data_Panel!$A$6:$A$44,B37),IF(A37=Data_Panel!$E$5,SUMIFS(Data_Panel!$E$6:$E$44,Data_Panel!$A$6:$A$44,B37),IF(A37=Data_Panel!$F$5,SUMIFS(Data_Panel!$F$6:$F$44,Data_Panel!$A$6:$A$44,B37),IF(A37=Data_Panel!$G$5,SUMIFS(Data_Panel!$G$6:$G$44,Data_Panel!$A$6:$A$44,B37),IF(A37=Data_Panel!$H$5,SUMIFS(Data_Panel!$H$6:$H$44,Data_Panel!$A$6:$A$44,B37),IF(A37=Data_Panel!$I$5,SUMIFS(Data_Panel!$I$6:$I$44,Data_Panel!$A$6:$A$44,B37),IF(A37=Data_Panel!$J$5,SUMIFS(Data_Panel!$J$6:$J$44,Data_Panel!$A$6:$A$44,B37),"period not in panel")))))))) -> 0 | M37: =IF(L37="not in panel",0,ABS(N(L37)-D37)) -> 0
A38: 2023-H2 | B38: A01 | C38: Automotive sales revenue | D38: 18457 | E38: EUR m | F38: DERIVED | G38: SQL_DERIVED | I38: FY - H1: 2023-FY (S026) minus 2023-H1 (S002) | J38: derived; inputs rounded: FY EUR 1m / H1 EUR 1m | K38: =COUNTIFS($A$6:$A$243,A38,$B$6:$B$243,B38) -> 1 | L38: =IF(COUNTIF(Data_Panel!$A$6:$A$44,B38)=0,"not in panel",IF(A38=Data_Panel!$D$5,SUMIFS(Data_Panel!$D$6:$D$44,Data_Panel!$A$6:$A$44,B38),IF(A38=Data_Panel!$E$5,SUMIFS(Data_Panel!$E$6:$E$44,Data_Panel!$A$6:$A$44,B38),IF(A38=Data_Panel!$F$5,SUMIFS(Data_Panel!$F$6:$F$44,Data_Panel!$A$6:$A$44,B38),IF(A38=Data_Panel!$G$5,SUMIFS(Data_Panel!$G$6:$G$44,Data_Panel!$A$6:$A$44,B38),IF(A38=Data_Panel!$H$5,SUMIFS(Data_Panel!$H$6:$H$44,Data_Panel!$A$6:$A$44,B38),IF(A38=Data_Panel!$I$5,SUMIFS(Data_Panel!$I$6:$I$44,Data_Panel!$A$6:$A$44,B38),IF(A38=Data_Panel!$J$5,SUMIFS(Data_Panel!$J$6:$J$44,Data_Panel!$A$6:$A$44,B38),"period not in panel")))))))) -> 18457 | M38: =IF(L38="not in panel",0,ABS(N(L38)-D38)) -> 0
A39: 2023-H2 | B39: A02 | C39: Automotive operating profit | D39: 3285 | E39: EUR m | F39: DERIVED | G39: SQL_DERIVED | I39: FY - H1: 2023-FY (S026) minus 2023-H1 (S002) | J39: derived; inputs rounded: FY EUR 1m / H1 EUR 1m | K39: =COUNTIFS($A$6:$A$243,A39,$B$6:$B$243,B39) -> 1 | L39: =IF(COUNTIF(Data_Panel!$A$6:$A$44,B39)=0,"not in panel",IF(A39=Data_Panel!$D$5,SUMIFS(Data_Panel!$D$6:$D$44,Data_Panel!$A$6:$A$44,B39),IF(A39=Data_Panel!$E$5,SUMIFS(Data_Panel!$E$6:$E$44,Data_Panel!$A$6:$A$44,B39),IF(A39=Data_Panel!$F$5,SUMIFS(Data_Panel!$F$6:$F$44,Data_Panel!$A$6:$A$44,B39),IF(A39=Data_Panel!$G$5,SUMIFS(Data_Panel!$G$6:$G$44,Data_Panel!$A$6:$A$44,B39),IF(A39=Data_Panel!$H$5,SUMIFS(Data_Panel!$H$6:$H$44,Data_Panel!$A$6:$A$44,B39),IF(A39=Data_Panel!$I$5,SUMIFS(Data_Panel!$I$6:$I$44,Data_Panel!$A$6:$A$44,B39),IF(A39=Data_Panel!$J$5,SUMIFS(Data_Panel!$J$6:$J$44,Data_Panel!$A$6:$A$44,B39),"period not in panel")))))))) -> 3285 | M39: =IF(L39="not in panel",0,ABS(N(L39)-D39)) -> 0
A40: 2023-H2 | B40: A03 | C40: Automotive EBITDA | D40: 4765 | E40: EUR m | F40: DERIVED | G40: SQL_DERIVED | I40: FY - H1: 2023-FY (S026) minus 2023-H1 (S002) | J40: derived; inputs rounded: FY EUR 1m / H1 EUR 1m | K40: =COUNTIFS($A$6:$A$243,A40,$B$6:$B$243,B40) -> 1 | L40: =IF(COUNTIF(Data_Panel!$A$6:$A$44,B40)=0,"not in panel",IF(A40=Data_Panel!$D$5,SUMIFS(Data_Panel!$D$6:$D$44,Data_Panel!$A$6:$A$44,B40),IF(A40=Data_Panel!$E$5,SUMIFS(Data_Panel!$E$6:$E$44,Data_Panel!$A$6:$A$44,B40),IF(A40=Data_Panel!$F$5,SUMIFS(Data_Panel!$F$6:$F$44,Data_Panel!$A$6:$A$44,B40),IF(A40=Data_Panel!$G$5,SUMIFS(Data_Panel!$G$6:$G$44,Data_Panel!$A$6:$A$44,B40),IF(A40=Data_Panel!$H$5,SUMIFS(Data_Panel!$H$6:$H$44,Data_Panel!$A$6:$A$44,B40),IF(A40=Data_Panel!$I$5,SUMIFS(Data_Panel!$I$6:$I$44,Data_Panel!$A$6:$A$44,B40),IF(A40=Data_Panel!$J$5,SUMIFS(Data_Panel!$J$6:$J$44,Data_Panel!$A$6:$A$44,B40),"period not in panel")))))))) -> 4765 | M40: =IF(L40="not in panel",0,ABS(N(L40)-D40)) -> 0
A41: 2023-H2 | B41: A05 | C41: Automotive R&D costs (total) | D41: 1289 | E41: EUR m | F41: DERIVED | G41: SQL_DERIVED | I41: FY - H1: 2023-FY (S011) minus 2023-H1 (S002) | J41: derived; inputs rounded: FY EUR 1m / H1 EUR 1m | K41: =COUNTIFS($A$6:$A$243,A41,$B$6:$B$243,B41) -> 1 | L41: =IF(COUNTIF(Data_Panel!$A$6:$A$44,B41)=0,"not in panel",IF(A41=Data_Panel!$D$5,SUMIFS(Data_Panel!$D$6:$D$44,Data_Panel!$A$6:$A$44,B41),IF(A41=Data_Panel!$E$5,SUMIFS(Data_Panel!$E$6:$E$44,Data_Panel!$A$6:$A$44,B41),IF(A41=Data_Panel!$F$5,SUMIFS(Data_Panel!$F$6:$F$44,Data_Panel!$A$6:$A$44,B41),IF(A41=Data_Panel!$G$5,SUMIFS(Data_Panel!$G$6:$G$44,Data_Panel!$A$6:$A$44,B41),IF(A41=Data_Panel!$H$5,SUMIFS(Data_Panel!$H$6:$H$44,Data_Panel!$A$6:$A$44,B41),IF(A41=Data_Panel!$I$5,SUMIFS(Data_Panel!$I$6:$I$44,Data_Panel!$A$6:$A$44,B41),IF(A41=Data_Panel!$J$5,SUMIFS(Data_Panel!$J$6:$J$44,Data_Panel!$A$6:$A$44,B41),"period not in panel")))))))) -> 1289 | M41: =IF(L41="not in panel",0,ABS(N(L41)-D41)) -> 0
A42: 2023-H2 | B42: A06 | C42: Automotive capitalised development costs | D42: 880 | E42: EUR m | F42: DERIVED | G42: SQL_DERIVED | I42: FY - H1: 2023-FY (S011) minus 2023-H1 (S002) | J42: derived; inputs rounded: FY EUR 1m / H1 EUR 1m | K42: =COUNTIFS($A$6:$A$243,A42,$B$6:$B$243,B42) -> 1 | L42: =IF(COUNTIF(Data_Panel!$A$6:$A$44,B42)=0,"not in panel",IF(A42=Data_Panel!$D$5,SUMIFS(Data_Panel!$D$6:$D$44,Data_Panel!$A$6:$A$44,B42),IF(A42=Data_Panel!$E$5,SUMIFS(Data_Panel!$E$6:$E$44,Data_Panel!$A$6:$A$44,B42),IF(A42=Data_Panel!$F$5,SUMIFS(Data_Panel!$F$6:$F$44,Data_Panel!$A$6:$A$44,B42),IF(A42=Data_Panel!$G$5,SUMIFS(Data_Panel!$G$6:$G$44,Data_Panel!$A$6:$A$44,B42),IF(A42=Data_Panel!$H$5,SUMIFS(Data_Panel!$H$6:$H$44,Data_Panel!$A$6:$A$44,B42),IF(A42=Data_Panel!$I$5,SUMIFS(Data_Panel!$I$6:$I$44,Data_Panel!$A$6:$A$44,B42),IF(A42=Data_Panel!$J$5,SUMIFS(Data_Panel!$J$6:$J$44,Data_Panel!$A$6:$A$44,B42),"period not in panel")))))))) -> 880 | M42: =IF(L42="not in panel",0,ABS(N(L42)-D42)) -> 0
A43: 2023-H2 | B43: A08 | C43: Expensed automotive R&D | D43: 410 | E43: EUR m | F43: DERIVED | G43: SQL_DERIVED | I43: FY - H1: 2023-FY (S011) minus 2023-H1 (S005) | J43: derived; inputs rounded: FY EUR 1m / H1 EUR 1m | K43: =COUNTIFS($A$6:$A$243,A43,$B$6:$B$243,B43) -> 1 | L43: =IF(COUNTIF(Data_Panel!$A$6:$A$44,B43)=0,"not in panel",IF(A43=Data_Panel!$D$5,SUMIFS(Data_Panel!$D$6:$D$44,Data_Panel!$A$6:$A$44,B43),IF(A43=Data_Panel!$E$5,SUMIFS(Data_Panel!$E$6:$E$44,Data_Panel!$A$6:$A$44,B43),IF(A43=Data_Panel!$F$5,SUMIFS(Data_Panel!$F$6:$F$44,Data_Panel!$A$6:$A$44,B43),IF(A43=Data_Panel!$G$5,SUMIFS(Data_Panel!$G$6:$G$44,Data_Panel!$A$6:$A$44,B43),IF(A43=Data_Panel!$H$5,SUMIFS(Data_Panel!$H$6:$H$44,Data_Panel!$A$6:$A$44,B43),IF(A43=Data_Panel!$I$5,SUMIFS(Data_Panel!$I$6:$I$44,Data_Panel!$A$6:$A$44,B43),IF(A43=Data_Panel!$J$5,SUMIFS(Data_Panel!$J$6:$J$44,Data_Panel!$A$6:$A$44,B43),"period not in panel")))))))) -> 410 | M43: =IF(L43="not in panel",0,ABS(N(L43)-D43)) -> 0
A44: 2023-H2 | B44: A09 | C44: Amortisation of capitalised R&D | D44: 533 | E44: EUR m | F44: DERIVED | G44: SQL_DERIVED | I44: FY - H1: 2023-FY (S011) minus 2023-H1 (S002) | J44: derived; inputs rounded: FY EUR 1m / H1 EUR 1m | K44: =COUNTIFS($A$6:$A$243,A44,$B$6:$B$243,B44) -> 1 | L44: =IF(COUNTIF(Data_Panel!$A$6:$A$44,B44)=0,"not in panel",IF(A44=Data_Panel!$D$5,SUMIFS(Data_Panel!$D$6:$D$44,Data_Panel!$A$6:$A$44,B44),IF(A44=Data_Panel!$E$5,SUMIFS(Data_Panel!$E$6:$E$44,Data_Panel!$A$6:$A$44,B44),IF(A44=Data_Panel!$F$5,SUMIFS(Data_Panel!$F$6:$F$44,Data_Panel!$A$6:$A$44,B44),IF(A44=Data_Panel!$G$5,SUMIFS(Data_Panel!$G$6:$G$44,Data_Panel!$A$6:$A$44,B44),IF(A44=Data_Panel!$H$5,SUMIFS(Data_Panel!$H$6:$H$44,Data_Panel!$A$6:$A$44,B44),IF(A44=Data_Panel!$I$5,SUMIFS(Data_Panel!$I$6:$I$44,Data_Panel!$A$6:$A$44,B44),IF(A44=Data_Panel!$J$5,SUMIFS(Data_Panel!$J$6:$J$44,Data_Panel!$A$6:$A$44,B44),"period not in panel")))))))) -> 533 | M44: =IF(L44="not in panel",0,ABS(N(L44)-D44)) -> 0
A45: 2023-H2 | B45: A10 | C45: Automotive capex | D45: 1098 | E45: EUR m | F45: DERIVED | G45: SQL_DERIVED | I45: FY - H1: 2023-FY (S011) minus 2023-H1 (S002) | J45: derived; inputs rounded: FY EUR 1m / H1 EUR 1m | K45: =COUNTIFS($A$6:$A$243,A45,$B$6:$B$243,B45) -> 1 | L45: =IF(COUNTIF(Data_Panel!$A$6:$A$44,B45)=0,"not in panel",IF(A45=Data_Panel!$D$5,SUMIFS(Data_Panel!$D$6:$D$44,Data_Panel!$A$6:$A$44,B45),IF(A45=Data_Panel!$E$5,SUMIFS(Data_Panel!$E$6:$E$44,Data_Panel!$A$6:$A$44,B45),IF(A45=Data_Panel!$F$5,SUMIFS(Data_Panel!$F$6:$F$44,Data_Panel!$A$6:$A$44,B45),IF(A45=Data_Panel!$G$5,SUMIFS(Data_Panel!$G$6:$G$44,Data_Panel!$A$6:$A$44,B45),IF(A45=Data_Panel!$H$5,SUMIFS(Data_Panel!$H$6:$H$44,Data_Panel!$A$6:$A$44,B45),IF(A45=Data_Panel!$I$5,SUMIFS(Data_Panel!$I$6:$I$44,Data_Panel!$A$6:$A$44,B45),IF(A45=Data_Panel!$J$5,SUMIFS(Data_Panel!$J$6:$J$44,Data_Panel!$A$6:$A$44,B45),"period not in panel")))))))) -> 1098 | M45: =IF(L45="not in panel",0,ABS(N(L45)-D45)) -> 0
A46: 2023-H2 | B46: A11 | C46: Automotive depreciation on capex | D46: 947 | E46: EUR m | F46: DERIVED | G46: SQL_DERIVED | I46: FY - H1: 2023-FY (S011) minus 2023-H1 (SQL derived) | J46: derived; inputs rounded: FY EUR 1m / H1 derived from EUR 1m inputs | K46: =COUNTIFS($A$6:$A$243,A46,$B$6:$B$243,B46) -> 1 | L46: =IF(COUNTIF(Data_Panel!$A$6:$A$44,B46)=0,"not in panel",IF(A46=Data_Panel!$D$5,SUMIFS(Data_Panel!$D$6:$D$44,Data_Panel!$A$6:$A$44,B46),IF(A46=Data_Panel!$E$5,SUMIFS(Data_Panel!$E$6:$E$44,Data_Panel!$A$6:$A$44,B46),IF(A46=Data_Panel!$F$5,SUMIFS(Data_Panel!$F$6:$F$44,Data_Panel!$A$6:$A$44,B46),IF(A46=Data_Panel!$G$5,SUMIFS(Data_Panel!$G$6:$G$44,Data_Panel!$A$6:$A$44,B46),IF(A46=Data_Panel!$H$5,SUMIFS(Data_Panel!$H$6:$H$44,Data_Panel!$A$6:$A$44,B46),IF(A46=Data_Panel!$I$5,SUMIFS(Data_Panel!$I$6:$I$44,Data_Panel!$A$6:$A$44,B46),IF(A46=Data_Panel!$J$5,SUMIFS(Data_Panel!$J$6:$J$44,Data_Panel!$A$6:$A$44,B46),"period not in panel")))))))) -> 947 | M46: =IF(L46="not in panel",0,ABS(N(L46)-D46)) -> 0
A47: 2023-H2 | B47: A12 | C47: Automotive total D&A | D47: 1480 | E47: EUR m | F47: DERIVED | G47: SQL_DERIVED | I47: FY - H1: 2023-FY (S011) minus 2023-H1 (S002) | J47: derived; inputs rounded: FY EUR 1m / H1 EUR 1m | K47: =COUNTIFS($A$6:$A$243,A47,$B$6:$B$243,B47) -> 1 | L47: =IF(COUNTIF(Data_Panel!$A$6:$A$44,B47)=0,"not in panel",IF(A47=Data_Panel!$D$5,SUMIFS(Data_Panel!$D$6:$D$44,Data_Panel!$A$6:$A$44,B47),IF(A47=Data_Panel!$E$5,SUMIFS(Data_Panel!$E$6:$E$44,Data_Panel!$A$6:$A$44,B47),IF(A47=Data_Panel!$F$5,SUMIFS(Data_Panel!$F$6:$F$44,Data_Panel!$A$6:$A$44,B47),IF(A47=Data_Panel!$G$5,SUMIFS(Data_Panel!$G$6:$G$44,Data_Panel!$A$6:$A$44,B47),IF(A47=Data_Panel!$H$5,SUMIFS(Data_Panel!$H$6:$H$44,Data_Panel!$A$6:$A$44,B47),IF(A47=Data_Panel!$I$5,SUMIFS(Data_Panel!$I$6:$I$44,Data_Panel!$A$6:$A$44,B47),IF(A47=Data_Panel!$J$5,SUMIFS(Data_Panel!$J$6:$J$44,Data_Panel!$A$6:$A$44,B47),"period not in panel")))))))) -> 1480 | M47: =IF(L47="not in panel",0,ABS(N(L47)-D47)) -> 0
A48: 2023-H2 | B48: A13 | C48: Automotive net cash flow | D48: 1756.4485 | E48: EUR m | F48: DERIVED | G48: SQL_DERIVED | I48: FY - H1: 2023-FY (S025) minus 2023-H1 (S025) | J48: derived; inputs rounded: FY exact (EUR, converted to EUR m) / H1 exact (EUR, converted to EUR m) | K48: =COUNTIFS($A$6:$A$243,A48,$B$6:$B$243,B48) -> 1 | L48: =IF(COUNTIF(Data_Panel!$A$6:$A$44,B48)=0,"not in panel",IF(A48=Data_Panel!$D$5,SUMIFS(Data_Panel!$D$6:$D$44,Data_Panel!$A$6:$A$44,B48),IF(A48=Data_Panel!$E$5,SUMIFS(Data_Panel!$E$6:$E$44,Data_Panel!$A$6:$A$44,B48),IF(A48=Data_Panel!$F$5,SUMIFS(Data_Panel!$F$6:$F$44,Data_Panel!$A$6:$A$44,B48),IF(A48=Data_Panel!$G$5,SUMIFS(Data_Panel!$G$6:$G$44,Data_Panel!$A$6:$A$44,B48),IF(A48=Data_Panel!$H$5,SUMIFS(Data_Panel!$H$6:$H$44,Data_Panel!$A$6:$A$44,B48),IF(A48=Data_Panel!$I$5,SUMIFS(Data_Panel!$I$6:$I$44,Data_Panel!$A$6:$A$44,B48),IF(A48=Data_Panel!$J$5,SUMIFS(Data_Panel!$J$6:$J$44,Data_Panel!$A$6:$A$44,B48),"period not in panel")))))))) -> 1756.4485 | M48: =IF(L48="not in panel",0,ABS(N(L48)-D48)) -> 0
A49: 2023-H2 | B49: A13a | C49: Automotive cash flows from operating activities | D49: 3864.0398 | E49: EUR m | F49: DERIVED | G49: SQL_DERIVED | I49: FY - H1: 2023-FY (S025) minus 2023-H1 (S025) | J49: derived; inputs rounded: FY exact (EUR, converted to EUR m) / H1 exact (EUR, converted to EUR m) | K49: =COUNTIFS($A$6:$A$243,A49,$B$6:$B$243,B49) -> 1 | L49: =IF(COUNTIF(Data_Panel!$A$6:$A$44,B49)=0,"not in panel",IF(A49=Data_Panel!$D$5,SUMIFS(Data_Panel!$D$6:$D$44,Data_Panel!$A$6:$A$44,B49),IF(A49=Data_Panel!$E$5,SUMIFS(Data_Panel!$E$6:$E$44,Data_Panel!$A$6:$A$44,B49),IF(A49=Data_Panel!$F$5,SUMIFS(Data_Panel!$F$6:$F$44,Data_Panel!$A$6:$A$44,B49),IF(A49=Data_Panel!$G$5,SUMIFS(Data_Panel!$G$6:$G$44,Data_Panel!$A$6:$A$44,B49),IF(A49=Data_Panel!$H$5,SUMIFS(Data_Panel!$H$6:$H$44,Data_Panel!$A$6:$A$44,B49),IF(A49=Data_Panel!$I$5,SUMIFS(Data_Panel!$I$6:$I$44,Data_Panel!$A$6:$A$44,B49),IF(A49=Data_Panel!$J$5,SUMIFS(Data_Panel!$J$6:$J$44,Data_Panel!$A$6:$A$44,B49),"period not in panel")))))))) -> 3864.0398 | M49: =IF(L49="not in panel",0,ABS(N(L49)-D49)) -> 0
... A63: 2023-H2 | B63: X05 | C63: Impairment losses included in automotive D&A | D63: 2 | E63: EUR m | F63: DERIVED | G63: SQL_DERIVED | I63: FY - H1: 2023-FY (S004) minus 2023-H1 (S002) | J63: derived; inputs rounded: FY EUR 1m / H1 EUR 1m | K63: =COUNTIFS($A$6:$A$243,A63,$B$6:$B$243,B63) -> 1 | L63: =IF(COUNTIF(Data_Panel!$A$6:$A$44,B63)=0,"not in panel",IF(A63=Data_Panel!$D$5,SUMIFS(Data_Panel!$D$6:$D$44,Data_Panel!$A$6:$A$44,B63),IF(A63=Data_Panel!$E$5,SUMIFS(Data_Panel!$E$6:$E$44,Data_Panel!$A$6:$A$44,B63),IF(A63=Data_Panel!$F$5,SUMIFS(Data_Panel!$F$6:$F$44,Data_Panel!$A$6:$A$44,B63),IF(A63=Data_Panel!$G$5,SUMIFS(Data_Panel!$G$6:$G$44,Data_Panel!$A$6:$A$44,B63),IF(A63=Data_Panel!$H$5,SUMIFS(Data_Panel!$H$6:$H$44,Data_Panel!$A$6:$A$44,B63),IF(A63=Data_Panel!$I$5,SUMIFS(Data_Panel!$I$6:$I$44,Data_Panel!$A$6:$A$44,B63),IF(A63=Data_Panel!$J$5,SUMIFS(Data_Panel!$J$6:$J$44,Data_Panel!$A$6:$A$44,B63),"period not in panel")))))))) -> 2 | M63: =IF(L63="not in panel",0,ABS(N(L63)-D63)) -> 0
A64: 2024-H1 | B64: A01 | C64: Automotive sales revenue | D64: 17695 | E64: EUR m | F64: FACT | G64: MANUAL | H64: S006 | I64: 10 (Automotive EBITDA margin table) | J64: EUR 1m | K64: =COUNTIFS($A$6:$A$243,A64,$B$6:$B$243,B64) -> 1 | L64: =IF(COUNTIF(Data_Panel!$A$6:$A$44,B64)=0,"not in panel",IF(A64=Data_Panel!$D$5,SUMIFS(Data_Panel!$D$6:$D$44,Data_Panel!$A$6:$A$44,B64),IF(A64=Data_Panel!$E$5,SUMIFS(Data_Panel!$E$6:$E$44,Data_Panel!$A$6:$A$44,B64),IF(A64=Data_Panel!$F$5,SUMIFS(Data_Panel!$F$6:$F$44,Data_Panel!$A$6:$A$44,B64),IF(A64=Data_Panel!$G$5,SUMIFS(Data_Panel!$G$6:$G$44,Data_Panel!$A$6:$A$44,B64),IF(A64=Data_Panel!$H$5,SUMIFS(Data_Panel!$H$6:$H$44,Data_Panel!$A$6:$A$44,B64),IF(A64=Data_Panel!$I$5,SUMIFS(Data_Panel!$I$6:$I$44,Data_Panel!$A$6:$A$44,B64),IF(A64=Data_Panel!$J$5,SUMIFS(Data_Panel!$J$6:$J$44,Data_Panel!$A$6:$A$44,B64),"period not in panel")))))))) -> 17695 | M64: =IF(L64="not in panel",0,ABS(N(L64)-D64)) -> 0
A65: 2024-H1 | B65: A02 | C65: Automotive operating profit | D65: 2904 | E65: EUR m | F65: FACT | G65: MANUAL | H65: S006 | I65: 10 (Automotive EBITDA margin table) | J65: EUR 1m | K65: =COUNTIFS($A$6:$A$243,A65,$B$6:$B$243,B65) -> 1 | L65: =IF(COUNTIF(Data_Panel!$A$6:$A$44,B65)=0,"not in panel",IF(A65=Data_Panel!$D$5,SUMIFS(Data_Panel!$D$6:$D$44,Data_Panel!$A$6:$A$44,B65),IF(A65=Data_Panel!$E$5,SUMIFS(Data_Panel!$E$6:$E$44,Data_Panel!$A$6:$A$44,B65),IF(A65=Data_Panel!$F$5,SUMIFS(Data_Panel!$F$6:$F$44,Data_Panel!$A$6:$A$44,B65),IF(A65=Data_Panel!$G$5,SUMIFS(Data_Panel!$G$6:$G$44,Data_Panel!$A$6:$A$44,B65),IF(A65=Data_Panel!$H$5,SUMIFS(Data_Panel!$H$6:$H$44,Data_Panel!$A$6:$A$44,B65),IF(A65=Data_Panel!$I$5,SUMIFS(Data_Panel!$I$6:$I$44,Data_Panel!$A$6:$A$44,B65),IF(A65=Data_Panel!$J$5,SUMIFS(Data_Panel!$J$6:$J$44,Data_Panel!$A$6:$A$44,B65),"period not in panel")))))))) -> 2904 | M65: =IF(L65="not in panel",0,ABS(N(L65)-D65)) -> 0
A66: 2024-H1 | B66: A03 | C66: Automotive EBITDA | D66: 4268 | E66: EUR m | F66: FACT | G66: MANUAL | H66: S006 | I66: 10 (Automotive EBITDA margin table) | J66: EUR 1m | K66: =COUNTIFS($A$6:$A$243,A66,$B$6:$B$243,B66) -> 1 | L66: =IF(COUNTIF(Data_Panel!$A$6:$A$44,B66)=0,"not in panel",IF(A66=Data_Panel!$D$5,SUMIFS(Data_Panel!$D$6:$D$44,Data_Panel!$A$6:$A$44,B66),IF(A66=Data_Panel!$E$5,SUMIFS(Data_Panel!$E$6:$E$44,Data_Panel!$A$6:$A$44,B66),IF(A66=Data_Panel!$F$5,SUMIFS(Data_Panel!$F$6:$F$44,Data_Panel!$A$6:$A$44,B66),IF(A66=Data_Panel!$G$5,SUMIFS(Data_Panel!$G$6:$G$44,Data_Panel!$A$6:$A$44,B66),IF(A66=Data_Panel!$H$5,SUMIFS(Data_Panel!$H$6:$H$44,Data_Panel!$A$6:$A$44,B66),IF(A66=Data_Panel!$I$5,SUMIFS(Data_Panel!$I$6:$I$44,Data_Panel!$A$6:$A$44,B66),IF(A66=Data_Panel!$J$5,SUMIFS(Data_Panel!$J$6:$J$44,Data_Panel!$A$6:$A$44,B66),"period not in panel")))))))) -> 4268 | M66: =IF(L66="not in panel",0,ABS(N(L66)-D66)) -> 0
A67: 2024-H1 | B67: A04 | C67: Automotive EBITDA margin | D67: 24.1 | E67: % | F67: FACT | G67: MANUAL | H67: S006 | I67: 10 (Automotive EBITDA margin table) | J67: 0.1pp | K67: =COUNTIFS($A$6:$A$243,A67,$B$6:$B$243,B67) -> 1 | L67: =IF(COUNTIF(Data_Panel!$A$6:$A$44,B67)=0,"not in panel",IF(A67=Data_Panel!$D$5,SUMIFS(Data_Panel!$D$6:$D$44,Data_Panel!$A$6:$A$44,B67),IF(A67=Data_Panel!$E$5,SUMIFS(Data_Panel!$E$6:$E$44,Data_Panel!$A$6:$A$44,B67),IF(A67=Data_Panel!$F$5,SUMIFS(Data_Panel!$F$6:$F$44,Data_Panel!$A$6:$A$44,B67),IF(A67=Data_Panel!$G$5,SUMIFS(Data_Panel!$G$6:$G$44,Data_Panel!$A$6:$A$44,B67),IF(A67=Data_Panel!$H$5,SUMIFS(Data_Panel!$H$6:$H$44,Data_Panel!$A$6:$A$44,B67),IF(A67=Data_Panel!$I$5,SUMIFS(Data_Panel!$I$6:$I$44,Data_Panel!$A$6:$A$44,B67),IF(A67=Data_Panel!$J$5,SUMIFS(Data_Panel!$J$6:$J$44,Data_Panel!$A$6:$A$44,B67),"period not in panel")))))))) -> 24.1 | M67: =IF(L67="not in panel",0,ABS(N(L67)-D67)) -> 0
A68: 2024-H1 | B68: A05 | C68: Automotive R&D costs (total) | D68: 1665 | E68: EUR m | F68: FACT | G68: MANUAL | H68: S016 | I68: 25 | J68: EUR 1m | K68: =COUNTIFS($A$6:$A$243,A68,$B$6:$B$243,B68) -> 1 | L68: =IF(COUNTIF(Data_Panel!$A$6:$A$44,B68)=0,"not in panel",IF(A68=Data_Panel!$D$5,SUMIFS(Data_Panel!$D$6:$D$44,Data_Panel!$A$6:$A$44,B68),IF(A68=Data_Panel!$E$5,SUMIFS(Data_Panel!$E$6:$E$44,Data_Panel!$A$6:$A$44,B68),IF(A68=Data_Panel!$F$5,SUMIFS(Data_Panel!$F$6:$F$44,Data_Panel!$A$6:$A$44,B68),IF(A68=Data_Panel!$G$5,SUMIFS(Data_Panel!$G$6:$G$44,Data_Panel!$A$6:$A$44,B68),IF(A68=Data_Panel!$H$5,SUMIFS(Data_Panel!$H$6:$H$44,Data_Panel!$A$6:$A$44,B68),IF(A68=Data_Panel!$I$5,SUMIFS(Data_Panel!$I$6:$I$44,Data_Panel!$A$6:$A$44,B68),IF(A68=Data_Panel!$J$5,SUMIFS(Data_Panel!$J$6:$J$44,Data_Panel!$A$6:$A$44,B68),"period not in panel")))))))) -> 1665 | M68: =IF(L68="not in panel",0,ABS(N(L68)-D68)) -> 0
A69: 2024-H1 | B69: A06 | C69: Automotive capitalised development costs | D69: 1123 | E69: EUR m | F69: FACT | G69: MANUAL | H69: S016 | I69: 25 | J69: EUR 1m | K69: =COUNTIFS($A$6:$A$243,A69,$B$6:$B$243,B69) -> 1 | L69: =IF(COUNTIF(Data_Panel!$A$6:$A$44,B69)=0,"not in panel",IF(A69=Data_Panel!$D$5,SUMIFS(Data_Panel!$D$6:$D$44,Data_Panel!$A$6:$A$44,B69),IF(A69=Data_Panel!$E$5,SUMIFS(Data_Panel!$E$6:$E$44,Data_Panel!$A$6:$A$44,B69),IF(A69=Data_Panel!$F$5,SUMIFS(Data_Panel!$F$6:$F$44,Data_Panel!$A$6:$A$44,B69),IF(A69=Data_Panel!$G$5,SUMIFS(Data_Panel!$G$6:$G$44,Data_Panel!$A$6:$A$44,B69),IF(A69=Data_Panel!$H$5,SUMIFS(Data_Panel!$H$6:$H$44,Data_Panel!$A$6:$A$44,B69),IF(A69=Data_Panel!$I$5,SUMIFS(Data_Panel!$I$6:$I$44,Data_Panel!$A$6:$A$44,B69),IF(A69=Data_Panel!$J$5,SUMIFS(Data_Panel!$J$6:$J$44,Data_Panel!$A$6:$A$44,B69),"period not in panel")))))))) -> 1123 | M69: =IF(L69="not in panel",0,ABS(N(L69)-D69)) -> 0
A70: 2024-H1 | B70: A07 | C70: Capitalisation rate | D70: 67.5 | E70: % | F70: FACT | G70: MANUAL | H70: S016 | I70: 25 | J70: 0.1pp | K70: =COUNTIFS($A$6:$A$243,A70,$B$6:$B$243,B70) -> 1 | L70: =IF(COUNTIF(Data_Panel!$A$6:$A$44,B70)=0,"not in panel",IF(A70=Data_Panel!$D$5,SUMIFS(Data_Panel!$D$6:$D$44,Data_Panel!$A$6:$A$44,B70),IF(A70=Data_Panel!$E$5,SUMIFS(Data_Panel!$E$6:$E$44,Data_Panel!$A$6:$A$44,B70),IF(A70=Data_Panel!$F$5,SUMIFS(Data_Panel!$F$6:$F$44,Data_Panel!$A$6:$A$44,B70),IF(A70=Data_Panel!$G$5,SUMIFS(Data_Panel!$G$6:$G$44,Data_Panel!$A$6:$A$44,B70),IF(A70=Data_Panel!$H$5,SUMIFS(Data_Panel!$H$6:$H$44,Data_Panel!$A$6:$A$44,B70),IF(A70=Data_Panel!$I$5,SUMIFS(Data_Panel!$I$6:$I$44,Data_Panel!$A$6:$A$44,B70),IF(A70=Data_Panel!$J$5,SUMIFS(Data_Panel!$J$6:$J$44,Data_Panel!$A$6:$A$44,B70),"period not in panel")))))))) -> 67.5 | M70: =IF(L70="not in panel",0,ABS(N(L70)-D70)) -> 0
A71: 2024-H1 | B71: A08 | C71: Expensed automotive R&D | D71: 541 | E71: EUR m | F71: FACT | G71: MANUAL | H71: S016 | I71: 25 | J71: EUR 1m | K71: =COUNTIFS($A$6:$A$243,A71,$B$6:$B$243,B71) -> 1 | L71: =IF(COUNTIF(Data_Panel!$A$6:$A$44,B71)=0,"not in panel",IF(A71=Data_Panel!$D$5,SUMIFS(Data_Panel!$D$6:$D$44,Data_Panel!$A$6:$A$44,B71),IF(A71=Data_Panel!$E$5,SUMIFS(Data_Panel!$E$6:$E$44,Data_Panel!$A$6:$A$44,B71),IF(A71=Data_Panel!$F$5,SUMIFS(Data_Panel!$F$6:$F$44,Data_Panel!$A$6:$A$44,B71),IF(A71=Data_Panel!$G$5,SUMIFS(Data_Panel!$G$6:$G$44,Data_Panel!$A$6:$A$44,B71),IF(A71=Data_Panel!$H$5,SUMIFS(Data_Panel!$H$6:$H$44,Data_Panel!$A$6:$A$44,B71),IF(A71=Data_Panel!$I$5,SUMIFS(Data_Panel!$I$6:$I$44,Data_Panel!$A$6:$A$44,B71),IF(A71=Data_Panel!$J$5,SUMIFS(Data_Panel!$J$6:$J$44,Data_Panel!$A$6:$A$44,B71),"period not in panel")))))))) -> 541 | M71: =IF(L71="not in panel",0,ABS(N(L71)-D71)) -> 0
A72: 2024-H1 | B72: A09 | C72: Amortisation of capitalised R&D | D72: 516 | E72: EUR m | F72: FACT | G72: MANUAL | H72: S016 | I72: 25 | J72: EUR 1m | K72: =COUNTIFS($A$6:$A$243,A72,$B$6:$B$243,B72) -> 1 | L72: =IF(COUNTIF(Data_Panel!$A$6:$A$44,B72)=0,"not in panel",IF(A72=Data_Panel!$D$5,SUMIFS(Data_Panel!$D$6:$D$44,Data_Panel!$A$6:$A$44,B72),IF(A72=Data_Panel!$E$5,SUMIFS(Data_Panel!$E$6:$E$44,Data_Panel!$A$6:$A$44,B72),IF(A72=Data_Panel!$F$5,SUMIFS(Data_Panel!$F$6:$F$44,Data_Panel!$A$6:$A$44,B72),IF(A72=Data_Panel!$G$5,SUMIFS(Data_Panel!$G$6:$G$44,Data_Panel!$A$6:$A$44,B72),IF(A72=Data_Panel!$H$5,SUMIFS(Data_Panel!$H$6:$H$44,Data_Panel!$A$6:$A$44,B72),IF(A72=Data_Panel!$I$5,SUMIFS(Data_Panel!$I$6:$I$44,Data_Panel!$A$6:$A$44,B72),IF(A72=Data_Panel!$J$5,SUMIFS(Data_Panel!$J$6:$J$44,Data_Panel!$A$6:$A$44,B72),"period not in panel")))))))) -> 516 | M72: =IF(L72="not in panel",0,ABS(N(L72)-D72)) -> 0
A73: 2024-H1 | B73: A10 | C73: Automotive capex | D73: 850 | E73: EUR m | F73: FACT | G73: MANUAL | H73: S016 | I73: 25 | J73: EUR 1m | K73: =COUNTIFS($A$6:$A$243,A73,$B$6:$B$243,B73) -> 1 | L73: =IF(COUNTIF(Data_Panel!$A$6:$A$44,B73)=0,"not in panel",IF(A73=Data_Panel!$D$5,SUMIFS(Data_Panel!$D$6:$D$44,Data_Panel!$A$6:$A$44,B73),IF(A73=Data_Panel!$E$5,SUMIFS(Data_Panel!$E$6:$E$44,Data_Panel!$A$6:$A$44,B73),IF(A73=Data_Panel!$F$5,SUMIFS(Data_Panel!$F$6:$F$44,Data_Panel!$A$6:$A$44,B73),IF(A73=Data_Panel!$G$5,SUMIFS(Data_Panel!$G$6:$G$44,Data_Panel!$A$6:$A$44,B73),IF(A73=Data_Panel!$H$5,SUMIFS(Data_Panel!$H$6:$H$44,Data_Panel!$A$6:$A$44,B73),IF(A73=Data_Panel!$I$5,SUMIFS(Data_Panel!$I$6:$I$44,Data_Panel!$A$6:$A$44,B73),IF(A73=Data_Panel!$J$5,SUMIFS(Data_Panel!$J$6:$J$44,Data_Panel!$A$6:$A$44,B73),"period not in panel")))))))) -> 850 | M73: =IF(L73="not in panel",0,ABS(N(L73)-D73)) -> 0
A74: 2024-H1 | B74: A11 | C74: Automotive depreciation on capex | D74: 849 | E74: EUR m | F74: FACT | G74: MANUAL | H74: S016 | I74: 25 | J74: EUR 1m | K74: =COUNTIFS($A$6:$A$243,A74,$B$6:$B$243,B74) -> 1 | L74: =IF(COUNTIF(Data_Panel!$A$6:$A$44,B74)=0,"not in panel",IF(A74=Data_Panel!$D$5,SUMIFS(Data_Panel!$D$6:$D$44,Data_Panel!$A$6:$A$44,B74),IF(A74=Data_Panel!$E$5,SUMIFS(Data_Panel!$E$6:$E$44,Data_Panel!$A$6:$A$44,B74),IF(A74=Data_Panel!$F$5,SUMIFS(Data_Panel!$F$6:$F$44,Data_Panel!$A$6:$A$44,B74),IF(A74=Data_Panel!$G$5,SUMIFS(Data_Panel!$G$6:$G$44,Data_Panel!$A$6:$A$44,B74),IF(A74=Data_Panel!$H$5,SUMIFS(Data_Panel!$H$6:$H$44,Data_Panel!$A$6:$A$44,B74),IF(A74=Data_Panel!$I$5,SUMIFS(Data_Panel!$I$6:$I$44,Data_Panel!$A$6:$A$44,B74),IF(A74=Data_Panel!$J$5,SUMIFS(Data_Panel!$J$6:$J$44,Data_Panel!$A$6:$A$44,B74),"period not in panel")))))))) -> 849 | M74: =IF(L74="not in panel",0,ABS(N(L74)-D74)) -> 0
A75: 2024-H1 | B75: A12 | C75: Automotive total D&A | D75: 1364 | E75: EUR m | F75: FACT | G75: MANUAL | H75: S016 | I75: 25 | J75: EUR 1m | K75: =COUNTIFS($A$6:$A$243,A75,$B$6:$B$243,B75) -> 1 | L75: =IF(COUNTIF(Data_Panel!$A$6:$A$44,B75)=0,"not in panel",IF(A75=Data_Panel!$D$5,SUMIFS(Data_Panel!$D$6:$D$44,Data_Panel!$A$6:$A$44,B75),IF(A75=Data_Panel!$E$5,SUMIFS(Data_Panel!$E$6:$E$44,Data_Panel!$A$6:$A$44,B75),IF(A75=Data_Panel!$F$5,SUMIFS(Data_Panel!$F$6:$F$44,Data_Panel!$A$6:$A$44,B75),IF(A75=Data_Panel!$G$5,SUMIFS(Data_Panel!$G$6:$G$44,Data_Panel!$A$6:$A$44,B75),IF(A75=Data_Panel!$H$5,SUMIFS(Data_Panel!$H$6:$H$44,Data_Panel!$A$6:$A$44,B75),IF(A75=Data_Panel!$I$5,SUMIFS(Data_Panel!$I$6:$I$44,Data_Panel!$A$6:$A$44,B75),IF(A75=Data_Panel!$J$5,SUMIFS(Data_Panel!$J$6:$J$44,Data_Panel!$A$6:$A$44,B75),"period not in panel")))))))) -> 1364 | M75: =IF(L75="not in panel",0,ABS(N(L75)-D75)) -> 0
... A99: 2024-H1 | B99: X05 | C99: Impairment losses included in automotive D&A | D99: 0 | E99: EUR m | F99: FACT | G99: MANUAL | H99: S006 | I99: 38 (segment reporting) | J99: EUR 1m | K99: =COUNTIFS($A$6:$A$243,A99,$B$6:$B$243,B99) -> 1 | L99: =IF(COUNTIF(Data_Panel!$A$6:$A$44,B99)=0,"not in panel",IF(A99=Data_Panel!$D$5,SUMIFS(Data_Panel!$D$6:$D$44,Data_Panel!$A$6:$A$44,B99),IF(A99=Data_Panel!$E$5,SUMIFS(Data_Panel!$E$6:$E$44,Data_Panel!$A$6:$A$44,B99),IF(A99=Data_Panel!$F$5,SUMIFS(Data_Panel!$F$6:$F$44,Data_Panel!$A$6:$A$44,B99),IF(A99=Data_Panel!$G$5,SUMIFS(Data_Panel!$G$6:$G$44,Data_Panel!$A$6:$A$44,B99),IF(A99=Data_Panel!$H$5,SUMIFS(Data_Panel!$H$6:$H$44,Data_Panel!$A$6:$A$44,B99),IF(A99=Data_Panel!$I$5,SUMIFS(Data_Panel!$I$6:$I$44,Data_Panel!$A$6:$A$44,B99),IF(A99=Data_Panel!$J$5,SUMIFS(Data_Panel!$J$6:$J$44,Data_Panel!$A$6:$A$44,B99),"period not in panel")))))))) -> 0 | M99: =IF(L99="not in panel",0,ABS(N(L99)-D99)) -> 0
A100: 2024-H2 | B100: A01 | C100: Automotive sales revenue | D100: 18743 | E100: EUR m | F100: DERIVED | G100: SQL_DERIVED | I100: FY - H1: 2024-FY (S026) minus 2024-H1 (S006) | J100: derived; inputs rounded: FY EUR 1m / H1 EUR 1m | K100: =COUNTIFS($A$6:$A$243,A100,$B$6:$B$243,B100) -> 1 | L100: =IF(COUNTIF(Data_Panel!$A$6:$A$44,B100)=0,"not in panel",IF(A100=Data_Panel!$D$5,SUMIFS(Data_Panel!$D$6:$D$44,Data_Panel!$A$6:$A$44,B100),IF(A100=Data_Panel!$E$5,SUMIFS(Data_Panel!$E$6:$E$44,Data_Panel!$A$6:$A$44,B100),IF(A100=Data_Panel!$F$5,SUMIFS(Data_Panel!$F$6:$F$44,Data_Panel!$A$6:$A$44,B100),IF(A100=Data_Panel!$G$5,SUMIFS(Data_Panel!$G$6:$G$44,Data_Panel!$A$6:$A$44,B100),IF(A100=Data_Panel!$H$5,SUMIFS(Data_Panel!$H$6:$H$44,Data_Panel!$A$6:$A$44,B100),IF(A100=Data_Panel!$I$5,SUMIFS(Data_Panel!$I$6:$I$44,Data_Panel!$A$6:$A$44,B100),IF(A100=Data_Panel!$J$5,SUMIFS(Data_Panel!$J$6:$J$44,Data_Panel!$A$6:$A$44,B100),"period not in panel")))))))) -> 18743 | M100: =IF(L100="not in panel",0,ABS(N(L100)-D100)) -> 0
A101: 2024-H2 | B101: A02 | C101: Automotive operating profit | D101: 2382 | E101: EUR m | F101: DERIVED | G101: SQL_DERIVED | I101: FY - H1: 2024-FY (S013) minus 2024-H1 (S006) | J101: derived; inputs rounded: FY EUR 1m / H1 EUR 1m | K101: =COUNTIFS($A$6:$A$243,A101,$B$6:$B$243,B101) -> 1 | L101: =IF(COUNTIF(Data_Panel!$A$6:$A$44,B101)=0,"not in panel",IF(A101=Data_Panel!$D$5,SUMIFS(Data_Panel!$D$6:$D$44,Data_Panel!$A$6:$A$44,B101),IF(A101=Data_Panel!$E$5,SUMIFS(Data_Panel!$E$6:$E$44,Data_Panel!$A$6:$A$44,B101),IF(A101=Data_Panel!$F$5,SUMIFS(Data_Panel!$F$6:$F$44,Data_Panel!$A$6:$A$44,B101),IF(A101=Data_Panel!$G$5,SUMIFS(Data_Panel!$G$6:$G$44,Data_Panel!$A$6:$A$44,B101),IF(A101=Data_Panel!$H$5,SUMIFS(Data_Panel!$H$6:$H$44,Data_Panel!$A$6:$A$44,B101),IF(A101=Data_Panel!$I$5,SUMIFS(Data_Panel!$I$6:$I$44,Data_Panel!$A$6:$A$44,B101),IF(A101=Data_Panel!$J$5,SUMIFS(Data_Panel!$J$6:$J$44,Data_Panel!$A$6:$A$44,B101),"period not in panel")))))))) -> 2382 | M101: =IF(L101="not in panel",0,ABS(N(L101)-D101)) -> 0
A102: 2024-H2 | B102: A03 | C102: Automotive EBITDA | D102: 4003 | E102: EUR m | F102: DERIVED | G102: SQL_DERIVED | I102: FY - H1: 2024-FY (S013) minus 2024-H1 (S006) | J102: derived; inputs rounded: FY EUR 1m / H1 EUR 1m | K102: =COUNTIFS($A$6:$A$243,A102,$B$6:$B$243,B102) -> 1 | L102: =IF(COUNTIF(Data_Panel!$A$6:$A$44,B102)=0,"not in panel",IF(A102=Data_Panel!$D$5,SUMIFS(Data_Panel!$D$6:$D$44,Data_Panel!$A$6:$A$44,B102),IF(A102=Data_Panel!$E$5,SUMIFS(Data_Panel!$E$6:$E$44,Data_Panel!$A$6:$A$44,B102),IF(A102=Data_Panel!$F$5,SUMIFS(Data_Panel!$F$6:$F$44,Data_Panel!$A$6:$A$44,B102),IF(A102=Data_Panel!$G$5,SUMIFS(Data_Panel!$G$6:$G$44,Data_Panel!$A$6:$A$44,B102),IF(A102=Data_Panel!$H$5,SUMIFS(Data_Panel!$H$6:$H$44,Data_Panel!$A$6:$A$44,B102),IF(A102=Data_Panel!$I$5,SUMIFS(Data_Panel!$I$6:$I$44,Data_Panel!$A$6:$A$44,B102),IF(A102=Data_Panel!$J$5,SUMIFS(Data_Panel!$J$6:$J$44,Data_Panel!$A$6:$A$44,B102),"period not in panel")))))))) -> 4003 | M102: =IF(L102="not in panel",0,ABS(N(L102)-D102)) -> 0
A103: 2024-H2 | B103: A05 | C103: Automotive R&D costs (total) | D103: 863 | E103: EUR m | F103: DERIVED | G103: SQL_DERIVED | I103: FY - H1: 2024-FY (S011) minus 2024-H1 (S016) | J103: derived; inputs rounded: FY EUR 1m / H1 EUR 1m | K103: =COUNTIFS($A$6:$A$243,A103,$B$6:$B$243,B103) -> 1 | L103: =IF(COUNTIF(Data_Panel!$A$6:$A$44,B103)=0,"not in panel",IF(A103=Data_Panel!$D$5,SUMIFS(Data_Panel!$D$6:$D$44,Data_Panel!$A$6:$A$44,B103),IF(A103=Data_Panel!$E$5,SUMIFS(Data_Panel!$E$6:$E$44,Data_Panel!$A$6:$A$44,B103),IF(A103=Data_Panel!$F$5,SUMIFS(Data_Panel!$F$6:$F$44,Data_Panel!$A$6:$A$44,B103),IF(A103=Data_Panel!$G$5,SUMIFS(Data_Panel!$G$6:$G$44,Data_Panel!$A$6:$A$44,B103),IF(A103=Data_Panel!$H$5,SUMIFS(Data_Panel!$H$6:$H$44,Data_Panel!$A$6:$A$44,B103),IF(A103=Data_Panel!$I$5,SUMIFS(Data_Panel!$I$6:$I$44,Data_Panel!$A$6:$A$44,B103),IF(A103=Data_Panel!$J$5,SUMIFS(Data_Panel!$J$6:$J$44,Data_Panel!$A$6:$A$44,B103),"period not in panel")))))))) -> 863 | M103: =IF(L103="not in panel",0,ABS(N(L103)-D103)) -> 0
A104: 2024-H2 | B104: A06 | C104: Automotive capitalised development costs | D104: 460 | E104: EUR m | F104: DERIVED | G104: SQL_DERIVED | I104: FY - H1: 2024-FY (S011) minus 2024-H1 (S016) | J104: derived; inputs rounded: FY EUR 1m / H1 EUR 1m | K104: =COUNTIFS($A$6:$A$243,A104,$B$6:$B$243,B104) -> 1 | L104: =IF(COUNTIF(Data_Panel!$A$6:$A$44,B104)=0,"not in panel",IF(A104=Data_Panel!$D$5,SUMIFS(Data_Panel!$D$6:$D$44,Data_Panel!$A$6:$A$44,B104),IF(A104=Data_Panel!$E$5,SUMIFS(Data_Panel!$E$6:$E$44,Data_Panel!$A$6:$A$44,B104),IF(A104=Data_Panel!$F$5,SUMIFS(Data_Panel!$F$6:$F$44,Data_Panel!$A$6:$A$44,B104),IF(A104=Data_Panel!$G$5,SUMIFS(Data_Panel!$G$6:$G$44,Data_Panel!$A$6:$A$44,B104),IF(A104=Data_Panel!$H$5,SUMIFS(Data_Panel!$H$6:$H$44,Data_Panel!$A$6:$A$44,B104),IF(A104=Data_Panel!$I$5,SUMIFS(Data_Panel!$I$6:$I$44,Data_Panel!$A$6:$A$44,B104),IF(A104=Data_Panel!$J$5,SUMIFS(Data_Panel!$J$6:$J$44,Data_Panel!$A$6:$A$44,B104),"period not in panel")))))))) -> 460 | M104: =IF(L104="not in panel",0,ABS(N(L104)-D104)) -> 0
A105: 2024-H2 | B105: A08 | C105: Expensed automotive R&D | D105: 404 | E105: EUR m | F105: DERIVED | G105: SQL_DERIVED | I105: FY - H1: 2024-FY (S011) minus 2024-H1 (S016) | J105: derived; inputs rounded: FY EUR 1m / H1 EUR 1m | K105: =COUNTIFS($A$6:$A$243,A105,$B$6:$B$243,B105) -> 1 | L105: =IF(COUNTIF(Data_Panel!$A$6:$A$44,B105)=0,"not in panel",IF(A105=Data_Panel!$D$5,SUMIFS(Data_Panel!$D$6:$D$44,Data_Panel!$A$6:$A$44,B105),IF(A105=Data_Panel!$E$5,SUMIFS(Data_Panel!$E$6:$E$44,Data_Panel!$A$6:$A$44,B105),IF(A105=Data_Panel!$F$5,SUMIFS(Data_Panel!$F$6:$F$44,Data_Panel!$A$6:$A$44,B105),IF(A105=Data_Panel!$G$5,SUMIFS(Data_Panel!$G$6:$G$44,Data_Panel!$A$6:$A$44,B105),IF(A105=Data_Panel!$H$5,SUMIFS(Data_Panel!$H$6:$H$44,Data_Panel!$A$6:$A$44,B105),IF(A105=Data_Panel!$I$5,SUMIFS(Data_Panel!$I$6:$I$44,Data_Panel!$A$6:$A$44,B105),IF(A105=Data_Panel!$J$5,SUMIFS(Data_Panel!$J$6:$J$44,Data_Panel!$A$6:$A$44,B105),"period not in panel")))))))) -> 404 | M105: =IF(L105="not in panel",0,ABS(N(L105)-D105)) -> 0
A106: 2024-H2 | B106: A09 | C106: Amortisation of capitalised R&D | D106: 585 | E106: EUR m | F106: DERIVED | G106: SQL_DERIVED | I106: FY - H1: 2024-FY (S011) minus 2024-H1 (S016) | J106: derived; inputs rounded: FY EUR 1m / H1 EUR 1m | K106: =COUNTIFS($A$6:$A$243,A106,$B$6:$B$243,B106) -> 1 | L106: =IF(COUNTIF(Data_Panel!$A$6:$A$44,B106)=0,"not in panel",IF(A106=Data_Panel!$D$5,SUMIFS(Data_Panel!$D$6:$D$44,Data_Panel!$A$6:$A$44,B106),IF(A106=Data_Panel!$E$5,SUMIFS(Data_Panel!$E$6:$E$44,Data_Panel!$A$6:$A$44,B106),IF(A106=Data_Panel!$F$5,SUMIFS(Data_Panel!$F$6:$F$44,Data_Panel!$A$6:$A$44,B106),IF(A106=Data_Panel!$G$5,SUMIFS(Data_Panel!$G$6:$G$44,Data_Panel!$A$6:$A$44,B106),IF(A106=Data_Panel!$H$5,SUMIFS(Data_Panel!$H$6:$H$44,Data_Panel!$A$6:$A$44,B106),IF(A106=Data_Panel!$I$5,SUMIFS(Data_Panel!$I$6:$I$44,Data_Panel!$A$6:$A$44,B106),IF(A106=Data_Panel!$J$5,SUMIFS(Data_Panel!$J$6:$J$44,Data_Panel!$A$6:$A$44,B106),"period not in panel")))))))) -> 585 | M106: =IF(L106="not in panel",0,ABS(N(L106)-D106)) -> 0
A107: 2024-H2 | B107: A10 | C107: Automotive capex | D107: 1269 | E107: EUR m | F107: DERIVED | G107: SQL_DERIVED | I107: FY - H1: 2024-FY (S011) minus 2024-H1 (S016) | J107: derived; inputs rounded: FY EUR 1m / H1 EUR 1m | K107: =COUNTIFS($A$6:$A$243,A107,$B$6:$B$243,B107) -> 1 | L107: =IF(COUNTIF(Data_Panel!$A$6:$A$44,B107)=0,"not in panel",IF(A107=Data_Panel!$D$5,SUMIFS(Data_Panel!$D$6:$D$44,Data_Panel!$A$6:$A$44,B107),IF(A107=Data_Panel!$E$5,SUMIFS(Data_Panel!$E$6:$E$44,Data_Panel!$A$6:$A$44,B107),IF(A107=Data_Panel!$F$5,SUMIFS(Data_Panel!$F$6:$F$44,Data_Panel!$A$6:$A$44,B107),IF(A107=Data_Panel!$G$5,SUMIFS(Data_Panel!$G$6:$G$44,Data_Panel!$A$6:$A$44,B107),IF(A107=Data_Panel!$H$5,SUMIFS(Data_Panel!$H$6:$H$44,Data_Panel!$A$6:$A$44,B107),IF(A107=Data_Panel!$I$5,SUMIFS(Data_Panel!$I$6:$I$44,Data_Panel!$A$6:$A$44,B107),IF(A107=Data_Panel!$J$5,SUMIFS(Data_Panel!$J$6:$J$44,Data_Panel!$A$6:$A$44,B107),"period not in panel")))))))) -> 1269 | M107: =IF(L107="not in panel",0,ABS(N(L107)-D107)) -> 0
A108: 2024-H2 | B108: A11 | C108: Automotive depreciation on capex | D108: 1035 | E108: EUR m | F108: DERIVED | G108: SQL_DERIVED | I108: FY - H1: 2024-FY (S011) minus 2024-H1 (S016) | J108: derived; inputs rounded: FY EUR 1m / H1 EUR 1m | K108: =COUNTIFS($A$6:$A$243,A108,$B$6:$B$243,B108) -> 1 | L108: =IF(COUNTIF(Data_Panel!$A$6:$A$44,B108)=0,"not in panel",IF(A108=Data_Panel!$D$5,SUMIFS(Data_Panel!$D$6:$D$44,Data_Panel!$A$6:$A$44,B108),IF(A108=Data_Panel!$E$5,SUMIFS(Data_Panel!$E$6:$E$44,Data_Panel!$A$6:$A$44,B108),IF(A108=Data_Panel!$F$5,SUMIFS(Data_Panel!$F$6:$F$44,Data_Panel!$A$6:$A$44,B108),IF(A108=Data_Panel!$G$5,SUMIFS(Data_Panel!$G$6:$G$44,Data_Panel!$A$6:$A$44,B108),IF(A108=Data_Panel!$H$5,SUMIFS(Data_Panel!$H$6:$H$44,Data_Panel!$A$6:$A$44,B108),IF(A108=Data_Panel!$I$5,SUMIFS(Data_Panel!$I$6:$I$44,Data_Panel!$A$6:$A$44,B108),IF(A108=Data_Panel!$J$5,SUMIFS(Data_Panel!$J$6:$J$44,Data_Panel!$A$6:$A$44,B108),"period not in panel")))))))) -> 1035 | M108: =IF(L108="not in panel",0,ABS(N(L108)-D108)) -> 0
A109: 2024-H2 | B109: A12 | C109: Automotive total D&A | D109: 1621 | E109: EUR m | F109: DERIVED | G109: SQL_DERIVED | I109: FY - H1: 2024-FY (S011) minus 2024-H1 (S016) | J109: derived; inputs rounded: FY EUR 1m / H1 EUR 1m | K109: =COUNTIFS($A$6:$A$243,A109,$B$6:$B$243,B109) -> 1 | L109: =IF(COUNTIF(Data_Panel!$A$6:$A$44,B109)=0,"not in panel",IF(A109=Data_Panel!$D$5,SUMIFS(Data_Panel!$D$6:$D$44,Data_Panel!$A$6:$A$44,B109),IF(A109=Data_Panel!$E$5,SUMIFS(Data_Panel!$E$6:$E$44,Data_Panel!$A$6:$A$44,B109),IF(A109=Data_Panel!$F$5,SUMIFS(Data_Panel!$F$6:$F$44,Data_Panel!$A$6:$A$44,B109),IF(A109=Data_Panel!$G$5,SUMIFS(Data_Panel!$G$6:$G$44,Data_Panel!$A$6:$A$44,B109),IF(A109=Data_Panel!$H$5,SUMIFS(Data_Panel!$H$6:$H$44,Data_Panel!$A$6:$A$44,B109),IF(A109=Data_Panel!$I$5,SUMIFS(Data_Panel!$I$6:$I$44,Data_Panel!$A$6:$A$44,B109),IF(A109=Data_Panel!$J$5,SUMIFS(Data_Panel!$J$6:$J$44,Data_Panel!$A$6:$A$44,B109),"period not in panel")))))))) -> 1621 | M109: =IF(L109="not in panel",0,ABS(N(L109)-D109)) -> 0
A110: 2024-H2 | B110: A13 | C110: Automotive net cash flow | D110: 2617.6258 | E110: EUR m | F110: DERIVED | G110: SQL_DERIVED | I110: FY - H1: 2024-FY (S025) minus 2024-H1 (S025) | J110: derived; inputs rounded: FY exact (EUR, converted to EUR m) / H1 exact (EUR, converted to EUR m) | K110: =COUNTIFS($A$6:$A$243,A110,$B$6:$B$243,B110) -> 1 | L110: =IF(COUNTIF(Data_Panel!$A$6:$A$44,B110)=0,"not in panel",IF(A110=Data_Panel!$D$5,SUMIFS(Data_Panel!$D$6:$D$44,Data_Panel!$A$6:$A$44,B110),IF(A110=Data_Panel!$E$5,SUMIFS(Data_Panel!$E$6:$E$44,Data_Panel!$A$6:$A$44,B110),IF(A110=Data_Panel!$F$5,SUMIFS(Data_Panel!$F$6:$F$44,Data_Panel!$A$6:$A$44,B110),IF(A110=Data_Panel!$G$5,SUMIFS(Data_Panel!$G$6:$G$44,Data_Panel!$A$6:$A$44,B110),IF(A110=Data_Panel!$H$5,SUMIFS(Data_Panel!$H$6:$H$44,Data_Panel!$A$6:$A$44,B110),IF(A110=Data_Panel!$I$5,SUMIFS(Data_Panel!$I$6:$I$44,Data_Panel!$A$6:$A$44,B110),IF(A110=Data_Panel!$J$5,SUMIFS(Data_Panel!$J$6:$J$44,Data_Panel!$A$6:$A$44,B110),"period not in panel")))))))) -> 2617.6258 | M110: =IF(L110="not in panel",0,ABS(N(L110)-D110)) -> 0
A111: 2024-H2 | B111: A13a | C111: Automotive cash flows from operating activities | D111: 4363.2863 | E111: EUR m | F111: DERIVED | G111: SQL_DERIVED | I111: FY - H1: 2024-FY (S025) minus 2024-H1 (S025) | J111: derived; inputs rounded: FY exact (EUR, converted to EUR m) / H1 exact (EUR, converted to EUR m) | K111: =COUNTIFS($A$6:$A$243,A111,$B$6:$B$243,B111) -> 1 | L111: =IF(COUNTIF(Data_Panel!$A$6:$A$44,B111)=0,"not in panel",IF(A111=Data_Panel!$D$5,SUMIFS(Data_Panel!$D$6:$D$44,Data_Panel!$A$6:$A$44,B111),IF(A111=Data_Panel!$E$5,SUMIFS(Data_Panel!$E$6:$E$44,Data_Panel!$A$6:$A$44,B111),IF(A111=Data_Panel!$F$5,SUMIFS(Data_Panel!$F$6:$F$44,Data_Panel!$A$6:$A$44,B111),IF(A111=Data_Panel!$G$5,SUMIFS(Data_Panel!$G$6:$G$44,Data_Panel!$A$6:$A$44,B111),IF(A111=Data_Panel!$H$5,SUMIFS(Data_Panel!$H$6:$H$44,Data_Panel!$A$6:$A$44,B111),IF(A111=Data_Panel!$I$5,SUMIFS(Data_Panel!$I$6:$I$44,Data_Panel!$A$6:$A$44,B111),IF(A111=Data_Panel!$J$5,SUMIFS(Data_Panel!$J$6:$J$44,Data_Panel!$A$6:$A$44,B111),"period not in panel")))))))) -> 4363.2863 | M111: =IF(L111="not in panel",0,ABS(N(L111)-D111)) -> 0
... A129: 2024-H2 | B129: X05 | C129: Impairment losses included in automotive D&A | D129: 3 | E129: EUR m | F129: DERIVED | G129: SQL_DERIVED | I129: FY - H1: 2024-FY (S008) minus 2024-H1 (S006) | J129: derived; inputs rounded: FY EUR 1m / H1 EUR 1m | K129: =COUNTIFS($A$6:$A$243,A129,$B$6:$B$243,B129) -> 1 | L129: =IF(COUNTIF(Data_Panel!$A$6:$A$44,B129)=0,"not in panel",IF(A129=Data_Panel!$D$5,SUMIFS(Data_Panel!$D$6:$D$44,Data_Panel!$A$6:$A$44,B129),IF(A129=Data_Panel!$E$5,SUMIFS(Data_Panel!$E$6:$E$44,Data_Panel!$A$6:$A$44,B129),IF(A129=Data_Panel!$F$5,SUMIFS(Data_Panel!$F$6:$F$44,Data_Panel!$A$6:$A$44,B129),IF(A129=Data_Panel!$G$5,SUMIFS(Data_Panel!$G$6:$G$44,Data_Panel!$A$6:$A$44,B129),IF(A129=Data_Panel!$H$5,SUMIFS(Data_Panel!$H$6:$H$44,Data_Panel!$A$6:$A$44,B129),IF(A129=Data_Panel!$I$5,SUMIFS(Data_Panel!$I$6:$I$44,Data_Panel!$A$6:$A$44,B129),IF(A129=Data_Panel!$J$5,SUMIFS(Data_Panel!$J$6:$J$44,Data_Panel!$A$6:$A$44,B129),"period not in panel")))))))) -> 3 | M129: =IF(L129="not in panel",0,ABS(N(L129)-D129)) -> 0
A130: 2025-H1 | B130: A01 | C130: Automotive sales revenue | D130: 16138 | E130: EUR m | F130: FACT | G130: MANUAL | H130: S010 | I130: 11 (Automotive EBITDA margin table) | J130: EUR 1m | K130: =COUNTIFS($A$6:$A$243,A130,$B$6:$B$243,B130) -> 1 | L130: =IF(COUNTIF(Data_Panel!$A$6:$A$44,B130)=0,"not in panel",IF(A130=Data_Panel!$D$5,SUMIFS(Data_Panel!$D$6:$D$44,Data_Panel!$A$6:$A$44,B130),IF(A130=Data_Panel!$E$5,SUMIFS(Data_Panel!$E$6:$E$44,Data_Panel!$A$6:$A$44,B130),IF(A130=Data_Panel!$F$5,SUMIFS(Data_Panel!$F$6:$F$44,Data_Panel!$A$6:$A$44,B130),IF(A130=Data_Panel!$G$5,SUMIFS(Data_Panel!$G$6:$G$44,Data_Panel!$A$6:$A$44,B130),IF(A130=Data_Panel!$H$5,SUMIFS(Data_Panel!$H$6:$H$44,Data_Panel!$A$6:$A$44,B130),IF(A130=Data_Panel!$I$5,SUMIFS(Data_Panel!$I$6:$I$44,Data_Panel!$A$6:$A$44,B130),IF(A130=Data_Panel!$J$5,SUMIFS(Data_Panel!$J$6:$J$44,Data_Panel!$A$6:$A$44,B130),"period not in panel")))))))) -> 16138 | M130: =IF(L130="not in panel",0,ABS(N(L130)-D130)) -> 0
A131: 2025-H1 | B131: A02 | C131: Automotive operating profit | D131: 832 | E131: EUR m | F131: FACT | G131: MANUAL | H131: S010 | I131: 11 (Automotive EBITDA margin table) | J131: EUR 1m | K131: =COUNTIFS($A$6:$A$243,A131,$B$6:$B$243,B131) -> 1 | L131: =IF(COUNTIF(Data_Panel!$A$6:$A$44,B131)=0,"not in panel",IF(A131=Data_Panel!$D$5,SUMIFS(Data_Panel!$D$6:$D$44,Data_Panel!$A$6:$A$44,B131),IF(A131=Data_Panel!$E$5,SUMIFS(Data_Panel!$E$6:$E$44,Data_Panel!$A$6:$A$44,B131),IF(A131=Data_Panel!$F$5,SUMIFS(Data_Panel!$F$6:$F$44,Data_Panel!$A$6:$A$44,B131),IF(A131=Data_Panel!$G$5,SUMIFS(Data_Panel!$G$6:$G$44,Data_Panel!$A$6:$A$44,B131),IF(A131=Data_Panel!$H$5,SUMIFS(Data_Panel!$H$6:$H$44,Data_Panel!$A$6:$A$44,B131),IF(A131=Data_Panel!$I$5,SUMIFS(Data_Panel!$I$6:$I$44,Data_Panel!$A$6:$A$44,B131),IF(A131=Data_Panel!$J$5,SUMIFS(Data_Panel!$J$6:$J$44,Data_Panel!$A$6:$A$44,B131),"period not in panel")))))))) -> 832 | M131: =IF(L131="not in panel",0,ABS(N(L131)-D131)) -> 0
A132: 2025-H1 | B132: A03 | C132: Automotive EBITDA | D132: 2588 | E132: EUR m | F132: FACT | G132: MANUAL | H132: S010 | I132: 11 (Automotive EBITDA margin table) | J132: EUR 1m | K132: =COUNTIFS($A$6:$A$243,A132,$B$6:$B$243,B132) -> 1 | L132: =IF(COUNTIF(Data_Panel!$A$6:$A$44,B132)=0,"not in panel",IF(A132=Data_Panel!$D$5,SUMIFS(Data_Panel!$D$6:$D$44,Data_Panel!$A$6:$A$44,B132),IF(A132=Data_Panel!$E$5,SUMIFS(Data_Panel!$E$6:$E$44,Data_Panel!$A$6:$A$44,B132),IF(A132=Data_Panel!$F$5,SUMIFS(Data_Panel!$F$6:$F$44,Data_Panel!$A$6:$A$44,B132),IF(A132=Data_Panel!$G$5,SUMIFS(Data_Panel!$G$6:$G$44,Data_Panel!$A$6:$A$44,B132),IF(A132=Data_Panel!$H$5,SUMIFS(Data_Panel!$H$6:$H$44,Data_Panel!$A$6:$A$44,B132),IF(A132=Data_Panel!$I$5,SUMIFS(Data_Panel!$I$6:$I$44,Data_Panel!$A$6:$A$44,B132),IF(A132=Data_Panel!$J$5,SUMIFS(Data_Panel!$J$6:$J$44,Data_Panel!$A$6:$A$44,B132),"period not in panel")))))))) -> 2588 | M132: =IF(L132="not in panel",0,ABS(N(L132)-D132)) -> 0
A133: 2025-H1 | B133: A04 | C133: Automotive EBITDA margin | D133: 16 | E133: % | F133: FACT | G133: MANUAL | H133: S010 | I133: 11 (Automotive EBITDA margin table) | J133: 0.1pp | K133: =COUNTIFS($A$6:$A$243,A133,$B$6:$B$243,B133) -> 1 | L133: =IF(COUNTIF(Data_Panel!$A$6:$A$44,B133)=0,"not in panel",IF(A133=Data_Panel!$D$5,SUMIFS(Data_Panel!$D$6:$D$44,Data_Panel!$A$6:$A$44,B133),IF(A133=Data_Panel!$E$5,SUMIFS(Data_Panel!$E$6:$E$44,Data_Panel!$A$6:$A$44,B133),IF(A133=Data_Panel!$F$5,SUMIFS(Data_Panel!$F$6:$F$44,Data_Panel!$A$6:$A$44,B133),IF(A133=Data_Panel!$G$5,SUMIFS(Data_Panel!$G$6:$G$44,Data_Panel!$A$6:$A$44,B133),IF(A133=Data_Panel!$H$5,SUMIFS(Data_Panel!$H$6:$H$44,Data_Panel!$A$6:$A$44,B133),IF(A133=Data_Panel!$I$5,SUMIFS(Data_Panel!$I$6:$I$44,Data_Panel!$A$6:$A$44,B133),IF(A133=Data_Panel!$J$5,SUMIFS(Data_Panel!$J$6:$J$44,Data_Panel!$A$6:$A$44,B133),"period not in panel")))))))) -> 16 | M133: =IF(L133="not in panel",0,ABS(N(L133)-D133)) -> 0
A134: 2025-H1 | B134: A05 | C134: Automotive R&D costs (total) | D134: 1264 | E134: EUR m | F134: FACT | G134: MANUAL | H134: S016 | I134: 25 | J134: EUR 1m | K134: =COUNTIFS($A$6:$A$243,A134,$B$6:$B$243,B134) -> 1 | L134: =IF(COUNTIF(Data_Panel!$A$6:$A$44,B134)=0,"not in panel",IF(A134=Data_Panel!$D$5,SUMIFS(Data_Panel!$D$6:$D$44,Data_Panel!$A$6:$A$44,B134),IF(A134=Data_Panel!$E$5,SUMIFS(Data_Panel!$E$6:$E$44,Data_Panel!$A$6:$A$44,B134),IF(A134=Data_Panel!$F$5,SUMIFS(Data_Panel!$F$6:$F$44,Data_Panel!$A$6:$A$44,B134),IF(A134=Data_Panel!$G$5,SUMIFS(Data_Panel!$G$6:$G$44,Data_Panel!$A$6:$A$44,B134),IF(A134=Data_Panel!$H$5,SUMIFS(Data_Panel!$H$6:$H$44,Data_Panel!$A$6:$A$44,B134),IF(A134=Data_Panel!$I$5,SUMIFS(Data_Panel!$I$6:$I$44,Data_Panel!$A$6:$A$44,B134),IF(A134=Data_Panel!$J$5,SUMIFS(Data_Panel!$J$6:$J$44,Data_Panel!$A$6:$A$44,B134),"period not in panel")))))))) -> 1264 | M134: =IF(L134="not in panel",0,ABS(N(L134)-D134)) -> 0
A135: 2025-H1 | B135: A06 | C135: Automotive capitalised development costs | D135: 575 | E135: EUR m | F135: FACT | G135: MANUAL | H135: S016 | I135: 25 | J135: EUR 1m | K135: =COUNTIFS($A$6:$A$243,A135,$B$6:$B$243,B135) -> 1 | L135: =IF(COUNTIF(Data_Panel!$A$6:$A$44,B135)=0,"not in panel",IF(A135=Data_Panel!$D$5,SUMIFS(Data_Panel!$D$6:$D$44,Data_Panel!$A$6:$A$44,B135),IF(A135=Data_Panel!$E$5,SUMIFS(Data_Panel!$E$6:$E$44,Data_Panel!$A$6:$A$44,B135),IF(A135=Data_Panel!$F$5,SUMIFS(Data_Panel!$F$6:$F$44,Data_Panel!$A$6:$A$44,B135),IF(A135=Data_Panel!$G$5,SUMIFS(Data_Panel!$G$6:$G$44,Data_Panel!$A$6:$A$44,B135),IF(A135=Data_Panel!$H$5,SUMIFS(Data_Panel!$H$6:$H$44,Data_Panel!$A$6:$A$44,B135),IF(A135=Data_Panel!$I$5,SUMIFS(Data_Panel!$I$6:$I$44,Data_Panel!$A$6:$A$44,B135),IF(A135=Data_Panel!$J$5,SUMIFS(Data_Panel!$J$6:$J$44,Data_Panel!$A$6:$A$44,B135),"period not in panel")))))))) -> 575 | M135: =IF(L135="not in panel",0,ABS(N(L135)-D135)) -> 0
A136: 2025-H1 | B136: A07 | C136: Capitalisation rate | D136: 45.5 | E136: % | F136: FACT | G136: MANUAL | H136: S016 | I136: 25 | J136: 0.1pp | K136: =COUNTIFS($A$6:$A$243,A136,$B$6:$B$243,B136) -> 1 | L136: =IF(COUNTIF(Data_Panel!$A$6:$A$44,B136)=0,"not in panel",IF(A136=Data_Panel!$D$5,SUMIFS(Data_Panel!$D$6:$D$44,Data_Panel!$A$6:$A$44,B136),IF(A136=Data_Panel!$E$5,SUMIFS(Data_Panel!$E$6:$E$44,Data_Panel!$A$6:$A$44,B136),IF(A136=Data_Panel!$F$5,SUMIFS(Data_Panel!$F$6:$F$44,Data_Panel!$A$6:$A$44,B136),IF(A136=Data_Panel!$G$5,SUMIFS(Data_Panel!$G$6:$G$44,Data_Panel!$A$6:$A$44,B136),IF(A136=Data_Panel!$H$5,SUMIFS(Data_Panel!$H$6:$H$44,Data_Panel!$A$6:$A$44,B136),IF(A136=Data_Panel!$I$5,SUMIFS(Data_Panel!$I$6:$I$44,Data_Panel!$A$6:$A$44,B136),IF(A136=Data_Panel!$J$5,SUMIFS(Data_Panel!$J$6:$J$44,Data_Panel!$A$6:$A$44,B136),"period not in panel")))))))) -> 45.5 | M136: =IF(L136="not in panel",0,ABS(N(L136)-D136)) -> 0
A137: 2025-H1 | B137: A08 | C137: Expensed automotive R&D | D137: 690 | E137: EUR m | F137: FACT | G137: MANUAL | H137: S016 | I137: 25 | J137: EUR 1m | K137: =COUNTIFS($A$6:$A$243,A137,$B$6:$B$243,B137) -> 1 | L137: =IF(COUNTIF(Data_Panel!$A$6:$A$44,B137)=0,"not in panel",IF(A137=Data_Panel!$D$5,SUMIFS(Data_Panel!$D$6:$D$44,Data_Panel!$A$6:$A$44,B137),IF(A137=Data_Panel!$E$5,SUMIFS(Data_Panel!$E$6:$E$44,Data_Panel!$A$6:$A$44,B137),IF(A137=Data_Panel!$F$5,SUMIFS(Data_Panel!$F$6:$F$44,Data_Panel!$A$6:$A$44,B137),IF(A137=Data_Panel!$G$5,SUMIFS(Data_Panel!$G$6:$G$44,Data_Panel!$A$6:$A$44,B137),IF(A137=Data_Panel!$H$5,SUMIFS(Data_Panel!$H$6:$H$44,Data_Panel!$A$6:$A$44,B137),IF(A137=Data_Panel!$I$5,SUMIFS(Data_Panel!$I$6:$I$44,Data_Panel!$A$6:$A$44,B137),IF(A137=Data_Panel!$J$5,SUMIFS(Data_Panel!$J$6:$J$44,Data_Panel!$A$6:$A$44,B137),"period not in panel")))))))) -> 690 | M137: =IF(L137="not in panel",0,ABS(N(L137)-D137)) -> 0
A138: 2025-H1 | B138: A09 | C138: Amortisation of capitalised R&D | D138: 600 | E138: EUR m | F138: FACT | G138: MANUAL | H138: S016 | I138: 25 | J138: EUR 1m | K138: =COUNTIFS($A$6:$A$243,A138,$B$6:$B$243,B138) -> 1 | L138: =IF(COUNTIF(Data_Panel!$A$6:$A$44,B138)=0,"not in panel",IF(A138=Data_Panel!$D$5,SUMIFS(Data_Panel!$D$6:$D$44,Data_Panel!$A$6:$A$44,B138),IF(A138=Data_Panel!$E$5,SUMIFS(Data_Panel!$E$6:$E$44,Data_Panel!$A$6:$A$44,B138),IF(A138=Data_Panel!$F$5,SUMIFS(Data_Panel!$F$6:$F$44,Data_Panel!$A$6:$A$44,B138),IF(A138=Data_Panel!$G$5,SUMIFS(Data_Panel!$G$6:$G$44,Data_Panel!$A$6:$A$44,B138),IF(A138=Data_Panel!$H$5,SUMIFS(Data_Panel!$H$6:$H$44,Data_Panel!$A$6:$A$44,B138),IF(A138=Data_Panel!$I$5,SUMIFS(Data_Panel!$I$6:$I$44,Data_Panel!$A$6:$A$44,B138),IF(A138=Data_Panel!$J$5,SUMIFS(Data_Panel!$J$6:$J$44,Data_Panel!$A$6:$A$44,B138),"period not in panel")))))))) -> 600 | M138: =IF(L138="not in panel",0,ABS(N(L138)-D138)) -> 0
A139: 2025-H1 | B139: A10 | C139: Automotive capex | D139: 965 | E139: EUR m | F139: FACT | G139: MANUAL | H139: S016 | I139: 25 | J139: EUR 1m | K139: =COUNTIFS($A$6:$A$243,A139,$B$6:$B$243,B139) -> 1 | L139: =IF(COUNTIF(Data_Panel!$A$6:$A$44,B139)=0,"not in panel",IF(A139=Data_Panel!$D$5,SUMIFS(Data_Panel!$D$6:$D$44,Data_Panel!$A$6:$A$44,B139),IF(A139=Data_Panel!$E$5,SUMIFS(Data_Panel!$E$6:$E$44,Data_Panel!$A$6:$A$44,B139),IF(A139=Data_Panel!$F$5,SUMIFS(Data_Panel!$F$6:$F$44,Data_Panel!$A$6:$A$44,B139),IF(A139=Data_Panel!$G$5,SUMIFS(Data_Panel!$G$6:$G$44,Data_Panel!$A$6:$A$44,B139),IF(A139=Data_Panel!$H$5,SUMIFS(Data_Panel!$H$6:$H$44,Data_Panel!$A$6:$A$44,B139),IF(A139=Data_Panel!$I$5,SUMIFS(Data_Panel!$I$6:$I$44,Data_Panel!$A$6:$A$44,B139),IF(A139=Data_Panel!$J$5,SUMIFS(Data_Panel!$J$6:$J$44,Data_Panel!$A$6:$A$44,B139),"period not in panel")))))))) -> 965 | M139: =IF(L139="not in panel",0,ABS(N(L139)-D139)) -> 0
A140: 2025-H1 | B140: A11 | C140: Automotive depreciation on capex | D140: 1156 | E140: EUR m | F140: FACT | G140: MANUAL | H140: S016 | I140: 25 | J140: EUR 1m | K140: =COUNTIFS($A$6:$A$243,A140,$B$6:$B$243,B140) -> 1 | L140: =IF(COUNTIF(Data_Panel!$A$6:$A$44,B140)=0,"not in panel",IF(A140=Data_Panel!$D$5,SUMIFS(Data_Panel!$D$6:$D$44,Data_Panel!$A$6:$A$44,B140),IF(A140=Data_Panel!$E$5,SUMIFS(Data_Panel!$E$6:$E$44,Data_Panel!$A$6:$A$44,B140),IF(A140=Data_Panel!$F$5,SUMIFS(Data_Panel!$F$6:$F$44,Data_Panel!$A$6:$A$44,B140),IF(A140=Data_Panel!$G$5,SUMIFS(Data_Panel!$G$6:$G$44,Data_Panel!$A$6:$A$44,B140),IF(A140=Data_Panel!$H$5,SUMIFS(Data_Panel!$H$6:$H$44,Data_Panel!$A$6:$A$44,B140),IF(A140=Data_Panel!$I$5,SUMIFS(Data_Panel!$I$6:$I$44,Data_Panel!$A$6:$A$44,B140),IF(A140=Data_Panel!$J$5,SUMIFS(Data_Panel!$J$6:$J$44,Data_Panel!$A$6:$A$44,B140),"period not in panel")))))))) -> 1156 | M140: =IF(L140="not in panel",0,ABS(N(L140)-D140)) -> 0
A141: 2025-H1 | B141: A12 | C141: Automotive total D&A | D141: 1756 | E141: EUR m | F141: FACT | G141: MANUAL | H141: S016 | I141: 25 | J141: EUR 1m | K141: =COUNTIFS($A$6:$A$243,A141,$B$6:$B$243,B141) -> 1 | L141: =IF(COUNTIF(Data_Panel!$A$6:$A$44,B141)=0,"not in panel",IF(A141=Data_Panel!$D$5,SUMIFS(Data_Panel!$D$6:$D$44,Data_Panel!$A$6:$A$44,B141),IF(A141=Data_Panel!$E$5,SUMIFS(Data_Panel!$E$6:$E$44,Data_Panel!$A$6:$A$44,B141),IF(A141=Data_Panel!$F$5,SUMIFS(Data_Panel!$F$6:$F$44,Data_Panel!$A$6:$A$44,B141),IF(A141=Data_Panel!$G$5,SUMIFS(Data_Panel!$G$6:$G$44,Data_Panel!$A$6:$A$44,B141),IF(A141=Data_Panel!$H$5,SUMIFS(Data_Panel!$H$6:$H$44,Data_Panel!$A$6:$A$44,B141),IF(A141=Data_Panel!$I$5,SUMIFS(Data_Panel!$I$6:$I$44,Data_Panel!$A$6:$A$44,B141),IF(A141=Data_Panel!$J$5,SUMIFS(Data_Panel!$J$6:$J$44,Data_Panel!$A$6:$A$44,B141),"period not in panel")))))))) -> 1756 | M141: =IF(L141="not in panel",0,ABS(N(L141)-D141)) -> 0
... A169: 2025-H1 | B169: X05 | C169: Impairment losses included in automotive D&A | D169: 295 | E169: EUR m | F169: FACT | G169: MANUAL | H169: S010 | I169: 32 | J169: EUR 1m | K169: =COUNTIFS($A$6:$A$243,A169,$B$6:$B$243,B169) -> 1 | L169: =IF(COUNTIF(Data_Panel!$A$6:$A$44,B169)=0,"not in panel",IF(A169=Data_Panel!$D$5,SUMIFS(Data_Panel!$D$6:$D$44,Data_Panel!$A$6:$A$44,B169),IF(A169=Data_Panel!$E$5,SUMIFS(Data_Panel!$E$6:$E$44,Data_Panel!$A$6:$A$44,B169),IF(A169=Data_Panel!$F$5,SUMIFS(Data_Panel!$F$6:$F$44,Data_Panel!$A$6:$A$44,B169),IF(A169=Data_Panel!$G$5,SUMIFS(Data_Panel!$G$6:$G$44,Data_Panel!$A$6:$A$44,B169),IF(A169=Data_Panel!$H$5,SUMIFS(Data_Panel!$H$6:$H$44,Data_Panel!$A$6:$A$44,B169),IF(A169=Data_Panel!$I$5,SUMIFS(Data_Panel!$I$6:$I$44,Data_Panel!$A$6:$A$44,B169),IF(A169=Data_Panel!$J$5,SUMIFS(Data_Panel!$J$6:$J$44,Data_Panel!$A$6:$A$44,B169),"period not in panel")))))))) -> 295 | M169: =IF(L169="not in panel",0,ABS(N(L169)-D169)) -> 0
A170: 2025-H2 | B170: A01 | C170: Automotive sales revenue | D170: 16047 | E170: EUR m | F170: DERIVED | G170: SQL_DERIVED | I170: FY - H1: 2025-FY (S013) minus 2025-H1 (S010) | J170: derived; inputs rounded: FY EUR 1m / H1 EUR 1m | K170: =COUNTIFS($A$6:$A$243,A170,$B$6:$B$243,B170) -> 1 | L170: =IF(COUNTIF(Data_Panel!$A$6:$A$44,B170)=0,"not in panel",IF(A170=Data_Panel!$D$5,SUMIFS(Data_Panel!$D$6:$D$44,Data_Panel!$A$6:$A$44,B170),IF(A170=Data_Panel!$E$5,SUMIFS(Data_Panel!$E$6:$E$44,Data_Panel!$A$6:$A$44,B170),IF(A170=Data_Panel!$F$5,SUMIFS(Data_Panel!$F$6:$F$44,Data_Panel!$A$6:$A$44,B170),IF(A170=Data_Panel!$G$5,SUMIFS(Data_Panel!$G$6:$G$44,Data_Panel!$A$6:$A$44,B170),IF(A170=Data_Panel!$H$5,SUMIFS(Data_Panel!$H$6:$H$44,Data_Panel!$A$6:$A$44,B170),IF(A170=Data_Panel!$I$5,SUMIFS(Data_Panel!$I$6:$I$44,Data_Panel!$A$6:$A$44,B170),IF(A170=Data_Panel!$J$5,SUMIFS(Data_Panel!$J$6:$J$44,Data_Panel!$A$6:$A$44,B170),"period not in panel")))))))) -> 16047 | M170: =IF(L170="not in panel",0,ABS(N(L170)-D170)) -> 0
A171: 2025-H2 | B171: A02 | C171: Automotive operating profit | D171: -742 | E171: EUR m | F171: DERIVED | G171: SQL_DERIVED | I171: FY - H1: 2025-FY (S013) minus 2025-H1 (S010) | J171: derived; inputs rounded: FY EUR 1m / H1 EUR 1m | K171: =COUNTIFS($A$6:$A$243,A171,$B$6:$B$243,B171) -> 1 | L171: =IF(COUNTIF(Data_Panel!$A$6:$A$44,B171)=0,"not in panel",IF(A171=Data_Panel!$D$5,SUMIFS(Data_Panel!$D$6:$D$44,Data_Panel!$A$6:$A$44,B171),IF(A171=Data_Panel!$E$5,SUMIFS(Data_Panel!$E$6:$E$44,Data_Panel!$A$6:$A$44,B171),IF(A171=Data_Panel!$F$5,SUMIFS(Data_Panel!$F$6:$F$44,Data_Panel!$A$6:$A$44,B171),IF(A171=Data_Panel!$G$5,SUMIFS(Data_Panel!$G$6:$G$44,Data_Panel!$A$6:$A$44,B171),IF(A171=Data_Panel!$H$5,SUMIFS(Data_Panel!$H$6:$H$44,Data_Panel!$A$6:$A$44,B171),IF(A171=Data_Panel!$I$5,SUMIFS(Data_Panel!$I$6:$I$44,Data_Panel!$A$6:$A$44,B171),IF(A171=Data_Panel!$J$5,SUMIFS(Data_Panel!$J$6:$J$44,Data_Panel!$A$6:$A$44,B171),"period not in panel")))))))) -> -742 | M171: =IF(L171="not in panel",0,ABS(N(L171)-D171)) -> 0
A172: 2025-H2 | B172: A03 | C172: Automotive EBITDA | D172: 1694 | E172: EUR m | F172: DERIVED | G172: SQL_DERIVED | I172: FY - H1: 2025-FY (S013) minus 2025-H1 (S010) | J172: derived; inputs rounded: FY EUR 1m / H1 EUR 1m | K172: =COUNTIFS($A$6:$A$243,A172,$B$6:$B$243,B172) -> 1 | L172: =IF(COUNTIF(Data_Panel!$A$6:$A$44,B172)=0,"not in panel",IF(A172=Data_Panel!$D$5,SUMIFS(Data_Panel!$D$6:$D$44,Data_Panel!$A$6:$A$44,B172),IF(A172=Data_Panel!$E$5,SUMIFS(Data_Panel!$E$6:$E$44,Data_Panel!$A$6:$A$44,B172),IF(A172=Data_Panel!$F$5,SUMIFS(Data_Panel!$F$6:$F$44,Data_Panel!$A$6:$A$44,B172),IF(A172=Data_Panel!$G$5,SUMIFS(Data_Panel!$G$6:$G$44,Data_Panel!$A$6:$A$44,B172),IF(A172=Data_Panel!$H$5,SUMIFS(Data_Panel!$H$6:$H$44,Data_Panel!$A$6:$A$44,B172),IF(A172=Data_Panel!$I$5,SUMIFS(Data_Panel!$I$6:$I$44,Data_Panel!$A$6:$A$44,B172),IF(A172=Data_Panel!$J$5,SUMIFS(Data_Panel!$J$6:$J$44,Data_Panel!$A$6:$A$44,B172),"period not in panel")))))))) -> 1694 | M172: =IF(L172="not in panel",0,ABS(N(L172)-D172)) -> 0
A173: 2025-H2 | B173: A05 | C173: Automotive R&D costs (total) | D173: 1028 | E173: EUR m | F173: DERIVED | G173: SQL_DERIVED | I173: FY - H1: 2025-FY (S011) minus 2025-H1 (S016) | J173: derived; inputs rounded: FY EUR 1m / H1 EUR 1m | K173: =COUNTIFS($A$6:$A$243,A173,$B$6:$B$243,B173) -> 1 | L173: =IF(COUNTIF(Data_Panel!$A$6:$A$44,B173)=0,"not in panel",IF(A173=Data_Panel!$D$5,SUMIFS(Data_Panel!$D$6:$D$44,Data_Panel!$A$6:$A$44,B173),IF(A173=Data_Panel!$E$5,SUMIFS(Data_Panel!$E$6:$E$44,Data_Panel!$A$6:$A$44,B173),IF(A173=Data_Panel!$F$5,SUMIFS(Data_Panel!$F$6:$F$44,Data_Panel!$A$6:$A$44,B173),IF(A173=Data_Panel!$G$5,SUMIFS(Data_Panel!$G$6:$G$44,Data_Panel!$A$6:$A$44,B173),IF(A173=Data_Panel!$H$5,SUMIFS(Data_Panel!$H$6:$H$44,Data_Panel!$A$6:$A$44,B173),IF(A173=Data_Panel!$I$5,SUMIFS(Data_Panel!$I$6:$I$44,Data_Panel!$A$6:$A$44,B173),IF(A173=Data_Panel!$J$5,SUMIFS(Data_Panel!$J$6:$J$44,Data_Panel!$A$6:$A$44,B173),"period not in panel")))))))) -> 1028 | M173: =IF(L173="not in panel",0,ABS(N(L173)-D173)) -> 0
A174: 2025-H2 | B174: A06 | C174: Automotive capitalised development costs | D174: 388 | E174: EUR m | F174: DERIVED | G174: SQL_DERIVED | I174: FY - H1: 2025-FY (S011) minus 2025-H1 (S016) | J174: derived; inputs rounded: FY EUR 1m / H1 EUR 1m | K174: =COUNTIFS($A$6:$A$243,A174,$B$6:$B$243,B174) -> 1 | L174: =IF(COUNTIF(Data_Panel!$A$6:$A$44,B174)=0,"not in panel",IF(A174=Data_Panel!$D$5,SUMIFS(Data_Panel!$D$6:$D$44,Data_Panel!$A$6:$A$44,B174),IF(A174=Data_Panel!$E$5,SUMIFS(Data_Panel!$E$6:$E$44,Data_Panel!$A$6:$A$44,B174),IF(A174=Data_Panel!$F$5,SUMIFS(Data_Panel!$F$6:$F$44,Data_Panel!$A$6:$A$44,B174),IF(A174=Data_Panel!$G$5,SUMIFS(Data_Panel!$G$6:$G$44,Data_Panel!$A$6:$A$44,B174),IF(A174=Data_Panel!$H$5,SUMIFS(Data_Panel!$H$6:$H$44,Data_Panel!$A$6:$A$44,B174),IF(A174=Data_Panel!$I$5,SUMIFS(Data_Panel!$I$6:$I$44,Data_Panel!$A$6:$A$44,B174),IF(A174=Data_Panel!$J$5,SUMIFS(Data_Panel!$J$6:$J$44,Data_Panel!$A$6:$A$44,B174),"period not in panel")))))))) -> 388 | M174: =IF(L174="not in panel",0,ABS(N(L174)-D174)) -> 0
A175: 2025-H2 | B175: A08 | C175: Expensed automotive R&D | D175: 639 | E175: EUR m | F175: DERIVED | G175: SQL_DERIVED | I175: FY - H1: 2025-FY (S011) minus 2025-H1 (S016) | J175: derived; inputs rounded: FY EUR 1m / H1 EUR 1m | K175: =COUNTIFS($A$6:$A$243,A175,$B$6:$B$243,B175) -> 1 | L175: =IF(COUNTIF(Data_Panel!$A$6:$A$44,B175)=0,"not in panel",IF(A175=Data_Panel!$D$5,SUMIFS(Data_Panel!$D$6:$D$44,Data_Panel!$A$6:$A$44,B175),IF(A175=Data_Panel!$E$5,SUMIFS(Data_Panel!$E$6:$E$44,Data_Panel!$A$6:$A$44,B175),IF(A175=Data_Panel!$F$5,SUMIFS(Data_Panel!$F$6:$F$44,Data_Panel!$A$6:$A$44,B175),IF(A175=Data_Panel!$G$5,SUMIFS(Data_Panel!$G$6:$G$44,Data_Panel!$A$6:$A$44,B175),IF(A175=Data_Panel!$H$5,SUMIFS(Data_Panel!$H$6:$H$44,Data_Panel!$A$6:$A$44,B175),IF(A175=Data_Panel!$I$5,SUMIFS(Data_Panel!$I$6:$I$44,Data_Panel!$A$6:$A$44,B175),IF(A175=Data_Panel!$J$5,SUMIFS(Data_Panel!$J$6:$J$44,Data_Panel!$A$6:$A$44,B175),"period not in panel")))))))) -> 639 | M175: =IF(L175="not in panel",0,ABS(N(L175)-D175)) -> 0
A176: 2025-H2 | B176: A09 | C176: Amortisation of capitalised R&D | D176: 1230 | E176: EUR m | F176: DERIVED | G176: SQL_DERIVED | I176: FY - H1: 2025-FY (S011) minus 2025-H1 (S016) | J176: derived; inputs rounded: FY EUR 1m / H1 EUR 1m | K176: =COUNTIFS($A$6:$A$243,A176,$B$6:$B$243,B176) -> 1 | L176: =IF(COUNTIF(Data_Panel!$A$6:$A$44,B176)=0,"not in panel",IF(A176=Data_Panel!$D$5,SUMIFS(Data_Panel!$D$6:$D$44,Data_Panel!$A$6:$A$44,B176),IF(A176=Data_Panel!$E$5,SUMIFS(Data_Panel!$E$6:$E$44,Data_Panel!$A$6:$A$44,B176),IF(A176=Data_Panel!$F$5,SUMIFS(Data_Panel!$F$6:$F$44,Data_Panel!$A$6:$A$44,B176),IF(A176=Data_Panel!$G$5,SUMIFS(Data_Panel!$G$6:$G$44,Data_Panel!$A$6:$A$44,B176),IF(A176=Data_Panel!$H$5,SUMIFS(Data_Panel!$H$6:$H$44,Data_Panel!$A$6:$A$44,B176),IF(A176=Data_Panel!$I$5,SUMIFS(Data_Panel!$I$6:$I$44,Data_Panel!$A$6:$A$44,B176),IF(A176=Data_Panel!$J$5,SUMIFS(Data_Panel!$J$6:$J$44,Data_Panel!$A$6:$A$44,B176),"period not in panel")))))))) -> 1230 | M176: =IF(L176="not in panel",0,ABS(N(L176)-D176)) -> 0
A177: 2025-H2 | B177: A10 | C177: Automotive capex | D177: 1172 | E177: EUR m | F177: DERIVED | G177: SQL_DERIVED | I177: FY - H1: 2025-FY (S011) minus 2025-H1 (S016) | J177: derived; inputs rounded: FY EUR 1m / H1 EUR 1m | K177: =COUNTIFS($A$6:$A$243,A177,$B$6:$B$243,B177) -> 1 | L177: =IF(COUNTIF(Data_Panel!$A$6:$A$44,B177)=0,"not in panel",IF(A177=Data_Panel!$D$5,SUMIFS(Data_Panel!$D$6:$D$44,Data_Panel!$A$6:$A$44,B177),IF(A177=Data_Panel!$E$5,SUMIFS(Data_Panel!$E$6:$E$44,Data_Panel!$A$6:$A$44,B177),IF(A177=Data_Panel!$F$5,SUMIFS(Data_Panel!$F$6:$F$44,Data_Panel!$A$6:$A$44,B177),IF(A177=Data_Panel!$G$5,SUMIFS(Data_Panel!$G$6:$G$44,Data_Panel!$A$6:$A$44,B177),IF(A177=Data_Panel!$H$5,SUMIFS(Data_Panel!$H$6:$H$44,Data_Panel!$A$6:$A$44,B177),IF(A177=Data_Panel!$I$5,SUMIFS(Data_Panel!$I$6:$I$44,Data_Panel!$A$6:$A$44,B177),IF(A177=Data_Panel!$J$5,SUMIFS(Data_Panel!$J$6:$J$44,Data_Panel!$A$6:$A$44,B177),"period not in panel")))))))) -> 1172 | M177: =IF(L177="not in panel",0,ABS(N(L177)-D177)) -> 0
A178: 2025-H2 | B178: A11 | C178: Automotive depreciation on capex | D178: 1206 | E178: EUR m | F178: DERIVED | G178: SQL_DERIVED | I178: FY - H1: 2025-FY (S011) minus 2025-H1 (S016) | J178: derived; inputs rounded: FY EUR 1m / H1 EUR 1m | K178: =COUNTIFS($A$6:$A$243,A178,$B$6:$B$243,B178) -> 1 | L178: =IF(COUNTIF(Data_Panel!$A$6:$A$44,B178)=0,"not in panel",IF(A178=Data_Panel!$D$5,SUMIFS(Data_Panel!$D$6:$D$44,Data_Panel!$A$6:$A$44,B178),IF(A178=Data_Panel!$E$5,SUMIFS(Data_Panel!$E$6:$E$44,Data_Panel!$A$6:$A$44,B178),IF(A178=Data_Panel!$F$5,SUMIFS(Data_Panel!$F$6:$F$44,Data_Panel!$A$6:$A$44,B178),IF(A178=Data_Panel!$G$5,SUMIFS(Data_Panel!$G$6:$G$44,Data_Panel!$A$6:$A$44,B178),IF(A178=Data_Panel!$H$5,SUMIFS(Data_Panel!$H$6:$H$44,Data_Panel!$A$6:$A$44,B178),IF(A178=Data_Panel!$I$5,SUMIFS(Data_Panel!$I$6:$I$44,Data_Panel!$A$6:$A$44,B178),IF(A178=Data_Panel!$J$5,SUMIFS(Data_Panel!$J$6:$J$44,Data_Panel!$A$6:$A$44,B178),"period not in panel")))))))) -> 1206 | M178: =IF(L178="not in panel",0,ABS(N(L178)-D178)) -> 0
A179: 2025-H2 | B179: A12 | C179: Automotive total D&A | D179: 2436 | E179: EUR m | F179: DERIVED | G179: SQL_DERIVED | I179: FY - H1: 2025-FY (S011) minus 2025-H1 (S016) | J179: derived; inputs rounded: FY EUR 1m / H1 EUR 1m | K179: =COUNTIFS($A$6:$A$243,A179,$B$6:$B$243,B179) -> 1 | L179: =IF(COUNTIF(Data_Panel!$A$6:$A$44,B179)=0,"not in panel",IF(A179=Data_Panel!$D$5,SUMIFS(Data_Panel!$D$6:$D$44,Data_Panel!$A$6:$A$44,B179),IF(A179=Data_Panel!$E$5,SUMIFS(Data_Panel!$E$6:$E$44,Data_Panel!$A$6:$A$44,B179),IF(A179=Data_Panel!$F$5,SUMIFS(Data_Panel!$F$6:$F$44,Data_Panel!$A$6:$A$44,B179),IF(A179=Data_Panel!$G$5,SUMIFS(Data_Panel!$G$6:$G$44,Data_Panel!$A$6:$A$44,B179),IF(A179=Data_Panel!$H$5,SUMIFS(Data_Panel!$H$6:$H$44,Data_Panel!$A$6:$A$44,B179),IF(A179=Data_Panel!$I$5,SUMIFS(Data_Panel!$I$6:$I$44,Data_Panel!$A$6:$A$44,B179),IF(A179=Data_Panel!$J$5,SUMIFS(Data_Panel!$J$6:$J$44,Data_Panel!$A$6:$A$44,B179),"period not in panel")))))))) -> 2436 | M179: =IF(L179="not in panel",0,ABS(N(L179)-D179)) -> 0
A180: 2025-H2 | B180: A13 | C180: Automotive net cash flow | D180: 1117.1216 | E180: EUR m | F180: DERIVED | G180: SQL_DERIVED | I180: FY - H1: 2025-FY (S025) minus 2025-H1 (S025) | J180: derived; inputs rounded: FY exact (EUR, converted to EUR m) / H1 exact (EUR, converted to EUR m) | K180: =COUNTIFS($A$6:$A$243,A180,$B$6:$B$243,B180) -> 1 | L180: =IF(COUNTIF(Data_Panel!$A$6:$A$44,B180)=0,"not in panel",IF(A180=Data_Panel!$D$5,SUMIFS(Data_Panel!$D$6:$D$44,Data_Panel!$A$6:$A$44,B180),IF(A180=Data_Panel!$E$5,SUMIFS(Data_Panel!$E$6:$E$44,Data_Panel!$A$6:$A$44,B180),IF(A180=Data_Panel!$F$5,SUMIFS(Data_Panel!$F$6:$F$44,Data_Panel!$A$6:$A$44,B180),IF(A180=Data_Panel!$G$5,SUMIFS(Data_Panel!$G$6:$G$44,Data_Panel!$A$6:$A$44,B180),IF(A180=Data_Panel!$H$5,SUMIFS(Data_Panel!$H$6:$H$44,Data_Panel!$A$6:$A$44,B180),IF(A180=Data_Panel!$I$5,SUMIFS(Data_Panel!$I$6:$I$44,Data_Panel!$A$6:$A$44,B180),IF(A180=Data_Panel!$J$5,SUMIFS(Data_Panel!$J$6:$J$44,Data_Panel!$A$6:$A$44,B180),"period not in panel")))))))) -> 1117.1216 | M180: =IF(L180="not in panel",0,ABS(N(L180)-D180)) -> 0
A181: 2025-H2 | B181: A13a | C181: Automotive cash flows from operating activities | D181: 2805.3866 | E181: EUR m | F181: DERIVED | G181: SQL_DERIVED | I181: FY - H1: 2025-FY (S025) minus 2025-H1 (S025) | J181: derived; inputs rounded: FY exact (EUR, converted to EUR m) / H1 exact (EUR, converted to EUR m) | K181: =COUNTIFS($A$6:$A$243,A181,$B$6:$B$243,B181) -> 1 | L181: =IF(COUNTIF(Data_Panel!$A$6:$A$44,B181)=0,"not in panel",IF(A181=Data_Panel!$D$5,SUMIFS(Data_Panel!$D$6:$D$44,Data_Panel!$A$6:$A$44,B181),IF(A181=Data_Panel!$E$5,SUMIFS(Data_Panel!$E$6:$E$44,Data_Panel!$A$6:$A$44,B181),IF(A181=Data_Panel!$F$5,SUMIFS(Data_Panel!$F$6:$F$44,Data_Panel!$A$6:$A$44,B181),IF(A181=Data_Panel!$G$5,SUMIFS(Data_Panel!$G$6:$G$44,Data_Panel!$A$6:$A$44,B181),IF(A181=Data_Panel!$H$5,SUMIFS(Data_Panel!$H$6:$H$44,Data_Panel!$A$6:$A$44,B181),IF(A181=Data_Panel!$I$5,SUMIFS(Data_Panel!$I$6:$I$44,Data_Panel!$A$6:$A$44,B181),IF(A181=Data_Panel!$J$5,SUMIFS(Data_Panel!$J$6:$J$44,Data_Panel!$A$6:$A$44,B181),"period not in panel")))))))) -> 2805.3866 | M181: =IF(L181="not in panel",0,ABS(N(L181)-D181)) -> 0
... A203: 2025-H2 | B203: X05 | C203: Impairment losses included in automotive D&A | D203: 900 | E203: EUR m | F203: DERIVED | G203: SQL_DERIVED | I203: FY - H1: 2025-FY (S012) minus 2025-H1 (S010) | J203: derived; inputs rounded: FY EUR 1m / H1 EUR 1m | K203: =COUNTIFS($A$6:$A$243,A203,$B$6:$B$243,B203) -> 1 | L203: =IF(COUNTIF(Data_Panel!$A$6:$A$44,B203)=0,"not in panel",IF(A203=Data_Panel!$D$5,SUMIFS(Data_Panel!$D$6:$D$44,Data_Panel!$A$6:$A$44,B203),IF(A203=Data_Panel!$E$5,SUMIFS(Data_Panel!$E$6:$E$44,Data_Panel!$A$6:$A$44,B203),IF(A203=Data_Panel!$F$5,SUMIFS(Data_Panel!$F$6:$F$44,Data_Panel!$A$6:$A$44,B203),IF(A203=Data_Panel!$G$5,SUMIFS(Data_Panel!$G$6:$G$44,Data_Panel!$A$6:$A$44,B203),IF(A203=Data_Panel!$H$5,SUMIFS(Data_Panel!$H$6:$H$44,Data_Panel!$A$6:$A$44,B203),IF(A203=Data_Panel!$I$5,SUMIFS(Data_Panel!$I$6:$I$44,Data_Panel!$A$6:$A$44,B203),IF(A203=Data_Panel!$J$5,SUMIFS(Data_Panel!$J$6:$J$44,Data_Panel!$A$6:$A$44,B203),"period not in panel")))))))) -> 900 | M203: =IF(L203="not in panel",0,ABS(N(L203)-D203)) -> 0
A204: 2026-H1 | B204: A01 | C204: Automotive sales revenue | D204: 15158 | E204: EUR m | F204: FACT | G204: MANUAL | H204: S017 | I204: 12 (Automotive EBITDA margin table) | J204: EUR 1m | K204: =COUNTIFS($A$6:$A$243,A204,$B$6:$B$243,B204) -> 1 | L204: =IF(COUNTIF(Data_Panel!$A$6:$A$44,B204)=0,"not in panel",IF(A204=Data_Panel!$D$5,SUMIFS(Data_Panel!$D$6:$D$44,Data_Panel!$A$6:$A$44,B204),IF(A204=Data_Panel!$E$5,SUMIFS(Data_Panel!$E$6:$E$44,Data_Panel!$A$6:$A$44,B204),IF(A204=Data_Panel!$F$5,SUMIFS(Data_Panel!$F$6:$F$44,Data_Panel!$A$6:$A$44,B204),IF(A204=Data_Panel!$G$5,SUMIFS(Data_Panel!$G$6:$G$44,Data_Panel!$A$6:$A$44,B204),IF(A204=Data_Panel!$H$5,SUMIFS(Data_Panel!$H$6:$H$44,Data_Panel!$A$6:$A$44,B204),IF(A204=Data_Panel!$I$5,SUMIFS(Data_Panel!$I$6:$I$44,Data_Panel!$A$6:$A$44,B204),IF(A204=Data_Panel!$J$5,SUMIFS(Data_Panel!$J$6:$J$44,Data_Panel!$A$6:$A$44,B204),"period not in panel")))))))) -> 15158 | M204: =IF(L204="not in panel",0,ABS(N(L204)-D204)) -> 0
A205: 2026-H1 | B205: A02 | C205: Automotive operating profit | D205: 1208 | E205: EUR m | F205: FACT | G205: MANUAL | H205: S017 | I205: 12 (Automotive EBITDA margin table) | J205: EUR 1m | K205: =COUNTIFS($A$6:$A$243,A205,$B$6:$B$243,B205) -> 1 | L205: =IF(COUNTIF(Data_Panel!$A$6:$A$44,B205)=0,"not in panel",IF(A205=Data_Panel!$D$5,SUMIFS(Data_Panel!$D$6:$D$44,Data_Panel!$A$6:$A$44,B205),IF(A205=Data_Panel!$E$5,SUMIFS(Data_Panel!$E$6:$E$44,Data_Panel!$A$6:$A$44,B205),IF(A205=Data_Panel!$F$5,SUMIFS(Data_Panel!$F$6:$F$44,Data_Panel!$A$6:$A$44,B205),IF(A205=Data_Panel!$G$5,SUMIFS(Data_Panel!$G$6:$G$44,Data_Panel!$A$6:$A$44,B205),IF(A205=Data_Panel!$H$5,SUMIFS(Data_Panel!$H$6:$H$44,Data_Panel!$A$6:$A$44,B205),IF(A205=Data_Panel!$I$5,SUMIFS(Data_Panel!$I$6:$I$44,Data_Panel!$A$6:$A$44,B205),IF(A205=Data_Panel!$J$5,SUMIFS(Data_Panel!$J$6:$J$44,Data_Panel!$A$6:$A$44,B205),"period not in panel")))))))) -> 1208 | M205: =IF(L205="not in panel",0,ABS(N(L205)-D205)) -> 0
A206: 2026-H1 | B206: A03 | C206: Automotive EBITDA | D206: 2767 | E206: EUR m | F206: FACT | G206: MANUAL | H206: S017 | I206: 12 (Automotive EBITDA margin table) | J206: EUR 1m | K206: =COUNTIFS($A$6:$A$243,A206,$B$6:$B$243,B206) -> 1 | L206: =IF(COUNTIF(Data_Panel!$A$6:$A$44,B206)=0,"not in panel",IF(A206=Data_Panel!$D$5,SUMIFS(Data_Panel!$D$6:$D$44,Data_Panel!$A$6:$A$44,B206),IF(A206=Data_Panel!$E$5,SUMIFS(Data_Panel!$E$6:$E$44,Data_Panel!$A$6:$A$44,B206),IF(A206=Data_Panel!$F$5,SUMIFS(Data_Panel!$F$6:$F$44,Data_Panel!$A$6:$A$44,B206),IF(A206=Data_Panel!$G$5,SUMIFS(Data_Panel!$G$6:$G$44,Data_Panel!$A$6:$A$44,B206),IF(A206=Data_Panel!$H$5,SUMIFS(Data_Panel!$H$6:$H$44,Data_Panel!$A$6:$A$44,B206),IF(A206=Data_Panel!$I$5,SUMIFS(Data_Panel!$I$6:$I$44,Data_Panel!$A$6:$A$44,B206),IF(A206=Data_Panel!$J$5,SUMIFS(Data_Panel!$J$6:$J$44,Data_Panel!$A$6:$A$44,B206),"period not in panel")))))))) -> 2767 | M206: =IF(L206="not in panel",0,ABS(N(L206)-D206)) -> 0
A207: 2026-H1 | B207: A04 | C207: Automotive EBITDA margin | D207: 18.3 | E207: % | F207: FACT | G207: MANUAL | H207: S017 | I207: 12 (Automotive EBITDA margin table) | J207: 0.1pp | K207: =COUNTIFS($A$6:$A$243,A207,$B$6:$B$243,B207) -> 1 | L207: =IF(COUNTIF(Data_Panel!$A$6:$A$44,B207)=0,"not in panel",IF(A207=Data_Panel!$D$5,SUMIFS(Data_Panel!$D$6:$D$44,Data_Panel!$A$6:$A$44,B207),IF(A207=Data_Panel!$E$5,SUMIFS(Data_Panel!$E$6:$E$44,Data_Panel!$A$6:$A$44,B207),IF(A207=Data_Panel!$F$5,SUMIFS(Data_Panel!$F$6:$F$44,Data_Panel!$A$6:$A$44,B207),IF(A207=Data_Panel!$G$5,SUMIFS(Data_Panel!$G$6:$G$44,Data_Panel!$A$6:$A$44,B207),IF(A207=Data_Panel!$H$5,SUMIFS(Data_Panel!$H$6:$H$44,Data_Panel!$A$6:$A$44,B207),IF(A207=Data_Panel!$I$5,SUMIFS(Data_Panel!$I$6:$I$44,Data_Panel!$A$6:$A$44,B207),IF(A207=Data_Panel!$J$5,SUMIFS(Data_Panel!$J$6:$J$44,Data_Panel!$A$6:$A$44,B207),"period not in panel")))))))) -> 18.3 | M207: =IF(L207="not in panel",0,ABS(N(L207)-D207)) -> 0
A208: 2026-H1 | B208: A05 | C208: Automotive R&D costs (total) | D208: 1116 | E208: EUR m | F208: FACT | G208: MANUAL | H208: S016 | I208: 25 | J208: EUR 1m | K208: =COUNTIFS($A$6:$A$243,A208,$B$6:$B$243,B208) -> 1 | L208: =IF(COUNTIF(Data_Panel!$A$6:$A$44,B208)=0,"not in panel",IF(A208=Data_Panel!$D$5,SUMIFS(Data_Panel!$D$6:$D$44,Data_Panel!$A$6:$A$44,B208),IF(A208=Data_Panel!$E$5,SUMIFS(Data_Panel!$E$6:$E$44,Data_Panel!$A$6:$A$44,B208),IF(A208=Data_Panel!$F$5,SUMIFS(Data_Panel!$F$6:$F$44,Data_Panel!$A$6:$A$44,B208),IF(A208=Data_Panel!$G$5,SUMIFS(Data_Panel!$G$6:$G$44,Data_Panel!$A$6:$A$44,B208),IF(A208=Data_Panel!$H$5,SUMIFS(Data_Panel!$H$6:$H$44,Data_Panel!$A$6:$A$44,B208),IF(A208=Data_Panel!$I$5,SUMIFS(Data_Panel!$I$6:$I$44,Data_Panel!$A$6:$A$44,B208),IF(A208=Data_Panel!$J$5,SUMIFS(Data_Panel!$J$6:$J$44,Data_Panel!$A$6:$A$44,B208),"period not in panel")))))))) -> 1116 | M208: =IF(L208="not in panel",0,ABS(N(L208)-D208)) -> 0
A209: 2026-H1 | B209: A06 | C209: Automotive capitalised development costs | D209: 487 | E209: EUR m | F209: FACT | G209: MANUAL | H209: S016 | I209: 25 | J209: EUR 1m | K209: =COUNTIFS($A$6:$A$243,A209,$B$6:$B$243,B209) -> 1 | L209: =IF(COUNTIF(Data_Panel!$A$6:$A$44,B209)=0,"not in panel",IF(A209=Data_Panel!$D$5,SUMIFS(Data_Panel!$D$6:$D$44,Data_Panel!$A$6:$A$44,B209),IF(A209=Data_Panel!$E$5,SUMIFS(Data_Panel!$E$6:$E$44,Data_Panel!$A$6:$A$44,B209),IF(A209=Data_Panel!$F$5,SUMIFS(Data_Panel!$F$6:$F$44,Data_Panel!$A$6:$A$44,B209),IF(A209=Data_Panel!$G$5,SUMIFS(Data_Panel!$G$6:$G$44,Data_Panel!$A$6:$A$44,B209),IF(A209=Data_Panel!$H$5,SUMIFS(Data_Panel!$H$6:$H$44,Data_Panel!$A$6:$A$44,B209),IF(A209=Data_Panel!$I$5,SUMIFS(Data_Panel!$I$6:$I$44,Data_Panel!$A$6:$A$44,B209),IF(A209=Data_Panel!$J$5,SUMIFS(Data_Panel!$J$6:$J$44,Data_Panel!$A$6:$A$44,B209),"period not in panel")))))))) -> 487 | M209: =IF(L209="not in panel",0,ABS(N(L209)-D209)) -> 0
A210: 2026-H1 | B210: A07 | C210: Capitalisation rate | D210: 43.6 | E210: % | F210: FACT | G210: MANUAL | H210: S016 | I210: 25 | J210: 0.1pp | K210: =COUNTIFS($A$6:$A$243,A210,$B$6:$B$243,B210) -> 1 | L210: =IF(COUNTIF(Data_Panel!$A$6:$A$44,B210)=0,"not in panel",IF(A210=Data_Panel!$D$5,SUMIFS(Data_Panel!$D$6:$D$44,Data_Panel!$A$6:$A$44,B210),IF(A210=Data_Panel!$E$5,SUMIFS(Data_Panel!$E$6:$E$44,Data_Panel!$A$6:$A$44,B210),IF(A210=Data_Panel!$F$5,SUMIFS(Data_Panel!$F$6:$F$44,Data_Panel!$A$6:$A$44,B210),IF(A210=Data_Panel!$G$5,SUMIFS(Data_Panel!$G$6:$G$44,Data_Panel!$A$6:$A$44,B210),IF(A210=Data_Panel!$H$5,SUMIFS(Data_Panel!$H$6:$H$44,Data_Panel!$A$6:$A$44,B210),IF(A210=Data_Panel!$I$5,SUMIFS(Data_Panel!$I$6:$I$44,Data_Panel!$A$6:$A$44,B210),IF(A210=Data_Panel!$J$5,SUMIFS(Data_Panel!$J$6:$J$44,Data_Panel!$A$6:$A$44,B210),"period not in panel")))))))) -> 43.6 | M210: =IF(L210="not in panel",0,ABS(N(L210)-D210)) -> 0
...

Sheet Data_Mix
A1: Data_Mix - controlled import of deliveries by model line and region
A2: Source: core.fact_deliveries_model / core.fact_deliveries_region (fact sheet S025; H2 = FY - H1, DERIVED). Blue = imported.
A5: period_code | B5: dimension | C5: member_id | D5: member_name | E5: top_level | F5: deliveries | G5: value_label | H5: source_id | I5: source_ref
A6: 2023-H1 | B6: model | C6: 718 | D6: 718 Boxster/Cayman | E6: TRUE | F6: 11035 | G6: FACT | H6: S025 | I6: 04 - Sales_deliveries by Model AA33
A7: 2023-H1 | B7: model | C7: 911 | D7: 911 | E7: TRUE | F7: 26124 | G7: FACT | H7: S025 | I7: 04 - Sales_deliveries by Model AA32
A8: 2023-H1 | B8: model | C8: CAY | D8: Cayenne | E8: TRUE | F8: 46884 | G8: FACT | H8: S025 | I8: 04 - Sales_deliveries by Model AA34
A9: 2023-H1 | B9: model | C9: MAC | D9: Macan (total) | E9: TRUE | F9: 47755 | G9: FACT | H9: S025 | I9: 04 - Sales_deliveries by Model AA36
A10: 2023-H1 | B10: model | C10: PAN | D10: Panamera | E10: TRUE | F10: 17565 | G10: FACT | H10: S025 | I10: 04 - Sales_deliveries by Model AA35
A11: 2023-H1 | B11: model | C11: TAY | D11: Taycan | E11: TRUE | F11: 17991 | G11: FACT | H11: S025 | I11: 04 - Sales_deliveries by Model AA39
A12: 2023-H1 | B12: region | C12: CN | D12: China | E12: TRUE | F12: 43832 | G12: FACT | H12: S025 | I12: 03 - Sales_deliveries by Region AA31
A13: 2023-H1 | B13: region | C13: DE | D13: Germany | E13: TRUE | F13: 17118 | G13: FACT | H13: S025 | I13: 03 - Sales_deliveries by Region AA29
A14: 2023-H1 | B14: region | C14: EU | D14: Europe excl. Germany | E14: TRUE | F14: 36574 | G14: FACT | H14: S025 | I14: 03 - Sales_deliveries by Region AA32
A15: 2023-H1 | B15: region | C15: NA | D15: North America | E15: TRUE | F15: 41937 | G15: FACT | H15: S025 | I15: 03 - Sales_deliveries by Region AA30
A16: 2023-H1 | B16: region | C16: OEM | D16: Overseas & Emerging Markets | E16: TRUE | F16: 27893 | G16: FACT | H16: S025 | I16: 03 - Sales_deliveries by Region AA33
A17: 2023-H2 | B17: model | C17: 718 | D17: 718 Boxster/Cayman | E17: TRUE | F17: 9483 | G17: DERIVED | I17: FY - H1 (fact sheet S025)
A18: 2023-H2 | B18: model | C18: 911 | D18: 911 | E18: TRUE | F18: 24022 | G18: DERIVED | I18: FY - H1 (fact sheet S025)
A19: 2023-H2 | B19: model | C19: CAY | D19: Cayenne | E19: TRUE | F19: 40669 | G19: DERIVED | I19: FY - H1 (fact sheet S025)
A20: 2023-H2 | B20: model | C20: MAC | D20: Macan (total) | E20: TRUE | F20: 39600 | G20: DERIVED | I20: FY - H1 (fact sheet S025)
A21: 2023-H2 | B21: model | C21: PAN | D21: Panamera | E21: TRUE | F21: 16455 | G21: DERIVED | I21: FY - H1 (fact sheet S025)
A22: 2023-H2 | B22: model | C22: TAY | D22: Taycan | E22: TRUE | F22: 22638 | G22: DERIVED | I22: FY - H1 (fact sheet S025)
A23: 2023-H2 | B23: region | C23: CN | D23: China | E23: TRUE | F23: 35451 | G23: DERIVED | I23: FY - H1 (fact sheet S025)
A24: 2023-H2 | B24: region | C24: DE | D24: Germany | E24: TRUE | F24: 15312 | G24: DERIVED | I24: FY - H1 (fact sheet S025)
A25: 2023-H2 | B25: region | C25: EU | D25: Europe excl. Germany | E25: TRUE | F25: 33655 | G25: DERIVED | I25: FY - H1 (fact sheet S025)
A26: 2023-H2 | B26: region | C26: NA | D26: North America | E26: TRUE | F26: 44122 | G26: DERIVED | I26: FY - H1 (fact sheet S025)
A27: 2023-H2 | B27: region | C27: OEM | D27: Overseas & Emerging Markets | E27: TRUE | F27: 24327 | G27: DERIVED | I27: FY - H1 (fact sheet S025)
A28: 2024-H1 | B28: model | C28: 718 | D28: 718 Boxster/Cayman | E28: TRUE | F28: 11886 | G28: FACT | H28: S025 | I28: 04 - Sales_deliveries by Model S33
A29: 2024-H1 | B29: model | C29: 911 | D29: 911 | E29: TRUE | F29: 28212 | G29: FACT | H29: S025 | I29: 04 - Sales_deliveries by Model S32
A30: 2024-H1 | B30: model | C30: CAY | D30: Cayenne | E30: TRUE | F30: 54587 | G30: FACT | H30: S025 | I30: 04 - Sales_deliveries by Model S34
A31: 2024-H1 | B31: model | C31: MAC | D31: Macan (total) | E31: TRUE | F31: 39167 | G31: FACT | H31: S025 | I31: 04 - Sales_deliveries by Model S36
A32: 2024-H1 | B32: model | C32: PAN | D32: Panamera | E32: TRUE | F32: 13255 | G32: FACT | H32: S025 | I32: 04 - Sales_deliveries by Model S35
A33: 2024-H1 | B33: model | C33: TAY | D33: Taycan | E33: TRUE | F33: 8838 | G33: FACT | H33: S025 | I33: 04 - Sales_deliveries by Model S39
A34: 2024-H1 | B34: region | C34: CN | D34: China | E34: TRUE | F34: 29551 | G34: FACT | H34: S025 | I34: 03 - Sales_deliveries by Region S31
A35: 2024-H1 | B35: region | C35: DE | D35: Germany | E35: TRUE | F35: 20811 | G35: FACT | H35: S025 | I35: 03 - Sales_deliveries by Region S29
A36: 2024-H1 | B36: region | C36: EU | D36: Europe excl. Germany | E36: TRUE | F36: 38611 | G36: FACT | H36: S025 | I36: 03 - Sales_deliveries by Region S32
A37: 2024-H1 | B37: region | C37: NA | D37: North America | E37: TRUE | F37: 39558 | G37: FACT | H37: S025 | I37: 03 - Sales_deliveries by Region S30
A38: 2024-H1 | B38: region | C38: OEM | D38: Overseas & Emerging Markets | E38: TRUE | F38: 27414 | G38: FACT | H38: S025 | I38: 03 - Sales_deliveries by Region S33
A39: 2024-H2 | B39: model | C39: 718 | D39: 718 Boxster/Cayman | E39: TRUE | F39: 11784 | G39: DERIVED | I39: FY - H1 (fact sheet S025)
A40: 2024-H2 | B40: model | C40: 911 | D40: 911 | E40: TRUE | F40: 22729 | G40: DERIVED | I40: FY - H1 (fact sheet S025)
A41: 2024-H2 | B41: model | C41: CAY | D41: Cayenne | E41: TRUE | F41: 48302 | G41: DERIVED | I41: FY - H1 (fact sheet S025)
A42: 2024-H2 | B42: model | C42: MAC | D42: Macan (total) | E42: TRUE | F42: 43628 | G42: DERIVED | I42: FY - H1 (fact sheet S025)
A43: 2024-H2 | B43: model | C43: PAN | D43: Panamera | E43: TRUE | F43: 16332 | G43: DERIVED | I43: FY - H1 (fact sheet S025)
A44: 2024-H2 | B44: model | C44: TAY | D44: Taycan | E44: TRUE | F44: 11998 | G44: DERIVED | I44: FY - H1 (fact sheet S025)
A45: 2024-H2 | B45: region | C45: CN | D45: China | E45: TRUE | F45: 27336 | G45: DERIVED | I45: FY - H1 (fact sheet S025)
A46: 2024-H2 | B46: region | C46: DE | D46: Germany | E46: TRUE | F46: 15047 | G46: DERIVED | I46: FY - H1 (fact sheet S025)
A47: 2024-H2 | B47: region | C47: EU | D47: Europe excl. Germany | E47: TRUE | F47: 37288 | G47: DERIVED | I47: FY - H1 (fact sheet S025)
A48: 2024-H2 | B48: region | C48: NA | D48: North America | E48: TRUE | F48: 46983 | G48: DERIVED | I48: FY - H1 (fact sheet S025)
A49: 2024-H2 | B49: region | C49: OEM | D49: Overseas & Emerging Markets | E49: TRUE | F49: 28119 | G49: DERIVED | I49: FY - H1 (fact sheet S025)
A50: 2025-H1 | B50: model | C50: 718 | D50: 718 Boxster/Cayman | E50: TRUE | F50: 10496 | G50: FACT | H50: S025 | I50: 04 - Sales_deliveries by Model K33
A51: 2025-H1 | B51: model | C51: 911 | D51: 911 | E51: TRUE | F51: 25608 | G51: FACT | H51: S025 | I51: 04 - Sales_deliveries by Model K32
A52: 2025-H1 | B52: model | C52: CAY | D52: Cayenne | E52: TRUE | F52: 41873 | G52: FACT | H52: S025 | I52: 04 - Sales_deliveries by Model K34
A53: 2025-H1 | B53: model | C53: MAC | D53: Macan (total) | E53: TRUE | F53: 45137 | G53: FACT | H53: S025 | I53: 04 - Sales_deliveries by Model K36
A54: 2025-H1 | B54: model | C54: MAC_BEV | D54: Macan BEV | E54: FALSE | F54: 25884 | G54: FACT | H54: S025 | I54: 04 - Sales_deliveries by Model K38
A55: 2025-H1 | B55: model | C55: MAC_ICE | D55: Macan ICE | E55: FALSE | F55: 19253 | G55: FACT | H55: S025 | I55: 04 - Sales_deliveries by Model K37
A56: 2025-H1 | B56: model | C56: PAN | D56: Panamera | E56: TRUE | F56: 14975 | G56: FACT | H56: S025 | I56: 04 - Sales_deliveries by Model K35
A57: 2025-H1 | B57: model | C57: TAY | D57: Taycan | E57: TRUE | F57: 8302 | G57: FACT | H57: S025 | I57: 04 - Sales_deliveries by Model K39
A58: 2025-H1 | B58: region | C58: CN | D58: China | E58: TRUE | F58: 21302 | G58: FACT | H58: S025 | I58: 03 - Sales_deliveries by Region K31
A59: 2025-H1 | B59: region | C59: DE | D59: Germany | E59: TRUE | F59: 15973 | G59: FACT | H59: S025 | I59: 03 - Sales_deliveries by Region K29
A60: 2025-H1 | B60: region | C60: EU | D60: Europe excl. Germany | E60: TRUE | F60: 35381 | G60: FACT | H60: S025 | I60: 03 - Sales_deliveries by Region K32
A61: 2025-H1 | B61: region | C61: NA | D61: North America | E61: TRUE | F61: 43577 | G61: FACT | H61: S025 | I61: 03 - Sales_deliveries by Region K30
A62: 2025-H1 | B62: region | C62: OEM | D62: Overseas & Emerging Markets | E62: TRUE | F62: 30158 | G62: FACT | H62: S025 | I62: 03 - Sales_deliveries by Region K33
A63: 2025-H2 | B63: model | C63: 718 | D63: 718 Boxster/Cayman | E63: TRUE | F63: 8116 | G63: DERIVED | I63: FY - H1 (fact sheet S025)
A64: 2025-H2 | B64: model | C64: 911 | D64: 911 | E64: TRUE | F64: 25975 | G64: DERIVED | I64: FY - H1 (fact sheet S025)
A65: 2025-H2 | B65: model | C65: CAY | D65: Cayenne | E65: TRUE | F65: 39013 | G65: DERIVED | I65: FY - H1 (fact sheet S025)
A66: 2025-H2 | B66: model | C66: MAC | D66: Macan (total) | E66: TRUE | F66: 39191 | G66: DERIVED | I66: FY - H1 (fact sheet S025)
A67: 2025-H2 | B67: model | C67: MAC_BEV | D67: Macan BEV | E67: FALSE | F67: 19483 | G67: DERIVED | I67: FY - H1 (fact sheet S025)
A68: 2025-H2 | B68: model | C68: MAC_ICE | D68: Macan ICE | E68: FALSE | F68: 19708 | G68: DERIVED | I68: FY - H1 (fact sheet S025)
A69: 2025-H2 | B69: model | C69: PAN | D69: Panamera | E69: TRUE | F69: 12726 | G69: DERIVED | I69: FY - H1 (fact sheet S025)
A70: 2025-H2 | B70: model | C70: TAY | D70: Taycan | E70: TRUE | F70: 8037 | G70: DERIVED | I70: FY - H1 (fact sheet S025)
A71: 2025-H2 | B71: region | C71: CN | D71: China | E71: TRUE | F71: 20636 | G71: DERIVED | I71: FY - H1 (fact sheet S025)
A72: 2025-H2 | B72: region | C72: DE | D72: Germany | E72: TRUE | F72: 13995 | G72: DERIVED | I72: FY - H1 (fact sheet S025)
A73: 2025-H2 | B73: region | C73: EU | D73: Europe excl. Germany | E73: TRUE | F73: 30959 | G73: DERIVED | I73: FY - H1 (fact sheet S025)
A74: 2025-H2 | B74: region | C74: NA | D74: North America | E74: TRUE | F74: 42652 | G74: DERIVED | I74: FY - H1 (fact sheet S025)
A75: 2025-H2 | B75: region | C75: OEM | D75: Overseas & Emerging Markets | E75: TRUE | F75: 24816 | G75: DERIVED | I75: FY - H1 (fact sheet S025)
A76: 2026-H1 | B76: model | C76: 718 | D76: 718 Boxster/Cayman | E76: TRUE | F76: 2789 | G76: FACT | H76: S025 | I76: 04 - Sales_deliveries by Model C33
A77: 2026-H1 | B77: model | C77: 911 | D77: 911 | E77: TRUE | F77: 30534 | G77: FACT | H77: S025 | I77: 04 - Sales_deliveries by Model C32
A78: 2026-H1 | B78: model | C78: CAY | D78: Cayenne | E78: TRUE | F78: 38141 | G78: FACT | H78: S025 | I78: 04 - Sales_deliveries by Model C34
A79: 2026-H1 | B79: model | C79: MAC | D79: Macan (total) | E79: TRUE | F79: 35315 | G79: FACT | H79: S025 | I79: 04 - Sales_deliveries by Model C36
A80: 2026-H1 | B80: model | C80: MAC_BEV | D80: Macan BEV | E80: FALSE | F80: 15620 | G80: FACT | H80: S025 | I80: 04 - Sales_deliveries by Model C38
A81: 2026-H1 | B81: model | C81: MAC_ICE | D81: Macan ICE | E81: FALSE | F81: 19695 | G81: FACT | H81: S025 | I81: 04 - Sales_deliveries by Model C37
A82: 2026-H1 | B82: model | C82: PAN | D82: Panamera | E82: TRUE | F82: 9308 | G82: FACT | H82: S025 | I82: 04 - Sales_deliveries by Model C35
A83: 2026-H1 | B83: model | C83: TAY | D83: Taycan | E83: TRUE | F83: 6219 | G83: FACT | H83: S025 | I83: 04 - Sales_deliveries by Model C39
A84: 2026-H1 | B84: region | C84: CN | D84: China | E84: TRUE | F84: 14501 | G84: FACT | H84: S025 | I84: 03 - Sales_deliveries by Region C31
A85: 2026-H1 | B85: region | C85: DE | D85: Germany | E85: TRUE | F85: 14938 | G85: FACT | H85: S025 | I85: 03 - Sales_deliveries by Region C29
A86: 2026-H1 | B86: region | C86: EU | D86: Europe excl. Germany | E86: TRUE | F86: 30278 | G86: FACT | H86: S025 | I86: 03 - Sales_deliveries by Region C32
A87: 2026-H1 | B87: region | C87: NA | D87: North America | E87: TRUE | F87: 37712 | G87: FACT | H87: S025 | I87: 03 - Sales_deliveries by Region C30
A88: 2026-H1 | B88: region | C88: OEM | D88: Overseas & Emerging Markets | E88: TRUE | F88: 24877 | G88: FACT | H88: S025 | I88: 03 - Sales_deliveries by Region C33

Sheet SQL_Outputs
A1: SQL_Outputs - mart view results imported for reconciliation only
A2: Blue = value exported from the PostgreSQL mart views after Phase 4 cleanup. The analysis sheets do NOT use these values; Audit_Checks compares them with the Excel formulas.
B5: mart column | C5: unit | D5: 2023-H1 | E5: 2023-H2 | F5: 2024-H1 | G5: 2024-H2 | H5: 2025-H1 | I5: 2025-H2 | J5: 2026-H1 | K5: mart view
B6: ebit_l0_reported | C6: EUR m | D6: 3852.2352 | E6: 3432.0724 | F6: 3061.4555 | G6: 2575.4372 | H6: 1006.7913 | I6: -593.50733 | J6: 1348.185 | K6: mart.v_ebit_adjusted
B7: ebit_l1_ex_realignment | C7: EUR m | D7: 3852.2352 | E7: 3432.0724 | F7: 3061.4555 | G7: 2575.4372 | H7: 1706.7913 | I7: 1806.4927 | J7: 1448.185 | K7: mart.v_ebit_adjusted
B8: ebit_l2_ex_realignment_tariffs | C8: EUR m | D8: 3852.2352 | E8: 3432.0724 | F8: 3061.4555 | G8: 2575.4372 | H8: 2106.7913 | I8: 2106.4927 | J8: 1848.185 | K8: mart.v_ebit_adjusted
B9: ebit_l3_hybrid_sensitivity | C9: EUR m | D9: 3827.2352 | E9: 4030.0724 | F9: 3302.4555 | G9: 3733.4372 | H9: 2592.7913 | I9: 2954.4927 | J9: 2459.185 | K9: mart.v_ebit_adjusted
B10: margin_l0_reported_pct | C10: % x100 | D10: 18.85 | E10: 17.08 | F10: 15.73 | G10: 12.49 | H10: 5.54 | I10: -3.28 | J10: 7.82 | K10: mart.v_ebit_adjusted
B11: margin_l1_pct | C11: % x100 | D11: 18.85 | E11: 17.08 | F11: 15.73 | G11: 12.49 | H11: 9.4 | I11: 9.97 | J11: 8.41 | K11: mart.v_ebit_adjusted
B12: margin_l2_pct | C12: % x100 | D12: 18.85 | E12: 17.08 | F12: 15.73 | G12: 12.49 | H12: 11.6 | I12: 11.63 | J12: 10.73 | K12: mart.v_ebit_adjusted
B13: margin_l3_hybrid_pct | C13: % x100 | D13: 18.73 | E13: 20.05 | F13: 16.97 | G13: 18.1 | H13: 14.28 | I13: 16.31 | J13: 14.27 | K13: mart.v_ebit_adjusted
B14: da_clean | C14: EUR m | D14: 1176 | E14: 1478 | F14: 1364 | G14: 1618 | H14: 1461 | I14: 1536 | J14: 1498 | K14: mart.v_da_clean
B15: rd_pl_charge | C15: EUR m | D15: 770 | E15: 943 | F15: 1057 | G15: 989 | H15: 1290 | I15: 1869 | J15: 1334 | K15: mart.v_rd_capitalisation
B16: ebit_effect_of_cap_rate_change | C16: EUR m | F16: 170.3 | G16: 130.2 | H16: 278.5 | I16: 158.9 | J16: 20.7 | K16: mart.v_rd_capitalisation
B17: asp_calc_eur_k | C17: EUR k | D17: 110.61 | E17: 113.37 | F17: 116.46 | G17: 116.65 | H17: 119.42 | I17: 122.95 | J17: 125.78 | K17: mart.v_asp_volume
B18: volume_effect | C18: EUR m | F18: -2085.8 | G18: -241.1 | H18: -1956.7 | I18: -3517.6 | J18: -1747.5 | K18: mart.v_asp_volume
B19: asp_effect | C19: EUR m | F19: 888.8 | G19: 527.1 | H19: 399.7 | I19: 821.6 | J19: 767.5 | K19: mart.v_asp_volume
B20: ncf_margin_pct | C20: % x100 | D20: 11.74 | E20: 9.52 | F20: 6.31 | G20: 13.97 | H20: 2.44 | I20: 6.96 | J20: 6.73 | K20: mart.v_cash_crosscheck
B21: simple_cash_proxy | C21: EUR m | D21: 2762 | E21: 2787 | F21: 2295 | G21: 2274 | H21: 1048 | I21: 134 | J21: 1374 | K21: mart.v_cash_crosscheck
B22: eff_residual_other_drivers | C22: EUR m | F22: -479.77976 | G22: -317.63522 | H22: -325.66415 | I22: -443.94452 | J22: -139.60625 | K22: mart.v_ebit_bridge_yoy
B23: pp_residual_other_drivers | C23: pp | F23: -2.466 | G23: -1.54 | H23: -1.794 | I23: -2.451 | J23: -0.81 | K23: mart.v_ebit_bridge_yoy
B26: mart.v_guidance_2026_summary (scenario combinations; % x100)
B27: h2_rev_min | D27: 17770.544
B28: h2_rev_max | D28: 18770.544
B29: h2_ebit_l0_min | D29: 576.81495
B30: h2_ebit_l0_max | D30: 1351.815
B31: h2_margin_l0_min | D31: 3.25
B32: h2_margin_l0_max | D32: 7.2
B33: h2_margin_l0_mid | D33: 5.25
B34: h2_margin_l1_min | D34: 7.1
B35: h2_margin_l1_max | D35: 11.69
B36: h2_margin_l1_mid | D36: 9.36
B37: h2_margin_l2_min | D37: 9.23
B38: h2_margin_l2_max | D38: 13.94
... B43: h2_2025_margin_l1 | D43: 9.97
B45: mart.v_guidance_2026 (27 scenario combinations; % x100)
B46: scenario_id | D46: h2_margin_l0 | E46: h2_margin_l1 | F46: h2_margin_l2
B47: high/high/high | D47: 7.2 | E47: 11.46 | F47: 13.59
B48: high/high/low | D48: 7.2 | E48: 10.93 | F48: 13.06
B49: high/high/mid | D49: 7.2 | E49: 11.2 | F49: 13.33
B50: high/low/high | D50: 3.37 | E50: 7.63 | F50: 9.76
B51: high/low/low | D51: 3.37 | E51: 7.1 | F51: 9.23
B52: high/low/mid | D52: 3.37 | E52: 7.36 | F52: 9.49
B53: high/mid/high | D53: 5.28 | E53: 9.55 | F53: 11.68
B54: high/mid/low | D54: 5.28 | E54: 9.01 | F54: 11.14
B55: high/mid/mid | D55: 5.28 | E55: 9.28 | F55: 11.41
B56: low/high/high | D56: 7.19 | E56: 11.69 | F56: 13.94
B57: low/high/low | D57: 7.19 | E57: 11.12 | F57: 13.38
B58: low/high/mid | D58: 7.19 | E58: 11.41 | F58: 13.66
... B73: mid/mid/mid | D73: 5.25 | E73: 9.36 | F73: 11.54
B75: mart.v_guidance_2026_auto (9 scenario combinations; % x100)
B76: scenario_id | D76: h2_auto_ebitda_margin | E76: h2_auto_ncf_margin
B77: high/high | D77: 15.85 | E77: 3.41
B78: high/low | D78: 12.01 | E78: -0.42
B79: high/mid | D79: 13.93 | E79: 1.49
B80: low/high | D80: 15.78 | E80: 3.32
B81: low/low | D81: 11.84 | E81: -0.62
B82: low/mid | D82: 13.81 | E82: 1.35
B83: mid/high | D83: 15.82 | E83: 3.37
B84: mid/low | D84: 11.93 | E84: -0.52
B85: mid/mid | D85: 13.87 | E85: 1.42

Sheet KPI_Overview
A1: KPI Overview - Porsche 2026 margin recovery
A2: Half-year view, group and automotive. All values are formulas linked to the analysis sheets (green = link).
A3: Question: Porsche's reported margin rose from 5.5% to 7.8% in H1 2026. After removing the exceptional items Porsche discloses, and isolating non-cash effects, is underlying profitability improving - and what does H2 2026 guidance imply?
B5: KPI | C5: unit | D5: =Data_Panel!D$5 -> 2023-H1 | E5: =Data_Panel!E$5 -> 2023-H2 | F5: =Data_Panel!F$5 -> 2024-H1 | G5: =Data_Panel!G$5 -> 2024-H2 | H5: =Data_Panel!H$5 -> 2025-H1 | I5: =Data_Panel!I$5 -> 2025-H2 | J5: =Data_Panel!J$5 -> 2026-H1 | L5: H1 2025 | M5: H1 2026 | N5: change | O5: definition / lineage
B6: Group sales revenue | C6: EUR m | D6: =EBIT_Analysis!D7 -> 20430.923 | E6: =EBIT_Analysis!E7 -> 20098.71 | F6: =EBIT_Analysis!F7 -> 19457.009 | G6: =EBIT_Analysis!G7 -> 20626.284 | H6: =EBIT_Analysis!H7 -> 18157.275 | I6: =EBIT_Analysis!I7 -> 18114.353 | J6: =EBIT_Analysis!J7 -> 17229.456 | L6: =H6 -> 18157.275 | M6: =J6 -> 17229.456 | N6: =M6-L6 -> -927.81945 | O6: Group, fact sheet S025
B7: L0 Reported EBIT | C7: EUR m | D7: =EBIT_Analysis!D8 -> 3852.2352 | E7: =EBIT_Analysis!E8 -> 3432.0724 | F7: =EBIT_Analysis!F8 -> 3061.4555 | G7: =EBIT_Analysis!G8 -> 2575.4372 | H7: =EBIT_Analysis!H8 -> 1006.7913 | I7: =EBIT_Analysis!I8 -> -593.50733 | J7: =EBIT_Analysis!J8 -> 1348.185 | L7: =H7 -> 1006.7913 | M7: =J7 -> 1348.185 | N7: =M7-L7 -> 341.39375 | O7: Group operating profit
B8: L0 Reported margin | C8: % | D8: =EBIT_Analysis!D9 -> 0.18854925 | E8: =EBIT_Analysis!E9 -> 0.17076083 | F8: =EBIT_Analysis!F9 -> 0.15734461 | G8: =EBIT_Analysis!G9 -> 0.12486191 | H8: =EBIT_Analysis!H9 -> 0.05544837 | I8: =EBIT_Analysis!I9 -> -0.032764479 | J8: =EBIT_Analysis!J9 -> 0.078248848 | L8: =H8 -> 0.05544837 | M8: =J8 -> 0.078248848 | N8: =(M8-L8)*100 -> 2.2800478 | O8: EBIT / revenue
B9: L1 EBIT excl. realignment & battery | C9: EUR m | D9: =EBIT_Analysis!D19 -> 3852.2352 | E9: =EBIT_Analysis!E19 -> 3432.0724 | F9: =EBIT_Analysis!F19 -> 3061.4555 | G9: =EBIT_Analysis!G19 -> 2575.4372 | H9: =EBIT_Analysis!H19 -> 1706.7913 | I9: =EBIT_Analysis!I19 -> 1806.4927 | J9: =EBIT_Analysis!J19 -> 1448.185 | L9: =H9 -> 1706.7913 | M9: =J9 -> 1448.185 | N9: =M9-L9 -> -258.60625 | O9: Headline adjusted level
B10: L1 margin | C10: % | D10: =EBIT_Analysis!D20 -> 0.18854925 | E10: =EBIT_Analysis!E20 -> 0.17076083 | F10: =EBIT_Analysis!F20 -> 0.15734461 | G10: =EBIT_Analysis!G20 -> 0.12486191 | H10: =EBIT_Analysis!H20 -> 0.09400041 | I10: =EBIT_Analysis!I20 -> 0.099727143 | J10: =EBIT_Analysis!J20 -> 0.084052862 | L10: =H10 -> 0.09400041 | M10: =J10 -> 0.084052862 | N10: =(M10-L10)*100 -> -0.99475482 | O10: Headline adjusted level
B11: L2 EBIT excl. realignment, battery & tariffs | C11: EUR m | D11: =EBIT_Analysis!D21 -> 3852.2352 | E11: =EBIT_Analysis!E21 -> 3432.0724 | F11: =EBIT_Analysis!F21 -> 3061.4555 | G11: =EBIT_Analysis!G21 -> 2575.4372 | H11: =EBIT_Analysis!H21 -> 2106.7913 | I11: =EBIT_Analysis!I21 -> 2106.4927 | J11: =EBIT_Analysis!J21 -> 1848.185 | L11: =H11 -> 2106.7913 | M11: =J11 -> 1848.185 | N11: =M11-L11 -> -258.60625 | O11: Headline adjusted level
B12: L2 margin | C12: % | D12: =EBIT_Analysis!D22 -> 0.18854925 | E12: =EBIT_Analysis!E22 -> 0.17076083 | F12: =EBIT_Analysis!F22 -> 0.15734461 | G12: =EBIT_Analysis!G22 -> 0.12486191 | H12: =EBIT_Analysis!H22 -> 0.11603015 | I12: =EBIT_Analysis!I22 -> 0.1162886 | J12: =EBIT_Analysis!J22 -> 0.10726892 | L12: =H12 -> 0.11603015 | M12: =J12 -> 0.10726892 | N12: =(M12-L12)*100 -> -0.87612298 | O12: Headline adjusted level
B13: Automotive revenue | C13: EUR m | D13: =Commercial!D7 -> 18892 | E13: =Commercial!E7 -> 18457 | F13: =Commercial!F7 -> 17695 | G13: =Commercial!G7 -> 18743 | H13: =Commercial!H7 -> 16138 | I13: =Commercial!I7 -> 16047 | J13: =Commercial!J7 -> 15158 | L13: =H13 -> 16138 | M13: =J13 -> 15158 | N13: =M13-L13 -> -980 | O13: Automotive segment
B14: Vehicle sales (wholesale) | C14: units | D14: =Commercial!D8 -> 170802 | E14: =Commercial!E8 -> 162803 | F14: =Commercial!F8 -> 151944 | G14: =Commercial!G8 -> 160676 | H14: =Commercial!H8 -> 135142 | I14: =Commercial!I8 -> 130521 | J14: =Commercial!J8 -> 120508 | L14: =H14 -> 135142 | M14: =J14 -> 120508 | N14: =M14/L14-1 -> -0.1082861 | O14: Fact sheet S025
B15: ASP (automotive revenue per vehicle sold) | C15: EUR k | D15: =Commercial!D11 -> 110.6076 | E15: =Commercial!E11 -> 113.37015 | F15: =Commercial!F11 -> 116.45738 | G15: =Commercial!G11 -> 116.6509 | H15: =Commercial!H11 -> 119.41513 | I15: =Commercial!I11 -> 122.94573 | J15: =Commercial!J11 -> 125.78418 | L15: =H15 -> 119.41513 | M15: =J15 -> 125.78418 | N15: =M15/L15-1 -> 0.053335339 | O15: Porsche ASP definition
B16: Deliveries (retail) | C16: units | D16: =Commercial!D9 -> 167354 | E16: =Commercial!E9 -> 152867 | F16: =Commercial!F9 -> 155945 | G16: =Commercial!G9 -> 154773 | H16: =Commercial!H9 -> 146391 | I16: =Commercial!I9 -> 133058 | J16: =Commercial!J9 -> 122306 | L16: =H16 -> 146391 | M16: =J16 -> 122306 | N16: =M16/L16-1 -> -0.16452514 | O16: Fact sheet S025
B17: Automotive net cash flow | C17: EUR m | D17: =Cash_Crosscheck!D12 -> 2216.9809 | E17: =Cash_Crosscheck!E12 -> 1756.4485 | F17: =Cash_Crosscheck!F12 -> 1117 | G17: =Cash_Crosscheck!G12 -> 2617.6258 | H17: =Cash_Crosscheck!H12 -> 393.99427 | I17: =Cash_Crosscheck!I12 -> 1117.1216 | J17: =Cash_Crosscheck!J12 -> 1020.2448 | L17: =H17 -> 393.99427 | M17: =J17 -> 1020.2448 | N17: =M17-L17 -> 626.25054 | O17: Fact sheet S025
B18: Net cash flow margin | C18: % | D18: =Cash_Crosscheck!D16 -> 0.11735025 | E18: =Cash_Crosscheck!E16 -> 0.095164355 | F18: =Cash_Crosscheck!F16 -> 0.063125177 | G18: =Cash_Crosscheck!G16 -> 0.13965885 | H18: =Cash_Crosscheck!H16 -> 0.024414071 | I18: =Cash_Crosscheck!I16 -> 0.069615604 | J18: =Cash_Crosscheck!J16 -> 0.06730735 | L18: =H18 -> 0.024414071 | M18: =J18 -> 0.06730735 | N18: =(M18-L18)*100 -> 4.289328 | O18: NCF / automotive revenue
B19: L3 (supplementary hybrid sensitivity) is deliberately not shown here; see EBIT_Analysis section E.
A21: Formula-driven readings (descriptive; interpretation follows in Phase 6)
B22: ="1. Reported margin: "&TEXT(EBIT_Analysis!H9,"0.0%")&" (H1 2025) -> "&TEXT(EBIT_Analysis!J9,"0.0%")&" (H1 2026), "&TEXT(EBIT_Analysis!J26,"+0.0;-0.0")&" pp; reported EBIT "&TEXT(EBIT_Analysis!J25,"+#,##0;-#,##0")&" EUR m." -> 1. Reported margin: 5.5% (H1 2025) -> 7.8% (H1 2026), +2.3 pp; reported EBIT +341 EUR m.
B23: ="2. Excluding disclosed realignment & battery items (L1): "&TEXT(EBIT_Analysis!H20,"0.0%")&" -> "&TEXT(EBIT_Analysis!J20,"0.0%")&" ("&TEXT(EBIT_Analysis!J28,"+0.0;-0.0")&" pp); L1 EBIT "&TEXT(EBIT_Analysis!J27,"+#,##0;-#,##0")&" EUR m." -> 2. Excluding disclosed realignment & battery items (L1): 9.4% -> 8.4% (-1.0 pp); L1 EBIT -259 EUR m.
B24: ="3. Also excluding US tariffs (L2): "&TEXT(EBIT_Analysis!H22,"0.0%")&" -> "&TEXT(EBIT_Analysis!J22,"0.0%")&" ("&TEXT(EBIT_Analysis!J30,"+0.0;-0.0")&" pp)." -> 3. Also excluding US tariffs (L2): 11.6% -> 10.7% (-0.9 pp).
B25: ="4. Of the "&TEXT(EBIT_Analysis!J40,"+#,##0;-#,##0")&" EUR m change in reported EBIT, lower exceptional items contributed "&TEXT(EBIT_Analysis!J41,"+#,##0;-#,##0")&" EUR m; residual / other EBIT drivers "&TEXT(EBIT_Analysis!J46,"+#,##0;-#,##0")&" EUR m." -> 4. Of the +341 EUR m change in reported EBIT, lower exceptional items contributed +600 EUR m; residual / other EBIT drivers -140 EUR m.
B26: ="5. ASP "&TEXT(Commercial!J11,"0.0")&" EUR k ("&TEXT(Commercial!J18,"+0.0%;-0.0%")&"), vehicle sales "&TEXT(Commercial!J17,"+0.0%;-0.0%")&": volume effect "&TEXT(Commercial!J20,"+#,##0;-#,##0")&" vs ASP effect "&TEXT(Commercial!J21,"+#,##0;-#,##0")&" EUR m." -> 5. ASP 125.8 EUR k (+5.3%), vehicle sales -10.8%: volume effect -1,748 vs ASP effect +768 EUR m.
B27: ="6. Guidance scenario combinations (not forecasts) imply an H2 2026 reported margin of "&TEXT(Guidance_Scenarios!C79,"0.0%")&"-"&TEXT(Guidance_Scenarios!E79,"0.0%")&" (all midpoints "&TEXT(Guidance_Scenarios!D79,"0.0%")&") and an L1 margin of "&TEXT(Guidance_Scenarios!C80,"0.0%")&"-"&TEXT(Guidance_Scenarios!E80,"0.0%")&" (midpoints "&TEXT(Guidance_Scenarios!D80,"0.0%")&") vs "&TEXT(EBIT_Analysis!J20,"0.0%")&" in H1 2026." -> 6. Guidance scenario combinations (not forecasts) imply an H2 2026 reported margin of 3.2%-7.2% (all midpoints 5.3%) and an L1 margin of 7.1%-11.7% (midpoints 9.4%) vs 8.4% in H1 2026.
B28: ="Model status: "&IF(COUNTIF(Audit_Checks!$H$7:$H$56,"FAIL")=0,"ALL "&COUNTA(Audit_Checks!$H$7:$H$56)&" CHECKS PASS",COUNTIF(Audit_Checks!$H$7:$H$56,"FAIL")&" OF "&COUNTA(Audit_Checks!$H$7:$H$56)&" CHECK(S) FAIL - see Audit_Checks") -> Model status: ALL 50 CHECKS PASS
B31: H1 2026 vs H1 2025 EBIT bridge (EUR m) - chart data
B32: Exceptional items | D32: =EBIT_Analysis!J41 -> 600
B33: US tariffs | D33: =EBIT_Analysis!J42 -> 0
B34: Capitalised dev. costs | D34: =EBIT_Analysis!J43 -> -88
B35: Clean D&A | D35: =EBIT_Analysis!J44 -> -37
B36: Financial Services | D36: =EBIT_Analysis!J45 -> 6
B37: Residual / other drivers | D37: =EBIT_Analysis!J46 -> -139.60625
B38: Total change in EBIT | D38: =EBIT_Analysis!J40 -> 341.39375

Sheet EBIT_Analysis
A1: Profitability / EBIT Analysis - reported vs adjusted, and the year-on-year bridge
A2: Group level. Headline levels L0/L1/L2. L3 is a supplementary hybrid sensitivity only (section E).
A3: Business question: After removing Porsche's disclosed exceptional items, is group profitability improving - and what moved EBIT?
A5: ID | B5: Measure | C5: Unit | D5: =Data_Panel!D$5 -> 2023-H1 | E5: =Data_Panel!E$5 -> 2023-H2 | F5: =Data_Panel!F$5 -> 2024-H1 | G5: =Data_Panel!G$5 -> 2024-H2 | H5: =Data_Panel!H$5 -> 2025-H1 | I5: =Data_Panel!I$5 -> 2025-H2 | J5: =Data_Panel!J$5 -> 2026-H1 | K5: Formula / source lineage
A6: A. Reported group profitability
A7: E01 | B7: Group sales revenue | C7: EUR m | D7: =Data_Panel!D6 -> 20430.923 | E7: =Data_Panel!E6 -> 20098.71 | F7: =Data_Panel!F6 -> 19457.009 | G7: =Data_Panel!G6 -> 20626.284 | H7: =Data_Panel!H6 -> 18157.275 | I7: =Data_Panel!I6 -> 18114.353 | J7: =Data_Panel!J6 -> 17229.456 | K7: Data_Panel G01 <- S025 fact sheet
A8: E02 | B8: L0 Reported EBIT | C8: EUR m | D8: =Data_Panel!D12 -> 3852.2352 | E8: =Data_Panel!E12 -> 3432.0724 | F8: =Data_Panel!F12 -> 3061.4555 | G8: =Data_Panel!G12 -> 2575.4372 | H8: =Data_Panel!H12 -> 1006.7913 | I8: =Data_Panel!I12 -> -593.50733 | J8: =Data_Panel!J12 -> 1348.185 | K8: Data_Panel G07 <- S025 fact sheet
A9: E03 | B9: L0 Reported margin (return on sales) | C9: % | D9: =D8/D7 -> 0.18854925 | E9: =E8/E7 -> 0.17076083 | F9: =F8/F7 -> 0.15734461 | G9: =G8/G7 -> 0.12486191 | H9: =H8/H7 -> 0.05544837 | I9: =I8/I7 -> -0.032764479 | J9: =J8/J7 -> 0.078248848 | K9: E02 / E01
A10: E04 | B10: Published group return on sales (reference) | C10: % | F10: 0.157 | H10: 0.055 | J10: 0.078 | K10: Input: S009 slide 27 (H1 2024), S016 slide 5 (H1 2025, H1 2026). Used only by check C28.
A11: E05 | B11: Check: calculated - published margin | C11: pp | D11: =IF(D10="",0,(D9-D10)*100) -> 0 | E11: =IF(E10="",0,(E9-E10)*100) -> 0 | F11: =IF(F10="",0,(F9-F10)*100) -> 0.034461068 | G11: =IF(G10="",0,(G9-G10)*100) -> 0 | H11: =IF(H10="",0,(H9-H10)*100) -> 0.044836976 | I11: =IF(I10="",0,(I9-I10)*100) -> 0 | J11: =IF(J10="",0,(J9-J10)*100) -> 0.024884813 | K11: 0 where no published value
A12: B. Exceptional items disclosed by Porsche (EUR m, positive = expense)
A13: E06 | B13: Strategic realignment incl. battery (net), used | C13: EUR m | D13: =IF(Data_Panel!D31="",0,Data_Panel!D31) -> 0 | E13: =IF(Data_Panel!E31="",0,Data_Panel!E31) -> 0 | F13: =IF(Data_Panel!F31="",0,Data_Panel!F31) -> 0 | G13: =IF(Data_Panel!G31="",0,Data_Panel!G31) -> 0 | H13: =IF(Data_Panel!H31="",0,Data_Panel!H31) -> 700 | I13: =IF(Data_Panel!I31="",0,Data_Panel!I31) -> 2400 | J13: =IF(Data_Panel!J31="",0,Data_Panel!J31) -> 100 | K13: Data_Panel X01 (S016 p.6; S011 p.6 FY2025 = 2.4 + 0.7, DERIVED). Blank -> 0 (assumption A-01).
B14: status | D14: =IF(Data_Panel!D31="","A-01: none disclosed -> 0","disclosed") -> A-01: none disclosed -> 0 | E14: =IF(Data_Panel!E31="","A-01: none disclosed -> 0","disclosed") -> A-01: none disclosed -> 0 | F14: =IF(Data_Panel!F31="","A-01: none disclosed -> 0","disclosed") -> A-01: none disclosed -> 0 | G14: =IF(Data_Panel!G31="","A-01: none disclosed -> 0","disclosed") -> A-01: none disclosed -> 0 | H14: =IF(Data_Panel!H31="","A-01: none disclosed -> 0","disclosed") -> disclosed | I14: =IF(Data_Panel!I31="","A-01: none disclosed -> 0","disclosed") -> disclosed | J14: =IF(Data_Panel!J31="","A-01: none disclosed -> 0","disclosed") -> disclosed
A15: E07 | B15: US import tariffs, used | C15: EUR m | D15: =IF(Data_Panel!D33="",0,Data_Panel!D33) -> 0 | E15: =IF(Data_Panel!E33="",0,Data_Panel!E33) -> 0 | F15: =IF(Data_Panel!F33="",0,Data_Panel!F33) -> 0 | G15: =IF(Data_Panel!G33="",0,Data_Panel!G33) -> 0 | H15: =IF(Data_Panel!H33="",0,Data_Panel!H33) -> 400 | I15: =IF(Data_Panel!I33="",0,Data_Panel!I33) -> 300 | J15: =IF(Data_Panel!J33="",0,Data_Panel!J33) -> 400 | K15: Data_Panel X03 (S010 p.5; S011 p.6; S016 p.6). Blank -> 0 (assumption A-02).
B16: status | D16: =IF(Data_Panel!D33="","A-02: none before Apr 2025 -> 0","disclosed") -> A-02: none before Apr 2025 -> 0 | E16: =IF(Data_Panel!E33="","A-02: none before Apr 2025 -> 0","disclosed") -> A-02: none before Apr 2025 -> 0 | F16: =IF(Data_Panel!F33="","A-02: none before Apr 2025 -> 0","disclosed") -> A-02: none before Apr 2025 -> 0 | G16: =IF(Data_Panel!G33="","A-02: none before Apr 2025 -> 0","disclosed") -> A-02: none before Apr 2025 -> 0 | H16: =IF(Data_Panel!H33="","A-02: none before Apr 2025 -> 0","disclosed") -> disclosed | I16: =IF(Data_Panel!I33="","A-02: none before Apr 2025 -> 0","disclosed") -> disclosed | J16: =IF(Data_Panel!J33="","A-02: none before Apr 2025 -> 0","disclosed") -> disclosed
A17: Impairments (Data_Panel X05) are NOT added here: they are already inside the realignment/battery line. Adding them would double count.
A18: C. Adjusted EBIT - HEADLINE LEVELS
A19: E08 | B19: L1 EBIT excl. realignment & battery | C19: EUR m | D19: =D8+D13 -> 3852.2352 | E19: =E8+E13 -> 3432.0724 | F19: =F8+F13 -> 3061.4555 | G19: =G8+G13 -> 2575.4372 | H19: =H8+H13 -> 1706.7913 | I19: =I8+I13 -> 1806.4927 | J19: =J8+J13 -> 1448.185 | K19: E02 + E06
A20: E09 | B20: L1 margin | C20: % | D20: =D19/D7 -> 0.18854925 | E20: =E19/E7 -> 0.17076083 | F20: =F19/F7 -> 0.15734461 | G20: =G19/G7 -> 0.12486191 | H20: =H19/H7 -> 0.09400041 | I20: =I19/I7 -> 0.099727143 | J20: =J19/J7 -> 0.084052862 | K20: E08 / E01
A21: E10 | B21: L2 EBIT excl. realignment, battery & US tariffs | C21: EUR m | D21: =D19+D15 -> 3852.2352 | E21: =E19+E15 -> 3432.0724 | F21: =F19+F15 -> 3061.4555 | G21: =G19+G15 -> 2575.4372 | H21: =H19+H15 -> 2106.7913 | I21: =I19+I15 -> 2106.4927 | J21: =J19+J15 -> 1848.185 | K21: E08 + E07
A22: E11 | B22: L2 margin | C22: % | D22: =D21/D7 -> 0.18854925 | E22: =E21/E7 -> 0.17076083 | F22: =F21/F7 -> 0.15734461 | G22: =G21/G7 -> 0.12486191 | H22: =H21/H7 -> 0.11603015 | I22: =I21/I7 -> 0.1162886 | J22: =J21/J7 -> 0.10726892 | K22: E10 / E01
A23: E12 | B23: Rounding band of adjustments (+/-) | C23: EUR m | D23: =(IF(Data_Panel!D31="",0,50)+IF(Data_Panel!D33="",0,50))*IF(RIGHT(D$5,2)="H2",2,1) -> 0 | E23: =(IF(Data_Panel!E31="",0,50)+IF(Data_Panel!E33="",0,50))*IF(RIGHT(E$5,2)="H2",2,1) -> 0 | F23: =(IF(Data_Panel!F31="",0,50)+IF(Data_Panel!F33="",0,50))*IF(RIGHT(F$5,2)="H2",2,1) -> 0 | G23: =(IF(Data_Panel!G31="",0,50)+IF(Data_Panel!G33="",0,50))*IF(RIGHT(G$5,2)="H2",2,1) -> 0 | H23: =(IF(Data_Panel!H31="",0,50)+IF(Data_Panel!H33="",0,50))*IF(RIGHT(H$5,2)="H2",2,1) -> 100 | I23: =(IF(Data_Panel!I31="",0,50)+IF(Data_Panel!I33="",0,50))*IF(RIGHT(I$5,2)="H2",2,1) -> 200 | J23: =(IF(Data_Panel!J31="",0,50)+IF(Data_Panel!J33="",0,50))*IF(RIGHT(J$5,2)="H2",2,1) -> 100 | K23: One-offs printed to EUR 0.1bn -> +/-50m each; doubled for derived H2 (A-09)
A24: D. Year-on-year change (same half of prior year)
A25: E13 | B25: Change in L0 EBIT | C25: EUR m | F25: =F8-D8 -> -790.77976 | G25: =G8-E8 -> -856.63522 | H25: =H8-F8 -> -2054.6642 | I25: =I8-G8 -> -3168.9445 | J25: =J8-H8 -> 341.39375
A26: E14 | B26: Change in L0 margin | C26: pp | F26: =(F9-D9)*100 -> -3.1204644 | G26: =(G9-E9)*100 -> -4.5898925 | H26: =(H9-F9)*100 -> -10.189624 | I26: =(I9-G9)*100 -> -15.762639 | J26: =(J9-H9)*100 -> 2.2800478
A27: E15 | B27: Change in L1 EBIT | C27: EUR m | F27: =F19-D19 -> -790.77976 | G27: =G19-E19 -> -856.63522 | H27: =H19-F19 -> -1354.6642 | I27: =I19-G19 -> -768.94452 | J27: =J19-H19 -> -258.60625
A28: E16 | B28: Change in L1 margin | C28: pp | F28: =(F20-D20)*100 -> -3.1204644 | G28: =(G20-E20)*100 -> -4.5898925 | H28: =(H20-F20)*100 -> -6.33442 | I28: =(I20-G20)*100 -> -2.5134763 | J28: =(J20-H20)*100 -> -0.99475482
A29: E17 | B29: Change in L2 EBIT | C29: EUR m | F29: =F21-D21 -> -790.77976 | G29: =G21-E21 -> -856.63522 | H29: =H21-F21 -> -954.66416 | I29: =I21-G21 -> -468.94452 | J29: =J21-H21 -> -258.60625
A30: E18 | B30: Change in L2 margin | C30: pp | F30: =(F22-D22)*100 -> -3.1204644 | G30: =(G22-E22)*100 -> -4.5898925 | H30: =(H22-F22)*100 -> -4.1314463 | I30: =(I22-G22)*100 -> -0.85733104 | J30: =(J22-H22)*100 -> -0.87612298
A31: E. SUPPLEMENTARY HYBRID SENSITIVITY (L3) - not underlying group profitability; NOT a headline KPI
A32: L3 = L1 + clean automotive D&A - automotive capitalised development costs: an EBITDA-type figure in which total automotive R&D costs are expensed as incurred. It mixes group EBIT with automotive-only items, so it is shown only as a sensitivity.
A33: E19 | B33: Clean automotive D&A (from RD_DA) | C33: EUR m | D33: =RD_DA!D34 -> 1176 | E33: =RD_DA!E34 -> 1478 | F33: =RD_DA!F34 -> 1364 | G33: =RD_DA!G34 -> 1618 | H33: =RD_DA!H34 -> 1461 | I33: =RD_DA!I34 -> 1536 | J33: =RD_DA!J34 -> 1498
A34: E20 | B34: Capitalised development costs | C34: EUR m | D34: =Data_Panel!D18 -> 1201 | E34: =Data_Panel!E18 -> 880 | F34: =Data_Panel!F18 -> 1123 | G34: =Data_Panel!G18 -> 460 | H34: =Data_Panel!H18 -> 575 | I34: =Data_Panel!I18 -> 388 | J34: =Data_Panel!J18 -> 487
A35: E21 | B35: L3 hybrid sensitivity | C35: EUR m | D35: =D19+D33-D34 -> 3827.2352 | E35: =E19+E33-E34 -> 4030.0724 | F35: =F19+F33-F34 -> 3302.4555 | G35: =G19+G33-G34 -> 3733.4372 | H35: =H19+H33-H34 -> 2592.7913 | I35: =I19+I33-I34 -> 2954.4927 | J35: =J19+J33-J34 -> 2459.185 | K35: E08 + E19 - E20
A36: E22 | B36: L3 hybrid margin (sensitivity only) | C36: % | D36: =D35/D7 -> 0.18732562 | E36: =E35/E7 -> 0.20051399 | F36: =F35/F7 -> 0.16973089 | G36: =G35/G7 -> 0.18100387 | H36: =H35/H7 -> 0.14279628 | I36: =I35/I7 -> 0.1631023 | J36: =J35/J7 -> 0.14273144
A37: E23 | B37: L3 if H1 2026 impairments are not inside D&A (A-04 false) | C37: EUR m | J37: =J35+RD_DA!J32 -> 2520.185
A38: F. Own year-on-year EBIT bridge (EUR m)
A39: E24 | B39: EBIT same half prior year | C39: EUR m | F39: =D8 -> 3852.2352 | G39: =E8 -> 3432.0724 | H39: =F8 -> 3061.4555 | I39: =G8 -> 2575.4372 | J39: =H8 -> 1006.7913
A40: E25 | B40: Change in reported EBIT | C40: EUR m | F40: =F8-F39 -> -790.77976 | G40: =G8-G39 -> -856.63522 | H40: =H8-H39 -> -2054.6642 | I40: =I8-I39 -> -3168.9445 | J40: =J8-J39 -> 341.39375
A41: E26 | B41: Exceptional items (realignment/battery, net) | C41: EUR m | F41: =-(F13-D13) -> 0 | G41: =-(G13-E13) -> 0 | H41: =-(H13-F13) -> -700 | I41: =-(I13-G13) -> -2400 | J41: =-(J13-H13) -> 600 | K41: -(change in E06)
A42: E27 | B42: US import tariffs | C42: EUR m | F42: =-(F15-D15) -> 0 | G42: =-(G15-E15) -> 0 | H42: =-(H15-F15) -> -400 | I42: =-(I15-G15) -> -300 | J42: =-(J15-H15) -> 0 | K42: -(change in E07)
A43: E28 | B43: Capitalised development costs | C43: EUR m | F43: =Data_Panel!F18-Data_Panel!D18 -> -78 | G43: =Data_Panel!G18-Data_Panel!E18 -> -420 | H43: =Data_Panel!H18-Data_Panel!F18 -> -548 | I43: =Data_Panel!I18-Data_Panel!G18 -> -72 | J43: =Data_Panel!J18-Data_Panel!H18 -> -88 | K43: change in A06 (more capitalisation = less cost in P&L)
A44: E29 | B44: Clean automotive D&A | C44: EUR m | F44: =-(F33-D33) -> -188 | G44: =-(G33-E33) -> -140 | H44: =-(H33-F33) -> -97 | I44: =-(I33-G33) -> 82 | J44: =-(J33-H33) -> -37 | K44: -(change in clean D&A); impairments excluded (no double count)
A45: E30 | B45: Financial Services EBIT | C45: EUR m | F45: =Data_Panel!F30-Data_Panel!D30 -> -45 | G45: =Data_Panel!G30-Data_Panel!E30 -> 21 | H45: =Data_Panel!H30-Data_Panel!F30 -> 16 | I45: =Data_Panel!I30-Data_Panel!G30 -> -35 | J45: =Data_Panel!J30-Data_Panel!H30 -> 6 | K45: change in F02
A46: E31 | B46: Residual / other EBIT drivers (not separated) | C46: EUR m | F46: =F40-F41-F42-F43-F44-F45 -> -479.77976 | G46: =G40-G41-G42-G43-G44-G45 -> -317.63522 | H46: =H40-H41-H42-H43-H44-H45 -> -325.66415 | I46: =I40-I41-I42-I43-I44-I45 -> -443.94452 | J46: =J40-J41-J42-J43-J44-J45 -> -139.60625 | K46: E25 - E26..E30. NOT operating performance: mixes price, mix, volume, total R&D cost changes, material/supplier costs, SG&A, other operating result, FX, consolidation, one-off rounding
A47: E32 | B47: Residual if A-04 false (H1 2026 impairments not in D&A) | C47: EUR m | J47: =J40-J41-J42-J43-(J44-RD_DA!J32)-J45 -> -78.606248
A48: G. Same bridge in margin points (pp) - closes exactly
A49: E33 | B49: Change in reported margin | C49: pp | F49: =F26 -> -3.1204644 | G49: =G26 -> -4.5898925 | H49: =H26 -> -10.189624 | I49: =I26 -> -15.762639 | J49: =J26 -> 2.2800478
A50: E34 | B50: Revenue denominator effect | C50: pp | F50: =100*F39*(1/F7-1/D7) -> 0.94377679 | G50: =100*G39*(1/G7-1/E7) -> -0.43676828 | H50: =100*H39*(1/H7-1/F7) -> 1.1263039 | I50: =100*I39*(1/I7-1/G7) -> 1.7314698 | J50: =100*J39*(1/J7-1/H7) -> 0.29859374 | K50: prior EBIT x (1/rev_cur - 1/rev_prior)
A51: E35 | B51: Exceptional items | C51: pp | F51: =100*F41/F7 -> 0 | G51: =100*G41/G7 -> 0 | H51: =100*H41/H7 -> -3.855204 | I51: =100*I41/I7 -> -13.249162 | J51: =100*J41/J7 -> 3.4824084
A52: E36 | B52: US import tariffs | C52: pp | F52: =100*F42/F7 -> 0 | G52: =100*G42/G7 -> 0 | H52: =100*H42/H7 -> -2.2029737 | I52: =100*I42/I7 -> -1.6561453 | J52: =100*J42/J7 -> 0
A53: E37 | B53: Capitalised development costs | C53: pp | F53: =100*F43/F7 -> -0.40088382 | G53: =100*G43/G7 -> -2.0362368 | H53: =100*H43/H7 -> -3.018074 | I53: =100*I43/I7 -> -0.39747487 | J53: =100*J43/J7 -> -0.51075323
A54: E38 | B54: Clean automotive D&A | C54: pp | F54: =100*F44/F7 -> -0.9662328 | G54: =100*G44/G7 -> -0.67874561 | H54: =100*H44/H7 -> -0.53422113 | I54: =100*I44/I7 -> 0.45267971 | J54: =100*J44/J7 -> -0.21474852
A55: E39 | B55: Financial Services EBIT | C55: pp | F55: =100*F45/F7 -> -0.23127913 | G55: =100*G45/G7 -> 0.10181184 | H55: =100*H45/H7 -> 0.08811895 | I55: =100*I45/I7 -> -0.19321695 | J55: =100*J45/J7 -> 0.034824084
A56: E40 | B56: Residual / other EBIT drivers | C56: pp | F56: =100*F46/F7 -> -2.4658454 | G56: =100*G46/G7 -> -1.5399537 | H56: =100*H46/H7 -> -1.793574 | I56: =100*I46/I7 -> -2.4507887 | J56: =100*J46/J7 -> -0.81027661
A57: E41 | B57: Check: components - total (must be 0) | C57: pp | F57: =F50+F51+F52+F53+F54+F55+F56-F49 -> 0 | G57: =G50+G51+G52+G53+G54+G55+G56-G49 -> 0 | H57: =H50+H51+H52+H53+H54+H55+H56-H49 -> 0 | I57: =I50+I51+I52+I53+I54+I55+I56-I49 -> 0 | J57: =J50+J51+J52+J53+J54+J55+J56-J49 -> 0
A58: H. Porsche's own bridge buckets (reconciliation of the total)
A59: E42 | B59: Gross margin without R&D | C59: EUR m | D59: =IF(Data_Panel!D36="","",Data_Panel!D36) | E59: =IF(Data_Panel!E36="","",Data_Panel!E36) | F59: =IF(Data_Panel!F36="","",Data_Panel!F36) -> -460 | G59: =IF(Data_Panel!G36="","",Data_Panel!G36) -> -540 | H59: =IF(Data_Panel!H36="","",Data_Panel!H36) -> -1620 | I59: =IF(Data_Panel!I36="","",Data_Panel!I36) -> -2550 | J59: =IF(Data_Panel!J36="","",Data_Panel!J36) -> 150 | K59: Data_Panel B01 (decks S005/S007/S009/S011/S016; H2 = FY - H1)
A60: E43 | B60: R&D | C60: EUR m | D60: =IF(Data_Panel!D37="","",Data_Panel!D37) | E60: =IF(Data_Panel!E37="","",Data_Panel!E37) | F60: =IF(Data_Panel!F37="","",Data_Panel!F37) -> -240 | G60: =IF(Data_Panel!G37="","",Data_Panel!G37) -> -60 | H60: =IF(Data_Panel!H37="","",Data_Panel!H37) -> -220 | I60: =IF(Data_Panel!I37="","",Data_Panel!I37) -> -890 | J60: =IF(Data_Panel!J37="","",Data_Panel!J37) -> -50
A61: E44 | B61: SG&A | C61: EUR m | D61: =IF(Data_Panel!D38="","",Data_Panel!D38) | E61: =IF(Data_Panel!E38="","",Data_Panel!E38) | F61: =IF(Data_Panel!F38="","",Data_Panel!F38) -> -160 | G61: =IF(Data_Panel!G38="","",Data_Panel!G38) -> -140 | H61: =IF(Data_Panel!H38="","",Data_Panel!H38) -> 40 | I61: =IF(Data_Panel!I38="","",Data_Panel!I38) -> 220 | J61: =IF(Data_Panel!J38="","",Data_Panel!J38) -> 10
A62: E45 | B62: Other | C62: EUR m | D62: =IF(Data_Panel!D39="","",Data_Panel!D39) | E62: =IF(Data_Panel!E39="","",Data_Panel!E39) | F62: =IF(Data_Panel!F39="","",Data_Panel!F39) -> 80 | G62: =IF(Data_Panel!G39="","",Data_Panel!G39) -> -180 | H62: =IF(Data_Panel!H39="","",Data_Panel!H39) -> -260 | I62: =IF(Data_Panel!I39="","",Data_Panel!I39) -> 50 | J62: =IF(Data_Panel!J39="","",Data_Panel!J39) -> 230
A63: E46 | B63: Sum of Porsche buckets | C63: EUR m | D63: =IF(Data_Panel!D36="","",SUM(D59,D60,D61,D62)) | E63: =IF(Data_Panel!E36="","",SUM(E59,E60,E61,E62)) | F63: =IF(Data_Panel!F36="","",SUM(F59,F60,F61,F62)) -> -780 | G63: =IF(Data_Panel!G36="","",SUM(G59,G60,G61,G62)) -> -920 | H63: =IF(Data_Panel!H36="","",SUM(H59,H60,H61,H62)) -> -2060 | I63: =IF(Data_Panel!I36="","",SUM(I59,I60,I61,I62)) -> -3170 | J63: =IF(Data_Panel!J36="","",SUM(J59,J60,J61,J62)) -> 340
A64: E47 | B64: Own change in EBIT - Porsche buckets | C64: EUR m | F64: =IF(F63="",0,F40-F63) -> -10.779761 | G64: =IF(G63="",0,G40-G63) -> 63.36478 | H64: =IF(H63="",0,H40-H63) -> 5.335845 | I64: =IF(I63="",0,I40-I63) -> 1.055482 | J64: =IF(J63="",0,J40-J63) -> 1.393752
A65: E48 | B65: Tolerance (Porsche rounding) | C65: EUR m | D65: =IF(AND(RIGHT(D$5,2)="H2",VALUE(LEFT(D$5,4))<=2024),250,50) -> 50 | E65: =IF(AND(RIGHT(E$5,2)="H2",VALUE(LEFT(E$5,4))<=2024),250,50) -> 250 | F65: =IF(AND(RIGHT(F$5,2)="H2",VALUE(LEFT(F$5,4))<=2024),250,50) -> 50 | G65: =IF(AND(RIGHT(G$5,2)="H2",VALUE(LEFT(G$5,4))<=2024),250,50) -> 250 | H65: =IF(AND(RIGHT(H$5,2)="H2",VALUE(LEFT(H$5,4))<=2024),250,50) -> 50 | I65: =IF(AND(RIGHT(I$5,2)="H2",VALUE(LEFT(I$5,4))<=2024),250,50) -> 50 | J65: =IF(AND(RIGHT(J$5,2)="H2",VALUE(LEFT(J$5,4))<=2024),250,50) -> 50 | K65: H2 2024 derived from FY2024 buckets printed to EUR 0.1bn

Sheet RD_DA
A1: R&D & D&A Analysis - capitalisation, P&L charge and impairment treatment
A2: Automotive segment. Total R&D costs are Porsche's accounting definition (not cash).
A3: Business question: Are non-cash accounting effects (R&D capitalisation, depreciation, impairments) flattering or hurting EBIT?
A5: ID | B5: Measure | C5: Unit | D5: =Data_Panel!D$5 -> 2023-H1 | E5: =Data_Panel!E$5 -> 2023-H2 | F5: =Data_Panel!F$5 -> 2024-H1 | G5: =Data_Panel!G$5 -> 2024-H2 | H5: =Data_Panel!H$5 -> 2025-H1 | I5: =Data_Panel!I$5 -> 2025-H2 | J5: =Data_Panel!J$5 -> 2026-H1 | K5: Formula / source lineage
A6: A. Automotive R&D - total R&D costs (Porsche definition) vs R&D charged to the P&L
A7: Total R&D costs = research costs + non-capitalisable development costs + capitalisable development costs (Porsche definition). This is an accounting cost total, NOT a cash-flow figure.
A8: R01 | B8: Automotive sales revenue | C8: EUR m | D8: =Data_Panel!D13 -> 18892 | E8: =Data_Panel!E13 -> 18457 | F8: =Data_Panel!F13 -> 17695 | G8: =Data_Panel!G13 -> 18743 | H8: =Data_Panel!H13 -> 16138 | I8: =Data_Panel!I13 -> 16047 | J8: =Data_Panel!J13 -> 15158
A9: R02 | B9: Total R&D costs | C9: EUR m | D9: =Data_Panel!D17 -> 1545 | E9: =Data_Panel!E17 -> 1289 | F9: =Data_Panel!F17 -> 1665 | G9: =Data_Panel!G17 -> 863 | H9: =Data_Panel!H17 -> 1264 | I9: =Data_Panel!I17 -> 1028 | J9: =Data_Panel!J17 -> 1116 | K9: A05: S011 slide 34 (FY), S016 slide 25 (H1 2024-26), S002 p.29 (H1 2023)
A10: R03 | B10: Capitalised development costs | C10: EUR m | D10: =Data_Panel!D18 -> 1201 | E10: =Data_Panel!E18 -> 880 | F10: =Data_Panel!F18 -> 1123 | G10: =Data_Panel!G18 -> 460 | H10: =Data_Panel!H18 -> 575 | I10: =Data_Panel!I18 -> 388 | J10: =Data_Panel!J18 -> 487
A11: R04 | B11: Expensed R&D | C11: EUR m | D11: =Data_Panel!D20 -> 343 | E11: =Data_Panel!E20 -> 410 | F11: =Data_Panel!F20 -> 541 | G11: =Data_Panel!G20 -> 404 | H11: =Data_Panel!H20 -> 690 | I11: =Data_Panel!I20 -> 639 | J11: =Data_Panel!J20 -> 629
A12: R05 | B12: Amortisation of capitalised R&D | C12: EUR m | D12: =Data_Panel!D21 -> 427 | E12: =Data_Panel!E21 -> 533 | F12: =Data_Panel!F21 -> 516 | G12: =Data_Panel!G21 -> 585 | H12: =Data_Panel!H21 -> 600 | I12: =Data_Panel!I21 -> 1230 | J12: =Data_Panel!J21 -> 705
A13: R06 | B13: R&D charged to the P&L (expensed + amortisation) | C13: EUR m | D13: =D11+D12 -> 770 | E13: =E11+E12 -> 943 | F13: =F11+F12 -> 1057 | G13: =G11+G12 -> 989 | H13: =H11+H12 -> 1290 | I13: =I11+I12 -> 1869 | J13: =J11+J12 -> 1334
A14: R07 | B14: Capitalisation rate (calculated) | C14: % | D14: =D10/D9 -> 0.77734628 | E14: =E10/E9 -> 0.68269977 | F14: =F10/F9 -> 0.67447447 | G14: =G10/G9 -> 0.53302433 | H14: =H10/H9 -> 0.45490506 | I14: =I10/I9 -> 0.37743191 | J14: =J10/J9 -> 0.43637993
A15: R08 | B15: Capitalisation rate (published) | C15: % | D15: =IF(Data_Panel!D19="","",Data_Panel!D19/100) -> 0.777 | E15: =IF(Data_Panel!E19="","",Data_Panel!E19/100) | F15: =IF(Data_Panel!F19="","",Data_Panel!F19/100) -> 0.675 | G15: =IF(Data_Panel!G19="","",Data_Panel!G19/100) | H15: =IF(Data_Panel!H19="","",Data_Panel!H19/100) -> 0.455 | I15: =IF(Data_Panel!I19="","",Data_Panel!I19/100) | J15: =IF(Data_Panel!J19="","",Data_Panel!J19/100) -> 0.436
A16: R09 | B16: Check: calculated - published | C16: pp | D16: =IF(D15="",0,(D14-D15)*100) -> 0.034627832 | E16: =IF(E15="",0,(E14-E15)*100) -> 0 | F16: =IF(F15="",0,(F14-F15)*100) -> -0.052552553 | G16: =IF(G15="",0,(G14-G15)*100) -> 0 | H16: =IF(H15="",0,(H14-H15)*100) -> -0.0094936709 | I16: =IF(I15="",0,(I14-I15)*100) -> 0 | J16: =IF(J15="",0,(J14-J15)*100) -> 0.037992832
A17: R10 | B17: Net capitalisation (capitalised - amortised) | C17: EUR m | D17: =D10-D12 -> 774 | E17: =E10-E12 -> 347 | F17: =F10-F12 -> 607 | G17: =G10-G12 -> -125 | H17: =H10-H12 -> -25 | I17: =I10-I12 -> -842 | J17: =J10-J12 -> -218 | K17: >0: P&L charge below total R&D costs
A18: R11 | B18: Total R&D costs / automotive revenue | C18: % | D18: =D9/D8 -> 0.081780648 | E18: =E9/E8 -> 0.069838002 | F18: =F9/F8 -> 0.094094377 | G18: =G9/G8 -> 0.046043856 | H18: =H9/H8 -> 0.078324452 | I18: =I9/I8 -> 0.064061818 | J18: =J9/J8 -> 0.073624489
A19: R12 | B19: R&D P&L charge / automotive revenue | C19: % | D19: =D13/D8 -> 0.040757993 | E19: =E13/E8 -> 0.051091727 | F19: =F13/F8 -> 0.059734388 | G19: =G13/G8 -> 0.052766366 | H19: =H13/H8 -> 0.079935556 | I19: =I13/I8 -> 0.11647037 | J19: =J13/J8 -> 0.088006333
A20: R13 | B20: P&L charge at prior-year capitalisation rate (illustrative) | C20: EUR m | F20: =F9*(1-D14)+F12 -> 886.71845 | G20: =G9*(1-E14)+G12 -> 858.8301 | H20: =H9*(1-F14)+H12 -> 1011.4643 | I20: =I9*(1-G14)+I12 -> 1710.051 | J20: =J9*(1-H14)+J12 -> 1313.3259 | K20: Counterfactual: same total R&D costs and amortisation, prior-year same-half rate
A21: R14 | B21: EBIT effect of capitalisation-rate change (+ = extra cost) | C21: EUR m | F21: =F13-F20 -> 170.28155 | G21: =G13-G20 -> 130.1699 | H21: =H13-H20 -> 278.53574 | I21: =I13-I20 -> 158.94902 | J21: =J13-J20 -> 20.674051
A22: R15 | B22: Change in R&D P&L charge | C22: EUR m | F22: =F13-D13 -> 287 | G22: =G13-E13 -> 46 | H22: =H13-F13 -> 233 | I22: =I13-G13 -> 880 | J22: =J13-H13 -> 44
A23: R16 | B23: Change in total R&D costs | C23: EUR m | F23: =F9-D9 -> 120 | G23: =G9-E9 -> -426 | H23: =H9-F9 -> -401 | I23: =I9-G9 -> 165 | J23: =J9-H9 -> -148
A24: R17 | B24: Change in amortisation | C24: EUR m | F24: =F12-D12 -> 89 | G24: =G12-E12 -> 52 | H24: =H12-F12 -> 84 | I24: =I12-G12 -> 645 | J24: =J12-H12 -> 105
A25: R18 | B25: Check: total - capitalised - expensed (rounding) | C25: EUR m | D25: =D9-D10-D11 -> 1 | E25: =E9-E10-E11 -> -1 | F25: =F9-F10-F11 -> 1 | G25: =G9-G10-G11 -> -1 | H25: =H9-H10-H11 -> -1 | I25: =I9-I10-I11 -> 1 | J25: =J9-J10-J11 -> 0
A26: H2 2025 amortisation (FY - H1) most likely contains impairments of capitalised development costs; Porsche does not disclose the split.
A27: B. Automotive D&A and impairment treatment
A28: R19 | B28: Automotive D&A total (incl. impairments) | C28: EUR m | D28: =Data_Panel!D24 -> 1176 | E28: =Data_Panel!E24 -> 1480 | F28: =Data_Panel!F24 -> 1364 | G28: =Data_Panel!G24 -> 1621 | H28: =Data_Panel!H24 -> 1756 | I28: =Data_Panel!I24 -> 2436 | J28: =Data_Panel!J24 -> 1559 | K28: A12: EBITDA tables and S011 slide 34 / S016 slide 25
A29: R20 | B29: Depreciation on capex (incl. impairments) | C29: EUR m | D29: =Data_Panel!D23 -> 749 | E29: =Data_Panel!E23 -> 947 | F29: =Data_Panel!F23 -> 849 | G29: =Data_Panel!G23 -> 1035 | H29: =Data_Panel!H23 -> 1156 | I29: =Data_Panel!I23 -> 1206 | J29: =Data_Panel!J23 -> 854 | K29: H1 2023 = A12 - A09 (DERIVED)
A30: R21 | B30: Amortisation of capitalised R&D | C30: EUR m | D30: =D12 -> 427 | E30: =E12 -> 533 | F30: =F12 -> 516 | G30: =G12 -> 585 | H30: =H12 -> 600 | I30: =I12 -> 1230 | J30: =J12 -> 705
A31: R22 | B31: Impairments disclosed inside D&A | C31: EUR m | D31: =IF(Data_Panel!D35="","",Data_Panel!D35) -> 0 | E31: =IF(Data_Panel!E35="","",Data_Panel!E35) -> 2 | F31: =IF(Data_Panel!F35="","",Data_Panel!F35) -> 0 | G31: =IF(Data_Panel!G35="","",Data_Panel!G35) -> 3 | H31: =IF(Data_Panel!H35="","",Data_Panel!H35) -> 295 | I31: =IF(Data_Panel!I35="","",Data_Panel!I35) -> 900 | J31: =IF(Data_Panel!J35="","",Data_Panel!J35) -> 61 | K31: X05: S002 p.38, S004 segment reporting (FY2023 = 2), S006 p.38, S008 segment reporting (FY2024 = 3), S010 p.32 (Cellforce 295), S012 segment reporting (FY2025 = 1,195; S011 slide 34 fn: around 1,200), S017 p.29 (43 + 18)
A32: R23 | B32: Impairments removed (used) | C32: EUR m | D32: =IF(Data_Panel!D35="",0,Data_Panel!D35) -> 0 | E32: =IF(Data_Panel!E35="",0,Data_Panel!E35) -> 2 | F32: =IF(Data_Panel!F35="",0,Data_Panel!F35) -> 0 | G32: =IF(Data_Panel!G35="",0,Data_Panel!G35) -> 3 | H32: =IF(Data_Panel!H35="",0,Data_Panel!H35) -> 295 | I32: =IF(Data_Panel!I35="",0,Data_Panel!I35) -> 900 | J32: =IF(Data_Panel!J35="",0,Data_Panel!J35) -> 61
A33: R24 | B33: treatment | D33: =IF(Data_Panel!D35="","A-03: not disclosed -> 0",IF(D$5="2026-H1","A-04: 61 assumed inside D&A (upper bound)",IF(AND(RIGHT(D$5,2)="H2",Data_Panel!D35>0),"H2 = FY - H1; split not disclosed","FACT"))) -> FACT | E33: =IF(Data_Panel!E35="","A-03: not disclosed -> 0",IF(E$5="2026-H1","A-04: 61 assumed inside D&A (upper bound)",IF(AND(RIGHT(E$5,2)="H2",Data_Panel!E35>0),"H2 = FY - H1; split not disclosed","FACT"))) -> H2 = FY - H1; split not disclosed | F33: =IF(Data_Panel!F35="","A-03: not disclosed -> 0",IF(F$5="2026-H1","A-04: 61 assumed inside D&A (upper bound)",IF(AND(RIGHT(F$5,2)="H2",Data_Panel!F35>0),"H2 = FY - H1; split not disclosed","FACT"))) -> FACT | G33: =IF(Data_Panel!G35="","A-03: not disclosed -> 0",IF(G$5="2026-H1","A-04: 61 assumed inside D&A (upper bound)",IF(AND(RIGHT(G$5,2)="H2",Data_Panel!G35>0),"H2 = FY - H1; split not disclosed","FACT"))) -> H2 = FY - H1; split not disclosed | H33: =IF(Data_Panel!H35="","A-03: not disclosed -> 0",IF(H$5="2026-H1","A-04: 61 assumed inside D&A (upper bound)",IF(AND(RIGHT(H$5,2)="H2",Data_Panel!H35>0),"H2 = FY - H1; split not disclosed","FACT"))) -> FACT | I33: =IF(Data_Panel!I35="","A-03: not disclosed -> 0",IF(I$5="2026-H1","A-04: 61 assumed inside D&A (upper bound)",IF(AND(RIGHT(I$5,2)="H2",Data_Panel!I35>0),"H2 = FY - H1; split not disclosed","FACT"))) -> H2 = FY - H1; split not disclosed | J33: =IF(Data_Panel!J35="","A-03: not disclosed -> 0",IF(J$5="2026-H1","A-04: 61 assumed inside D&A (upper bound)",IF(AND(RIGHT(J$5,2)="H2",Data_Panel!J35>0),"H2 = FY - H1; split not disclosed","FACT"))) -> A-04: 61 assumed inside D&A (upper bound)
A34: R25 | B34: Clean automotive D&A (excl. impairments) | C34: EUR m | D34: =D28-D32 -> 1176 | E34: =E28-E32 -> 1478 | F34: =F28-F32 -> 1364 | G34: =G28-G32 -> 1618 | H34: =H28-H32 -> 1461 | I34: =I28-I32 -> 1536 | J34: =J28-J32 -> 1498
A35: R26 | B35: D&A total / automotive revenue | C35: % | D35: =D28/D8 -> 0.062248571 | E35: =E28/E8 -> 0.080186379 | F35: =F28/F8 -> 0.077083922 | G35: =G28/G8 -> 0.086485621 | H35: =H28/H8 -> 0.1088115 | I35: =I28/I8 -> 0.15180408 | J35: =J28/J8 -> 0.10284998
A36: R27 | B36: Clean D&A / automotive revenue | C36: % | D36: =D34/D8 -> 0.062248571 | E36: =E34/E8 -> 0.080078019 | F36: =F34/F8 -> 0.077083922 | G36: =G34/G8 -> 0.086325562 | H36: =H34/H8 -> 0.090531664 | I36: =I34/I8 -> 0.095718826 | J36: =J34/J8 -> 0.098825703
A37: R28 | B37: Clean depreciation on capex (where impairment line is known) | C37: EUR m | D37: =IF(D32=0,D29,IF(D$5="2025-H1",D29-D32,"n/a")) -> 749 | E37: =IF(E32=0,E29,IF(E$5="2025-H1",E29-E32,"n/a")) -> n/a | F37: =IF(F32=0,F29,IF(F$5="2025-H1",F29-F32,"n/a")) -> 849 | G37: =IF(G32=0,G29,IF(G$5="2025-H1",G29-G32,"n/a")) -> n/a | H37: =IF(H32=0,H29,IF(H$5="2025-H1",H29-H32,"n/a")) -> 861 | I37: =IF(I32=0,I29,IF(I$5="2025-H1",I29-I32,"n/a")) -> n/a | J37: =IF(J32=0,J29,IF(J$5="2025-H1",J29-J32,"n/a")) -> n/a | K37: H1 2025: Cellforce impairment sits in PP&E depreciation (S010 p.32)
A38: R29 | B38: Change in D&A total | C38: EUR m | F38: =F28-D28 -> 188 | G38: =G28-E28 -> 141 | H38: =H28-F28 -> 392 | I38: =I28-G28 -> 815 | J38: =J28-H28 -> -197
A39: R30 | B39: Change in clean D&A | C39: EUR m | F39: =F34-D34 -> 188 | G39: =G34-E34 -> 140 | H39: =H34-F34 -> 97 | I39: =I34-G34 -> -82 | J39: =J34-H34 -> 37
A40: R31 | B40: Check: D&A - amortisation - depreciation (rounding) | C40: EUR m | D40: =D28-D12-D29 -> 0 | E40: =E28-E12-E29 -> 0 | F40: =F28-F12-F29 -> -1 | G40: =G28-G12-G29 -> 1 | H40: =H28-H12-H29 -> 0 | I40: =I28-I12-I29 -> 0 | J40: =J28-J12-J29 -> 0

Sheet Commercial
A1: Commercial / Value-over-Volume Analysis
A2: Automotive segment. ASP uses Porsche's definition (automotive revenue / vehicles sold, wholesale).
A3: Business question: Is higher revenue per car compensating for lower volume?
A5: ID | B5: Measure | C5: Unit | D5: =Data_Panel!D$5 -> 2023-H1 | E5: =Data_Panel!E$5 -> 2023-H2 | F5: =Data_Panel!F$5 -> 2024-H1 | G5: =Data_Panel!G$5 -> 2024-H2 | H5: =Data_Panel!H$5 -> 2025-H1 | I5: =Data_Panel!I$5 -> 2025-H2 | J5: =Data_Panel!J$5 -> 2026-H1 | K5: Formula / source lineage
A6: A. Revenue per vehicle sold (Porsche ASP definition) and volume
A7: V01 | B7: Automotive sales revenue | C7: EUR m | D7: =Data_Panel!D13 -> 18892 | E7: =Data_Panel!E13 -> 18457 | F7: =Data_Panel!F13 -> 17695 | G7: =Data_Panel!G13 -> 18743 | H7: =Data_Panel!H13 -> 16138 | I7: =Data_Panel!I13 -> 16047 | J7: =Data_Panel!J13 -> 15158
A8: V02 | B8: Vehicle sales (wholesale units) | C8: units | D8: =Data_Panel!D42 -> 170802 | E8: =Data_Panel!E42 -> 162803 | F8: =Data_Panel!F42 -> 151944 | G8: =Data_Panel!G42 -> 160676 | H8: =Data_Panel!H42 -> 135142 | I8: =Data_Panel!I42 -> 130521 | J8: =Data_Panel!J42 -> 120508 | K8: O04: S025 fact sheet
A9: V03 | B9: Deliveries to customers (retail units) | C9: units | D9: =Data_Panel!D41 -> 167354 | E9: =Data_Panel!E41 -> 152867 | F9: =Data_Panel!F41 -> 155945 | G9: =Data_Panel!G41 -> 154773 | H9: =Data_Panel!H41 -> 146391 | I9: =Data_Panel!I41 -> 133058 | J9: =Data_Panel!J41 -> 122306
A10: V04 | B10: Wholesale - retail units (proxy for channel stock change) | C10: units | D10: =D8-D9 -> 3448 | E10: =E8-E9 -> 9936 | F10: =F8-F9 -> -4001 | G10: =G8-G9 -> 5903 | H10: =H8-H9 -> -11249 | I10: =I8-I9 -> -2537 | J10: =J8-J9 -> -1798 | K10: PROXY
A11: V05 | B11: ASP = automotive revenue per vehicle sold | C11: EUR k | D11: =D7*1000/D8 -> 110.6076 | E11: =E7*1000/E8 -> 113.37015 | F11: =F7*1000/F8 -> 116.45738 | G11: =G7*1000/G8 -> 116.6509 | H11: =H7*1000/H8 -> 119.41513 | I11: =I7*1000/I8 -> 122.94573 | J11: =J7*1000/J8 -> 125.78418 | K11: Porsche definition: automotive sales revenue / vehicles sold. Includes parts, services, non-vehicle revenue.
A12: V06 | B12: ASP published by Porsche | C12: EUR k | D12: =IF(Data_Panel!D43="","",Data_Panel!D43) -> 111 | E12: =IF(Data_Panel!E43="","",Data_Panel!E43) | F12: =IF(Data_Panel!F43="","",Data_Panel!F43) -> 116 | G12: =IF(Data_Panel!G43="","",Data_Panel!G43) | H12: =IF(Data_Panel!H43="","",Data_Panel!H43) -> 119 | I12: =IF(Data_Panel!I43="","",Data_Panel!I43) | J12: =IF(Data_Panel!J43="","",Data_Panel!J43) -> 126 | K12: O06: S005 p.20, S009 p.32, S011 p.10, S016 p.10
A13: V07 | B13: Check: calculated - published (published rounded to EUR 1k) | C13: EUR k | D13: =IF(D12="",0,D11-D12) -> -0.39239587 | E13: =IF(E12="",0,E11-E12) -> 0 | F13: =IF(F12="",0,F11-F12) -> 0.45737903 | G13: =IF(G12="",0,G11-G12) -> 0 | H13: =IF(H12="",0,H11-H12) -> 0.41513371 | I13: =IF(I12="",0,I11-I12) -> 0 | J13: =IF(J12="",0,J11-J12) -> -0.2158197
A14: V08 | B14: Revenue per delivery (reference only; different denominator) | C14: EUR k | D14: =D7*1000/D9 -> 112.88646 | E14: =E7*1000/E9 -> 120.73894 | F14: =F7*1000/F9 -> 113.46949 | G14: =G7*1000/G9 -> 121.09993 | H14: =H7*1000/H9 -> 110.23902 | I14: =I7*1000/I9 -> 120.60154 | J14: =J7*1000/J9 -> 123.93505
A15: V09 | B15: BEV share of deliveries (published) | C15: % | D15: =IF(Data_Panel!D44="","",Data_Panel!D44/100) -> 0.108 | E15: =IF(Data_Panel!E44="","",Data_Panel!E44/100) | F15: =IF(Data_Panel!F44="","",Data_Panel!F44/100) -> 0.059 | G15: =IF(Data_Panel!G44="","",Data_Panel!G44/100) | H15: =IF(Data_Panel!H44="","",Data_Panel!H44/100) -> 0.235 | I15: =IF(Data_Panel!I44="","",Data_Panel!I44/100) | J15: =IF(Data_Panel!J44="","",Data_Panel!J44/100) -> 0.194
A16: B. Year-on-year: volume effect vs ASP effect on automotive revenue
A17: V10 | B17: Change in vehicle sales | C17: % | F17: =F8/D8-1 -> -0.11040854 | G17: =G8/E8-1 -> -0.01306487 | H17: =H8/F8-1 -> -0.11058021 | I17: =I8/G8-1 -> -0.18767582 | J17: =J8/H8-1 -> -0.1082861
A18: V11 | B18: Change in ASP | C18: % | F18: =F11/D11-1 -> 0.052887638 | G18: =G11/E11-1 -> 0.028938423 | H18: =H11/F11-1 -> 0.025397744 | I18: =I11/G11-1 -> 0.053963004 | J18: =J11/H11-1 -> 0.053335339
A19: V12 | B19: Change in automotive revenue | C19: EUR m | F19: =F7-D7 -> -1197 | G19: =G7-E7 -> 286 | H19: =H7-F7 -> -1557 | I19: =I7-G7 -> -2696 | J19: =J7-H7 -> -980
A20: V13 | B20: Volume effect (unit change at prior-year ASP) | C20: EUR m | F20: =(F8-D8)*D11/1000 -> -2085.8382 | G20: =(G8-E8)*E11/1000 -> -241.1383 | H20: =(H8-F8)*F11/1000 -> -1956.7169 | I20: =(I8-G8)*G11/1000 -> -3517.6079 | J20: =(J8-H8)*H11/1000 -> -1747.5211
A21: V14 | B21: ASP effect (ASP change at current units) | C21: EUR m | F21: =(F11-D11)*F8/1000 -> 888.8382 | G21: =(G11-E11)*G8/1000 -> 527.1383 | H21: =(H11-F11)*H8/1000 -> 399.71688 | I21: =(I11-G11)*I8/1000 -> 821.60789 | J21: =(J11-H11)*J8/1000 -> 767.52107 | K21: Residual of price, model mix, derivative mix, options, FX and non-vehicle revenue - NOT 'price'
A22: V15 | B22: Check: volume + ASP effect - revenue change (must be 0) | C22: EUR m | F22: =F20+F21-F19 -> 0 | G22: =G20+G21-G19 -> 0 | H22: =H20+H21-H19 -> 0 | I22: =I20+I21-I19 -> 0 | J22: =J20+J21-J19 -> 0
A23: C. Delivery mix by model line (retail units; drives the ASP effect only indirectly)
B24: 911 | C24: units | D24: =SUMIFS(Data_Mix!$F$6:$F$88,Data_Mix!$A$6:$A$88,D$5,Data_Mix!$B$6:$B$88,"model",Data_Mix!$C$6:$C$88,"911") -> 26124 | E24: =SUMIFS(Data_Mix!$F$6:$F$88,Data_Mix!$A$6:$A$88,E$5,Data_Mix!$B$6:$B$88,"model",Data_Mix!$C$6:$C$88,"911") -> 24022 | F24: =SUMIFS(Data_Mix!$F$6:$F$88,Data_Mix!$A$6:$A$88,F$5,Data_Mix!$B$6:$B$88,"model",Data_Mix!$C$6:$C$88,"911") -> 28212 | G24: =SUMIFS(Data_Mix!$F$6:$F$88,Data_Mix!$A$6:$A$88,G$5,Data_Mix!$B$6:$B$88,"model",Data_Mix!$C$6:$C$88,"911") -> 22729 | H24: =SUMIFS(Data_Mix!$F$6:$F$88,Data_Mix!$A$6:$A$88,H$5,Data_Mix!$B$6:$B$88,"model",Data_Mix!$C$6:$C$88,"911") -> 25608 | I24: =SUMIFS(Data_Mix!$F$6:$F$88,Data_Mix!$A$6:$A$88,I$5,Data_Mix!$B$6:$B$88,"model",Data_Mix!$C$6:$C$88,"911") -> 25975 | J24: =SUMIFS(Data_Mix!$F$6:$F$88,Data_Mix!$A$6:$A$88,J$5,Data_Mix!$B$6:$B$88,"model",Data_Mix!$C$6:$C$88,"911") -> 30534 | K24: Data_Mix (S025)
B25: 718 Boxster/Cayman | C25: units | D25: =SUMIFS(Data_Mix!$F$6:$F$88,Data_Mix!$A$6:$A$88,D$5,Data_Mix!$B$6:$B$88,"model",Data_Mix!$C$6:$C$88,"718") -> 11035 | E25: =SUMIFS(Data_Mix!$F$6:$F$88,Data_Mix!$A$6:$A$88,E$5,Data_Mix!$B$6:$B$88,"model",Data_Mix!$C$6:$C$88,"718") -> 9483 | F25: =SUMIFS(Data_Mix!$F$6:$F$88,Data_Mix!$A$6:$A$88,F$5,Data_Mix!$B$6:$B$88,"model",Data_Mix!$C$6:$C$88,"718") -> 11886 | G25: =SUMIFS(Data_Mix!$F$6:$F$88,Data_Mix!$A$6:$A$88,G$5,Data_Mix!$B$6:$B$88,"model",Data_Mix!$C$6:$C$88,"718") -> 11784 | H25: =SUMIFS(Data_Mix!$F$6:$F$88,Data_Mix!$A$6:$A$88,H$5,Data_Mix!$B$6:$B$88,"model",Data_Mix!$C$6:$C$88,"718") -> 10496 | I25: =SUMIFS(Data_Mix!$F$6:$F$88,Data_Mix!$A$6:$A$88,I$5,Data_Mix!$B$6:$B$88,"model",Data_Mix!$C$6:$C$88,"718") -> 8116 | J25: =SUMIFS(Data_Mix!$F$6:$F$88,Data_Mix!$A$6:$A$88,J$5,Data_Mix!$B$6:$B$88,"model",Data_Mix!$C$6:$C$88,"718") -> 2789 | K25: Data_Mix (S025)
