Workbook

Sheet README
A1: File | B1: PCL_02_Manual_Inputs.xlsx - Phase 2: hand-entry of the variables that exist only in Porsche PDFs.
A2: Why this file | B2: The Porsche fact sheets (S024/S025) are extracted by script. They do not contain segment, EBITDA, R&D, D&A, one-off, ASP or BEV data. Those ~150 values are entered here, each tied to a source and page.
A3: What you edit | B3: Nothing, unless a source value is corrected. The workbook was populated by the lead analyst (Phase 2) and is the controlled input record for the SQL database (export_to_csv.py).
A4: How to enter | B4: If a value must be corrected: type it exactly as printed, in the unit shown in column H (Unit_as_shown). Do not convert. EUR bn -> 0.7 ; EUR m -> 1116 ; % -> 18.3 ; EUR k -> 126. Negative amounts keep their sign as printed.
A5: Rounding | B5: Column M (Rounding_as_shown) states the precision of the source. Never add digits the source does not show.
A6: Blue / black | B6: Blue = your hard-coded input. Black = formula. Green = value pulled from another sheet.
A7: Example row | B7: Row 36 (A05, H1_2026 = 1116, S016 slide 25) was the template's example row; it is now an ordinary verified input (V1).
A8: Checks | B8: Sheet 'Checks' turns OK / CHECK / PENDING as you type. Every CHECK must be resolved or explained in Note before Phase 3.
A9: FS_Reference | B9: Group revenue, EBIT, vehicle sales and deliveries by half-year from the fact sheet S025 (FACT). Used only by the checks.
A10: Independent re-check | B10: Double_checked (column O) follows ONE rule, applied to every row; column S (Verification_basis) states the basis per row: Y = V1 verbatim quote from the document text, or V2 value confirmed by reconciliation to the independent fact sheet S025 (or DERIVED from V1 components). N = V3 automated extraction without independent confirmation, or V4 DERIVED with an unconfirmed premise. N/A = blank row (data gap). Live counts: sheet 'Checks', rows 13-16.
A11: Status | B11: Populated by the lead analyst on 2026-09-28 from Porsche primary documents. Blue = value as printed. Grey = deliberately blank (reason in Note). Label column distinguishes FACT and DERIVED. Source re-check (Oct 2026): rows M095 (X05 FY2023 = 2), M097 (X05 FY2024 = 3) and M143 (O06 FY2023 = 112) filled from the official reports; M099 (X05 FY2025) refined from 1,200 to the exact 1,195. One gap remains (M093, X04 FY2025: not disclosed).

Sheet Inputs
A1: Rec_ID | B1: Var_ID | C1: Variable | D1: Period | E1: Source_ID | F1: Page | G1: Fallback_source | H1: Unit_as_shown | I1: Value_as_shown | J1: Value_std | K1: Std_unit | L1: Label | M1: Rounding_as_shown | N1: Entered_By | O1: Double_checked (Y/N) | P1: Note | Q1: Key | R1: Instruction | S1: Verification_basis
A2: M001 | B2: A01 | C2: Automotive sales revenue | D2: H1_2023 | E2: S002 | F2: 9 (Automotive EBITDA margin table) | G2: S001 p.7/9/11 (EUR bn) | H2: EUR m | I2: 18892 | J2: =IF(I2="","",IF(H2="EUR bn",I2*1000,I2)) -> 18892 | K2: =IF(H2="EUR bn","EUR m",H2) -> EUR m | L2: FACT | M2: EUR 1m | N2: Lead analyst (Claude) | O2: Y | P2: Verbatim from document text | Q2: =B2&"|"&D2 -> A01|H1_2023 | S2: V1: verbatim quote from the document text
A3: M002 | B3: A01 | C3: Automotive sales revenue | D3: FY_2023 | E3: S026 | F3: Automotive results of operations (2023 in brackets) | G3: S003 p.56/60 (EUR bn) | H3: EUR m | I3: 37349 | J3: =IF(I3="","",IF(H3="EUR bn",I3*1000,I3)) -> 37349 | K3: =IF(H3="EUR bn","EUR m",H3) -> EUR m | L3: FACT | M3: EUR 1m | N3: Lead analyst (Claude) | O3: Y | P3: Verbatim from document text | Q3: =B3&"|"&D3 -> A01|FY_2023 | S3: V1: verbatim quote from the document text
A4: M003 | B4: A01 | C4: Automotive sales revenue | D4: H1_2024 | E4: S006 | F4: 10 (Automotive EBITDA margin table) | G4: S005 p.14/17/21 (EUR bn) | H4: EUR m | I4: 17695 | J4: =IF(I4="","",IF(H4="EUR bn",I4*1000,I4)) -> 17695 | K4: =IF(H4="EUR bn","EUR m",H4) -> EUR m | L4: FACT | M4: EUR 1m | N4: Lead analyst (Claude) | O4: Y | P4: Verbatim from document text | Q4: =B4&"|"&D4 -> A01|H1_2024 | S4: V1: verbatim quote from the document text
A5: M004 | B5: A01 | C5: Automotive sales revenue | D5: FY_2024 | E5: S026 | F5: Automotive results of operations | G5: S007 p.66/70 (EUR bn) | H5: EUR m | I5: 36438 | J5: =IF(I5="","",IF(H5="EUR bn",I5*1000,I5)) -> 36438 | K5: =IF(H5="EUR bn","EUR m",H5) -> EUR m | L5: FACT | M5: EUR 1m | N5: Lead analyst (Claude) | O5: Y | P5: Verbatim from document text | Q5: =B5&"|"&D5 -> A01|FY_2024 | S5: V1: verbatim quote from the document text
A6: M005 | B6: A01 | C6: Automotive sales revenue | D6: H1_2025 | E6: S010 | F6: 11 (Automotive EBITDA margin table) | G6: S009 p.29/33 (EUR bn) | H6: EUR m | I6: 16138 | J6: =IF(I6="","",IF(H6="EUR bn",I6*1000,I6)) -> 16138 | K6: =IF(H6="EUR bn","EUR m",H6) -> EUR m | L6: FACT | M6: EUR 1m | N6: Lead analyst (Claude) | O6: Y | P6: Verbatim from document text | Q6: =B6&"|"&D6 -> A01|H1_2025 | S6: V1: verbatim quote from the document text
A7: M006 | B7: A01 | C7: Automotive sales revenue | D7: FY_2025 | E7: S013 | F7: Automotive results of operations | G7: S011 p.11 (EUR bn) | H7: EUR m | I7: 32185 | J7: =IF(I7="","",IF(H7="EUR bn",I7*1000,I7)) -> 32185 | K7: =IF(H7="EUR bn","EUR m",H7) -> EUR m | L7: FACT | M7: EUR 1m | N7: Lead analyst (Claude) | O7: Y | P7: Verbatim from document text | Q7: =B7&"|"&D7 -> A01|FY_2025 | S7: V1: verbatim quote from the document text
A8: M007 | B8: A01 | C8: Automotive sales revenue | D8: H1_2026 | E8: S017 | F8: 12 (Automotive EBITDA margin table) | G8: S016 p.7/11 (EUR bn) | H8: EUR m | I8: 15158 | J8: =IF(I8="","",IF(H8="EUR bn",I8*1000,I8)) -> 15158 | K8: =IF(H8="EUR bn","EUR m",H8) -> EUR m | L8: FACT | M8: EUR 1m | N8: Lead analyst (Claude) | O8: Y | P8: Verbatim from document text | Q8: =B8&"|"&D8 -> A01|H1_2026 | S8: V1: verbatim quote from the document text
A9: M008 | B9: A02 | C9: Automotive operating profit | D9: H1_2023 | E9: S002 | F9: 9 (Automotive EBITDA margin table) | G9: S001 p.7/9/11 (EUR bn) | H9: EUR m | I9: 3653 | J9: =IF(I9="","",IF(H9="EUR bn",I9*1000,I9)) -> 3653 | K9: =IF(H9="EUR bn","EUR m",H9) -> EUR m | L9: FACT | M9: EUR 1m | N9: Lead analyst (Claude) | O9: Y | P9: Verbatim from document text | Q9: =B9&"|"&D9 -> A02|H1_2023 | S9: V1: verbatim quote from the document text
A10: M009 | B10: A02 | C10: Automotive operating profit | D10: FY_2023 | E10: S026 | F10: Automotive results of operations (2023 in brackets) | G10: S003 p.56/60 (EUR bn) | H10: EUR m | I10: 6938 | J10: =IF(I10="","",IF(H10="EUR bn",I10*1000,I10)) -> 6938 | K10: =IF(H10="EUR bn","EUR m",H10) -> EUR m | L10: FACT | M10: EUR 1m | N10: Lead analyst (Claude) | O10: Y | P10: Verbatim from document text | Q10: =B10&"|"&D10 -> A02|FY_2023 | S10: V1: verbatim quote from the document text
A11: M010 | B11: A02 | C11: Automotive operating profit | D11: H1_2024 | E11: S006 | F11: 10 (Automotive EBITDA margin table) | G11: S005 p.14/17/21 (EUR bn) | H11: EUR m | I11: 2904 | J11: =IF(I11="","",IF(H11="EUR bn",I11*1000,I11)) -> 2904 | K11: =IF(H11="EUR bn","EUR m",H11) -> EUR m | L11: FACT | M11: EUR 1m | N11: Lead analyst (Claude) | O11: Y | P11: Verbatim from document text | Q11: =B11&"|"&D11 -> A02|H1_2024 | S11: V1: verbatim quote from the document text
A12: M011 | B12: A02 | C12: Automotive operating profit | D12: FY_2024 | E12: S013 | F12: Automotive results of operations (2024 in brackets) | G12: S007 p.66/70 (EUR bn) | H12: EUR m | I12: 5286 | J12: =IF(I12="","",IF(H12="EUR bn",I12*1000,I12)) -> 5286 | K12: =IF(H12="EUR bn","EUR m",H12) -> EUR m | L12: FACT | M12: EUR 1m | N12: Lead analyst (Claude) | O12: Y | P12: Verbatim from document text; also S026 | Q12: =B12&"|"&D12 -> A02|FY_2024 | S12: V1: verbatim quote from the document text
A13: M012 | B13: A02 | C13: Automotive operating profit | D13: H1_2025 | E13: S010 | F13: 11 (Automotive EBITDA margin table) | G13: S009 p.29/33 (EUR bn) | H13: EUR m | I13: 832 | J13: =IF(I13="","",IF(H13="EUR bn",I13*1000,I13)) -> 832 | K13: =IF(H13="EUR bn","EUR m",H13) -> EUR m | L13: FACT | M13: EUR 1m | N13: Lead analyst (Claude) | O13: Y | P13: Verbatim from document text | Q13: =B13&"|"&D13 -> A02|H1_2025 | S13: V1: verbatim quote from the document text
... A22: M021 | B22: A03 | C22: Automotive EBITDA | D22: H1_2026 | E22: S017 | F22: 12 (Automotive EBITDA margin table) | G22: S016 p.7/11 (EUR bn) | H22: EUR m | I22: 2767 | J22: =IF(I22="","",IF(H22="EUR bn",I22*1000,I22)) -> 2767 | K22: =IF(H22="EUR bn","EUR m",H22) -> EUR m | L22: FACT | M22: EUR 1m | N22: Lead analyst (Claude) | O22: Y | P22: Verbatim from document text | Q22: =B22&"|"&D22 -> A03|H1_2026 | S22: V1: verbatim quote from the document text
A23: M022 | B23: A04 | C23: Automotive EBITDA margin | D23: H1_2023 | E23: S002 | F23: 9 (Automotive EBITDA margin table) | G23: S001 p.7/9/11 (EUR bn) | H23: % | I23: 25.6 | J23: =IF(I23="","",IF(H23="EUR bn",I23*1000,I23)) -> 25.6 | K23: =IF(H23="EUR bn","EUR m",H23) -> % | L23: FACT | M23: 0.1pp | N23: Lead analyst (Claude) | O23: Y | P23: Verbatim from document text | Q23: =B23&"|"&D23 -> A04|H1_2023 | R23: Enter 18.3 for 18.3% | S23: V1: verbatim quote from the document text
A24: M023 | B24: A04 | C24: Automotive EBITDA margin | D24: FY_2023 | E24: S026 | F24: Automotive results of operations (2023 in brackets) | G24: S003 p.56/60 (EUR bn) | H24: % | I24: 25.7 | J24: =IF(I24="","",IF(H24="EUR bn",I24*1000,I24)) -> 25.7 | K24: =IF(H24="EUR bn","EUR m",H24) -> % | L24: FACT | M24: 0.1pp | N24: Lead analyst (Claude) | O24: Y | P24: Verbatim from document text | Q24: =B24&"|"&D24 -> A04|FY_2023 | R24: Enter 18.3 for 18.3% | S24: V1: verbatim quote from the document text
A25: M024 | B25: A04 | C25: Automotive EBITDA margin | D25: H1_2024 | E25: S006 | F25: 10 (Automotive EBITDA margin table) | G25: S005 p.14/17/21 (EUR bn) | H25: % | I25: 24.1 | J25: =IF(I25="","",IF(H25="EUR bn",I25*1000,I25)) -> 24.1 | K25: =IF(H25="EUR bn","EUR m",H25) -> % | L25: FACT | M25: 0.1pp | N25: Lead analyst (Claude) | O25: Y | P25: Verbatim from document text | Q25: =B25&"|"&D25 -> A04|H1_2024 | R25: Enter 18.3 for 18.3% | S25: V1: verbatim quote from the document text
A26: M025 | B26: A04 | C26: Automotive EBITDA margin | D26: FY_2024 | E26: S026 | F26: Automotive results of operations | G26: S007 p.66/70 (EUR bn) | H26: % | I26: 22.7 | J26: =IF(I26="","",IF(H26="EUR bn",I26*1000,I26)) -> 22.7 | K26: =IF(H26="EUR bn","EUR m",H26) -> % | L26: FACT | M26: 0.1pp | N26: Lead analyst (Claude) | O26: Y | P26: Verbatim from document text | Q26: =B26&"|"&D26 -> A04|FY_2024 | R26: Enter 18.3 for 18.3% | S26: V1: verbatim quote from the document text
A27: M026 | B27: A04 | C27: Automotive EBITDA margin | D27: H1_2025 | E27: S010 | F27: 11 (Automotive EBITDA margin table) | G27: S009 p.29/33 (EUR bn) | H27: % | I27: 16 | J27: =IF(I27="","",IF(H27="EUR bn",I27*1000,I27)) -> 16 | K27: =IF(H27="EUR bn","EUR m",H27) -> % | L27: FACT | M27: 0.1pp | N27: Lead analyst (Claude) | O27: Y | P27: Verbatim from document text | Q27: =B27&"|"&D27 -> A04|H1_2025 | R27: Enter 18.3 for 18.3% | S27: V1: verbatim quote from the document text
A28: M027 | B28: A04 | C28: Automotive EBITDA margin | D28: FY_2025 | E28: S013 | F28: Automotive results of operations | G28: S011 p.11 (EUR bn) | H28: % | I28: 13.3 | J28: =IF(I28="","",IF(H28="EUR bn",I28*1000,I28)) -> 13.3 | K28: =IF(H28="EUR bn","EUR m",H28) -> % | L28: FACT | M28: 0.1pp | N28: Lead analyst (Claude) | O28: Y | P28: Verbatim from document text | Q28: =B28&"|"&D28 -> A04|FY_2025 | R28: Enter 18.3 for 18.3% | S28: V1: verbatim quote from the document text
A29: M028 | B29: A04 | C29: Automotive EBITDA margin | D29: H1_2026 | E29: S017 | F29: 12 (Automotive EBITDA margin table) | G29: S016 p.7/11 (EUR bn) | H29: % | I29: 18.3 | J29: =IF(I29="","",IF(H29="EUR bn",I29*1000,I29)) -> 18.3 | K29: =IF(H29="EUR bn","EUR m",H29) -> % | L29: FACT | M29: 0.1pp | N29: Lead analyst (Claude) | O29: Y | P29: Verbatim from document text | Q29: =B29&"|"&D29 -> A04|H1_2026 | R29: Enter 18.3 for 18.3% | S29: V1: verbatim quote from the document text
A30: M029 | B30: A05 | C30: Automotive R&D costs (total) | D30: H1_2023 | E30: S002 | F30: 29 (Note 3) | G30: S002 p.6 | H30: EUR m | I30: 1545 | J30: =IF(I30="","",IF(H30="EUR bn",I30*1000,I30)) -> 1545 | K30: =IF(H30="EUR bn","EUR m",H30) -> EUR m | L30: FACT | M30: EUR 1m | N30: Lead analyst (Claude) | O30: Y | P30: Verbatim from document text; same figure as prior-year column in S006 p.8 | Q30: =B30&"|"&D30 -> A05|H1_2023 | S30: V1: verbatim quote from the document text
A31: M030 | B31: A05 | C31: Automotive R&D costs (total) | D31: FY_2023 | E31: S011 | F31: 34 | G31: S003 p.66 | H31: EUR m | I31: 2834 | J31: =IF(I31="","",IF(H31="EUR bn",I31*1000,I31)) -> 2834 | K31: =IF(H31="EUR bn","EUR m",H31) -> EUR m | L31: FACT | M31: EUR 1m | N31: Lead analyst (Claude) | O31: Y | P31: Verbatim from document text | Q31: =B31&"|"&D31 -> A05|FY_2023 | S31: V1: verbatim quote from the document text
A32: M031 | B32: A05 | C32: Automotive R&D costs (total) | D32: H1_2024 | E32: S016 | F32: 25 | G32: S005 p.28 | H32: EUR m | I32: 1665 | J32: =IF(I32="","",IF(H32="EUR bn",I32*1000,I32)) -> 1665 | K32: =IF(H32="EUR bn","EUR m",H32) -> EUR m | L32: FACT | M32: EUR 1m | N32: Lead analyst (Claude) | O32: Y | P32: Verbatim from document text | Q32: =B32&"|"&D32 -> A05|H1_2024 | S32: V1: verbatim quote from the document text
A33: M032 | B33: A05 | C33: Automotive R&D costs (total) | D33: FY_2024 | E33: S011 | F33: 34 | G33: S007 p.78 | H33: EUR m | I33: 2528 | J33: =IF(I33="","",IF(H33="EUR bn",I33*1000,I33)) -> 2528 | K33: =IF(H33="EUR bn","EUR m",H33) -> EUR m | L33: FACT | M33: EUR 1m | N33: Lead analyst (Claude) | O33: Y | P33: Verbatim from document text | Q33: =B33&"|"&D33 -> A05|FY_2024 | S33: V1: verbatim quote from the document text
A34: M033 | B34: A05 | C34: Automotive R&D costs (total) | D34: H1_2025 | E34: S016 | F34: 25 | G34: S009 p.43 | H34: EUR m | I34: 1264 | J34: =IF(I34="","",IF(H34="EUR bn",I34*1000,I34)) -> 1264 | K34: =IF(H34="EUR bn","EUR m",H34) -> EUR m | L34: FACT | M34: EUR 1m | N34: Lead analyst (Claude) | O34: Y | P34: Verbatim from document text. Restated: S010 p.9 (published July 2025) showed 1,258; S016 (latest) shows 1,264. Latest-document rule applied (AF-09). | Q34: =B34&"|"&D34 -> A05|H1_2025 | S34: V1: verbatim quote from the document text
A35: M034 | B35: A05 | C35: Automotive R&D costs (total) | D35: FY_2025 | E35: S011 | F35: 34 | H35: EUR m | I35: 2292 | J35: =IF(I35="","",IF(H35="EUR bn",I35*1000,I35)) -> 2292 | K35: =IF(H35="EUR bn","EUR m",H35) -> EUR m | L35: FACT | M35: EUR 1m | N35: Lead analyst (Claude) | O35: Y | P35: Verbatim from document text | Q35: =B35&"|"&D35 -> A05|FY_2025 | S35: V1: verbatim quote from the document text
A36: M035 | B36: A05 | C36: Automotive R&D costs (total) | D36: H1_2026 | E36: S016 | F36: 25 | H36: EUR m | I36: 1116 | J36: =IF(I36="","",IF(H36="EUR bn",I36*1000,I36)) -> 1116 | K36: =IF(H36="EUR bn","EUR m",H36) -> EUR m | L36: FACT | M36: EUR 1m | N36: Lead analyst (Claude) | O36: Y | P36: Verbatim from document text | Q36: =B36&"|"&D36 -> A05|H1_2026 | S36: V1: verbatim quote from the document text
A37: M036 | B37: A06 | C37: Automotive capitalised development costs | D37: H1_2023 | E37: S002 | F37: 29 (Note 3) | G37: S002 p.6 | H37: EUR m | I37: 1201 | J37: =IF(I37="","",IF(H37="EUR bn",I37*1000,I37)) -> 1201 | K37: =IF(H37="EUR bn","EUR m",H37) -> EUR m | L37: FACT | M37: EUR 1m | N37: Lead analyst (Claude) | O37: Y | P37: Verbatim from document text | Q37: =B37&"|"&D37 -> A06|H1_2023 | S37: V1: verbatim quote from the document text
A38: M037 | B38: A06 | C38: Automotive capitalised development costs | D38: FY_2023 | E38: S011 | F38: 34 | G38: S003 p.66 | H38: EUR m | I38: 2081 | J38: =IF(I38="","",IF(H38="EUR bn",I38*1000,I38)) -> 2081 | K38: =IF(H38="EUR bn","EUR m",H38) -> EUR m | L38: FACT | M38: EUR 1m | N38: Lead analyst (Claude) | O38: Y | P38: Verbatim from document text | Q38: =B38&"|"&D38 -> A06|FY_2023 | S38: V1: verbatim quote from the document text
A39: M038 | B39: A06 | C39: Automotive capitalised development costs | D39: H1_2024 | E39: S016 | F39: 25 | G39: S005 p.28 | H39: EUR m | I39: 1123 | J39: =IF(I39="","",IF(H39="EUR bn",I39*1000,I39)) -> 1123 | K39: =IF(H39="EUR bn","EUR m",H39) -> EUR m | L39: FACT | M39: EUR 1m | N39: Lead analyst (Claude) | O39: Y | P39: Verbatim from document text | Q39: =B39&"|"&D39 -> A06|H1_2024 | S39: V1: verbatim quote from the document text
A40: M039 | B40: A06 | C40: Automotive capitalised development costs | D40: FY_2024 | E40: S011 | F40: 34 | G40: S007 p.78 | H40: EUR m | I40: 1583 | J40: =IF(I40="","",IF(H40="EUR bn",I40*1000,I40)) -> 1583 | K40: =IF(H40="EUR bn","EUR m",H40) -> EUR m | L40: FACT | M40: EUR 1m | N40: Lead analyst (Claude) | O40: Y | P40: Verbatim from document text | Q40: =B40&"|"&D40 -> A06|FY_2024 | S40: V1: verbatim quote from the document text
A41: M040 | B41: A06 | C41: Automotive capitalised development costs | D41: H1_2025 | E41: S016 | F41: 25 | G41: S009 p.43 | H41: EUR m | I41: 575 | J41: =IF(I41="","",IF(H41="EUR bn",I41*1000,I41)) -> 575 | K41: =IF(H41="EUR bn","EUR m",H41) -> EUR m | L41: FACT | M41: EUR 1m | N41: Lead analyst (Claude) | O41: Y | P41: Verbatim from document text | Q41: =B41&"|"&D41 -> A06|H1_2025 | S41: V1: verbatim quote from the document text
A42: M041 | B42: A06 | C42: Automotive capitalised development costs | D42: FY_2025 | E42: S011 | F42: 34 | H42: EUR m | I42: 963 | J42: =IF(I42="","",IF(H42="EUR bn",I42*1000,I42)) -> 963 | K42: =IF(H42="EUR bn","EUR m",H42) -> EUR m | L42: FACT | M42: EUR 1m | N42: Lead analyst (Claude) | O42: Y | P42: Verbatim from document text | Q42: =B42&"|"&D42 -> A06|FY_2025 | S42: V1: verbatim quote from the document text
A43: M042 | B43: A06 | C43: Automotive capitalised development costs | D43: H1_2026 | E43: S016 | F43: 25 | H43: EUR m | I43: 487 | J43: =IF(I43="","",IF(H43="EUR bn",I43*1000,I43)) -> 487 | K43: =IF(H43="EUR bn","EUR m",H43) -> EUR m | L43: FACT | M43: EUR 1m | N43: Lead analyst (Claude) | O43: Y | P43: Verbatim from document text | Q43: =B43&"|"&D43 -> A06|H1_2026 | S43: V1: verbatim quote from the document text
A44: M043 | B44: A07 | C44: Capitalisation rate | D44: H1_2023 | E44: S002 | F44: 29 (Note 3) | G44: S002 p.6 | H44: % | I44: 77.7 | J44: =IF(I44="","",IF(H44="EUR bn",I44*1000,I44)) -> 77.7 | K44: =IF(H44="EUR bn","EUR m",H44) -> % | L44: FACT | M44: 0.1pp | N44: Lead analyst (Claude) | O44: Y | P44: Verbatim from document text | Q44: =B44&"|"&D44 -> A07|H1_2023 | R44: Enter 43.6 for 43.6% | S44: V1: verbatim quote from the document text
A45: M044 | B45: A07 | C45: Capitalisation rate | D45: FY_2023 | E45: S011 | F45: 34 | G45: S003 p.66 | H45: % | I45: 73.5 | J45: =IF(I45="","",IF(H45="EUR bn",I45*1000,I45)) -> 73.5 | K45: =IF(H45="EUR bn","EUR m",H45) -> % | L45: FACT | M45: 0.1pp | N45: Lead analyst (Claude) | O45: Y | P45: Verbatim from document text | Q45: =B45&"|"&D45 -> A07|FY_2023 | R45: Enter 43.6 for 43.6% | S45: V1: verbatim quote from the document text
A46: M045 | B46: A07 | C46: Capitalisation rate | D46: H1_2024 | E46: S016 | F46: 25 | G46: S005 p.28 | H46: % | I46: 67.5 | J46: =IF(I46="","",IF(H46="EUR bn",I46*1000,I46)) -> 67.5 | K46: =IF(H46="EUR bn","EUR m",H46) -> % | L46: FACT | M46: 0.1pp | N46: Lead analyst (Claude) | O46: Y | P46: Verbatim from document text | Q46: =B46&"|"&D46 -> A07|H1_2024 | R46: Enter 43.6 for 43.6% | S46: V1: verbatim quote from the document text
A47: M046 | B47: A07 | C47: Capitalisation rate | D47: FY_2024 | E47: S011 | F47: 34 | G47: S007 p.78 | H47: % | I47: 62.6 | J47: =IF(I47="","",IF(H47="EUR bn",I47*1000,I47)) -> 62.6 | K47: =IF(H47="EUR bn","EUR m",H47) -> % | L47: FACT | M47: 0.1pp | N47: Lead analyst (Claude) | O47: Y | P47: Verbatim from document text | Q47: =B47&"|"&D47 -> A07|FY_2024 | R47: Enter 43.6 for 43.6% | S47: V1: verbatim quote from the document text
A48: M047 | B48: A07 | C48: Capitalisation rate | D48: H1_2025 | E48: S016 | F48: 25 | G48: S009 p.43 | H48: % | I48: 45.5 | J48: =IF(I48="","",IF(H48="EUR bn",I48*1000,I48)) -> 45.5 | K48: =IF(H48="EUR bn","EUR m",H48) -> % | L48: FACT | M48: 0.1pp | N48: Lead analyst (Claude) | O48: Y | P48: Verbatim from document text | Q48: =B48&"|"&D48 -> A07|H1_2025 | R48: Enter 43.6 for 43.6% | S48: V1: verbatim quote from the document text
A49: M048 | B49: A07 | C49: Capitalisation rate | D49: FY_2025 | E49: S011 | F49: 34 | H49: % | I49: 42 | J49: =IF(I49="","",IF(H49="EUR bn",I49*1000,I49)) -> 42 | K49: =IF(H49="EUR bn","EUR m",H49) -> % | L49: FACT | M49: 0.1pp | N49: Lead analyst (Claude) | O49: Y | P49: Verbatim from document text | Q49: =B49&"|"&D49 -> A07|FY_2025 | R49: Enter 43.6 for 43.6% | S49: V1: verbatim quote from the document text
A50: M049 | B50: A07 | C50: Capitalisation rate | D50: H1_2026 | E50: S016 | F50: 25 | H50: % | I50: 43.6 | J50: =IF(I50="","",IF(H50="EUR bn",I50*1000,I50)) -> 43.6 | K50: =IF(H50="EUR bn","EUR m",H50) -> % | L50: FACT | M50: 0.1pp | N50: Lead analyst (Claude) | O50: Y | P50: Verbatim from document text | Q50: =B50&"|"&D50 -> A07|H1_2026 | R50: Enter 43.6 for 43.6% | S50: V1: verbatim quote from the document text
A51: M050 | B51: A08 | C51: Expensed automotive R&D | D51: H1_2023 | E51: S005 | F51: 28 (prior-year column) | G51: S002 p.6 | H51: EUR m | I51: 343 | J51: =IF(I51="","",IF(H51="EUR bn",I51*1000,I51)) -> 343 | K51: =IF(H51="EUR bn","EUR m",H51) -> EUR m | L51: FACT | M51: EUR 1m | N51: Lead analyst (Claude) | O51: N | P51: Located by automated extraction of S005 slide 28 (expensed R&D (A) = 343). A05 - A06 = 344; 1m difference is rounding. Spot-check slide 28. | Q51: =B51&"|"&D51 -> A08|H1_2023 | S51: V3: automated extraction only; consistent within EUR 1m with other PDF values (A05 - A06 = 344, CHK1) but not reconciled to an independent source
A52: M051 | B52: A08 | C52: Expensed automotive R&D | D52: FY_2023 | E52: S011 | F52: 34 | G52: S003 p.66 | H52: EUR m | I52: 753 | J52: =IF(I52="","",IF(H52="EUR bn",I52*1000,I52)) -> 753 | K52: =IF(H52="EUR bn","EUR m",H52) -> EUR m | L52: FACT | M52: EUR 1m | N52: Lead analyst (Claude) | O52: Y | P52: Verbatim from document text | Q52: =B52&"|"&D52 -> A08|FY_2023 | S52: V1: verbatim quote from the document text
A53: M052 | B53: A08 | C53: Expensed automotive R&D | D53: H1_2024 | E53: S016 | F53: 25 | G53: S005 p.28 | H53: EUR m | I53: 541 | J53: =IF(I53="","",IF(H53="EUR bn",I53*1000,I53)) -> 541 | K53: =IF(H53="EUR bn","EUR m",H53) -> EUR m | L53: FACT | M53: EUR 1m | N53: Lead analyst (Claude) | O53: Y | P53: Verbatim from document text | Q53: =B53&"|"&D53 -> A08|H1_2024 | S53: V1: verbatim quote from the document text
A54: M053 | B54: A08 | C54: Expensed automotive R&D | D54: FY_2024 | E54: S011 | F54: 34 | G54: S007 p.78 | H54: EUR m | I54: 945 | J54: =IF(I54="","",IF(H54="EUR bn",I54*1000,I54)) -> 945 | K54: =IF(H54="EUR bn","EUR m",H54) -> EUR m | L54: FACT | M54: EUR 1m | N54: Lead analyst (Claude) | O54: Y | P54: Verbatim from document text | Q54: =B54&"|"&D54 -> A08|FY_2024 | S54: V1: verbatim quote from the document text
A55: M054 | B55: A08 | C55: Expensed automotive R&D | D55: H1_2025 | E55: S016 | F55: 25 | G55: S009 p.43 | H55: EUR m | I55: 690 | J55: =IF(I55="","",IF(H55="EUR bn",I55*1000,I55)) -> 690 | K55: =IF(H55="EUR bn","EUR m",H55) -> EUR m | L55: FACT | M55: EUR 1m | N55: Lead analyst (Claude) | O55: Y | P55: Verbatim from document text | Q55: =B55&"|"&D55 -> A08|H1_2025 | S55: V1: verbatim quote from the document text
A56: M055 | B56: A08 | C56: Expensed automotive R&D | D56: FY_2025 | E56: S011 | F56: 34 | H56: EUR m | I56: 1329 | J56: =IF(I56="","",IF(H56="EUR bn",I56*1000,I56)) -> 1329 | K56: =IF(H56="EUR bn","EUR m",H56) -> EUR m | L56: FACT | M56: EUR 1m | N56: Lead analyst (Claude) | O56: Y | P56: Verbatim from document text | Q56: =B56&"|"&D56 -> A08|FY_2025 | S56: V1: verbatim quote from the document text
A57: M056 | B57: A08 | C57: Expensed automotive R&D | D57: H1_2026 | E57: S016 | F57: 25 | H57: EUR m | I57: 629 | J57: =IF(I57="","",IF(H57="EUR bn",I57*1000,I57)) -> 629 | K57: =IF(H57="EUR bn","EUR m",H57) -> EUR m | L57: FACT | M57: EUR 1m | N57: Lead analyst (Claude) | O57: Y | P57: Verbatim from document text | Q57: =B57&"|"&D57 -> A08|H1_2026 | S57: V1: verbatim quote from the document text
A58: M057 | B58: A09 | C58: Amortisation of capitalised R&D | D58: H1_2023 | E58: S002 | F58: 29 (Note 3) | G58: S002 p.6 | H58: EUR m | I58: 427 | J58: =IF(I58="","",IF(H58="EUR bn",I58*1000,I58)) -> 427 | K58: =IF(H58="EUR bn","EUR m",H58) -> EUR m | L58: FACT | M58: EUR 1m | N58: Lead analyst (Claude) | O58: Y | P58: Verbatim from document text; same in S006 p.8 | Q58: =B58&"|"&D58 -> A09|H1_2023 | S58: V1: verbatim quote from the document text
A59: M058 | B59: A09 | C59: Amortisation of capitalised R&D | D59: FY_2023 | E59: S011 | F59: 34 | G59: S003 p.66 | H59: EUR m | I59: 960 | J59: =IF(I59="","",IF(H59="EUR bn",I59*1000,I59)) -> 960 | K59: =IF(H59="EUR bn","EUR m",H59) -> EUR m | L59: FACT | M59: EUR 1m | N59: Lead analyst (Claude) | O59: Y | P59: Verbatim from document text | Q59: =B59&"|"&D59 -> A09|FY_2023 | S59: V1: verbatim quote from the document text
A60: M059 | B60: A09 | C60: Amortisation of capitalised R&D | D60: H1_2024 | E60: S016 | F60: 25 | G60: S005 p.28 | H60: EUR m | I60: 516 | J60: =IF(I60="","",IF(H60="EUR bn",I60*1000,I60)) -> 516 | K60: =IF(H60="EUR bn","EUR m",H60) -> EUR m | L60: FACT | M60: EUR 1m | N60: Lead analyst (Claude) | O60: Y | P60: Verbatim from document text | Q60: =B60&"|"&D60 -> A09|H1_2024 | S60: V1: verbatim quote from the document text
A61: M060 | B61: A09 | C61: Amortisation of capitalised R&D | D61: FY_2024 | E61: S011 | F61: 34 | G61: S007 p.78 | H61: EUR m | I61: 1101 | J61: =IF(I61="","",IF(H61="EUR bn",I61*1000,I61)) -> 1101 | K61: =IF(H61="EUR bn","EUR m",H61) -> EUR m | L61: FACT | M61: EUR 1m | N61: Lead analyst (Claude) | O61: Y | P61: Verbatim from document text | Q61: =B61&"|"&D61 -> A09|FY_2024 | S61: V1: verbatim quote from the document text
A62: M061 | B62: A09 | C62: Amortisation of capitalised R&D | D62: H1_2025 | E62: S016 | F62: 25 | G62: S009 p.43 | H62: EUR m | I62: 600 | J62: =IF(I62="","",IF(H62="EUR bn",I62*1000,I62)) -> 600 | K62: =IF(H62="EUR bn","EUR m",H62) -> EUR m | L62: FACT | M62: EUR 1m | N62: Lead analyst (Claude) | O62: Y | P62: Verbatim from document text | Q62: =B62&"|"&D62 -> A09|H1_2025 | S62: V1: verbatim quote from the document text
A63: M062 | B63: A09 | C63: Amortisation of capitalised R&D | D63: FY_2025 | E63: S011 | F63: 34 | H63: EUR m | I63: 1830 | J63: =IF(I63="","",IF(H63="EUR bn",I63*1000,I63)) -> 1830 | K63: =IF(H63="EUR bn","EUR m",H63) -> EUR m | L63: FACT | M63: EUR 1m | N63: Lead analyst (Claude) | O63: Y | P63: Verbatim from document text | Q63: =B63&"|"&D63 -> A09|FY_2025 | S63: V1: verbatim quote from the document text
A64: M063 | B64: A09 | C64: Amortisation of capitalised R&D | D64: H1_2026 | E64: S016 | F64: 25 | H64: EUR m | I64: 705 | J64: =IF(I64="","",IF(H64="EUR bn",I64*1000,I64)) -> 705 | K64: =IF(H64="EUR bn","EUR m",H64) -> EUR m | L64: FACT | M64: EUR 1m | N64: Lead analyst (Claude) | O64: Y | P64: Verbatim from document text | Q64: =B64&"|"&D64 -> A09|H1_2026 | S64: V1: verbatim quote from the document text
A65: M064 | B65: A10 | C65: Automotive capex | D65: H1_2023 | E65: S002 | F65: 3 (key figures) | G65: S002 p.6 | H65: EUR m | I65: 866 | J65: =IF(I65="","",IF(H65="EUR bn",I65*1000,I65)) -> 866 | K65: =IF(H65="EUR bn","EUR m",H65) -> EUR m | L65: FACT | M65: EUR 1m | N65: Lead analyst (Claude) | O65: Y | P65: Verbatim from document text; same in S006 p.8 prior-year column | Q65: =B65&"|"&D65 -> A10|H1_2023 | S65: V1: verbatim quote from the document text
A66: M065 | B66: A10 | C66: Automotive capex | D66: FY_2023 | E66: S011 | F66: 34 | G66: S003 p.66 | H66: EUR m | I66: 1964 | J66: =IF(I66="","",IF(H66="EUR bn",I66*1000,I66)) -> 1964 | K66: =IF(H66="EUR bn","EUR m",H66) -> EUR m | L66: FACT | M66: EUR 1m | N66: Lead analyst (Claude) | O66: Y | P66: Verbatim from document text | Q66: =B66&"|"&D66 -> A10|FY_2023 | S66: V1: verbatim quote from the document text
A67: M066 | B67: A10 | C67: Automotive capex | D67: H1_2024 | E67: S016 | F67: 25 | G67: S005 p.28 | H67: EUR m | I67: 850 | J67: =IF(I67="","",IF(H67="EUR bn",I67*1000,I67)) -> 850 | K67: =IF(H67="EUR bn","EUR m",H67) -> EUR m | L67: FACT | M67: EUR 1m | N67: Lead analyst (Claude) | O67: Y | P67: Verbatim from document text | Q67: =B67&"|"&D67 -> A10|H1_2024 | S67: V1: verbatim quote from the document text
A68: M067 | B68: A10 | C68: Automotive capex | D68: FY_2024 | E68: S011 | F68: 34 | G68: S007 p.78 | H68: EUR m | I68: 2119 | J68: =IF(I68="","",IF(H68="EUR bn",I68*1000,I68)) -> 2119 | K68: =IF(H68="EUR bn","EUR m",H68) -> EUR m | L68: FACT | M68: EUR 1m | N68: Lead analyst (Claude) | O68: Y | P68: Verbatim from document text | Q68: =B68&"|"&D68 -> A10|FY_2024 | S68: V1: verbatim quote from the document text
A69: M068 | B69: A10 | C69: Automotive capex | D69: H1_2025 | E69: S016 | F69: 25 | G69: S009 p.43 | H69: EUR m | I69: 965 | J69: =IF(I69="","",IF(H69="EUR bn",I69*1000,I69)) -> 965 | K69: =IF(H69="EUR bn","EUR m",H69) -> EUR m | L69: FACT | M69: EUR 1m | N69: Lead analyst (Claude) | O69: Y | P69: Verbatim from document text | Q69: =B69&"|"&D69 -> A10|H1_2025 | S69: V1: verbatim quote from the document text
A70: M069 | B70: A10 | C70: Automotive capex | D70: FY_2025 | E70: S011 | F70: 34 | H70: EUR m | I70: 2137 | J70: =IF(I70="","",IF(H70="EUR bn",I70*1000,I70)) -> 2137 | K70: =IF(H70="EUR bn","EUR m",H70) -> EUR m | L70: FACT | M70: EUR 1m | N70: Lead analyst (Claude) | O70: Y | P70: Verbatim from document text | Q70: =B70&"|"&D70 -> A10|FY_2025 | S70: V1: verbatim quote from the document text
A71: M070 | B71: A10 | C71: Automotive capex | D71: H1_2026 | E71: S016 | F71: 25 | H71: EUR m | I71: 906 | J71: =IF(I71="","",IF(H71="EUR bn",I71*1000,I71)) -> 906 | K71: =IF(H71="EUR bn","EUR m",H71) -> EUR m | L71: FACT | M71: EUR 1m | N71: Lead analyst (Claude) | O71: Y | P71: Verbatim from document text | Q71: =B71&"|"&D71 -> A10|H1_2026 | S71: V1: verbatim quote from the document text
A72: M071 | B72: A11 | C72: Automotive depreciation on capex (incl. impairments) | D72: FY_2023 | E72: S011 | F72: 34 | G72: S003 p.66 | H72: EUR m | I72: 1696 | J72: =IF(I72="","",IF(H72="EUR bn",I72*1000,I72)) -> 1696 | K72: =IF(H72="EUR bn","EUR m",H72) -> EUR m | L72: FACT | M72: EUR 1m | N72: Lead analyst (Claude) | O72: Y | P72: Verbatim from document text | Q72: =B72&"|"&D72 -> A11|FY_2023 | S72: V1: verbatim quote from the document text
A73: M072 | B73: A11 | C73: Automotive depreciation on capex (incl. impairments) | D73: H1_2024 | E73: S016 | F73: 25 | G73: S005 p.28 | H73: EUR m | I73: 849 | J73: =IF(I73="","",IF(H73="EUR bn",I73*1000,I73)) -> 849 | K73: =IF(H73="EUR bn","EUR m",H73) -> EUR m | L73: FACT | M73: EUR 1m | N73: Lead analyst (Claude) | O73: Y | P73: Verbatim from document text | Q73: =B73&"|"&D73 -> A11|H1_2024 | S73: V1: verbatim quote from the document text
A74: M073 | B74: A11 | C74: Automotive depreciation on capex (incl. impairments) | D74: FY_2024 | E74: S011 | F74: 34 | G74: S007 p.78 | H74: EUR m | I74: 1884 | J74: =IF(I74="","",IF(H74="EUR bn",I74*1000,I74)) -> 1884 | K74: =IF(H74="EUR bn","EUR m",H74) -> EUR m | L74: FACT | M74: EUR 1m | N74: Lead analyst (Claude) | O74: Y | P74: Verbatim from document text | Q74: =B74&"|"&D74 -> A11|FY_2024 | S74: V1: verbatim quote from the document text
A75: M074 | B75: A11 | C75: Automotive depreciation on capex (incl. impairments) | D75: H1_2025 | E75: S016 | F75: 25 | G75: S009 p.43 | H75: EUR m | I75: 1156 | J75: =IF(I75="","",IF(H75="EUR bn",I75*1000,I75)) -> 1156 | K75: =IF(H75="EUR bn","EUR m",H75) -> EUR m | L75: FACT | M75: EUR 1m | N75: Lead analyst (Claude) | O75: Y | P75: Verbatim from document text. Includes EUR 295m Cellforce impairment (S010 p.32). | Q75: =B75&"|"&D75 -> A11|H1_2025 | S75: V1: verbatim quote from the document text
A76: M075 | B76: A11 | C76: Automotive depreciation on capex (incl. impairments) | D76: FY_2025 | E76: S011 | F76: 34 | H76: EUR m | I76: 2362 | J76: =IF(I76="","",IF(H76="EUR bn",I76*1000,I76)) -> 2362 | K76: =IF(H76="EUR bn","EUR m",H76) -> EUR m | L76: FACT | M76: EUR 1m | N76: Lead analyst (Claude) | O76: Y | P76: Verbatim from document text. Includes around EUR 1,200m impairment losses (S011 slide 34 footnote). | Q76: =B76&"|"&D76 -> A11|FY_2025 | S76: V1: verbatim quote from the document text
A77: M076 | B77: A11 | C77: Automotive depreciation on capex (incl. impairments) | D77: H1_2026 | E77: S016 | F77: 25 | H77: EUR m | I77: 854 | J77: =IF(I77="","",IF(H77="EUR bn",I77*1000,I77)) -> 854 | K77: =IF(H77="EUR bn","EUR m",H77) -> EUR m | L77: FACT | M77: EUR 1m | N77: Lead analyst (Claude) | O77: Y | P77: Verbatim from document text | Q77: =B77&"|"&D77 -> A11|H1_2026 | S77: V1: verbatim quote from the document text
A78: M077 | B78: A12 | C78: Automotive total D&A (incl. impairments) | D78: H1_2023 | E78: S002 | F78: 9 (Automotive EBITDA margin table) | G78: S002 p.6 | H78: EUR m | I78: 1176 | J78: =IF(I78="","",IF(H78="EUR bn",I78*1000,I78)) -> 1176 | K78: =IF(H78="EUR bn","EUR m",H78) -> EUR m | L78: FACT | M78: EUR 1m | N78: Lead analyst (Claude) | O78: Y | P78: Verbatim from document text ('depreciation and amortization and impairment losses'); A02 + A12 = A03 exactly | Q78: =B78&"|"&D78 -> A12|H1_2023 | R78: Must equal A03 - A02 for H1 2023 | S78: V1: verbatim quote from the document text
A79: M078 | B79: A12 | C79: Automotive total D&A (incl. impairments) | D79: FY_2023 | E79: S011 | F79: 34 | G79: S003 p.66 | H79: EUR m | I79: 2656 | J79: =IF(I79="","",IF(H79="EUR bn",I79*1000,I79)) -> 2656 | K79: =IF(H79="EUR bn","EUR m",H79) -> EUR m | L79: FACT | M79: EUR 1m | N79: Lead analyst (Claude) | O79: Y | P79: Verbatim from document text | Q79: =B79&"|"&D79 -> A12|FY_2023 | S79: V1: verbatim quote from the document text
A80: M079 | B80: A12 | C80: Automotive total D&A (incl. impairments) | D80: H1_2024 | E80: S016 | F80: 25 | G80: S005 p.28 | H80: EUR m | I80: 1364 | J80: =IF(I80="","",IF(H80="EUR bn",I80*1000,I80)) -> 1364 | K80: =IF(H80="EUR bn","EUR m",H80) -> EUR m | L80: FACT | M80: EUR 1m | N80: Lead analyst (Claude) | O80: Y | P80: Verbatim from document text | Q80: =B80&"|"&D80 -> A12|H1_2024 | S80: V1: verbatim quote from the document text
A81: M080 | B81: A12 | C81: Automotive total D&A (incl. impairments) | D81: FY_2024 | E81: S011 | F81: 34 | G81: S007 p.78 | H81: EUR m | I81: 2985 | J81: =IF(I81="","",IF(H81="EUR bn",I81*1000,I81)) -> 2985 | K81: =IF(H81="EUR bn","EUR m",H81) -> EUR m | L81: FACT | M81: EUR 1m | N81: Lead analyst (Claude) | O81: Y | P81: Verbatim from document text | Q81: =B81&"|"&D81 -> A12|FY_2024 | S81: V1: verbatim quote from the document text
A82: M081 | B82: A12 | C82: Automotive total D&A (incl. impairments) | D82: H1_2025 | E82: S016 | F82: 25 | G82: S009 p.43 | H82: EUR m | I82: 1756 | J82: =IF(I82="","",IF(H82="EUR bn",I82*1000,I82)) -> 1756 | K82: =IF(H82="EUR bn","EUR m",H82) -> EUR m | L82: FACT | M82: EUR 1m | N82: Lead analyst (Claude) | O82: Y | P82: Verbatim from document text. Includes EUR 295m Cellforce impairment (S010 p.32). | Q82: =B82&"|"&D82 -> A12|H1_2025 | S82: V1: verbatim quote from the document text
A83: M082 | B83: A12 | C83: Automotive total D&A (incl. impairments) | D83: FY_2025 | E83: S011 | F83: 34 | H83: EUR m | I83: 4192 | J83: =IF(I83="","",IF(H83="EUR bn",I83*1000,I83)) -> 4192 | K83: =IF(H83="EUR bn","EUR m",H83) -> EUR m | L83: FACT | M83: EUR 1m | N83: Lead analyst (Claude) | O83: Y | P83: Verbatim from document text. Includes around EUR 1,200m impairment losses (S011 slide 34 footnote). | Q83: =B83&"|"&D83 -> A12|FY_2025 | S83: V1: verbatim quote from the document text
A84: M083 | B84: A12 | C84: Automotive total D&A (incl. impairments) | D84: H1_2026 | E84: S016 | F84: 25 | H84: EUR m | I84: 1559 | J84: =IF(I84="","",IF(H84="EUR bn",I84*1000,I84)) -> 1559 | K84: =IF(H84="EUR bn","EUR m",H84) -> EUR m | L84: FACT | M84: EUR 1m | N84: Lead analyst (Claude) | O84: Y | P84: Verbatim from document text | Q84: =B84&"|"&D84 -> A12|H1_2026 | S84: V1: verbatim quote from the document text
A85: M084 | B85: X01 | C85: Strategic realignment incl. battery (net charge) | D85: H1_2025 | E85: S016 | F85: 6 (footnote 1) | G85: S009 p.28 | H85: EUR bn | I85: 0.7 | J85: =IF(I85="","",IF(H85="EUR bn",I85*1000,I85)) -> 700 | K85: =IF(H85="EUR bn","EUR m",H85) -> EUR m | L85: FACT | M85: EUR 0.1bn | N85: Lead analyst (Claude) | O85: Y | P85: 'extraordinary expenses of EUR 0.7bn related to strategic realignment' - includes battery activities | Q85: =B85&"|"&D85 -> X01|H1_2025 | R85: Combined realignment + battery = 0.7 | S85: V1: verbatim quote from the document text
A86: M085 | B86: X01 | C86: Strategic realignment incl. battery (net charge) | D86: FY_2025 | E86: S011 | F86: 6 | H86: EUR bn | I86: 3.1 | J86: =IF(I86="","",IF(H86="EUR bn",I86*1000,I86)) -> 3100 | K86: =IF(H86="EUR bn","EUR m",H86) -> EUR m | L86: DERIVED | M86: EUR 0.1bn | N86: Lead analyst (Claude) | O86: Y | P86: DERIVED = 2.4 (strategic realignment & product strategy) + 0.7 (battery activities), both printed on S011 slide 6 and in S015. Kept combined to match the H1 definition of X01. | Q86: =B86&"|"&D86 -> X01|FY_2025 | R86: Enter realignment of product strategy + rescaling (~2.4) PLUS battery (~0.7) = combined line; battery also in X02 | S86: V1 (DERIVED): both components (2.4 and 0.7) read from the raw text of S011 slide 6 and confirmed in S015
A87: M086 | B87: X01 | C87: Strategic realignment incl. battery (net charge) | D87: H1_2026 | E87: S016 | F87: 6 and 11 | G87: S018 | H87: EUR bn | I87: 0.1 | J87: =IF(I87="","",IF(H87="EUR bn",I87*1000,I87)) -> 100 | K87: =IF(H87="EUR bn","EUR m",H87) -> EUR m | L87: FACT | M87: EUR 0.1bn | N87: Lead analyst (Claude) | O87: Y | P87: NET burden 'approximately EUR 0.1bn' = ~0.4bn charges less ~0.3bn provision release (X04) | Q87: =B87&"|"&D87 -> X01|H1_2026 | R87: NET figure (~0.1 = ~0.4 charges less ~0.3 release) | S87: V1: verbatim quote from the document text
A88: M087 | B88: X02 | C88: of which battery activities | D88: H1_2025 | E88: S010 | F88: 5 and 30 | H88: EUR bn | I88: 0.4 | J88: =IF(I88="","",IF(H88="EUR bn",I88*1000,I88)) -> 400 | K88: =IF(H88="EUR bn","EUR m",H88) -> EUR m | L88: FACT | M88: EUR 0.1bn | N88: Lead analyst (Claude) | O88: Y | P88: Memo, inside X01. Verbatim: 'special expenses of EUR 0.4 billion ... write-downs of production facilities'. S009 slide 28 sub-split conflicts at 0.1bn level (AF-01). | Note (Oct 2026): S009 slide 28 shows battery activities 0.5 (with realignment 0.2 and tariffs 0.4, total app. 1.1). The half-year report wording (0.4) is kept; the memo is not used in any KPI. | Q88: =B88&"|"&D88 -> X02|H1_2025 | R88: Memo: already inside X01 | S88: V1: verbatim quote from the document text
A89: M088 | B89: X02 | C89: of which battery activities | D89: FY_2025 | E89: S011 | F89: 6 | H89: EUR bn | I89: 0.7 | J89: =IF(I89="","",IF(H89="EUR bn",I89*1000,I89)) -> 700 | K89: =IF(H89="EUR bn","EUR m",H89) -> EUR m | L89: FACT | M89: EUR 0.1bn | N89: Lead analyst (Claude) | O89: Y | P89: Memo, inside X01. Also S015: 'approximately 700 million euros'. | Q89: =B89&"|"&D89 -> X02|FY_2025 | R89: Memo: already inside X01 | S89: V1: verbatim quote from the document text
A90: M089 | B90: X03 | C90: US import tariffs (expense) | D90: H1_2025 | E90: S010 | F90: 5 and 30 | G90: S016 p.6 fn1 | H90: EUR bn | I90: 0.4 | J90: =IF(I90="","",IF(H90="EUR bn",I90*1000,I90)) -> 400 | K90: =IF(H90="EUR bn","EUR m",H90) -> EUR m | L90: FACT | M90: EUR 0.1bn | N90: Lead analyst (Claude) | O90: Y | P90: Verbatim: 'additional expenses of EUR 0.4 billion in the first half of the year 2025'; same in S016 p.6 fn1 | Q90: =B90&"|"&D90 -> X03|H1_2025 | S90: V1: verbatim quote from the document text
A91: M090 | B91: X03 | C91: US import tariffs (expense) | D91: FY_2025 | E91: S011 | F91: 6 | H91: EUR bn | I91: 0.7 | J91: =IF(I91="","",IF(H91="EUR bn",I91*1000,I91)) -> 700 | K91: =IF(H91="EUR bn","EUR m",H91) -> EUR m | L91: FACT | M91: EUR 0.1bn | N91: Lead analyst (Claude) | O91: Y | P91: Also S015: 'approximately 700 million euros' | Q91: =B91&"|"&D91 -> X03|FY_2025 | S91: V1: verbatim quote from the document text
A92: M091 | B92: X03 | C92: US import tariffs (expense) | D92: H1_2026 | E92: S016 | F92: 6 (footnote 2) | H92: EUR bn | I92: 0.4 | J92: =IF(I92="","",IF(H92="EUR bn",I92*1000,I92)) -> 400 | K92: =IF(H92="EUR bn","EUR m",H92) -> EUR m | L92: FACT | M92: EUR 0.1bn | N92: Lead analyst (Claude) | O92: Y | P92: 'Included expenses of EUR 0.4 bn for US Tariffs' | Q92: =B92&"|"&D92 -> X03|H1_2026 | S92: V1: verbatim quote from the document text
A93: M092 | B93: X04 | C93: Provision releases related to realignment | D93: H1_2026 | E93: S016 | F93: 6 and 11 | G93: S017 p.11/14 | H93: EUR bn | I93: 0.3 | J93: =IF(I93="","",IF(H93="EUR bn",I93*1000,I93)) -> 300 | K93: =IF(H93="EUR bn","EUR m",H93) -> EUR m | L93: FACT | M93: EUR 0.1bn | N93: Lead analyst (Claude) | O93: Y | P93: Benefit 'of approximately EUR 0.3 bn from the release of a provision after successful supplier settlements' | Q93: =B93&"|"&D93 -> X04|H1_2026 | R93: Enter as a positive number (benefit) | S93: V1: verbatim quote from the document text
A94: M093 | B94: X04 | C94: Provision releases related to realignment | D94: FY_2025 | E94: S012 | F94: Searched: full document (247 PDF pages) | H94: EUR bn | J94: =IF(I94="","",IF(H94="EUR bn",I94*1000,I94)) | K94: =IF(H94="EUR bn","EUR m",H94) -> EUR m | L94: FACT | M94: EUR 0.1bn | N94: Lead analyst (Claude) | O94: N/A | P94: BLANK: not disclosed. Source re-check Oct 2026 (official PDF text layer read in full). All 44 mentions of "realignment" in S012 checked: no realignment provision release is stated; only generic totals (provision reversals 276, provisions table; income from reversal of provisions and accruals 97, other operating income note). Not estimated. | Q94: =B94&"|"&D94 -> X04|FY_2025 | R94: Leave blank if not disclosed; write 'not disclosed' in Note | S94: GAP: no value entered (reason in Note) - nothing to verify
A95: M094 | B95: X05 | C95: Impairment losses included in automotive D&A | D95: H1_2023 | E95: S002 | F95: 38-39 (segment reporting) | H95: EUR m | I95: 0 | J95: =IF(I95="","",IF(H95="EUR bn",I95*1000,I95)) -> 0 | K95: =IF(H95="EUR bn","EUR m",H95) -> EUR m | L95: FACT | M95: EUR 1m | N95: Lead analyst (Claude) | O95: Y | P95: Automotive impairment losses shown as '-' (nil); only FS leased-asset impairments (EUR 75m) | Q95: =B95&"|"&D95 -> X05|H1_2023 | R95: Only FS leased-asset impairments found; automotive impairments: search notes. If none disclosed, enter 0 and note 'none disclosed' | S95: V1: verbatim quote from the document text
A96: M095 | B96: X05 | C96: Impairment losses included in automotive D&A | D96: FY_2023 | E96: S004 | F96: Segment reporting table, PDF p.153 (printed pp.304-305) | H96: EUR m | I96: 2 | J96: =IF(I96="","",IF(H96="EUR bn",I96*1000,I96)) -> 2 | K96: =IF(H96="EUR bn","EUR m",H96) -> EUR m | L96: FACT | M96: EUR 1m | N96: Lead analyst (Claude) | O96: Y | P96: Verbatim (segment reporting 2023, row "Impairment losses"): "2 160 162" = automotive 2, financial services 160, total 162. Source re-check Oct 2026 (official PDF text layer read in full). Previously recorded as a gap. | Q96: =B96&"|"&D96 -> X05|FY_2023 | R96: Search impairment note | S96: V1: verbatim quote from the document text
A97: M096 | B97: X05 | C97: Impairment losses included in automotive D&A | D97: H1_2024 | E97: S006 | F97: 38 (segment reporting) | H97: EUR m | I97: 0 | J97: =IF(I97="","",IF(H97="EUR bn",I97*1000,I97)) -> 0 | K97: =IF(H97="EUR bn","EUR m",H97) -> EUR m | L97: FACT | M97: EUR 1m | N97: Lead analyst (Claude) | O97: Y | P97: Automotive impairment losses shown as 0; FS EUR 87m | Q97: =B97&"|"&D97 -> X05|H1_2024 | R97: Same as H1 2023 | S97: V1: verbatim quote from the document text
A98: M097 | B98: X05 | C98: Impairment losses included in automotive D&A | D98: FY_2024 | E98: S008 | F98: Segment reporting table, PDF p.189 (printed p.30 of the financial statements) | H98: EUR m | I98: 3 | J98: =IF(I98="","",IF(H98="EUR bn",I98*1000,I98)) -> 3 | K98: =IF(H98="EUR bn","EUR m",H98) -> EUR m | L98: FACT | M98: EUR 1m | N98: Lead analyst (Claude) | O98: Y | P98: Verbatim (segment reporting 2024, row "Impairment losses"): "3 207 210" = automotive 3, financial services 207, total 210. Source re-check Oct 2026 (official PDF text layer read in full). Previously recorded as a gap. | Q98: =B98&"|"&D98 -> X05|FY_2024 | R98: Search impairment note | S98: V1: verbatim quote from the document text
A99: M098 | B99: X05 | C99: Impairment losses included in automotive D&A | D99: H1_2025 | E99: S010 | F99: 32 | H99: EUR m | I99: 295 | J99: =IF(I99="","",IF(H99="EUR bn",I99*1000,I99)) -> 295 | K99: =IF(H99="EUR bn","EUR m",H99) -> EUR m | L99: FACT | M99: EUR 1m | N99: Lead analyst (Claude) | O99: Y | P99: Verbatim: 'Depreciation of property, plant and equipment includes the impairment of Cellforce Group GmbH in the amount of EUR 295 million' | Q99: =B99&"|"&D99 -> X05|H1_2025 | R99: Cellforce impairment inside PP&E depreciation | S99: V1: verbatim quote from the document text
A100: M099 | B100: X05 | C100: Impairment losses included in automotive D&A | D100: FY_2025 | E100: S012 | F100: Segment reporting table, PDF p.176 (printed p.33 of the financial statements) | G100: S011 p.34 footnote | H100: EUR m | I100: 1195 | J100: =IF(I100="","",IF(H100="EUR bn",I100*1000,I100)) -> 1195 | K100: =IF(H100="EUR bn","EUR m",H100) -> EUR m | L100: FACT | M100: EUR 1m | N100: Lead analyst (Claude) | O100: Y | P100: Verbatim (segment reporting 2025, row "Impairment losses"): "1,195 250 1,446" = automotive 1,195. S011 slide 34 footnote rounds this as "Includes around EUR 1,200 mn of impairment losses due to the strategic realignment". Source re-check Oct 2026 (official PDF text layer read in full). Value changed from 1,200 (rounded) to 1,195 (exact). | Q100: =B100&"|"&D100 -> X05|FY_2025 | R100: 'around 1,200' -> enter 1200, rounding EUR 100m | S100: V1: verbatim quote from the document text
A101: M100 | B101: X05 | C101: Impairment losses included in automotive D&A | D101: H1_2026 | E101: S017 | F101: 29 | H101: EUR m | I101: 61 | J101: =IF(I101="","",IF(H101="EUR bn",I101*1000,I101)) -> 61 | K101: =IF(H101="EUR bn","EUR m",H101) -> EUR m | L101: DERIVED | M101: EUR 1m | N101: Lead analyst (Claude) | O101: N | P101: DERIVED = 43 (Porsche eBike Performance) + 18 (Cellforce), both published. NOT confirmed that both sit inside automotive D&A (A12); treat as upper bound. | Q101: =B101&"|"&D101 -> X05|H1_2026 | R101: eBike + Cellforce impairments; confirm they sit in automotive D&A | S101: V4: DERIVED from two verbatim-quoted amounts (43 + 18, S017 p.29); classification inside automotive D&A NOT confirmed (assumption A-04)
A102: M101 | B102: F01 | C102: Financial Services sales revenue | D102: H1_2023 | E102: S002 | F102: 38 (segment reporting) | H102: EUR m | I102: 1652 | J102: =IF(I102="","",IF(H102="EUR bn",I102*1000,I102)) -> 1652 | K102: =IF(H102="EUR bn","EUR m",H102) -> EUR m | L102: FACT | M102: EUR 1m | N102: Lead analyst (Claude) | O102: Y | P102: Verbatim from document text | Q102: =B102&"|"&D102 -> F01|H1_2023 | S102: V1: verbatim quote from the document text
A103: M102 | B103: F01 | C103: Financial Services sales revenue | D103: FY_2023 | E103: S026 | F103: Financial services results of operations (2023 in brackets) | H103: EUR m | I103: 3444 | J103: =IF(I103="","",IF(H103="EUR bn",I103*1000,I103)) -> 3444 | K103: =IF(H103="EUR bn","EUR m",H103) -> EUR m | L103: FACT | M103: EUR 1m | N103: Lead analyst (Claude) | O103: Y | P103: Verbatim from document text | Q103: =B103&"|"&D103 -> F01|FY_2023 | S103: V1: verbatim quote from the document text
A104: M103 | B104: F01 | C104: Financial Services sales revenue | D104: H1_2024 | E104: S006 | F104: 38 (segment reporting) | H104: EUR m | I104: 1894 | J104: =IF(I104="","",IF(H104="EUR bn",I104*1000,I104)) -> 1894 | K104: =IF(H104="EUR bn","EUR m",H104) -> EUR m | L104: FACT | M104: EUR 1m | N104: Lead analyst (Claude) | O104: Y | P104: Verbatim from document text | Q104: =B104&"|"&D104 -> F01|H1_2024 | S104: V1: verbatim quote from the document text
A105: M104 | B105: F01 | C105: Financial Services sales revenue | D105: FY_2024 | E105: S013 | F105: Financial services results of operations (2024 in brackets) | H105: EUR m | I105: 3910 | J105: =IF(I105="","",IF(H105="EUR bn",I105*1000,I105)) -> 3910 | K105: =IF(H105="EUR bn","EUR m",H105) -> EUR m | L105: FACT | M105: EUR 1m | N105: Lead analyst (Claude) | O105: Y | P105: Verbatim from document text | Q105: =B105&"|"&D105 -> F01|FY_2024 | S105: V1: verbatim quote from the document text
A106: M105 | B106: F01 | C106: Financial Services sales revenue | D106: H1_2025 | E106: S010 | F106: 42 (segment reporting) | H106: EUR m | I106: 2152 | J106: =IF(I106="","",IF(H106="EUR bn",I106*1000,I106)) -> 2152 | K106: =IF(H106="EUR bn","EUR m",H106) -> EUR m | L106: FACT | M106: EUR 1m | N106: Lead analyst (Claude) | O106: Y | P106: Verbatim from document text | Q106: =B106&"|"&D106 -> F01|H1_2025 | S106: V1: verbatim quote from the document text
A107: M106 | B107: F01 | C107: Financial Services sales revenue | D107: FY_2025 | E107: S013 | F107: Financial services results of operations | H107: EUR m | I107: 4384 | J107: =IF(I107="","",IF(H107="EUR bn",I107*1000,I107)) -> 4384 | K107: =IF(H107="EUR bn","EUR m",H107) -> EUR m | L107: FACT | M107: EUR 1m | N107: Lead analyst (Claude) | O107: Y | P107: Verbatim from document text | Q107: =B107&"|"&D107 -> F01|FY_2025 | S107: V1: verbatim quote from the document text
A108: M107 | B108: F01 | C108: Financial Services sales revenue | D108: H1_2026 | E108: S017 | F108: 39 (segment reporting) | H108: EUR m | I108: 2206 | J108: =IF(I108="","",IF(H108="EUR bn",I108*1000,I108)) -> 2206 | K108: =IF(H108="EUR bn","EUR m",H108) -> EUR m | L108: FACT | M108: EUR 1m | N108: Lead analyst (Claude) | O108: Y | P108: Verbatim from document text | Q108: =B108&"|"&D108 -> F01|H1_2026 | S108: V1: verbatim quote from the document text
...

Sheet FS_Reference
A1: Period | B1: G01 Group revenue (EUR m) | C1: G07 Group EBIT (EUR m) | D1: O04 Vehicle sales (units) | E1: O01 Deliveries (units) | F1: Source | G1: G03 Gross profit (EUR m) | H1: G04+G05 SG&A (EUR m) | I1: G06 Net other operating result (EUR m)
A2: H1_2022 | B2: 17921.7 | C2: 3480.2 | D2: 148568 | E2: 145860 | F2: S025 fact sheet via pcl_extract_factsheets.py (FACT) - 2022 IFRS 17 restated | G2: 5053.6 | H2: -1722 | I2: 149
A3: FY_2022 | B3: 37637.4 | C3: 6772.4 | D3: 313721 | E3: 309884 | F3: S025 fact sheet via pcl_extract_factsheets.py (FACT) - 2022 IFRS 17 restated | G3: 10548.6 | H3: -4008.2 | I3: 231.9
A4: H1_2023 | B4: 20430.9 | C4: 3852.2 | D4: 170802 | E4: 167354 | F4: S025 fact sheet via pcl_extract_factsheets.py (FACT) | G4: 5909.4 | H4: -2168 | I4: 110.9
A5: FY_2023 | B5: 40529.6 | C5: 7284.3 | D5: 333605 | E5: 320221 | F5: S025 fact sheet via pcl_extract_factsheets.py (FACT) | G5: 11605.9 | H5: -4656.2 | I5: 334.6
A6: H1_2024 | B6: 19457 | C6: 3061.5 | D6: 151944 | E6: 155945 | F6: S025 fact sheet via pcl_extract_factsheets.py (FACT) | G6: 5206 | H6: -2331.1 | I6: 186.6
A7: FY_2024 | B7: 40083.3 | C7: 5636.9 | D7: 312620 | E7: 310718 | F7: S025 fact sheet via pcl_extract_factsheets.py (FACT) | G7: 10327.4 | H7: -4958.7 | I7: 268.1
A8: H1_2025 | B8: 18157.3 | C8: 1006.8 | D8: 135142 | E8: 146391 | F8: S025 fact sheet via pcl_extract_factsheets.py (FACT) | G8: 3363.9 | H8: -2288.2 | I8: -68.9
A9: FY_2025 | B9: 36271.6 | C9: 413.3 | D9: 265663 | E9: 279449 | F9: S025 fact sheet via pcl_extract_factsheets.py (FACT) | G9: 5050.9 | H9: -4694.2 | I9: 56.7
A10: H1_2026 | B10: 17229.5 | C10: 1348.2 | D10: 120508 | E10: 122306 | F10: S025 fact sheet via pcl_extract_factsheets.py (FACT) | G10: 3465.8 | H10: -2275.5 | I10: 157.9

Sheet Checks
A1: Period | B1: CHK1 R&D: A05 = A06 + A08 (+/-2) | C1: CHK2 Cap. rate: A06/A05 = A07 (+/-0.2pp) | D1: CHK3 D&A: A12 = A09 + A11 (+/-2) | E1: CHK4 EBITDA: A03 = A02 + A12 (+/-60) | F1: CHK5 Margin: A03/A01 = A04 (+/-0.15pp) | G1: CHK6 ASP: A01/vehicle sales = O06 (+/-1.5k) | H1: CHK7 Bridge: prior EBIT + B01..B04 = EBIT | I1: CHK8 Bridge SG&A: B03 = change in G04+G05 (fact sheet) | J1: CHK9 Bridge Other: B04 = change in G06 (fact sheet) | K1: CHK10 Bridge: B01 + B02 = change in gross profit G03 | L1: Bridge tolerance (EUR m) | M1: Entered rows | N1: Blank rows with explanation | O1: Rows expected
A2: H1_2023 | B2: =IF((COUNTIFS(Inputs!$Q$2:$Q$156,"A05|"&$A2,Inputs!$I$2:$I$156,"<>"))*(COUNTIFS(Inputs!$Q$2:$Q$156,"A06|"&$A2,Inputs!$I$2:$I$156,"<>"))*(COUNTIFS(Inputs!$Q$2:$Q$156,"A08|"&$A2,Inputs!$I$2:$I$156,"<>"))=0,"PENDING",IF(ABS(SUMIFS(Inputs!$J$2:$J$156,Inputs!$Q$2:$Q$156,"A05|"&$A2)-SUMIFS(Inputs!$J$2:$J$156,Inputs!$Q$2:$Q$156,"A06|"&$A2)-SUMIFS(Inputs!$J$2:$J$156,Inputs!$Q$2:$Q$156,"A08|"&$A2))<=2,"OK","CHECK")) -> OK | C2: =IF((COUNTIFS(Inputs!$Q$2:$Q$156,"A05|"&$A2,Inputs!$I$2:$I$156,"<>"))*(COUNTIFS(Inputs!$Q$2:$Q$156,"A06|"&$A2,Inputs!$I$2:$I$156,"<>"))*(COUNTIFS(Inputs!$Q$2:$Q$156,"A07|"&$A2,Inputs!$I$2:$I$156,"<>"))=0,"PENDING",IF(ABS(SUMIFS(Inputs!$J$2:$J$156,Inputs!$Q$2:$Q$156,"A06|"&$A2)/SUMIFS(Inputs!$J$2:$J$156,Inputs!$Q$2:$Q$156,"A05|"&$A2)*100-SUMIFS(Inputs!$J$2:$J$156,Inputs!$Q$2:$Q$156,"A07|"&$A2))<=0.2,"OK","CHECK")) -> OK | D2: ="N/A (A11 derived)" -> N/A (A11 derived) | E2: =IF((COUNTIFS(Inputs!$Q$2:$Q$156,"A03|"&$A2,Inputs!$I$2:$I$156,"<>"))*(COUNTIFS(Inputs!$Q$2:$Q$156,"A02|"&$A2,Inputs!$I$2:$I$156,"<>"))*(COUNTIFS(Inputs!$Q$2:$Q$156,"A12|"&$A2,Inputs!$I$2:$I$156,"<>"))=0,"PENDING",IF(ABS(SUMIFS(Inputs!$J$2:$J$156,Inputs!$Q$2:$Q$156,"A03|"&$A2)-SUMIFS(Inputs!$J$2:$J$156,Inputs!$Q$2:$Q$156,"A02|"&$A2)-SUMIFS(Inputs!$J$2:$J$156,Inputs!$Q$2:$Q$156,"A12|"&$A2))<=60,"OK","CHECK")) -> OK | F2: =IF((COUNTIFS(Inputs!$Q$2:$Q$156,"A03|"&$A2,Inputs!$I$2:$I$156,"<>"))*(COUNTIFS(Inputs!$Q$2:$Q$156,"A01|"&$A2,Inputs!$I$2:$I$156,"<>"))*(COUNTIFS(Inputs!$Q$2:$Q$156,"A04|"&$A2,Inputs!$I$2:$I$156,"<>"))=0,"PENDING",IF(ABS(SUMIFS(Inputs!$J$2:$J$156,Inputs!$Q$2:$Q$156,"A03|"&$A2)/SUMIFS(Inputs!$J$2:$J$156,Inputs!$Q$2:$Q$156,"A01|"&$A2)*100-SUMIFS(Inputs!$J$2:$J$156,Inputs!$Q$2:$Q$156,"A04|"&$A2))<=0.15,"OK","CHECK")) -> OK | G2: =IF((COUNTIFS(Inputs!$Q$2:$Q$156,"A01|"&$A2,Inputs!$I$2:$I$156,"<>"))*(COUNTIFS(Inputs!$Q$2:$Q$156,"O06|"&$A2,Inputs!$I$2:$I$156,"<>"))=0,IF(COUNTIFS(Inputs!$Q$2:$Q$156,"O06|"&$A2,Inputs!$I$2:$I$156,"",Inputs!$P$2:$P$156,"<>")>0,"N/A (blank - see Inputs note)","PENDING"),IF(ABS(SUMIFS(Inputs!$J$2:$J$156,Inputs!$Q$2:$Q$156,"A01|"&$A2)*1000/INDEX(FS_Reference!$D$2:$D$10,MATCH($A2,FS_Reference!$A$2:$A$10,0))-SUMIFS(Inputs!$J$2:$J$156,Inputs!$Q$2:$Q$156,"O06|"&$A2))<=1.5,"OK","CHECK")) -> OK | H2: ="N/A (bridge is qualitative)" -> N/A (bridge is qualitative) | I2: ="N/A (bridge is qualitative)" -> N/A (bridge is qualitative) | J2: ="N/A (bridge is qualitative)" -> N/A (bridge is qualitative) | K2: ="N/A (bridge is qualitative)" -> N/A (bridge is qualitative) | L2: 50 | M2: =COUNTIFS(Inputs!$D$2:$D$156,$A2,Inputs!$I$2:$I$156,"<>") -> 16 | N2: =COUNTIFS(Inputs!$D$2:$D$156,$A2,Inputs!$I$2:$I$156,"",Inputs!$P$2:$P$156,"<>") -> 0 | O2: =COUNTIFS(Inputs!$D$2:$D$156,$A2) -> 16
A3: FY_2023 | B3: =IF((COUNTIFS(Inputs!$Q$2:$Q$156,"A05|"&$A3,Inputs!$I$2:$I$156,"<>"))*(COUNTIFS(Inputs!$Q$2:$Q$156,"A06|"&$A3,Inputs!$I$2:$I$156,"<>"))*(COUNTIFS(Inputs!$Q$2:$Q$156,"A08|"&$A3,Inputs!$I$2:$I$156,"<>"))=0,"PENDING",IF(ABS(SUMIFS(Inputs!$J$2:$J$156,Inputs!$Q$2:$Q$156,"A05|"&$A3)-SUMIFS(Inputs!$J$2:$J$156,Inputs!$Q$2:$Q$156,"A06|"&$A3)-SUMIFS(Inputs!$J$2:$J$156,Inputs!$Q$2:$Q$156,"A08|"&$A3))<=2,"OK","CHECK")) -> OK | C3: =IF((COUNTIFS(Inputs!$Q$2:$Q$156,"A05|"&$A3,Inputs!$I$2:$I$156,"<>"))*(COUNTIFS(Inputs!$Q$2:$Q$156,"A06|"&$A3,Inputs!$I$2:$I$156,"<>"))*(COUNTIFS(Inputs!$Q$2:$Q$156,"A07|"&$A3,Inputs!$I$2:$I$156,"<>"))=0,"PENDING",IF(ABS(SUMIFS(Inputs!$J$2:$J$156,Inputs!$Q$2:$Q$156,"A06|"&$A3)/SUMIFS(Inputs!$J$2:$J$156,Inputs!$Q$2:$Q$156,"A05|"&$A3)*100-SUMIFS(Inputs!$J$2:$J$156,Inputs!$Q$2:$Q$156,"A07|"&$A3))<=0.2,"OK","CHECK")) -> OK | D3: =IF((COUNTIFS(Inputs!$Q$2:$Q$156,"A12|"&$A3,Inputs!$I$2:$I$156,"<>"))*(COUNTIFS(Inputs!$Q$2:$Q$156,"A09|"&$A3,Inputs!$I$2:$I$156,"<>"))*(COUNTIFS(Inputs!$Q$2:$Q$156,"A11|"&$A3,Inputs!$I$2:$I$156,"<>"))=0,"PENDING",IF(ABS(SUMIFS(Inputs!$J$2:$J$156,Inputs!$Q$2:$Q$156,"A12|"&$A3)-SUMIFS(Inputs!$J$2:$J$156,Inputs!$Q$2:$Q$156,"A09|"&$A3)-SUMIFS(Inputs!$J$2:$J$156,Inputs!$Q$2:$Q$156,"A11|"&$A3))<=2,"OK","CHECK")) -> OK | E3: =IF((COUNTIFS(Inputs!$Q$2:$Q$156,"A03|"&$A3,Inputs!$I$2:$I$156,"<>"))*(COUNTIFS(Inputs!$Q$2:$Q$156,"A02|"&$A3,Inputs!$I$2:$I$156,"<>"))*(COUNTIFS(Inputs!$Q$2:$Q$156,"A12|"&$A3,Inputs!$I$2:$I$156,"<>"))=0,"PENDING",IF(ABS(SUMIFS(Inputs!$J$2:$J$156,Inputs!$Q$2:$Q$156,"A03|"&$A3)-SUMIFS(Inputs!$J$2:$J$156,Inputs!$Q$2:$Q$156,"A02|"&$A3)-SUMIFS(Inputs!$J$2:$J$156,Inputs!$Q$2:$Q$156,"A12|"&$A3))<=60,"OK","CHECK")) -> OK | F3: =IF((COUNTIFS(Inputs!$Q$2:$Q$156,"A03|"&$A3,Inputs!$I$2:$I$156,"<>"))*(COUNTIFS(Inputs!$Q$2:$Q$156,"A01|"&$A3,Inputs!$I$2:$I$156,"<>"))*(COUNTIFS(Inputs!$Q$2:$Q$156,"A04|"&$A3,Inputs!$I$2:$I$156,"<>"))=0,"PENDING",IF(ABS(SUMIFS(Inputs!$J$2:$J$156,Inputs!$Q$2:$Q$156,"A03|"&$A3)/SUMIFS(Inputs!$J$2:$J$156,Inputs!$Q$2:$Q$156,"A01|"&$A3)*100-SUMIFS(Inputs!$J$2:$J$156,Inputs!$Q$2:$Q$156,"A04|"&$A3))<=0.15,"OK","CHECK")) -> OK | G3: =IF((COUNTIFS(Inputs!$Q$2:$Q$156,"A01|"&$A3,Inputs!$I$2:$I$156,"<>"))*(COUNTIFS(Inputs!$Q$2:$Q$156,"O06|"&$A3,Inputs!$I$2:$I$156,"<>"))=0,IF(COUNTIFS(Inputs!$Q$2:$Q$156,"O06|"&$A3,Inputs!$I$2:$I$156,"",Inputs!$P$2:$P$156,"<>")>0,"N/A (blank - see Inputs note)","PENDING"),IF(ABS(SUMIFS(Inputs!$J$2:$J$156,Inputs!$Q$2:$Q$156,"A01|"&$A3)*1000/INDEX(FS_Reference!$D$2:$D$10,MATCH($A3,FS_Reference!$A$2:$A$10,0))-SUMIFS(Inputs!$J$2:$J$156,Inputs!$Q$2:$Q$156,"O06|"&$A3))<=1.5,"OK","CHECK")) -> OK | H3: =IF((COUNTIFS(Inputs!$Q$2:$Q$156,"B01|"&$A3,Inputs!$I$2:$I$156,"<>"))*(COUNTIFS(Inputs!$Q$2:$Q$156,"B02|"&$A3,Inputs!$I$2:$I$156,"<>"))*(COUNTIFS(Inputs!$Q$2:$Q$156,"B03|"&$A3,Inputs!$I$2:$I$156,"<>"))*(COUNTIFS(Inputs!$Q$2:$Q$156,"B04|"&$A3,Inputs!$I$2:$I$156,"<>"))=0,"PENDING",IF(ABS(INDEX(FS_Reference!$C$2:$C$10,MATCH("FY_2022",FS_Reference!$A$2:$A$10,0))+SUMIFS(Inputs!$J$2:$J$156,Inputs!$Q$2:$Q$156,"B01|"&$A3)+SUMIFS(Inputs!$J$2:$J$156,Inputs!$Q$2:$Q$156,"B02|"&$A3)+SUMIFS(Inputs!$J$2:$J$156,Inputs!$Q$2:$Q$156,"B03|"&$A3)+SUMIFS(Inputs!$J$2:$J$156,Inputs!$Q$2:$Q$156,"B04|"&$A3)-INDEX(FS_Reference!$C$2:$C$10,MATCH($A3,FS_Reference!$A$2:$A$10,0)))<=$L3,"OK","CHECK")) -> OK | I3: =IF(COUNTIFS(Inputs!$Q$2:$Q$156,"B03|"&$A3,Inputs!$I$2:$I$156,"<>")=0,"PENDING",IF(ABS(INDEX(FS_Reference!$H$2:$H$10,MATCH($A3,FS_Reference!$A$2:$A$10,0))-INDEX(FS_Reference!$H$2:$H$10,MATCH("FY_2022",FS_Reference!$A$2:$A$10,0))-SUMIFS(Inputs!$J$2:$J$156,Inputs!$Q$2:$Q$156,"B03|"&$A3))<=$L3/2,"OK","CHECK")) -> OK | J3: =IF(COUNTIFS(Inputs!$Q$2:$Q$156,"B04|"&$A3,Inputs!$I$2:$I$156,"<>")=0,"PENDING",IF(ABS(INDEX(FS_Reference!$I$2:$I$10,MATCH($A3,FS_Reference!$A$2:$A$10,0))-INDEX(FS_Reference!$I$2:$I$10,MATCH("FY_2022",FS_Reference!$A$2:$A$10,0))-SUMIFS(Inputs!$J$2:$J$156,Inputs!$Q$2:$Q$156,"B04|"&$A3))<=$L3/2,"OK","CHECK")) -> OK | K3: =IF((COUNTIFS(Inputs!$Q$2:$Q$156,"B01|"&$A3,Inputs!$I$2:$I$156,"<>"))*(COUNTIFS(Inputs!$Q$2:$Q$156,"B02|"&$A3,Inputs!$I$2:$I$156,"<>"))=0,"PENDING",IF(ABS(INDEX(FS_Reference!$G$2:$G$10,MATCH($A3,FS_Reference!$A$2:$A$10,0))-INDEX(FS_Reference!$G$2:$G$10,MATCH("FY_2022",FS_Reference!$A$2:$A$10,0))-SUMIFS(Inputs!$J$2:$J$156,Inputs!$Q$2:$Q$156,"B01|"&$A3)-SUMIFS(Inputs!$J$2:$J$156,Inputs!$Q$2:$Q$156,"B02|"&$A3))<=$L3,"OK","CHECK")) -> OK | L3: 250 | M3: =COUNTIFS(Inputs!$D$2:$D$156,$A3,Inputs!$I$2:$I$156,"<>") -> 21 | N3: =COUNTIFS(Inputs!$D$2:$D$156,$A3,Inputs!$I$2:$I$156,"",Inputs!$P$2:$P$156,"<>") -> 0 | O3: =COUNTIFS(Inputs!$D$2:$D$156,$A3) -> 21
A4: H1_2024 | B4: =IF((COUNTIFS(Inputs!$Q$2:$Q$156,"A05|"&$A4,Inputs!$I$2:$I$156,"<>"))*(COUNTIFS(Inputs!$Q$2:$Q$156,"A06|"&$A4,Inputs!$I$2:$I$156,"<>"))*(COUNTIFS(Inputs!$Q$2:$Q$156,"A08|"&$A4,Inputs!$I$2:$I$156,"<>"))=0,"PENDING",IF(ABS(SUMIFS(Inputs!$J$2:$J$156,Inputs!$Q$2:$Q$156,"A05|"&$A4)-SUMIFS(Inputs!$J$2:$J$156,Inputs!$Q$2:$Q$156,"A06|"&$A4)-SUMIFS(Inputs!$J$2:$J$156,Inputs!$Q$2:$Q$156,"A08|"&$A4))<=2,"OK","CHECK")) -> OK | C4: =IF((COUNTIFS(Inputs!$Q$2:$Q$156,"A05|"&$A4,Inputs!$I$2:$I$156,"<>"))*(COUNTIFS(Inputs!$Q$2:$Q$156,"A06|"&$A4,Inputs!$I$2:$I$156,"<>"))*(COUNTIFS(Inputs!$Q$2:$Q$156,"A07|"&$A4,Inputs!$I$2:$I$156,"<>"))=0,"PENDING",IF(ABS(SUMIFS(Inputs!$J$2:$J$156,Inputs!$Q$2:$Q$156,"A06|"&$A4)/SUMIFS(Inputs!$J$2:$J$156,Inputs!$Q$2:$Q$156,"A05|"&$A4)*100-SUMIFS(Inputs!$J$2:$J$156,Inputs!$Q$2:$Q$156,"A07|"&$A4))<=0.2,"OK","CHECK")) -> OK | D4: =IF((COUNTIFS(Inputs!$Q$2:$Q$156,"A12|"&$A4,Inputs!$I$2:$I$156,"<>"))*(COUNTIFS(Inputs!$Q$2:$Q$156,"A09|"&$A4,Inputs!$I$2:$I$156,"<>"))*(COUNTIFS(Inputs!$Q$2:$Q$156,"A11|"&$A4,Inputs!$I$2:$I$156,"<>"))=0,"PENDING",IF(ABS(SUMIFS(Inputs!$J$2:$J$156,Inputs!$Q$2:$Q$156,"A12|"&$A4)-SUMIFS(Inputs!$J$2:$J$156,Inputs!$Q$2:$Q$156,"A09|"&$A4)-SUMIFS(Inputs!$J$2:$J$156,Inputs!$Q$2:$Q$156,"A11|"&$A4))<=2,"OK","CHECK")) -> OK | E4: =IF((COUNTIFS(Inputs!$Q$2:$Q$156,"A03|"&$A4,Inputs!$I$2:$I$156,"<>"))*(COUNTIFS(Inputs!$Q$2:$Q$156,"A02|"&$A4,Inputs!$I$2:$I$156,"<>"))*(COUNTIFS(Inputs!$Q$2:$Q$156,"A12|"&$A4,Inputs!$I$2:$I$156,"<>"))=0,"PENDING",IF(ABS(SUMIFS(Inputs!$J$2:$J$156,Inputs!$Q$2:$Q$156,"A03|"&$A4)-SUMIFS(Inputs!$J$2:$J$156,Inputs!$Q$2:$Q$156,"A02|"&$A4)-SUMIFS(Inputs!$J$2:$J$156,Inputs!$Q$2:$Q$156,"A12|"&$A4))<=60,"OK","CHECK")) -> OK | F4: =IF((COUNTIFS(Inputs!$Q$2:$Q$156,"A03|"&$A4,Inputs!$I$2:$I$156,"<>"))*(COUNTIFS(Inputs!$Q$2:$Q$156,"A01|"&$A4,Inputs!$I$2:$I$156,"<>"))*(COUNTIFS(Inputs!$Q$2:$Q$156,"A04|"&$A4,Inputs!$I$2:$I$156,"<>"))=0,"PENDING",IF(ABS(SUMIFS(Inputs!$J$2:$J$156,Inputs!$Q$2:$Q$156,"A03|"&$A4)/SUMIFS(Inputs!$J$2:$J$156,Inputs!$Q$2:$Q$156,"A01|"&$A4)*100-SUMIFS(Inputs!$J$2:$J$156,Inputs!$Q$2:$Q$156,"A04|"&$A4))<=0.15,"OK","CHECK")) -> OK | G4: =IF((COUNTIFS(Inputs!$Q$2:$Q$156,"A01|"&$A4,Inputs!$I$2:$I$156,"<>"))*(COUNTIFS(Inputs!$Q$2:$Q$156,"O06|"&$A4,Inputs!$I$2:$I$156,"<>"))=0,IF(COUNTIFS(Inputs!$Q$2:$Q$156,"O06|"&$A4,Inputs!$I$2:$I$156,"",Inputs!$P$2:$P$156,"<>")>0,"N/A (blank - see Inputs note)","PENDING"),IF(ABS(SUMIFS(Inputs!$J$2:$J$156,Inputs!$Q$2:$Q$156,"A01|"&$A4)*1000/INDEX(FS_Reference!$D$2:$D$10,MATCH($A4,FS_Reference!$A$2:$A$10,0))-SUMIFS(Inputs!$J$2:$J$156,Inputs!$Q$2:$Q$156,"O06|"&$A4))<=1.5,"OK","CHECK")) -> OK | H4: =IF((COUNTIFS(Inputs!$Q$2:$Q$156,"B01|"&$A4,Inputs!$I$2:$I$156,"<>"))*(COUNTIFS(Inputs!$Q$2:$Q$156,"B02|"&$A4,Inputs!$I$2:$I$156,"<>"))*(COUNTIFS(Inputs!$Q$2:$Q$156,"B03|"&$A4,Inputs!$I$2:$I$156,"<>"))*(COUNTIFS(Inputs!$Q$2:$Q$156,"B04|"&$A4,Inputs!$I$2:$I$156,"<>"))=0,"PENDING",IF(ABS(INDEX(FS_Reference!$C$2:$C$10,MATCH("H1_2023",FS_Reference!$A$2:$A$10,0))+SUMIFS(Inputs!$J$2:$J$156,Inputs!$Q$2:$Q$156,"B01|"&$A4)+SUMIFS(Inputs!$J$2:$J$156,Inputs!$Q$2:$Q$156,"B02|"&$A4)+SUMIFS(Inputs!$J$2:$J$156,Inputs!$Q$2:$Q$156,"B03|"&$A4)+SUMIFS(Inputs!$J$2:$J$156,Inputs!$Q$2:$Q$156,"B04|"&$A4)-INDEX(FS_Reference!$C$2:$C$10,MATCH($A4,FS_Reference!$A$2:$A$10,0)))<=$L4,"OK","CHECK")) -> OK | I4: =IF(COUNTIFS(Inputs!$Q$2:$Q$156,"B03|"&$A4,Inputs!$I$2:$I$156,"<>")=0,"PENDING",IF(ABS(INDEX(FS_Reference!$H$2:$H$10,MATCH($A4,FS_Reference!$A$2:$A$10,0))-INDEX(FS_Reference!$H$2:$H$10,MATCH("H1_2023",FS_Reference!$A$2:$A$10,0))-SUMIFS(Inputs!$J$2:$J$156,Inputs!$Q$2:$Q$156,"B03|"&$A4))<=$L4/2,"OK","CHECK")) -> OK | J4: =IF(COUNTIFS(Inputs!$Q$2:$Q$156,"B04|"&$A4,Inputs!$I$2:$I$156,"<>")=0,"PENDING",IF(ABS(INDEX(FS_Reference!$I$2:$I$10,MATCH($A4,FS_Reference!$A$2:$A$10,0))-INDEX(FS_Reference!$I$2:$I$10,MATCH("H1_2023",FS_Reference!$A$2:$A$10,0))-SUMIFS(Inputs!$J$2:$J$156,Inputs!$Q$2:$Q$156,"B04|"&$A4))<=$L4/2,"OK","CHECK")) -> OK | K4: =IF((COUNTIFS(Inputs!$Q$2:$Q$156,"B01|"&$A4,Inputs!$I$2:$I$156,"<>"))*(COUNTIFS(Inputs!$Q$2:$Q$156,"B02|"&$A4,Inputs!$I$2:$I$156,"<>"))=0,"PENDING",IF(ABS(INDEX(FS_Reference!$G$2:$G$10,MATCH($A4,FS_Reference!$A$2:$A$10,0))-INDEX(FS_Reference!$G$2:$G$10,MATCH("H1_2023",FS_Reference!$A$2:$A$10,0))-SUMIFS(Inputs!$J$2:$J$156,Inputs!$Q$2:$Q$156,"B01|"&$A4)-SUMIFS(Inputs!$J$2:$J$156,Inputs!$Q$2:$Q$156,"B02|"&$A4))<=$L4,"OK","CHECK")) -> OK | L4: 50 | M4: =COUNTIFS(Inputs!$D$2:$D$156,$A4,Inputs!$I$2:$I$156,"<>") -> 21 | N4: =COUNTIFS(Inputs!$D$2:$D$156,$A4,Inputs!$I$2:$I$156,"",Inputs!$P$2:$P$156,"<>") -> 0 | O4: =COUNTIFS(Inputs!$D$2:$D$156,$A4) -> 21
A5: FY_2024 | B5: =IF((COUNTIFS(Inputs!$Q$2:$Q$156,"A05|"&$A5,Inputs!$I$2:$I$156,"<>"))*(COUNTIFS(Inputs!$Q$2:$Q$156,"A06|"&$A5,Inputs!$I$2:$I$156,"<>"))*(COUNTIFS(Inputs!$Q$2:$Q$156,"A08|"&$A5,Inputs!$I$2:$I$156,"<>"))=0,"PENDING",IF(ABS(SUMIFS(Inputs!$J$2:$J$156,Inputs!$Q$2:$Q$156,"A05|"&$A5)-SUMIFS(Inputs!$J$2:$J$156,Inputs!$Q$2:$Q$156,"A06|"&$A5)-SUMIFS(Inputs!$J$2:$J$156,Inputs!$Q$2:$Q$156,"A08|"&$A5))<=2,"OK","CHECK")) -> OK | C5: =IF((COUNTIFS(Inputs!$Q$2:$Q$156,"A05|"&$A5,Inputs!$I$2:$I$156,"<>"))*(COUNTIFS(Inputs!$Q$2:$Q$156,"A06|"&$A5,Inputs!$I$2:$I$156,"<>"))*(COUNTIFS(Inputs!$Q$2:$Q$156,"A07|"&$A5,Inputs!$I$2:$I$156,"<>"))=0,"PENDING",IF(ABS(SUMIFS(Inputs!$J$2:$J$156,Inputs!$Q$2:$Q$156,"A06|"&$A5)/SUMIFS(Inputs!$J$2:$J$156,Inputs!$Q$2:$Q$156,"A05|"&$A5)*100-SUMIFS(Inputs!$J$2:$J$156,Inputs!$Q$2:$Q$156,"A07|"&$A5))<=0.2,"OK","CHECK")) -> OK | D5: =IF((COUNTIFS(Inputs!$Q$2:$Q$156,"A12|"&$A5,Inputs!$I$2:$I$156,"<>"))*(COUNTIFS(Inputs!$Q$2:$Q$156,"A09|"&$A5,Inputs!$I$2:$I$156,"<>"))*(COUNTIFS(Inputs!$Q$2:$Q$156,"A11|"&$A5,Inputs!$I$2:$I$156,"<>"))=0,"PENDING",IF(ABS(SUMIFS(Inputs!$J$2:$J$156,Inputs!$Q$2:$Q$156,"A12|"&$A5)-SUMIFS(Inputs!$J$2:$J$156,Inputs!$Q$2:$Q$156,"A09|"&$A5)-SUMIFS(Inputs!$J$2:$J$156,Inputs!$Q$2:$Q$156,"A11|"&$A5))<=2,"OK","CHECK")) -> OK | E5: =IF((COUNTIFS(Inputs!$Q$2:$Q$156,"A03|"&$A5,Inputs!$I$2:$I$156,"<>"))*(COUNTIFS(Inputs!$Q$2:$Q$156,"A02|"&$A5,Inputs!$I$2:$I$156,"<>"))*(COUNTIFS(Inputs!$Q$2:$Q$156,"A12|"&$A5,Inputs!$I$2:$I$156,"<>"))=0,"PENDING",IF(ABS(SUMIFS(Inputs!$J$2:$J$156,Inputs!$Q$2:$Q$156,"A03|"&$A5)-SUMIFS(Inputs!$J$2:$J$156,Inputs!$Q$2:$Q$156,"A02|"&$A5)-SUMIFS(Inputs!$J$2:$J$156,Inputs!$Q$2:$Q$156,"A12|"&$A5))<=60,"OK","CHECK")) -> OK | F5: =IF((COUNTIFS(Inputs!$Q$2:$Q$156,"A03|"&$A5,Inputs!$I$2:$I$156,"<>"))*(COUNTIFS(Inputs!$Q$2:$Q$156,"A01|"&$A5,Inputs!$I$2:$I$156,"<>"))*(COUNTIFS(Inputs!$Q$2:$Q$156,"A04|"&$A5,Inputs!$I$2:$I$156,"<>"))=0,"PENDING",IF(ABS(SUMIFS(Inputs!$J$2:$J$156,Inputs!$Q$2:$Q$156,"A03|"&$A5)/SUMIFS(Inputs!$J$2:$J$156,Inputs!$Q$2:$Q$156,"A01|"&$A5)*100-SUMIFS(Inputs!$J$2:$J$156,Inputs!$Q$2:$Q$156,"A04|"&$A5))<=0.15,"OK","CHECK")) -> OK | G5: =IF((COUNTIFS(Inputs!$Q$2:$Q$156,"A01|"&$A5,Inputs!$I$2:$I$156,"<>"))*(COUNTIFS(Inputs!$Q$2:$Q$156,"O06|"&$A5,Inputs!$I$2:$I$156,"<>"))=0,IF(COUNTIFS(Inputs!$Q$2:$Q$156,"O06|"&$A5,Inputs!$I$2:$I$156,"",Inputs!$P$2:$P$156,"<>")>0,"N/A (blank - see Inputs note)","PENDING"),IF(ABS(SUMIFS(Inputs!$J$2:$J$156,Inputs!$Q$2:$Q$156,"A01|"&$A5)*1000/INDEX(FS_Reference!$D$2:$D$10,MATCH($A5,FS_Reference!$A$2:$A$10,0))-SUMIFS(Inputs!$J$2:$J$156,Inputs!$Q$2:$Q$156,"O06|"&$A5))<=1.5,"OK","CHECK")) -> OK | H5: =IF((COUNTIFS(Inputs!$Q$2:$Q$156,"B01|"&$A5,Inputs!$I$2:$I$156,"<>"))*(COUNTIFS(Inputs!$Q$2:$Q$156,"B02|"&$A5,Inputs!$I$2:$I$156,"<>"))*(COUNTIFS(Inputs!$Q$2:$Q$156,"B03|"&$A5,Inputs!$I$2:$I$156,"<>"))*(COUNTIFS(Inputs!$Q$2:$Q$156,"B04|"&$A5,Inputs!$I$2:$I$156,"<>"))=0,"PENDING",IF(ABS(INDEX(FS_Reference!$C$2:$C$10,MATCH("FY_2023",FS_Reference!$A$2:$A$10,0))+SUMIFS(Inputs!$J$2:$J$156,Inputs!$Q$2:$Q$156,"B01|"&$A5)+SUMIFS(Inputs!$J$2:$J$156,Inputs!$Q$2:$Q$156,"B02|"&$A5)+SUMIFS(Inputs!$J$2:$J$156,Inputs!$Q$2:$Q$156,"B03|"&$A5)+SUMIFS(Inputs!$J$2:$J$156,Inputs!$Q$2:$Q$156,"B04|"&$A5)-INDEX(FS_Reference!$C$2:$C$10,MATCH($A5,FS_Reference!$A$2:$A$10,0)))<=$L5,"OK","CHECK")) -> OK | I5: =IF(COUNTIFS(Inputs!$Q$2:$Q$156,"B03|"&$A5,Inputs!$I$2:$I$156,"<>")=0,"PENDING",IF(ABS(INDEX(FS_Reference!$H$2:$H$10,MATCH($A5,FS_Reference!$A$2:$A$10,0))-INDEX(FS_Reference!$H$2:$H$10,MATCH("FY_2023",FS_Reference!$A$2:$A$10,0))-SUMIFS(Inputs!$J$2:$J$156,Inputs!$Q$2:$Q$156,"B03|"&$A5))<=$L5/2,"OK","CHECK")) -> OK | J5: =IF(COUNTIFS(Inputs!$Q$2:$Q$156,"B04|"&$A5,Inputs!$I$2:$I$156,"<>")=0,"PENDING",IF(ABS(INDEX(FS_Reference!$I$2:$I$10,MATCH($A5,FS_Reference!$A$2:$A$10,0))-INDEX(FS_Reference!$I$2:$I$10,MATCH("FY_2023",FS_Reference!$A$2:$A$10,0))-SUMIFS(Inputs!$J$2:$J$156,Inputs!$Q$2:$Q$156,"B04|"&$A5))<=$L5/2,"OK","CHECK")) -> OK | K5: =IF((COUNTIFS(Inputs!$Q$2:$Q$156,"B01|"&$A5,Inputs!$I$2:$I$156,"<>"))*(COUNTIFS(Inputs!$Q$2:$Q$156,"B02|"&$A5,Inputs!$I$2:$I$156,"<>"))=0,"PENDING",IF(ABS(INDEX(FS_Reference!$G$2:$G$10,MATCH($A5,FS_Reference!$A$2:$A$10,0))-INDEX(FS_Reference!$G$2:$G$10,MATCH("FY_2023",FS_Reference!$A$2:$A$10,0))-SUMIFS(Inputs!$J$2:$J$156,Inputs!$Q$2:$Q$156,"B01|"&$A5)-SUMIFS(Inputs!$J$2:$J$156,Inputs!$Q$2:$Q$156,"B02|"&$A5))<=$L5,"OK","CHECK")) -> OK | L5: 250 | M5: =COUNTIFS(Inputs!$D$2:$D$156,$A5,Inputs!$I$2:$I$156,"<>") -> 21 | N5: =COUNTIFS(Inputs!$D$2:$D$156,$A5,Inputs!$I$2:$I$156,"",Inputs!$P$2:$P$156,"<>") -> 0 | O5: =COUNTIFS(Inputs!$D$2:$D$156,$A5) -> 21
A6: H1_2025 | B6: =IF((COUNTIFS(Inputs!$Q$2:$Q$156,"A05|"&$A6,Inputs!$I$2:$I$156,"<>"))*(COUNTIFS(Inputs!$Q$2:$Q$156,"A06|"&$A6,Inputs!$I$2:$I$156,"<>"))*(COUNTIFS(Inputs!$Q$2:$Q$156,"A08|"&$A6,Inputs!$I$2:$I$156,"<>"))=0,"PENDING",IF(ABS(SUMIFS(Inputs!$J$2:$J$156,Inputs!$Q$2:$Q$156,"A05|"&$A6)-SUMIFS(Inputs!$J$2:$J$156,Inputs!$Q$2:$Q$156,"A06|"&$A6)-SUMIFS(Inputs!$J$2:$J$156,Inputs!$Q$2:$Q$156,"A08|"&$A6))<=2,"OK","CHECK")) -> OK | C6: =IF((COUNTIFS(Inputs!$Q$2:$Q$156,"A05|"&$A6,Inputs!$I$2:$I$156,"<>"))*(COUNTIFS(Inputs!$Q$2:$Q$156,"A06|"&$A6,Inputs!$I$2:$I$156,"<>"))*(COUNTIFS(Inputs!$Q$2:$Q$156,"A07|"&$A6,Inputs!$I$2:$I$156,"<>"))=0,"PENDING",IF(ABS(SUMIFS(Inputs!$J$2:$J$156,Inputs!$Q$2:$Q$156,"A06|"&$A6)/SUMIFS(Inputs!$J$2:$J$156,Inputs!$Q$2:$Q$156,"A05|"&$A6)*100-SUMIFS(Inputs!$J$2:$J$156,Inputs!$Q$2:$Q$156,"A07|"&$A6))<=0.2,"OK","CHECK")) -> OK | D6: =IF((COUNTIFS(Inputs!$Q$2:$Q$156,"A12|"&$A6,Inputs!$I$2:$I$156,"<>"))*(COUNTIFS(Inputs!$Q$2:$Q$156,"A09|"&$A6,Inputs!$I$2:$I$156,"<>"))*(COUNTIFS(Inputs!$Q$2:$Q$156,"A11|"&$A6,Inputs!$I$2:$I$156,"<>"))=0,"PENDING",IF(ABS(SUMIFS(Inputs!$J$2:$J$156,Inputs!$Q$2:$Q$156,"A12|"&$A6)-SUMIFS(Inputs!$J$2:$J$156,Inputs!$Q$2:$Q$156,"A09|"&$A6)-SUMIFS(Inputs!$J$2:$J$156,Inputs!$Q$2:$Q$156,"A11|"&$A6))<=2,"OK","CHECK")) -> OK | E6: =IF((COUNTIFS(Inputs!$Q$2:$Q$156,"A03|"&$A6,Inputs!$I$2:$I$156,"<>"))*(COUNTIFS(Inputs!$Q$2:$Q$156,"A02|"&$A6,Inputs!$I$2:$I$156,"<>"))*(COUNTIFS(Inputs!$Q$2:$Q$156,"A12|"&$A6,Inputs!$I$2:$I$156,"<>"))=0,"PENDING",IF(ABS(SUMIFS(Inputs!$J$2:$J$156,Inputs!$Q$2:$Q$156,"A03|"&$A6)-SUMIFS(Inputs!$J$2:$J$156,Inputs!$Q$2:$Q$156,"A02|"&$A6)-SUMIFS(Inputs!$J$2:$J$156,Inputs!$Q$2:$Q$156,"A12|"&$A6))<=60,"OK","CHECK")) -> OK | F6: =IF((COUNTIFS(Inputs!$Q$2:$Q$156,"A03|"&$A6,Inputs!$I$2:$I$156,"<>"))*(COUNTIFS(Inputs!$Q$2:$Q$156,"A01|"&$A6,Inputs!$I$2:$I$156,"<>"))*(COUNTIFS(Inputs!$Q$2:$Q$156,"A04|"&$A6,Inputs!$I$2:$I$156,"<>"))=0,"PENDING",IF(ABS(SUMIFS(Inputs!$J$2:$J$156,Inputs!$Q$2:$Q$156,"A03|"&$A6)/SUMIFS(Inputs!$J$2:$J$156,Inputs!$Q$2:$Q$156,"A01|"&$A6)*100-SUMIFS(Inputs!$J$2:$J$156,Inputs!$Q$2:$Q$156,"A04|"&$A6))<=0.15,"OK","CHECK")) -> OK | G6: =IF((COUNTIFS(Inputs!$Q$2:$Q$156,"A01|"&$A6,Inputs!$I$2:$I$156,"<>"))*(COUNTIFS(Inputs!$Q$2:$Q$156,"O06|"&$A6,Inputs!$I$2:$I$156,"<>"))=0,IF(COUNTIFS(Inputs!$Q$2:$Q$156,"O06|"&$A6,Inputs!$I$2:$I$156,"",Inputs!$P$2:$P$156,"<>")>0,"N/A (blank - see Inputs note)","PENDING"),IF(ABS(SUMIFS(Inputs!$J$2:$J$156,Inputs!$Q$2:$Q$156,"A01|"&$A6)*1000/INDEX(FS_Reference!$D$2:$D$10,MATCH($A6,FS_Reference!$A$2:$A$10,0))-SUMIFS(Inputs!$J$2:$J$156,Inputs!$Q$2:$Q$156,"O06|"&$A6))<=1.5,"OK","CHECK")) -> OK | H6: =IF((COUNTIFS(Inputs!$Q$2:$Q$156,"B01|"&$A6,Inputs!$I$2:$I$156,"<>"))*(COUNTIFS(Inputs!$Q$2:$Q$156,"B02|"&$A6,Inputs!$I$2:$I$156,"<>"))*(COUNTIFS(Inputs!$Q$2:$Q$156,"B03|"&$A6,Inputs!$I$2:$I$156,"<>"))*(COUNTIFS(Inputs!$Q$2:$Q$156,"B04|"&$A6,Inputs!$I$2:$I$156,"<>"))=0,"PENDING",IF(ABS(INDEX(FS_Reference!$C$2:$C$10,MATCH("H1_2024",FS_Reference!$A$2:$A$10,0))+SUMIFS(Inputs!$J$2:$J$156,Inputs!$Q$2:$Q$156,"B01|"&$A6)+SUMIFS(Inputs!$J$2:$J$156,Inputs!$Q$2:$Q$156,"B02|"&$A6)+SUMIFS(Inputs!$J$2:$J$156,Inputs!$Q$2:$Q$156,"B03|"&$A6)+SUMIFS(Inputs!$J$2:$J$156,Inputs!$Q$2:$Q$156,"B04|"&$A6)-INDEX(FS_Reference!$C$2:$C$10,MATCH($A6,FS_Reference!$A$2:$A$10,0)))<=$L6,"OK","CHECK")) -> OK | I6: =IF(COUNTIFS(Inputs!$Q$2:$Q$156,"B03|"&$A6,Inputs!$I$2:$I$156,"<>")=0,"PENDING",IF(ABS(INDEX(FS_Reference!$H$2:$H$10,MATCH($A6,FS_Reference!$A$2:$A$10,0))-INDEX(FS_Reference!$H$2:$H$10,MATCH("H1_2024",FS_Reference!$A$2:$A$10,0))-SUMIFS(Inputs!$J$2:$J$156,Inputs!$Q$2:$Q$156,"B03|"&$A6))<=$L6/2,"OK","CHECK")) -> OK | J6: =IF(COUNTIFS(Inputs!$Q$2:$Q$156,"B04|"&$A6,Inputs!$I$2:$I$156,"<>")=0,"PENDING",IF(ABS(INDEX(FS_Reference!$I$2:$I$10,MATCH($A6,FS_Reference!$A$2:$A$10,0))-INDEX(FS_Reference!$I$2:$I$10,MATCH("H1_2024",FS_Reference!$A$2:$A$10,0))-SUMIFS(Inputs!$J$2:$J$156,Inputs!$Q$2:$Q$156,"B04|"&$A6))<=$L6/2,"OK","CHECK")) -> OK | K6: =IF((COUNTIFS(Inputs!$Q$2:$Q$156,"B01|"&$A6,Inputs!$I$2:$I$156,"<>"))*(COUNTIFS(Inputs!$Q$2:$Q$156,"B02|"&$A6,Inputs!$I$2:$I$156,"<>"))=0,"PENDING",IF(ABS(INDEX(FS_Reference!$G$2:$G$10,MATCH($A6,FS_Reference!$A$2:$A$10,0))-INDEX(FS_Reference!$G$2:$G$10,MATCH("H1_2024",FS_Reference!$A$2:$A$10,0))-SUMIFS(Inputs!$J$2:$J$156,Inputs!$Q$2:$Q$156,"B01|"&$A6)-SUMIFS(Inputs!$J$2:$J$156,Inputs!$Q$2:$Q$156,"B02|"&$A6))<=$L6,"OK","CHECK")) -> OK | L6: 50 | M6: =COUNTIFS(Inputs!$D$2:$D$156,$A6,Inputs!$I$2:$I$156,"<>") -> 25 | N6: =COUNTIFS(Inputs!$D$2:$D$156,$A6,Inputs!$I$2:$I$156,"",Inputs!$P$2:$P$156,"<>") -> 0 | O6: =COUNTIFS(Inputs!$D$2:$D$156,$A6) -> 25
A7: FY_2025 | B7: =IF((COUNTIFS(Inputs!$Q$2:$Q$156,"A05|"&$A7,Inputs!$I$2:$I$156,"<>"))*(COUNTIFS(Inputs!$Q$2:$Q$156,"A06|"&$A7,Inputs!$I$2:$I$156,"<>"))*(COUNTIFS(Inputs!$Q$2:$Q$156,"A08|"&$A7,Inputs!$I$2:$I$156,"<>"))=0,"PENDING",IF(ABS(SUMIFS(Inputs!$J$2:$J$156,Inputs!$Q$2:$Q$156,"A05|"&$A7)-SUMIFS(Inputs!$J$2:$J$156,Inputs!$Q$2:$Q$156,"A06|"&$A7)-SUMIFS(Inputs!$J$2:$J$156,Inputs!$Q$2:$Q$156,"A08|"&$A7))<=2,"OK","CHECK")) -> OK | C7: =IF((COUNTIFS(Inputs!$Q$2:$Q$156,"A05|"&$A7,Inputs!$I$2:$I$156,"<>"))*(COUNTIFS(Inputs!$Q$2:$Q$156,"A06|"&$A7,Inputs!$I$2:$I$156,"<>"))*(COUNTIFS(Inputs!$Q$2:$Q$156,"A07|"&$A7,Inputs!$I$2:$I$156,"<>"))=0,"PENDING",IF(ABS(SUMIFS(Inputs!$J$2:$J$156,Inputs!$Q$2:$Q$156,"A06|"&$A7)/SUMIFS(Inputs!$J$2:$J$156,Inputs!$Q$2:$Q$156,"A05|"&$A7)*100-SUMIFS(Inputs!$J$2:$J$156,Inputs!$Q$2:$Q$156,"A07|"&$A7))<=0.2,"OK","CHECK")) -> OK | D7: =IF((COUNTIFS(Inputs!$Q$2:$Q$156,"A12|"&$A7,Inputs!$I$2:$I$156,"<>"))*(COUNTIFS(Inputs!$Q$2:$Q$156,"A09|"&$A7,Inputs!$I$2:$I$156,"<>"))*(COUNTIFS(Inputs!$Q$2:$Q$156,"A11|"&$A7,Inputs!$I$2:$I$156,"<>"))=0,"PENDING",IF(ABS(SUMIFS(Inputs!$J$2:$J$156,Inputs!$Q$2:$Q$156,"A12|"&$A7)-SUMIFS(Inputs!$J$2:$J$156,Inputs!$Q$2:$Q$156,"A09|"&$A7)-SUMIFS(Inputs!$J$2:$J$156,Inputs!$Q$2:$Q$156,"A11|"&$A7))<=2,"OK","CHECK")) -> OK | E7: =IF((COUNTIFS(Inputs!$Q$2:$Q$156,"A03|"&$A7,Inputs!$I$2:$I$156,"<>"))*(COUNTIFS(Inputs!$Q$2:$Q$156,"A02|"&$A7,Inputs!$I$2:$I$156,"<>"))*(COUNTIFS(Inputs!$Q$2:$Q$156,"A12|"&$A7,Inputs!$I$2:$I$156,"<>"))=0,"PENDING",IF(ABS(SUMIFS(Inputs!$J$2:$J$156,Inputs!$Q$2:$Q$156,"A03|"&$A7)-SUMIFS(Inputs!$J$2:$J$156,Inputs!$Q$2:$Q$156,"A02|"&$A7)-SUMIFS(Inputs!$J$2:$J$156,Inputs!$Q$2:$Q$156,"A12|"&$A7))<=60,"OK","CHECK")) -> OK | F7: =IF((COUNTIFS(Inputs!$Q$2:$Q$156,"A03|"&$A7,Inputs!$I$2:$I$156,"<>"))*(COUNTIFS(Inputs!$Q$2:$Q$156,"A01|"&$A7,Inputs!$I$2:$I$156,"<>"))*(COUNTIFS(Inputs!$Q$2:$Q$156,"A04|"&$A7,Inputs!$I$2:$I$156,"<>"))=0,"PENDING",IF(ABS(SUMIFS(Inputs!$J$2:$J$156,Inputs!$Q$2:$Q$156,"A03|"&$A7)/SUMIFS(Inputs!$J$2:$J$156,Inputs!$Q$2:$Q$156,"A01|"&$A7)*100-SUMIFS(Inputs!$J$2:$J$156,Inputs!$Q$2:$Q$156,"A04|"&$A7))<=0.15,"OK","CHECK")) -> OK | G7: =IF((COUNTIFS(Inputs!$Q$2:$Q$156,"A01|"&$A7,Inputs!$I$2:$I$156,"<>"))*(COUNTIFS(Inputs!$Q$2:$Q$156,"O06|"&$A7,Inputs!$I$2:$I$156,"<>"))=0,IF(COUNTIFS(Inputs!$Q$2:$Q$156,"O06|"&$A7,Inputs!$I$2:$I$156,"",Inputs!$P$2:$P$156,"<>")>0,"N/A (blank - see Inputs note)","PENDING"),IF(ABS(SUMIFS(Inputs!$J$2:$J$156,Inputs!$Q$2:$Q$156,"A01|"&$A7)*1000/INDEX(FS_Reference!$D$2:$D$10,MATCH($A7,FS_Reference!$A$2:$A$10,0))-SUMIFS(Inputs!$J$2:$J$156,Inputs!$Q$2:$Q$156,"O06|"&$A7))<=1.5,"OK","CHECK")) -> OK | H7: =IF((COUNTIFS(Inputs!$Q$2:$Q$156,"B01|"&$A7,Inputs!$I$2:$I$156,"<>"))*(COUNTIFS(Inputs!$Q$2:$Q$156,"B02|"&$A7,Inputs!$I$2:$I$156,"<>"))*(COUNTIFS(Inputs!$Q$2:$Q$156,"B03|"&$A7,Inputs!$I$2:$I$156,"<>"))*(COUNTIFS(Inputs!$Q$2:$Q$156,"B04|"&$A7,Inputs!$I$2:$I$156,"<>"))=0,"PENDING",IF(ABS(INDEX(FS_Reference!$C$2:$C$10,MATCH("FY_2024",FS_Reference!$A$2:$A$10,0))+SUMIFS(Inputs!$J$2:$J$156,Inputs!$Q$2:$Q$156,"B01|"&$A7)+SUMIFS(Inputs!$J$2:$J$156,Inputs!$Q$2:$Q$156,"B02|"&$A7)+SUMIFS(Inputs!$J$2:$J$156,Inputs!$Q$2:$Q$156,"B03|"&$A7)+SUMIFS(Inputs!$J$2:$J$156,Inputs!$Q$2:$Q$156,"B04|"&$A7)-INDEX(FS_Reference!$C$2:$C$10,MATCH($A7,FS_Reference!$A$2:$A$10,0)))<=$L7,"OK","CHECK")) -> OK | I7: =IF(COUNTIFS(Inputs!$Q$2:$Q$156,"B03|"&$A7,Inputs!$I$2:$I$156,"<>")=0,"PENDING",IF(ABS(INDEX(FS_Reference!$H$2:$H$10,MATCH($A7,FS_Reference!$A$2:$A$10,0))-INDEX(FS_Reference!$H$2:$H$10,MATCH("FY_2024",FS_Reference!$A$2:$A$10,0))-SUMIFS(Inputs!$J$2:$J$156,Inputs!$Q$2:$Q$156,"B03|"&$A7))<=$L7/2,"OK","CHECK")) -> OK | J7: =IF(COUNTIFS(Inputs!$Q$2:$Q$156,"B04|"&$A7,Inputs!$I$2:$I$156,"<>")=0,"PENDING",IF(ABS(INDEX(FS_Reference!$I$2:$I$10,MATCH($A7,FS_Reference!$A$2:$A$10,0))-INDEX(FS_Reference!$I$2:$I$10,MATCH("FY_2024",FS_Reference!$A$2:$A$10,0))-SUMIFS(Inputs!$J$2:$J$156,Inputs!$Q$2:$Q$156,"B04|"&$A7))<=$L7/2,"OK","CHECK")) -> OK | K7: =IF((COUNTIFS(Inputs!$Q$2:$Q$156,"B01|"&$A7,Inputs!$I$2:$I$156,"<>"))*(COUNTIFS(Inputs!$Q$2:$Q$156,"B02|"&$A7,Inputs!$I$2:$I$156,"<>"))=0,"PENDING",IF(ABS(INDEX(FS_Reference!$G$2:$G$10,MATCH($A7,FS_Reference!$A$2:$A$10,0))-INDEX(FS_Reference!$G$2:$G$10,MATCH("FY_2024",FS_Reference!$A$2:$A$10,0))-SUMIFS(Inputs!$J$2:$J$156,Inputs!$Q$2:$Q$156,"B01|"&$A7)-SUMIFS(Inputs!$J$2:$J$156,Inputs!$Q$2:$Q$156,"B02|"&$A7))<=$L7,"OK","CHECK")) -> OK | L7: 50 | M7: =COUNTIFS(Inputs!$D$2:$D$156,$A7,Inputs!$I$2:$I$156,"<>") -> 25 | N7: =COUNTIFS(Inputs!$D$2:$D$156,$A7,Inputs!$I$2:$I$156,"",Inputs!$P$2:$P$156,"<>") -> 1 | O7: =COUNTIFS(Inputs!$D$2:$D$156,$A7) -> 26
A8: H1_2026 | B8: =IF((COUNTIFS(Inputs!$Q$2:$Q$156,"A05|"&$A8,Inputs!$I$2:$I$156,"<>"))*(COUNTIFS(Inputs!$Q$2:$Q$156,"A06|"&$A8,Inputs!$I$2:$I$156,"<>"))*(COUNTIFS(Inputs!$Q$2:$Q$156,"A08|"&$A8,Inputs!$I$2:$I$156,"<>"))=0,"PENDING",IF(ABS(SUMIFS(Inputs!$J$2:$J$156,Inputs!$Q$2:$Q$156,"A05|"&$A8)-SUMIFS(Inputs!$J$2:$J$156,Inputs!$Q$2:$Q$156,"A06|"&$A8)-SUMIFS(Inputs!$J$2:$J$156,Inputs!$Q$2:$Q$156,"A08|"&$A8))<=2,"OK","CHECK")) -> OK | C8: =IF((COUNTIFS(Inputs!$Q$2:$Q$156,"A05|"&$A8,Inputs!$I$2:$I$156,"<>"))*(COUNTIFS(Inputs!$Q$2:$Q$156,"A06|"&$A8,Inputs!$I$2:$I$156,"<>"))*(COUNTIFS(Inputs!$Q$2:$Q$156,"A07|"&$A8,Inputs!$I$2:$I$156,"<>"))=0,"PENDING",IF(ABS(SUMIFS(Inputs!$J$2:$J$156,Inputs!$Q$2:$Q$156,"A06|"&$A8)/SUMIFS(Inputs!$J$2:$J$156,Inputs!$Q$2:$Q$156,"A05|"&$A8)*100-SUMIFS(Inputs!$J$2:$J$156,Inputs!$Q$2:$Q$156,"A07|"&$A8))<=0.2,"OK","CHECK")) -> OK | D8: =IF((COUNTIFS(Inputs!$Q$2:$Q$156,"A12|"&$A8,Inputs!$I$2:$I$156,"<>"))*(COUNTIFS(Inputs!$Q$2:$Q$156,"A09|"&$A8,Inputs!$I$2:$I$156,"<>"))*(COUNTIFS(Inputs!$Q$2:$Q$156,"A11|"&$A8,Inputs!$I$2:$I$156,"<>"))=0,"PENDING",IF(ABS(SUMIFS(Inputs!$J$2:$J$156,Inputs!$Q$2:$Q$156,"A12|"&$A8)-SUMIFS(Inputs!$J$2:$J$156,Inputs!$Q$2:$Q$156,"A09|"&$A8)-SUMIFS(Inputs!$J$2:$J$156,Inputs!$Q$2:$Q$156,"A11|"&$A8))<=2,"OK","CHECK")) -> OK | E8: =IF((COUNTIFS(Inputs!$Q$2:$Q$156,"A03|"&$A8,Inputs!$I$2:$I$156,"<>"))*(COUNTIFS(Inputs!$Q$2:$Q$156,"A02|"&$A8,Inputs!$I$2:$I$156,"<>"))*(COUNTIFS(Inputs!$Q$2:$Q$156,"A12|"&$A8,Inputs!$I$2:$I$156,"<>"))=0,"PENDING",IF(ABS(SUMIFS(Inputs!$J$2:$J$156,Inputs!$Q$2:$Q$156,"A03|"&$A8)-SUMIFS(Inputs!$J$2:$J$156,Inputs!$Q$2:$Q$156,"A02|"&$A8)-SUMIFS(Inputs!$J$2:$J$156,Inputs!$Q$2:$Q$156,"A12|"&$A8))<=60,"OK","CHECK")) -> OK | F8: =IF((COUNTIFS(Inputs!$Q$2:$Q$156,"A03|"&$A8,Inputs!$I$2:$I$156,"<>"))*(COUNTIFS(Inputs!$Q$2:$Q$156,"A01|"&$A8,Inputs!$I$2:$I$156,"<>"))*(COUNTIFS(Inputs!$Q$2:$Q$156,"A04|"&$A8,Inputs!$I$2:$I$156,"<>"))=0,"PENDING",IF(ABS(SUMIFS(Inputs!$J$2:$J$156,Inputs!$Q$2:$Q$156,"A03|"&$A8)/SUMIFS(Inputs!$J$2:$J$156,Inputs!$Q$2:$Q$156,"A01|"&$A8)*100-SUMIFS(Inputs!$J$2:$J$156,Inputs!$Q$2:$Q$156,"A04|"&$A8))<=0.15,"OK","CHECK")) -> OK | G8: =IF((COUNTIFS(Inputs!$Q$2:$Q$156,"A01|"&$A8,Inputs!$I$2:$I$156,"<>"))*(COUNTIFS(Inputs!$Q$2:$Q$156,"O06|"&$A8,Inputs!$I$2:$I$156,"<>"))=0,IF(COUNTIFS(Inputs!$Q$2:$Q$156,"O06|"&$A8,Inputs!$I$2:$I$156,"",Inputs!$P$2:$P$156,"<>")>0,"N/A (blank - see Inputs note)","PENDING"),IF(ABS(SUMIFS(Inputs!$J$2:$J$156,Inputs!$Q$2:$Q$156,"A01|"&$A8)*1000/INDEX(FS_Reference!$D$2:$D$10,MATCH($A8,FS_Reference!$A$2:$A$10,0))-SUMIFS(Inputs!$J$2:$J$156,Inputs!$Q$2:$Q$156,"O06|"&$A8))<=1.5,"OK","CHECK")) -> OK | H8: =IF((COUNTIFS(Inputs!$Q$2:$Q$156,"B01|"&$A8,Inputs!$I$2:$I$156,"<>"))*(COUNTIFS(Inputs!$Q$2:$Q$156,"B02|"&$A8,Inputs!$I$2:$I$156,"<>"))*(COUNTIFS(Inputs!$Q$2:$Q$156,"B03|"&$A8,Inputs!$I$2:$I$156,"<>"))*(COUNTIFS(Inputs!$Q$2:$Q$156,"B04|"&$A8,Inputs!$I$2:$I$156,"<>"))=0,"PENDING",IF(ABS(INDEX(FS_Reference!$C$2:$C$10,MATCH("H1_2025",FS_Reference!$A$2:$A$10,0))+SUMIFS(Inputs!$J$2:$J$156,Inputs!$Q$2:$Q$156,"B01|"&$A8)+SUMIFS(Inputs!$J$2:$J$156,Inputs!$Q$2:$Q$156,"B02|"&$A8)+SUMIFS(Inputs!$J$2:$J$156,Inputs!$Q$2:$Q$156,"B03|"&$A8)+SUMIFS(Inputs!$J$2:$J$156,Inputs!$Q$2:$Q$156,"B04|"&$A8)-INDEX(FS_Reference!$C$2:$C$10,MATCH($A8,FS_Reference!$A$2:$A$10,0)))<=$L8,"OK","CHECK")) -> OK | I8: =IF(COUNTIFS(Inputs!$Q$2:$Q$156,"B03|"&$A8,Inputs!$I$2:$I$156,"<>")=0,"PENDING",IF(ABS(INDEX(FS_Reference!$H$2:$H$10,MATCH($A8,FS_Reference!$A$2:$A$10,0))-INDEX(FS_Reference!$H$2:$H$10,MATCH("H1_2025",FS_Reference!$A$2:$A$10,0))-SUMIFS(Inputs!$J$2:$J$156,Inputs!$Q$2:$Q$156,"B03|"&$A8))<=$L8/2,"OK","CHECK")) -> OK | J8: =IF(COUNTIFS(Inputs!$Q$2:$Q$156,"B04|"&$A8,Inputs!$I$2:$I$156,"<>")=0,"PENDING",IF(ABS(INDEX(FS_Reference!$I$2:$I$10,MATCH($A8,FS_Reference!$A$2:$A$10,0))-INDEX(FS_Reference!$I$2:$I$10,MATCH("H1_2025",FS_Reference!$A$2:$A$10,0))-SUMIFS(Inputs!$J$2:$J$156,Inputs!$Q$2:$Q$156,"B04|"&$A8))<=$L8/2,"OK","CHECK")) -> OK | K8: =IF((COUNTIFS(Inputs!$Q$2:$Q$156,"B01|"&$A8,Inputs!$I$2:$I$156,"<>"))*(COUNTIFS(Inputs!$Q$2:$Q$156,"B02|"&$A8,Inputs!$I$2:$I$156,"<>"))=0,"PENDING",IF(ABS(INDEX(FS_Reference!$G$2:$G$10,MATCH($A8,FS_Reference!$A$2:$A$10,0))-INDEX(FS_Reference!$G$2:$G$10,MATCH("H1_2025",FS_Reference!$A$2:$A$10,0))-SUMIFS(Inputs!$J$2:$J$156,Inputs!$Q$2:$Q$156,"B01|"&$A8)-SUMIFS(Inputs!$J$2:$J$156,Inputs!$Q$2:$Q$156,"B02|"&$A8))<=$L8,"OK","CHECK")) -> OK | L8: 50 | M8: =COUNTIFS(Inputs!$D$2:$D$156,$A8,Inputs!$I$2:$I$156,"<>") -> 25 | N8: =COUNTIFS(Inputs!$D$2:$D$156,$A8,Inputs!$I$2:$I$156,"",Inputs!$P$2:$P$156,"<>") -> 0 | O8: =COUNTIFS(Inputs!$D$2:$D$156,$A8) -> 25
A10: Total | M10: =SUM(M2:M8) -> 154 | N10: =SUM(N2:N8) -> 1 | O10: =SUM(O2:O8) -> 155
A12: Double_checked status (counted from Inputs column O)
A13: Y | B13: =COUNTIF(Inputs!$O$2:$O$156,"Y") -> 151
A14: N | B14: =COUNTIF(Inputs!$O$2:$O$156,"N") -> 3
A15: N/A | B15: =COUNTIF(Inputs!$O$2:$O$156,"N/A") -> 1
A16: Total | B16: =SUM(B13:B15) -> 155
